Workbook

Sheet TMP(NewPCC)_IndirectCost
C1: =Pay_Items!D55 -> Joint Clean and Reseal, Concrete | I1: Hidden
A2: Initial Construction Costs: | E2: Average Daily Revenue: | F2: =IF('General Information'!$D$38="Yes",SUMIF(RevenueData!$A:$A,'General Information'!$D$10,RevenueData!$B:$B)+SUMIF(RevenueData!$A:$A,'General Information'!$D$10,RevenueData!$C:$C)+SUMIF(RevenueData!$A:$A,'General Information'!$D$10,RevenueData!$D:$D)+SUMIF(RevenueData!$A:$A,'General Information'!$D$10,RevenueData!$E:$E)+SUMIF(RevenueData!$A:$A,'General Information'!$D$10,RevenueData!$F:$F)+SUMIF(RevenueData!$A:$A,'General Information'!$D$10,RevenueData!$G:$G)+SUMIF(RevenueData!$A:$A,'General Information'!$D$10,RevenueData!$H:$H),0) -> 3239.39 | G2: =IF(AND('General Information'!$D$38="Yes",F2=0),"No revenue data for this airport - lost revenue set to $0. Contact Aeronautics.","") | J2: Maintenance 1 | R2: Rehabilitation 1
A4: Pavement Type: | C4: New PCC | E4: Maintenance 1 Duration (Days) | F4: =ROUNDUP(C5*550/(50*100/9)/10000,0)+ROUNDUP(C5*'Maintenance Policies'!D38/10000,0)+ROUNDUP(C5*'Maintenance Policies'!D39/5000,0)+ROUNDUP(C5*'Maintenance Policies'!D40/5000,0) -> 10
A5: Mainline Pavement Area: | C5: ='General Information'!D26 -> 66667 | D5: S.Y. | E5: Rehabilitation 1 Duration (Days) | F5: =ROUNDUP(C5*550/(50*100/9)/10000,0)+ROUNDUP(C5*'Maintenance Policies'!D44/10000,0)+ROUNDUP(C5*'Maintenance Policies'!D43/5000,0)+ROUNDUP(C5*'Maintenance Policies'!D42/5000,0)+ROUNDUP(C5*'Maintenance Policies'!D41/1000,0)+7 -> 19
A6: Initial Construction Year: | C6: ='General Information'!D25 -> 2028
A7: Markings Area: | C7: ='General Information'!D28 -> 15000 | D7: S.F. | J7: No. of Slabs: | K7: =C5/((12.5*12.5)/9) -> 3840.0192
J8: Joint length: | K8: =K7*25+((K7/8)*12.5) -> 102000.51
A12: Item No. | B12: Pay Item | C12: Description | D12: Unit | E12: Qty | F12: Unit Cost | G12: Item Cost | J12: Item No. | K12: Pay Item | L12: Description | M12: Unit | N12: Qty | O12: Unit Cost | P12: Item Cost | R12: Item No. | S12: Pay Item | T12: Description | U12: Unit | V12: Qty | W12: Unit Cost | X12: Item Cost
A13: 1 | B13: =IF(C13="",0,VLOOKUP(C13,CHOOSE({1,2},Table2[Pay Item Description],Table2[Pay Item No.]),2,0)) -> 0 | D13: =IF(C13="","N/A",VLOOKUP(C13,CHOOSE({1,2},Table2[Pay Item Description],Table2[Units]),2,0)) -> N/A | F13: =IF(C13="","N/A",VLOOKUP(C13,CHOOSE({1,2},Table2[Pay Item Description],Table2[Unit Cost]),2,0)) -> N/A | G13: =IF(B13<>0,F13*E13,0) -> 0 | I13: =Pay_Items!D55 -> Joint Clean and Reseal, Concrete | J13: 1 | K13: =IF(L13="",0,VLOOKUP(L13,CHOOSE({1,2},Table2[Pay Item Description],Table2[Pay Item No.]),2,0)) -> P-605-5.1a | L13: =Pay_Items!D55 -> Joint Clean and Reseal, Concrete | M13: =IF(L13="","N/A",VLOOKUP(L13,CHOOSE({1,2},Table2[Pay Item Description],Table2[Units]),2,0)) -> L.F. | N13: =K8*'Maintenance Policies'!D37 -> 102000.51 | O13: =IF(L13="","N/A",VLOOKUP(L13,CHOOSE({1,2},Table2[Pay Item Description],Table2[Unit Cost]),2,0)) -> 7 | P13: =O13*N13 -> 714003.57 | R13: 1 | S13: =IF(T13="",0,VLOOKUP(T13,CHOOSE({1,2},Table2[Pay Item Description],Table2[Pay Item No.]),2,0)) -> P-101-5.5c | T13: =Pay_Items!D15 -> Slab Replacement, Concrete | U13: =IF(T13="","N/A",VLOOKUP(T13,CHOOSE({1,2},Table2[Pay Item Description],Table2[Units]),2,0)) -> S.Y. | V13: ='Maintenance Policies'!D41*C5 -> 1333.34 | W13: =IF(T13="","N/A",VLOOKUP(T13,CHOOSE({1,2},Table2[Pay Item Description],Table2[Unit Cost]),2,0)) -> 100 | X13: =W13*V13 -> 133334
A14: 2 | B14: =IF(C14="",0,VLOOKUP(C14,CHOOSE({1,2},Table2[Pay Item Description],Table2[Pay Item No.]),2,0)) -> 0 | D14: =IF(C14="","N/A",VLOOKUP(C14,CHOOSE({1,2},Table2[Pay Item Description],Table2[Units]),2,0)) -> N/A | F14: =IF(C14="","N/A",VLOOKUP(C14,CHOOSE({1,2},Table2[Pay Item Description],Table2[Unit Cost]),2,0)) -> N/A | G14: =IF(B14<>0,F14*E14,0) -> 0 | J14: 2 | K14: =VLOOKUP(L14,CHOOSE({1,2},Table2[Pay Item Description],Table2[Pay Item No.]),2,0) -> P-101-5.2c | L14: =Pay_Items!D8 -> Crack Seal, Concrete | M14: =IF(L14="","N/A",VLOOKUP(L14,CHOOSE({1,2},Table2[Pay Item Description],Table2[Units]),2,0)) -> L.F. | N14: ='Maintenance Policies'!D38*(C5*9) -> 1500.0075 | O14: =IF(L14="","N/A",VLOOKUP(L14,CHOOSE({1,2},Table2[Pay Item Description],Table2[Unit Cost]),2,0)) -> 8 | P14: =O14*N14 -> 12000.06 | R14: 2 | S14: =VLOOKUP(T14,CHOOSE({1,2},Table2[Pay Item Description],Table2[Pay Item No.]),2,0) -> P-101-5.5b | T14: =Pay_Items!D14 -> Full-Depth Repair, Concrete | U14: =IF(T14="","N/A",VLOOKUP(T14,CHOOSE({1,2},Table2[Pay Item Description],Table2[Units]),2,0)) -> S.Y. | V14: ='Maintenance Policies'!D42*C5 -> 200.001 | W14: =IF(T14="","N/A",VLOOKUP(T14,CHOOSE({1,2},Table2[Pay Item Description],Table2[Unit Cost]),2,0)) -> 120 | X14: =W14*V14 -> 24000.12
A15: 3 | B15: =IF(C15="",0,VLOOKUP(C15,CHOOSE({1,2},Table2[Pay Item Description],Table2[Pay Item No.]),2,0)) -> 0 | D15: =IF(C15="","N/A",VLOOKUP(C15,CHOOSE({1,2},Table2[Pay Item Description],Table2[Units]),2,0)) -> N/A | F15: =IF(C15="","N/A",VLOOKUP(C15,CHOOSE({1,2},Table2[Pay Item Description],Table2[Unit Cost]),2,0)) -> N/A | G15: =IF(B15<>0,F15*E15,0) -> 0 | J15: 3 | K15: =VLOOKUP(L15,CHOOSE({1,2},Table2[Pay Item Description],Table2[Pay Item No.]),2,0) -> P-101-5.5a | L15: =Pay_Items!D13 -> Spall Repair, Concrete | M15: =IF(L15="","N/A",VLOOKUP(L15,CHOOSE({1,2},Table2[Pay Item Description],Table2[Units]),2,0)) -> S.F. | N15: ='Maintenance Policies'!D39*(C5*9) -> 780.0039 | O15: =IF(L15="","N/A",VLOOKUP(L15,CHOOSE({1,2},Table2[Pay Item Description],Table2[Unit Cost]),2,0)) -> 60 | P15: =O15*N15 -> 46800.234 | R15: 3 | S15: =VLOOKUP(T15,CHOOSE({1,2},Table2[Pay Item Description],Table2[Pay Item No.]),2,0) -> P-101-5.5a | T15: =Pay_Items!D13 -> Spall Repair, Concrete | U15: =IF(T15="","N/A",VLOOKUP(T15,CHOOSE({1,2},Table2[Pay Item Description],Table2[Units]),2,0)) -> S.F. | V15: ='Maintenance Policies'!D43*(C5*9) -> 780.0039 | W15: =IF(T15="","N/A",VLOOKUP(T15,CHOOSE({1,2},Table2[Pay Item Description],Table2[Unit Cost]),2,0)) -> 60 | X15: =W15*V15 -> 46800.234
A16: 4 | B16: =IF(C16="",0,VLOOKUP(C16,CHOOSE({1,2},Table2[Pay Item Description],Table2[Pay Item No.]),2,0)) -> 0 | D16: =IF(C16="","N/A",VLOOKUP(C16,CHOOSE({1,2},Table2[Pay Item Description],Table2[Units]),2,0)) -> N/A | F16: =IF(C16="","N/A",VLOOKUP(C16,CHOOSE({1,2},Table2[Pay Item Description],Table2[Unit Cost]),2,0)) -> N/A | G16: =IF(B16<>0,F16*E16,0) -> 0 | J16: 4 | K16: =VLOOKUP(L16,CHOOSE({1,2},Table2[Pay Item Description],Table2[Pay Item No.]),2,0) -> P-101-5.5b | L16: =Pay_Items!D14 -> Full-Depth Repair, Concrete | M16: =IF(L16="","N/A",VLOOKUP(L16,CHOOSE({1,2},Table2[Pay Item Description],Table2[Units]),2,0)) -> S.Y. | N16: ='Maintenance Policies'!D40*C5 -> 200.001 | O16: =IF(L16="","N/A",VLOOKUP(L16,CHOOSE({1,2},Table2[Pay Item Description],Table2[Unit Cost]),2,0)) -> 120 | P16: =O16*N16 -> 24000.12 | R16: 4 | S16: =VLOOKUP(T16,CHOOSE({1,2},Table2[Pay Item Description],Table2[Pay Item No.]),2,0) -> P-101-5.2c | T16: =Pay_Items!D8 -> Crack Seal, Concrete | U16: =IF(T16="","N/A",VLOOKUP(T16,CHOOSE({1,2},Table2[Pay Item Description],Table2[Units]),2,0)) -> L.F. | V16: ='Maintenance Policies'!D44*(C5*9) -> 1800.009 | W16: =IF(T16="","N/A",VLOOKUP(T16,CHOOSE({1,2},Table2[Pay Item Description],Table2[Unit Cost]),2,0)) -> 8 | X16: =W16*V16 -> 14400.072
A17: 5 | B17: =IF(C17="",0,VLOOKUP(C17,CHOOSE({1,2},Table2[Pay Item Description],Table2[Pay Item No.]),2,0)) -> 0 | D17: =IF(C17="","N/A",VLOOKUP(C17,CHOOSE({1,2},Table2[Pay Item Description],Table2[Units]),2,0)) -> N/A | F17: =IF(C17="","N/A",VLOOKUP(C17,CHOOSE({1,2},Table2[Pay Item Description],Table2[Unit Cost]),2,0)) -> N/A | G17: =IF(B17<>0,F17*E17,0) -> 0 | O17: Subtotal | P17: =SUM(P13:P16) -> 796803.98 | R17: 5 | S17: =VLOOKUP(T17,CHOOSE({1,2},Table2[Pay Item Description],Table2[Pay Item No.]),2,0) -> P-605-5.1a | T17: =Pay_Items!D55 -> Joint Clean and Reseal, Concrete | U17: =IF(T17="","N/A",VLOOKUP(T17,CHOOSE({1,2},Table2[Pay Item Description],Table2[Units]),2,0)) -> L.F. | V17: ='Maintenance Policies'!D45*K8 -> 102000.51 | W17: =IF(T17="","N/A",VLOOKUP(T17,CHOOSE({1,2},Table2[Pay Item Description],Table2[Unit Cost]),2,0)) -> 7 | X17: =W17*V17 -> 714003.57
A18: 6 | B18: =IF(C18="",0,VLOOKUP(C18,CHOOSE({1,2},Table2[Pay Item Description],Table2[Pay Item No.]),2,0)) -> 0 | D18: =IF(C18="","N/A",VLOOKUP(C18,CHOOSE({1,2},Table2[Pay Item Description],Table2[Units]),2,0)) -> N/A | F18: =IF(C18="","N/A",VLOOKUP(C18,CHOOSE({1,2},Table2[Pay Item Description],Table2[Unit Cost]),2,0)) -> N/A | G18: =IF(B18<>0,F18*E18,0) -> 0 | L18: Mobilization | P18: =('General Information'!$D$36/100)*P17 -> 79680.398 | W18: Subtotal | X18: =SUM(X13:X17) -> 932538
A19: 7 | B19: =IF(C19="",0,VLOOKUP(C19,CHOOSE({1,2},Table2[Pay Item Description],Table2[Pay Item No.]),2,0)) -> 0 | D19: =IF(C19="","N/A",VLOOKUP(C19,CHOOSE({1,2},Table2[Pay Item Description],Table2[Units]),2,0)) -> N/A | F19: =IF(C19="","N/A",VLOOKUP(C19,CHOOSE({1,2},Table2[Pay Item Description],Table2[Unit Cost]),2,0)) -> N/A | G19: =IF(B19<>0,F19*E19,0) -> 0 | L19: Engineering | P19: =('General Information'!$D$37/100)*P17 -> 39840.199 | T19: Mobilization | X19: =('General Information'!$D$36/100)*X18 -> 93253.8
A20: 8 | B20: =IF(C20="",0,VLOOKUP(C20,CHOOSE({1,2},Table2[Pay Item Description],Table2[Pay Item No.]),2,0)) -> 0 | D20: =IF(C20="","N/A",VLOOKUP(C20,CHOOSE({1,2},Table2[Pay Item Description],Table2[Units]),2,0)) -> N/A | F20: =IF(C20="","N/A",VLOOKUP(C20,CHOOSE({1,2},Table2[Pay Item Description],Table2[Unit Cost]),2,0)) -> N/A | G20: =IF(B20<>0,F20*E20,0) -> 0 | O20: Total | P20: =SUM(P17:P19) -> 916324.58 | T20: Engineering | X20: =('General Information'!$D$37/100)*X18 -> 46626.9
A21: 9 | B21: =IF(C21="",0,VLOOKUP(C21,CHOOSE({1,2},Table2[Pay Item Description],Table2[Pay Item No.]),2,0)) -> 0 | D21: =IF(C21="","N/A",VLOOKUP(C21,CHOOSE({1,2},Table2[Pay Item Description],Table2[Units]),2,0)) -> N/A | F21: =IF(C21="","N/A",VLOOKUP(C21,CHOOSE({1,2},Table2[Pay Item Description],Table2[Unit Cost]),2,0)) -> N/A | G21: =IF(B21<>0,F21*E21,0) -> 0 | W21: Total | X21: =SUM(X18:X20) -> 1072418.7
A22: 10 | B22: =IF(C22="",0,VLOOKUP(C22,CHOOSE({1,2},Table2[Pay Item Description],Table2[Pay Item No.]),2,0)) -> 0 | D22: =IF(C22="","N/A",VLOOKUP(C22,CHOOSE({1,2},Table2[Pay Item Description],Table2[Units]),2,0)) -> N/A | F22: =IF(C22="","N/A",VLOOKUP(C22,CHOOSE({1,2},Table2[Pay Item Description],Table2[Unit Cost]),2,0)) -> N/A | G22: =IF(B22<>0,F22*E22,0) -> 0
A24: Subtotal | G24: =SUM(G13:G22) -> 0
B25: Mobilization | G25: =('General Information'!$D$36/100)*G24 -> 0
B26: Engineering | G26: =('General Information'!$D$37/100)*G24 -> 0
A27: Total | G27: =SUM(G24:G26) -> 0
A33: Net Present Worth
A34: PCC Reconstruction - Alternative 2 | I34: Hidden
B36: Item | C36: Year Applied | D36: Actual Cost | E36: Discounted Cost
B37: Initial Construction | C37: =C6 -> 2028 | D37: =G27 -> 0 | E37: =D37 -> 0 | K37: Year | L37: Direct Cost | M37: Indirect Cost | N37: Total Discounted Cost
B38: Maintenance 1 | C38: ='Maintenance Policies'!E37 -> 19 | D38: =P20 -> 916324.58 | E38: =IF(C38>'General Information'!$D$33,0,D38/(1+('General Information'!$D$34/100))^C38) -> 522567.1 | K38: =C6 -> 2028 | L38: =IF(K38-$C$6>'General Information'!$D$33,0,IF(K38=$C$6,$D$37,0)+SUMIFS($D$38:$D$42,$C$38:$C$42,K38-$C$6,$B$38:$B$42,"<>*Indirect*")) -> 0 | M38: =IF(K38-$C$6>'General Information'!$D$33,0,SUMIFS($D$38:$D$42,$C$38:$C$42,K38-$C$6,$B$38:$B$42,"*Indirect*")) -> 0 | N38: =IF(K38-$C$6>'General Information'!$D$33,0,IF(K38=$C$6,$E$37,0)+SUMIF($C$38:$C$42,K38-$C$6,$E$38:$E$42)) -> 0
B39: Maintenance 1 Indirect Cost | C39: ='Maintenance Policies'!E37 -> 19 | D39: =F2*F4 -> 32393.9 | E39: =IF(C39>'General Information'!$D$33,0,D39/(1+('General Information'!$D$34/100))^C39) -> 18473.789 | K39: =K38+1 -> 2029 | L39: =IF(K39-$C$6>'General Information'!$D$33,0,IF(K39=$C$6,$D$37,0)+SUMIFS($D$38:$D$42,$C$38:$C$42,K39-$C$6,$B$38:$B$42,"<>*Indirect*")) -> 0 | M39: =IF(K39-$C$6>'General Information'!$D$33,0,SUMIFS($D$38:$D$42,$C$38:$C$42,K39-$C$6,$B$38:$B$42,"*Indirect*")) -> 0 | N39: =IF(K39-$C$6>'General Information'!$D$33,0,IF(K39=$C$6,$E$37,0)+SUMIF($C$38:$C$42,K39-$C$6,$E$38:$E$42)) -> 0
B40: Rehabilitation 1 | C40: ='Maintenance Policies'!E41 -> 27 | D40: =X21 -> 1072418.7 | E40: =IF(C40>'General Information'!$D$33,0,D40/(1+('General Information'!$D$34/100))^C40) -> 482791.16 | K40: =K39+1 -> 2030 | L40: =IF(K40-$C$6>'General Information'!$D$33,0,IF(K40=$C$6,$D$37,0)+SUMIFS($D$38:$D$42,$C$38:$C$42,K40-$C$6,$B$38:$B$42,"<>*Indirect*")) -> 0 | M40: =IF(K40-$C$6>'General Information'!$D$33,0,SUMIFS($D$38:$D$42,$C$38:$C$42,K40-$C$6,$B$38:$B$42,"*Indirect*")) -> 0 | N40: =IF(K40-$C$6>'General Information'!$D$33,0,IF(K40=$C$6,$E$37,0)+SUMIF($C$38:$C$42,K40-$C$6,$E$38:$E$42)) -> 0
B41: Rehabilitation 1 Indirect Cost | C41: ='Maintenance Policies'!E41 -> 27 | D41: =F2*F5 -> 61548.41 | E41: =IF(C41>'General Information'!$D$33,0,D41/(1+('General Information'!$D$34/100))^C41) -> 27708.421 | K41: =K40+1 -> 2031 | L41: =IF(K41-$C$6>'General Information'!$D$33,0,IF(K41=$C$6,$D$37,0)+SUMIFS($D$38:$D$42,$C$38:$C$42,K41-$C$6,$B$38:$B$42,"<>*Indirect*")) -> 0 | M41: =IF(K41-$C$6>'General Information'!$D$33,0,SUMIFS($D$38:$D$42,$C$38:$C$42,K41-$C$6,$B$38:$B$42,"*Indirect*")) -> 0 | N41: =IF(K41-$C$6>'General Information'!$D$33,0,IF(K41=$C$6,$E$37,0)+SUMIF($C$38:$C$42,K41-$C$6,$E$38:$E$42)) -> 0
B42: Salvage | C42: ='General Information'!D33 -> 30 | D42: =-'Maintenance Policies'!D46*G27 -> 0 | E42: =IF(C42>'General Information'!$D$33,0,D42/(1+('General Information'!$D$34/100))^C42) -> 0 | K42: =K41+1 -> 2032 | L42: =IF(K42-$C$6>'General Information'!$D$33,0,IF(K42=$C$6,$D$37,0)+SUMIFS($D$38:$D$42,$C$38:$C$42,K42-$C$6,$B$38:$B$42,"<>*Indirect*")) -> 0 | M42: =IF(K42-$C$6>'General Information'!$D$33,0,SUMIFS($D$38:$D$42,$C$38:$C$42,K42-$C$6,$B$38:$B$42,"*Indirect*")) -> 0 | N42: =IF(K42-$C$6>'General Information'!$D$33,0,IF(K42=$C$6,$E$37,0)+SUMIF($C$38:$C$42,K42-$C$6,$E$38:$E$42)) -> 0
B43: Net Present Worth | E43: =SUM(E37:E42) -> 1051540.5 | K43: =K42+1 -> 2033 | L43: =IF(K43-$C$6>'General Information'!$D$33,0,IF(K43=$C$6,$D$37,0)+SUMIFS($D$38:$D$42,$C$38:$C$42,K43-$C$6,$B$38:$B$42,"<>*Indirect*")) -> 0 | M43: =IF(K43-$C$6>'General Information'!$D$33,0,SUMIFS($D$38:$D$42,$C$38:$C$42,K43-$C$6,$B$38:$B$42,"*Indirect*")) -> 0 | N43: =IF(K43-$C$6>'General Information'!$D$33,0,IF(K43=$C$6,$E$37,0)+SUMIF($C$38:$C$42,K43-$C$6,$E$38:$E$42)) -> 0
K44: =K43+1 -> 2034 | L44: =IF(K44-$C$6>'General Information'!$D$33,0,IF(K44=$C$6,$D$37,0)+SUMIFS($D$38:$D$42,$C$38:$C$42,K44-$C$6,$B$38:$B$42,"<>*Indirect*")) -> 0 | M44: =IF(K44-$C$6>'General Information'!$D$33,0,SUMIFS($D$38:$D$42,$C$38:$C$42,K44-$C$6,$B$38:$B$42,"*Indirect*")) -> 0 | N44: =IF(K44-$C$6>'General Information'!$D$33,0,IF(K44=$C$6,$E$37,0)+SUMIF($C$38:$C$42,K44-$C$6,$E$38:$E$42)) -> 0
K45: =K44+1 -> 2035 | L45: =IF(K45-$C$6>'General Information'!$D$33,0,IF(K45=$C$6,$D$37,0)+SUMIFS($D$38:$D$42,$C$38:$C$42,K45-$C$6,$B$38:$B$42,"<>*Indirect*")) -> 0 | M45: =IF(K45-$C$6>'General Information'!$D$33,0,SUMIFS($D$38:$D$42,$C$38:$C$42,K45-$C$6,$B$38:$B$42,"*Indirect*")) -> 0 | N45: =IF(K45-$C$6>'General Information'!$D$33,0,IF(K45=$C$6,$E$37,0)+SUMIF($C$38:$C$42,K45-$C$6,$E$38:$E$42)) -> 0
K46: =K45+1 -> 2036 | L46: =IF(K46-$C$6>'General Information'!$D$33,0,IF(K46=$C$6,$D$37,0)+SUMIFS($D$38:$D$42,$C$38:$C$42,K46-$C$6,$B$38:$B$42,"<>*Indirect*")) -> 0 | M46: =IF(K46-$C$6>'General Information'!$D$33,0,SUMIFS($D$38:$D$42,$C$38:$C$42,K46-$C$6,$B$38:$B$42,"*Indirect*")) -> 0 | N46: =IF(K46-$C$6>'General Information'!$D$33,0,IF(K46=$C$6,$E$37,0)+SUMIF($C$38:$C$42,K46-$C$6,$E$38:$E$42)) -> 0
K47: =K46+1 -> 2037 | L47: =IF(K47-$C$6>'General Information'!$D$33,0,IF(K47=$C$6,$D$37,0)+SUMIFS($D$38:$D$42,$C$38:$C$42,K47-$C$6,$B$38:$B$42,"<>*Indirect*")) -> 0 | M47: =IF(K47-$C$6>'General Information'!$D$33,0,SUMIFS($D$38:$D$42,$C$38:$C$42,K47-$C$6,$B$38:$B$42,"*Indirect*")) -> 0 | N47: =IF(K47-$C$6>'General Information'!$D$33,0,IF(K47=$C$6,$E$37,0)+SUMIF($C$38:$C$42,K47-$C$6,$E$38:$E$42)) -> 0
K48: =K47+1 -> 2038 | L48: =IF(K48-$C$6>'General Information'!$D$33,0,IF(K48=$C$6,$D$37,0)+SUMIFS($D$38:$D$42,$C$38:$C$42,K48-$C$6,$B$38:$B$42,"<>*Indirect*")) -> 0 | M48: =IF(K48-$C$6>'General Information'!$D$33,0,SUMIFS($D$38:$D$42,$C$38:$C$42,K48-$C$6,$B$38:$B$42,"*Indirect*")) -> 0 | N48: =IF(K48-$C$6>'General Information'!$D$33,0,IF(K48=$C$6,$E$37,0)+SUMIF($C$38:$C$42,K48-$C$6,$E$38:$E$42)) -> 0
K49: =K48+1 -> 2039 | L49: =IF(K49-$C$6>'General Information'!$D$33,0,IF(K49=$C$6,$D$37,0)+SUMIFS($D$38:$D$42,$C$38:$C$42,K49-$C$6,$B$38:$B$42,"<>*Indirect*")) -> 0 | M49: =IF(K49-$C$6>'General Information'!$D$33,0,SUMIFS($D$38:$D$42,$C$38:$C$42,K49-$C$6,$B$38:$B$42,"*Indirect*")) -> 0 | N49: =IF(K49-$C$6>'General Information'!$D$33,0,IF(K49=$C$6,$E$37,0)+SUMIF($C$38:$C$42,K49-$C$6,$E$38:$E$42)) -> 0
K50: =K49+1 -> 2040 | L50: =IF(K50-$C$6>'General Information'!$D$33,0,IF(K50=$C$6,$D$37,0)+SUMIFS($D$38:$D$42,$C$38:$C$42,K50-$C$6,$B$38:$B$42,"<>*Indirect*")) -> 0 | M50: =IF(K50-$C$6>'General Information'!$D$33,0,SUMIFS($D$38:$D$42,$C$38:$C$42,K50-$C$6,$B$38:$B$42,"*Indirect*")) -> 0 | N50: =IF(K50-$C$6>'General Information'!$D$33,0,IF(K50=$C$6,$E$37,0)+SUMIF($C$38:$C$42,K50-$C$6,$E$38:$E$42)) -> 0
K51: =K50+1 -> 2041 | L51: =IF(K51-$C$6>'General Information'!$D$33,0,IF(K51=$C$6,$D$37,0)+SUMIFS($D$38:$D$42,$C$38:$C$42,K51-$C$6,$B$38:$B$42,"<>*Indirect*")) -> 0 | M51: =IF(K51-$C$6>'General Information'!$D$33,0,SUMIFS($D$38:$D$42,$C$38:$C$42,K51-$C$6,$B$38:$B$42,"*Indirect*")) -> 0 | N51: =IF(K51-$C$6>'General Information'!$D$33,0,IF(K51=$C$6,$E$37,0)+SUMIF($C$38:$C$42,K51-$C$6,$E$38:$E$42)) -> 0
K52: =K51+1 -> 2042 | L52: =IF(K52-$C$6>'General Information'!$D$33,0,IF(K52=$C$6,$D$37,0)+SUMIFS($D$38:$D$42,$C$38:$C$42,K52-$C$6,$B$38:$B$42,"<>*Indirect*")) -> 0 | M52: =IF(K52-$C$6>'General Information'!$D$33,0,SUMIFS($D$38:$D$42,$C$38:$C$42,K52-$C$6,$B$38:$B$42,"*Indirect*")) -> 0 | N52: =IF(K52-$C$6>'General Information'!$D$33,0,IF(K52=$C$6,$E$37,0)+SUMIF($C$38:$C$42,K52-$C$6,$E$38:$E$42)) -> 0
K53: =K52+1 -> 2043 | L53: =IF(K53-$C$6>'General Information'!$D$33,0,IF(K53=$C$6,$D$37,0)+SUMIFS($D$38:$D$42,$C$38:$C$42,K53-$C$6,$B$38:$B$42,"<>*Indirect*")) -> 0 | M53: =IF(K53-$C$6>'General Information'!$D$33,0,SUMIFS($D$38:$D$42,$C$38:$C$42,K53-$C$6,$B$38:$B$42,"*Indirect*")) -> 0 | N53: =IF(K53-$C$6>'General Information'!$D$33,0,IF(K53=$C$6,$E$37,0)+SUMIF($C$38:$C$42,K53-$C$6,$E$38:$E$42)) -> 0
K54: =K53+1 -> 2044 | L54: =IF(K54-$C$6>'General Information'!$D$33,0,IF(K54=$C$6,$D$37,0)+SUMIFS($D$38:$D$42,$C$38:$C$42,K54-$C$6,$B$38:$B$42,"<>*Indirect*")) -> 0 | M54: =IF(K54-$C$6>'General Information'!$D$33,0,SUMIFS($D$38:$D$42,$C$38:$C$42,K54-$C$6,$B$38:$B$42,"*Indirect*")) -> 0 | N54: =IF(K54-$C$6>'General Information'!$D$33,0,IF(K54=$C$6,$E$37,0)+SUMIF($C$38:$C$42,K54-$C$6,$E$38:$E$42)) -> 0
K55: =K54+1 -> 2045 | L55: =IF(K55-$C$6>'General Information'!$D$33,0,IF(K55=$C$6,$D$37,0)+SUMIFS($D$38:$D$42,$C$38:$C$42,K55-$C$6,$B$38:$B$42,"<>*Indirect*")) -> 0 | M55: =IF(K55-$C$6>'General Information'!$D$33,0,SUMIFS($D$38:$D$42,$C$38:$C$42,K55-$C$6,$B$38:$B$42,"*Indirect*")) -> 0 | N55: =IF(K55-$C$6>'General Information'!$D$33,0,IF(K55=$C$6,$E$37,0)+SUMIF($C$38:$C$42,K55-$C$6,$E$38:$E$42)) -> 0
... K68: =K67+1 -> 2058 | L68: =IF(K68-$C$6>'General Information'!$D$33,0,IF(K68=$C$6,$D$37,0)+SUMIFS($D$38:$D$42,$C$38:$C$42,K68-$C$6,$B$38:$B$42,"<>*Indirect*")) -> 0 | M68: =IF(K68-$C$6>'General Information'!$D$33,0,SUMIFS($D$38:$D$42,$C$38:$C$42,K68-$C$6,$B$38:$B$42,"*Indirect*")) -> 0 | N68: =IF(K68-$C$6>'General Information'!$D$33,0,IF(K68=$C$6,$E$37,0)+SUMIF($C$38:$C$42,K68-$C$6,$E$38:$E$42)) -> 0

Sheet Overview
E2: Tennessee Department of Transportation
E3: Aeronautics Division
E4: 7335 Centennial Boulevard
E5: Nashville, Tennessee 37209
E6: 615-741-3208
E7: https://www.tn.gov/tdot/aeronautics.html
B9: Overview:

Sheet Instructions
E2: Tennessee Department of Transportation
E3: Aeronautics Division
E4: 7335 Centennial Boulevard
E5: Nashville, Tennessee 37209
E6: 615-741-3208
E7: https://www.tn.gov/tdot/aeronautics.html
B9: Instructions:

Sheet General Information
K7: Hidden
B8: Airport Information: | L8: Name | M8: ID | N8: City | O8: County | P8: Region | Q8: Owner | S8: Branch Use
C9: Airport Name: | D9: Outlaw Field | N9: N/A | O9: N/A
C10: Airport ID: | D10: =IF(D9="","N/A",VLOOKUP(Airport_Name,Table17[],2)) -> CKV | L10: Abernathy Field | M10: GZS | N10: Pulaski | O10: Giles | P10: Middle | S10: Runway
C11: City: | D11: =IF(D9="","N/A",VLOOKUP(Airport_Name,Table17[],3)) -> Clarksville | L11: Arnold Field | M11: M31 | N11: Halls | O11: Lauderdale | P11: West | S11: Taxiway
C12: Airport Owner: | D12: =IF(D9="","N/A",VLOOKUP(Airport_Name,Table17[],6)) -> 0 | L12: Beech River Regional Airport | M12: PVE | N12: Lexington/Parsons | O12: Henderson | P12: West | S12: Apron
C13: State Region: | D13: =IF(D9="","N/A",VLOOKUP(Airport_Name,Table17[],5)) -> Middle | L13: Benton County Airport | M13: 0M4 | N13: Camden | O13: Benton | P13: West
C14: Design Consultant: | D14: ARA | L14: Bomar Field-Shelbyville Municipal Airport | M14: SYI | N14: Shelbyville | O14: Bedford | P14: Middle
C15: Project Number: | D15: 5936 | L15: Carroll County Airport | M15: HZD | N15: Huntingdon | O15: Carroll | P15: West | S15: Markings Type
C16: Project Name: | D16: Runway 17-35 Reconstruction | L16: Centerville Municipal Airport | M16: GHM | N16: Centerville | O16: Hickman | P16: Middle
C17: Date of LCCA: | L17: Charles W. Baker Field | M17: 2M8 | N17: Millington | O17: Shelby | P17: West | S17: Reflective
L18: Chilhowee Gliderport | M18: 92A | N18: Benton | O18: Polk | P18: East | S18: Non-Reflective
L19: Cleveland Regional Jetport | M19: RZR | N19: Cleveland | O19: Bradley | P19: East
B20: Project Information: | L20: Collegedale Municipal Airport | M20: FGU | N20: Collegedale | O20: Hamilton | P20: East
C21: Branch Type: | D21: Runway | L21: Colonel Tommy C. Stiner-Campbell County Airport | M21: JAU | N21: Jacksboro | O21: Campbell | P21: East | S21: Weight Category
C22: Branch Name: | D22: Runway 17-35 | L22: Covington Municipal Airport | M22: M04 | N22: Covington | O22: Tipton | P22: West
C23: Project Type: | D23: Reconstruction | L23: Crossville Memorial Airport/Whitson Field | M23: CSV | N23: Crossville | O23: Cumberland | P23: East | S23: < 60,000 lbs
C24: Project Description: | D24: Full-depth reconstruction, 6,000 x 100 ft | L24: Dallas Bay Skypark Airport | M24: 1A0 | N24: Chattanooga | O24: Hamilton | P24: East | S24: > 60,000 to < 100,000 lbs
C25: Intial Construction Year: | D25: 2028 | L25: Dickson Municipal Airport | M25: M02 | N25: Dickson | O25: Dickson | P25: Middle | S25: > 100,000 lbs
C26: Mainline Area, S.Y.: | D26: 66667 | L26: Dyersburg Municipal Airport | M26: DYR | N26: Dyersburg | O26: Dyer | P26: West
C27: Shoulder Area, S.Y.: | D27: 0 | L27: Elizabethton Municipal Airport | M27: 0A9 | N27: Elizabethton | O27: Carter | P27: East
C28: Markings, S.F.: | D28: 15000 | L28: Ellington Airport | M28: LUG | N28: Lewisburg | O28: Marshall | P28: Middle
C29: Markings, Type: | D29: Reflective | L29: Everett-Stewart Airport | M29: UCY | N29: Union City | O29: Obion | P29: West
L30: Fayette County Airport | M30: FYE | N30: Somerville | O30: Fayette | P30: West
L31: Fayetteville Municipal Airport | M31: FYM | N31: Fayetteville | O31: Lincoln | P31: Middle
B32: LCCA Parameters: | L32: Franklin County Airport | M32: UOS | N32: Sewanee | O32: Franklin | P32: Middle
C33: Analysis Period, years: | D33: 30 | L33: Gatlinburg-Pigeon Forge Airport | M33: GKT | N33: Sevierville | O33: Sevier | P33: East
C34: Discount Rate, percent: | D34: 3 | L34: General Dewitt Spain Airport | M34: M01 | N34: Memphis | O34: Shelby | P34: West
C35: Salvage Value, $: | D35: Remaining service life at end of analysis period (as percent of cost) | L35: Gibson County Airport | M35: TGC | N35: Trenton | O35: Gibson | P35: West
C36: Mobilization, percent: | D36: 10 | L36: Greeneville-Green County Municipal Airport | M36: GCY | N36: Greeneville | O36: Greene | P36: East
C37: Engineering, percent: | D37: 5 | L37: Hassell-Carroll Field | M37: M29 | N37: Clifton | O37: Wayne | P37: Middle
C38: Account Indirect Cost (Yes/No) | D38: Yes | L38: Hawkins County Airport | M38: RVN | N38: Rogersville | O38: Hawkins | P38: East
C39: Airport Daily Revenue | D39: =IF(D38<>"Yes","",IF(COUNTIF(RevenueData!$A:$A,$D$10)=0,"Missing Airport Revenue",SUMIF(RevenueData!$A:$A,$D$10,RevenueData!$B:$B)+SUMIF(RevenueData!$A:$A,$D$10,RevenueData!$C:$C)+SUMIF(RevenueData!$A:$A,$D$10,RevenueData!$D:$D)+SUMIF(RevenueData!$A:$A,$D$10,RevenueData!$E:$E)+SUMIF(RevenueData!$A:$A,$D$10,RevenueData!$F:$F)+SUMIF(RevenueData!$A:$A,$D$10,RevenueData!$G:$G)+SUMIF(RevenueData!$A:$A,$D$10,RevenueData!$H:$H))) -> 3239.39 | L39: Henry County Airport | M39: PHT | N39: Paris | O39: Henry | P39: West
L40: Houston County Airport | M40: M93 | N40: McKinnon | O40: Houston | P40: Middle
B41: Alternative Setup: | L41: Humboldt Municipal Airport | M41: M53 | N41: Humboldt | O41: Gibson | P41: West
L42: Humphreys County Airport | M42: 0M5 | N42: Waverly | O42: Humphreys | P42: Middle
L43: Jackson County Airport | M43: 1A7 | N43: Gainesboro | O43: Jackson | P43: Middle
B44: LCCA Summary: | D44: =HYPERLINK("#Summary!G1","View Summary ►") -> View Summary ► | L44: James Tucker-Perry County Airport | M44: M15 | N44: Linden | O44: Perry | P44: Middle
L45: Jamestown Municipal Airport | M45: 2A1 | N45: Jamestown | O45: Fentress | P45: Middle
L46: John A. Baker Field | M46: 0M3 | N46: Hohenwald | O46: Lewis | P46: Middle
L47: John C. Tune Airport | M47: JWN | N47: Nashville | O47: Davidson | P47: Middle
L48: Johnson City Airport | M48: 0A4 | N48: Johnson City | O48: Washington | P48: East
L49: Johnson County Airport | M49: 6A4 | N49: Mountain City | O49: Johnson | P49: East
L50: Knoxville Downtown Island Airport | M50: DKX | N50: Knoxville | O50: Knox | P50: East
L51: Lafayette Municipal Airport | M51: 3M7 | N51: Lafayette | O51: Macon | P51: Middle
L52: Lawrenceburg-Lawrence County Airport | M52: 2M2 | N52: Lawrenceburg | O52: Lawrence | P52: Middle
L53: Lebanon Municipal Airport | M53: M54 | N53: Lebanon | O53: Wilson | P53: Middle
L54: Livingston Municipal Airport | M54: 8A3 | N54: Livingston | O54: Overton | P54: Middle
L55: Lovell Field | M55: CHA | N55: Chattanooga | O55: Hamilton | P55: East
L56: Marion County Airport-Brown Field | M56: APT | N56: Jasper | O56: Marion | P56: East
... L88: Wolf River | M88: 54M | N88: Rossville | O88: Fayette | P88: West

Sheet Pay_Items
G1: Average Pay Item Unit Cost
A2: Division | B2: Division Type | C2: Pay Item No. | D2: Pay Item Description | E2: Units | F2: Unit Cost | G2: Middle | H2: West | I2: East
B3: Default | E3: N/A | F3: N/A
A4: Part 3 – Sitework | B4: Sitework | C4: P-101-5.1a | D4: Pavement Removal, Asphalt | E4: S.Y. | F4: 4.2 | J4: Thickness adjustment or multiple
B5: Sitework | C5: P-101-5.1b | D5: Pavement Removal, Concrete | E5: S.Y. | J5: Thickness adjustment or multiple
B6: Sitework | C6: P-101-5.2a | D6: Crack Repair (Type I), Asphalt | E6: L.F. | F6: 4
B7: Sitework | C7: P-101-5.2b | D7: Crack Repair (Type II), Asphalt | E7: L.F. | F7: 6.5
B8: Sitework | C8: P-101-5.2c | D8: Crack Seal, Concrete | E8: L.F. | F8: 8
B9: Sitework | C9: P-101-5.2d | D9: Crack Repair, Concrete | E9: L.F. | F9: 8.5
B10: Sitework | C10: P-101-5.3 | D10: Markings Removal | E10: S.F. | F10: =7/9 -> 0.77777778
B11: Sitework | C11: P-101-5.4a | D11: Spall Repair, Asphalt | E11: S.F. | F11: 8.5 | J11: Thickness adjustment or multiple
B12: Sitework | C12: P-101-5.4b | D12: Full-Depth Repair, Asphalt | E12: S.F. | J12: Assumed Section: 4-inch HMA; 4-inch P-209
B13: Sitework | C13: P-101-5.5a | D13: Spall Repair, Concrete | E13: S.F. | F13: 60 | J13: Thickness adjustment or multiple
B14: Sitework | C14: P-101-5.5b | D14: Full-Depth Repair, Concrete | E14: S.Y. | F14: 120 | J14: Thickness adjustment or multiple
B15: Sitework | C15: P-101-5.5c | D15: Slab Replacement, Concrete | E15: S.Y. | F15: 100
B16: Sitework | C16: P-101-5.6 | D16: Cold Milling | E16: S.Y. | F16: =10/2 -> 5 | J16: Thickness adjustment or multiple
B17: Sitework | C17: P-152-4.1 | D17: Unclassified Excavation | E17: C.Y.
B18: Sitework | C18: P-152-4.2 | D18: Embankment In-Place | E18: C.Y.
B19: Sitework | C19: P-154-5.1 | D19: Subbase Course | E19: C.Y. | F19: 55
B20: Sitework | C20: P-154-5.2 | D20: Separation Geotextile (P-154) | E20: S.Y.
B21: Sitework | C21: P-155-8.1 | D21: Lime Treated subgrade | E21: S.Y. | F21: 10 | J21: Thickness adjustment or multiple
B22: Sitework | C22: P-156-8.1 | D22: Cement-Treated Subgrade | E22: S.Y. | J22: Thickness adjustment or multiple
B23: Sitework | C23: P-157-8.1a | D23: Cement Kiln Dust-Treated Subgrade | E23: S.Y. | J23: Thickness adjustment or multiple
B24: Sitework | C24: P-157-8.1b | D24: Lime Kiln Dust-Treated Subgrade | E24: S.Y. | J24: Thickness adjustment or multiple
B25: Sitework | C25: P-158-8.1 | D25: Fly Ash-Treated Subgrade | E25: S.Y. | J25: Thickness adjustment or multiple
A26: Part 4 – Base Courses | B26: Base Course | C26: P-207-5.1 | D26: In-Place Full Depth Reclamation (FDR) Recycled Asphalt Aggregate Base Course | E26: S.Y. | J26: Thickness adjustment or multiple
B27: Base Course | C27: P-208-5.1 | D27: Aggregate Base Course | E27: C.Y.
B28: Base Course | C28: P-208-5.2 | D28: Separation Geotextile (P-208) | E28: S.Y.
B29: Base Course | C29: P-209-5.1 | D29: Crushed Aggregate Base Course | E29: C.Y. | F29: 65
B30: Base Course | C30: P-209-5.2 | D30: Separation Geotextile (P-209) | E30: S.Y.
B31: Base Course | C31: P-219-5.1 | D31: Recycled Concrete Aggregate Base Course | E31: C.Y.
B32: Base Course | C32: P-219-5.2 | D32: Separation Geotextile (P-219) | E32: S.Y.
B33: Base Course | C33: P-220-6.1 | D33: Cement-Treated Soil Base Course | E33: S.Y. | J33: Thickness adjustment or multiple
A34: Part 5 – Stabilized Base Courses | B34: Stabilized Base Course | C34: P-304-8.1 | D34: Cement-Treated Base Course | E34: C.Y. | J34: If S.Y., then thickness adjustment
B35: Stabilized Base Course | C35: P-306-8.1 | D35: Lean Concrete Base Course | E35: C.Y. | J35: If S.Y., then thickness adjustment
B36: Stabilized Base Course | C36: P-307-7.1 | D36: Cement-Treated Permeable Base Course (CTPB) | E36: C.Y. | J36: If S.Y., then thickness adjustment
A37: Part 6 – Flexible Pavements | B37: Flexible Pavement | C37: P-401-8.1a | D37: Asphalt Surface Course | E37: TON | F37: 130
B38: Flexible Pavement | C38: P-401-8.1b | D38: Asphalt Base Course | E38: TON | F38: 120
B39: Flexible Pavement | C39: P-401-8.1c | D39: Asphalt Leveling Course | E39: TON | F39: 110
B40: Flexible Pavement | C40: P-403-8.1a | D40: Asphalt Mixture Surface Course | E40: TON
B41: Flexible Pavement | C41: P-403-8.1b | D41: Asphalt Mixture Base Course | E41: TON
B42: Flexible Pavement | C42: P-403-8.1c | D42: Asphalt Mixture Leveling Course | E42: TON
B43: Flexible Pavement | C43: P-407-X.1 | D43: Asphalt-Treated Permeable Base Course (ATPB) | E43: TON
A44: Part 7 – Rigid Pavement | B44: Cement Concrete | C44: P-501-8.1a | D44: Concrete Pavement, 5-inch | E44: S.Y. | F44: 79 | J44: Thickness adjustment or multiple
B45: Cement Concrete | C45: P-501-8.1b | D45: Concrete Pavement, 6-inch | E45: S.Y. | F45: 82 | J45: Thickness adjustment or multiple
B46: Cement Concrete | C46: P-501-8.1c | D46: Concrete Pavement, 9-inch | E46: S.Y. | F46: 85 | J46: Thickness adjustment or multiple
B47: Cement Concrete | C47: P-501-8.1d | D47: Concrete Pavement, 11-inch | E47: S.Y. | F47: 91 | J47: Thickness adjustment or multiple
A48: Part 8 – Surface Treatments | B48: Surface Treatment | C48: P-608-8.1 | D48: Emulsified Asphalt Surface Treatment | E48: S.Y. | F48: 4
B49: Surface Treatment | C49: P-623-8.1 | D49: Emulsified Asphalt Spray Seal Coat | E49: S.Y. | F49: 5
B50: Surface Treatment | C50: P-626-6.1 | D50: Emulsified Asphalt Slurry Seal Surface Treatment | E50: S.Y. | F50: 7
B51: Surface Treatment | C51: P-629-8.1 | D51: Thermoplastic Coal Tar Emulsion Surface Treatment | E51: S.Y.
B52: Surface Treatment | C52: P-630-7.1a | D52: Refined Coal Tar Emulsion Without Additives, Slurry Seal Surface Treatment | E52: S.Y.
B53: Surface Treatment | C53: P-631-7.1b | D53: Refined Coal Tar Emulsion With Additives, Slurry Seal Surface Treatment | E53: S.Y.
A54: Part 9 – Miscellaneous | B54: Tack Coat | C54: P-603-5.1 | D54: Emulsified Asphalt Tack Coat | E54: GAL | F54: 4.5 | J54: Assume 0.1 gal/SY for mill and overlay
B55: Joint Sealant | C55: P-605-5.1a | D55: Joint Clean and Reseal, Concrete | E55: L.F. | F55: 7 | J55: Assume 12.5x12.5 slabs for these GA pavements
B56: Marking | C56: P-620-5.1a | D56: Markings (prep, markings, reflective media) | E56: S.F. | F56: =6/9 -> 0.66666667
B57: Marking | C57: P-620-5.1b | D57: Markings (prep, markings, non-reflective media) | E57: S.F.
B58: Grooving | C58: P-621-5.1A | D58: Grooving, Asphalt | E58: S.Y.
B59: Grooving | C59: P-621-5.1B | D59: Grooving, Concrete | E59: S.Y.

Sheet Database
A1: Alternative List
A3: Name | B3: Type | C3: Description | D3: Alt Worksheet Name
A4: Alternative 1 | B4: HMA-New | C4: New HMA | D4: Alt 1 (New HMA)
A5: Alternative 2 | B5: PCC-New | C5: New PCC | D5: Alt 2 (New PCC)

Sheet Maintenance Policies
B8: Table 1. New HMA maintenance policies.
B9: Asphalt Maintenance | C9: Maintenance Item | D9: Rate | E9: Year Applied
B10: Maintenance 1 | C10: Surface treatment, SYD | D10: 1 | E10: 4
C11: Paint markings, SFT | D11: 1
B12: Maintenance 2 | C12: Surface treatment, SYD | D12: 1 | E12: 8
C13: Paint markings, SFT | D13: 1
B14: Maintenance 3 | C14: Patching: 0.75% of area | D14: 0.0075 | E14: 12
C15: Crack sealing: 3.25% of area as linear feet | D15: 0.0325
C16: Surface treatment: 100% of area | D16: 1
C17: Paint markings: 100% of markings | D17: 1
B18: Maintenance 4 | C18: Patching: 1.00% of area | D18: 0.01 | E18: 16
C19: Crack sealing: 3.50% of area as linear feet | D19: 0.035
C20: Surface treatment: 100% of area | D20: 1
C21: Paint markings: 100% of markings | D21: 1
B22: Rehabilitation 1 | C22: Mill and overlay: 4-inch cold mill, tack coat, and asphalt overlay | D22: 1 | E22: 20
C23: Pre-overlay crack repair: 1.5% of area as linear feet | D23: 0.015
C24: Pre-overlay patching: 0.5% of area | D24: 0.005
C25: Paint markings: 100% of markings | D25: 1
B26: Maintenance 5 | C26: Surface treatment: 100% of area | D26: 1 | E26: 24
C27: Paint markings: 100% of markings | D27: 1
B28: Maintenance 6 | C28: Patching: 1.25% of area | D28: 0.0125 | E28: 28
C29: Crack sealing: 4.0% of area as linear feet | D29: 0.04
C30: Surface treatment: 100% of area | D30: 1
C31: Paint markings: 100% of markings | D31: 1
B32: Salvage | C32: Salvage value: 2 years (0.125) of mill and overlay | D32: 0.125 | E32: 30
B35: Table 2. New PCC maintenance policies.
B36: Concrete Maintenance | C36: Maintenance Item | D36: Rate | E36: Year Applied
B37: Maintenance 1 | C37: Joint resealing: 100% of joints | D37: 1 | E37: 19
C38: Crack sealing: 0.25% of area as linear feet | D38: 0.0025
C39: Partial-depth patching: 0.13% of area | D39: 0.0013
C40: Full-depth patching: 0.30% of area | D40: 0.003
B41: Rehabilitation 1 | C41: Slab replacements: 2% of area | D41: 0.02 | E41: 27
C42: Full-depth patching: 0.30% of area | D42: 0.003
C43: Partial-depth patching: 0.13% of area | D43: 0.0013
C44: Crack sealing: 0.30% of area as linear feet | D44: 0.003
C45: Joint sealing: 100% of joints | D45: 1
B46: Salvage | C46: Salvage value: 10 years (0.25) of initial construction | D46: 0.25 | E46: 30
B49: Table 3. First HMA Overlay maintenance policies.
B50: Asphalt Maintenance | C50: Maintenance Item | D50: Rate | E50: Year Applied
B51: Maintenance 1 | C51: Surface treatment: 100% of area | D51: 1 | E51: 4
C52: Paint markings: 100% of markings | D52: 1
B53: Maintenance 2 | C53: Patching: 1.25% of area | D53: 0.0125 | E53: 8
C54: Crack sealing: 4.0% of area as linear feet | D54: 0.04
C55: Surface treatment: 100% of area | D55: 1
C56: Paint markings: 100% of markings | D56: 1
B57: Maintenance 3 | C57: Surface treatment, SYD | D57: 1 | E57: 12
C58: Paint markings, SFT | D58: 1
B59: Rehabilitation 2 | C59: Mill and overlay: 4-inch cold mill, tack coat, and asphalt overlay | D59: 1 | E59: 16
C60: Pre-overlay crack repair: 2% of area as linear feet | D60: 0.015
C61: Pre-overlay patching: 1% of area | D61: 0.005
C62: Paint markings: 100% of markings | D62: 1
B63: Maintenance 4 | C63: Surface treatment: 100% of area | D63: 1 | E63: 20
C64: Paint markings: 100% of markings | D64: 1
B65: Maintenance 5 | C65: Patching: 1.25% of area | D65: 0.0125 | E65: 24
C66: Crack sealing: 4.0% of area as linear feet | D66: 0.04
C67: Surface treatment: 100% of area | D67: 1
C68: Paint markings: 100% of markings | D68: 1
B69: Maintenance 6 | C69: Surface treatment: 100% of area | D69: 1 | E69: 28
C70: Paint markings: 100% of markings | D70: 1
B71: Salvage | C71: Salvage value: Need for reconstruction (zero salvage) | D71: 0 | E71: 30
B74: Table 4. PCC rehabilitation maintenance policies.
B75: Concrete Maintenance | C75: Maintenance Item | D75: Rate | E75: Year Applied
B76: Maintenance 1 | C76: Joint resealing: 100% of joints | D76: 1 | E76: 15
C77: Crack sealing: 0.35% of area as linear feet | D77: 0.0035
C78: Partial-depth patching: 0.2% of area | D78: 0.002
C79: Full-depth patching: 0.30% of area | D79: 0.003
B80: Rehabilitation 1 | C80: Slab replacements: 5% of area | D80: 0.05 | E80: 25
C81: Full-depth patching: 0.30% of area | D81: 0.003
C82: Partial-depth patching: 0.15% of area | D82: 0.0015
C83: Crack sealing: 0.30% of area as linear feet | D83: 0.003
C84: Joint sealing: 100% of joints | D84: 1
B85: Salvage | C85: Salvage value: Need for reconstruction (zero salvage) | D85: 0 | E85: 30

Sheet TMP(NewHMA)_IndirectCost
I1: Hidden
A2: Initial Construction Costs: | E2: Average Daily Revenue: | F2: =IF('General Information'!$D$38="Yes",SUMIF(RevenueData!$A:$A,'General Information'!$D$10,RevenueData!$B:$B)+SUMIF(RevenueData!$A:$A,'General Information'!$D$10,RevenueData!$C:$C)+SUMIF(RevenueData!$A:$A,'General Information'!$D$10,RevenueData!$D:$D)+SUMIF(RevenueData!$A:$A,'General Information'!$D$10,RevenueData!$E:$E)+SUMIF(RevenueData!$A:$A,'General Information'!$D$10,RevenueData!$F:$F)+SUMIF(RevenueData!$A:$A,'General Information'!$D$10,RevenueData!$G:$G)+SUMIF(RevenueData!$A:$A,'General Information'!$D$10,RevenueData!$H:$H),0) -> 3239.39 | G2: =IF(AND('General Information'!$D$38="Yes",F2=0),"No revenue data for this airport - lost revenue set to $0. Contact Aeronautics.","") | J2: Maintenance 1 | R2: Maintenance 2 | Z2: Maintenance 3 | AH2: Maintenance 4 | AP2: Rehabilitation 1 | AX2: Maintenance 5 | BF2: Maintenance 6
A4: Pavement Type: | C4: New HMA | E4: Maintenance 1 Duration (Days) | F4: =ROUNDUP((C5/15000),0)+ROUNDUP((C8/20000),0)+ROUNDUP((C8/50000),0) -> 7
A5: Mainline Pavement Area: | C5: ='General Information'!D26 -> 66667 | D5: S.Y. | E5: Maintenance 2 Duration (Days) | F5: =ROUNDUP((C5/15000),0)+ROUNDUP((C8/20000),0)+ROUNDUP((C8/50000),0) -> 7
A6: Initial Construction Year: | C6: ='General Information'!D25 -> 2028 | E6: Maintenance 3 Duration (Days) | F6: =ROUNDUP((C5/15000),0)+ROUNDUP((C8/20000),0)+ROUNDUP((C8/50000),0)+ROUNDUP((C5*'Maintenance Policies'!D15/10000),0)+ROUNDUP((C5*'Maintenance Policies'!D14/5000),0) -> 9 | AP6: Mill and overlay: | AQ6: 2 | AR6: inches
A7: Asphalt Surface Treatment Type: | C7: Emulsified Asphalt Surface Treatment | D7: Select alternative treatment, if planned. | E7: Maintenance 4 Duration (Days) | F7: =ROUNDUP((C5/15000),0)+ROUNDUP((C8/20000),0)+ROUNDUP((C8/50000),0)+ROUNDUP((C5*'Maintenance Policies'!D18/10000),0)+ROUNDUP((C5*'Maintenance Policies'!D19/5000),0) -> 9 | AP7: Asphalt: | AQ7: 120 | AR7: lbs/SY-in
A8: Markings Area: | C8: ='General Information'!D28 -> 15000 | D8: S.F. | E8: Rehabilitation 1 Duration (Days) | F8: =ROUNDUP((C5/3800),0)+ROUNDUP((C8/50000),0) -> 19
E9: Maintenance 5 Duration (Days) | F9: =ROUNDUP((C5/15000),0)+ROUNDUP((C8/20000),0)+ROUNDUP((C8/50000),0) -> 7 | AP9: Tack Coat Application | AQ9: 0.1 | AR9: gal/S.Y.
E10: Maintenance 6 Duration (Days) | F10: =ROUNDUP((C5/15000),0)+ROUNDUP((C8/20000),0)+ROUNDUP((C8/50000),0)+ROUNDUP((C5*'Maintenance Policies'!D28/10000),0)+ROUNDUP((C5*'Maintenance Policies'!D29/5000),0) -> 9
A12: Item No. | B12: Pay Item | C12: Description | D12: Unit | E12: Qty | F12: Unit Cost | G12: Item Cost | J12: Item No. | K12: Pay Item | L12: Description | M12: Unit | N12: Qty | O12: Unit Cost | P12: Item Cost | R12: Item No. | S12: Pay Item | T12: Description | U12: Unit | V12: Qty | W12: Unit Cost | X12: Item Cost | Z12: Item No. | AA12: Pay Item | AB12: Description | AC12: Unit | AD12: Qty | AE12: Unit Cost | AF12: Item Cost | AH12: Item No. | AI12: Pay Item | AJ12: Description | AK12: Unit | AL12: Qty | AM12: Unit Cost | AN12: Item Cost | AP12: Item No. | AQ12: Pay Item | AR12: Description | AS12: Unit | AT12: Qty | AU12: Unit Cost | AV12: Item Cost | AX12: Item No. | AY12: Pay Item | AZ12: Description | BA12: Unit | BB12: Qty | BC12: Unit Cost | BD12: Item Cost | BF12: Item No. | BG12: Pay Item | BH12: Description | BI12: Unit | BJ12: Qty | BK12: Unit Cost | BL12: Item Cost
A13: 1 | B13: =IF(C13="",0,VLOOKUP(C13,CHOOSE({1,2},Table2[Pay Item Description],Table2[Pay Item No.]),2,0)) -> 0 | D13: =IF(C13="","N/A",VLOOKUP(C13,CHOOSE({1,2},Table2[Pay Item Description],Table2[Units]),2,0)) -> N/A | F13: =IF(C13="","N/A",VLOOKUP(C13,CHOOSE({1,2},Table2[Pay Item Description],Table2[Unit Cost]),2,0)) -> N/A | G13: =IF(B13<>0,F13*E13,0) -> 0 | J13: 1 | K13: =IF(L13="",0,VLOOKUP(L13,CHOOSE({1,2},Table2[Pay Item Description],Table2[Pay Item No.]),2,0)) -> P-608-8.1 | L13: =C7 -> Emulsified Asphalt Surface Treatment | M13: =VLOOKUP(L13,CHOOSE({1,2},Table2[Pay Item Description],Table2[Units]),2,0) -> S.Y. | N13: ='Maintenance Policies'!D10*$C$5 -> 66667 | O13: =IF(L13="","N/A",VLOOKUP(L13,CHOOSE({1,2},Table2[Pay Item Description],Table2[Unit Cost]),2,0)) -> 4 | P13: =O13*N13 -> 266668 | R13: 1 | S13: =IF(T13="",0,VLOOKUP(T13,CHOOSE({1,2},Table2[Pay Item Description],Table2[Pay Item No.]),2,0)) -> P-608-8.1 | T13: =C7 -> Emulsified Asphalt Surface Treatment | U13: =VLOOKUP(T13,CHOOSE({1,2},Table2[Pay Item Description],Table2[Units]),2,0) -> S.Y. | V13: ='Maintenance Policies'!D12*$C$5 -> 66667 | W13: =IF(T13="","N/A",VLOOKUP(T13,CHOOSE({1,2},Table2[Pay Item Description],Table2[Unit Cost]),2,0)) -> 4 | X13: =W13*V13 -> 266668 | Z13: 1 | AA13: =IF(AB13="",0,VLOOKUP(AB13,CHOOSE({1,2},Table2[Pay Item Description],Table2[Pay Item No.]),2,0)) -> P-101-5.4a | AB13: =Pay_Items!D11 -> Spall Repair, Asphalt | AC13: =IF(AB13="","N/A",VLOOKUP(AB13,CHOOSE({1,2},Table2[Pay Item Description],Table2[Units]),2,0)) -> S.F. | AD13: ='Maintenance Policies'!D14*($C$5*9) -> 4500.0225 | AE13: =IF(AB13="","N/A",VLOOKUP(AB13,CHOOSE({1,2},Table2[Pay Item Description],Table2[Unit Cost]),2,0)) -> 8.5 | AF13: =AE13*AD13 -> 38250.191 | AH13: 1 | AI13: =IF(AJ13="",0,VLOOKUP(AJ13,CHOOSE({1,2},Table2[Pay Item Description],Table2[Pay Item No.]),2,0)) -> P-101-5.4a | AJ13: =Pay_Items!D11 -> Spall Repair, Asphalt | AK13: =IF(AJ13="","N/A",VLOOKUP(AJ13,CHOOSE({1,2},Table2[Pay Item Description],Table2[Units]),2,0)) -> S.F. | AL13: ='Maintenance Policies'!D18*($C$5*9) -> 6000.03 | AM13: =IF(AJ13="","N/A",VLOOKUP(AJ13,CHOOSE({1,2},Table2[Pay Item Description],Table2[Unit Cost]),2,0)) -> 8.5 | AN13: =AM13*AL13 -> 51000.255 | AP13: 1 | AQ13: =IF(AR13="",0,VLOOKUP(AR13,CHOOSE({1,2},Table2[Pay Item Description],Table2[Pay Item No.]),2,0)) -> P-101-5.6 | AR13: =Pay_Items!D16 -> Cold Milling | AS13: =IF(AR13="","N/A",VLOOKUP(AR13,CHOOSE({1,2},Table2[Pay Item Description],Table2[Units]),2,0)) -> S.Y. | AT13: ='Maintenance Policies'!D22*$C$5 -> 66667 | AU13: =IF(AR13="","N/A",VLOOKUP(AR13,CHOOSE({1,2},Table2[Pay Item Description],Table2[Unit Cost]),2,0)) -> 5 | AV13: =AU13*AT13 -> 333335 | AX13: 1 | AY13: =IF(AZ13="",0,VLOOKUP(AZ13,CHOOSE({1,2},Table2[Pay Item Description],Table2[Pay Item No.]),2,0)) -> P-608-8.1 | AZ13: =C7 -> Emulsified Asphalt Surface Treatment | BA13: =IF(AZ13="","N/A",VLOOKUP(AZ13,CHOOSE({1,2},Table2[Pay Item Description],Table2[Units]),2,0)) -> S.Y. | BB13: ='Maintenance Policies'!D26*$C$5 -> 66667 | BC13: =IF(AZ13="","N/A",VLOOKUP(AZ13,CHOOSE({1,2},Table2[Pay Item Description],Table2[Unit Cost]),2,0)) -> 4 | BD13: =BC13*BB13 -> 266668 | BF13: 1 | BG13: =IF(BH13="",0,VLOOKUP(BH13,CHOOSE({1,2},Table2[Pay Item Description],Table2[Pay Item No.]),2,0)) -> P-101-5.4a | BH13: =Pay_Items!D11 -> Spall Repair, Asphalt | BI13: =IF(BH13="","N/A",VLOOKUP(BH13,CHOOSE({1,2},Table2[Pay Item Description],Table2[Units]),2,0)) -> S.F. | BJ13: ='Maintenance Policies'!D28*($C$5*9) -> 7500.0375 | BK13: =IF(BH13="","N/A",VLOOKUP(BH13,CHOOSE({1,2},Table2[Pay Item Description],Table2[Unit Cost]),2,0)) -> 8.5 | BL13: =BK13*BJ13 -> 63750.319
A14: 2 | B14: =IF(C14="",0,VLOOKUP(C14,CHOOSE({1,2},Table2[Pay Item Description],Table2[Pay Item No.]),2,0)) -> 0 | D14: =IF(C14="","N/A",VLOOKUP(C14,CHOOSE({1,2},Table2[Pay Item Description],Table2[Units]),2,0)) -> N/A | F14: =IF(C14="","N/A",VLOOKUP(C14,CHOOSE({1,2},Table2[Pay Item Description],Table2[Unit Cost]),2,0)) -> N/A | G14: =IF(B14<>0,F14*E14,0) -> 0 | J14: 2 | K14: =IF(L14="",0,VLOOKUP(L14,CHOOSE({1,2},Table2[Pay Item Description],Table2[Pay Item No.]),2,0)) -> P-101-5.3 | L14: =Pay_Items!D10 -> Markings Removal | M14: =IF(L14="","N/A",VLOOKUP(L14,CHOOSE({1,2},Table2[Pay Item Description],Table2[Units]),2,0)) -> S.F. | N14: ='Maintenance Policies'!D10*$C$8 -> 15000 | O14: =IF(L14="","N/A",VLOOKUP(L14,CHOOSE({1,2},Table2[Pay Item Description],Table2[Unit Cost]),2,0)) -> 0.77777778 | P14: =O14*N14 -> 11666.667 | R14: 2 | S14: =IF(T14="",0,VLOOKUP(T14,CHOOSE({1,2},Table2[Pay Item Description],Table2[Pay Item No.]),2,0)) -> P-101-5.3 | T14: =Pay_Items!D10 -> Markings Removal | U14: =IF(T14="","N/A",VLOOKUP(T14,CHOOSE({1,2},Table2[Pay Item Description],Table2[Units]),2,0)) -> S.F. | V14: ='Maintenance Policies'!D12*$C$8 -> 15000 | W14: =IF(T14="","N/A",VLOOKUP(T14,CHOOSE({1,2},Table2[Pay Item Description],Table2[Unit Cost]),2,0)) -> 0.77777778 | X14: =W14*V14 -> 11666.667 | Z14: 2 | AA14: =IF(AB14="",0,VLOOKUP(AB14,CHOOSE({1,2},Table2[Pay Item Description],Table2[Pay Item No.]),2,0)) -> P-101-5.2a | AB14: =Pay_Items!D6 -> Crack Repair (Type I), Asphalt | AC14: =IF(AB14="","N/A",VLOOKUP(AB14,CHOOSE({1,2},Table2[Pay Item Description],Table2[Units]),2,0)) -> L.F. | AD14: ='Maintenance Policies'!D15*($C$5*9) -> 19500.097 | AE14: =IF(AB14="","N/A",VLOOKUP(AB14,CHOOSE({1,2},Table2[Pay Item Description],Table2[Unit Cost]),2,0)) -> 4 | AF14: =AE14*AD14 -> 78000.39 | AH14: 2 | AI14: =IF(AJ14="",0,VLOOKUP(AJ14,CHOOSE({1,2},Table2[Pay Item Description],Table2[Pay Item No.]),2,0)) -> P-101-5.2a | AJ14: =Pay_Items!D6 -> Crack Repair (Type I), Asphalt | AK14: =IF(AJ14="","N/A",VLOOKUP(AJ14,CHOOSE({1,2},Table2[Pay Item Description],Table2[Units]),2,0)) -> L.F. | AL14: ='Maintenance Policies'!D19*($C$5*9) -> 21000.105 | AM14: =IF(AJ14="","N/A",VLOOKUP(AJ14,CHOOSE({1,2},Table2[Pay Item Description],Table2[Unit Cost]),2,0)) -> 4 | AN14: =AM14*AL14 -> 84000.42 | AP14: 2 | AQ14: =IF(AR14="",0,VLOOKUP(AR14,CHOOSE({1,2},Table2[Pay Item Description],Table2[Pay Item No.]),2,0)) -> P-603-5.1 | AR14: =Pay_Items!D54 -> Emulsified Asphalt Tack Coat | AS14: =IF(AR14="","N/A",VLOOKUP(AR14,CHOOSE({1,2},Table2[Pay Item Description],Table2[Units]),2,0)) -> GAL | AT14: ='Maintenance Policies'!D22*$C$5*AQ9 -> 6666.7 | AU14: =IF(AR14="","N/A",VLOOKUP(AR14,CHOOSE({1,2},Table2[Pay Item Description],Table2[Unit Cost]),2,0)) -> 4.5 | AV14: =AU14*AT14 -> 30000.15 | AX14: 2 | AY14: =IF(AZ14="",0,VLOOKUP(AZ14,CHOOSE({1,2},Table2[Pay Item Description],Table2[Pay Item No.]),2,0)) -> P-101-5.3 | AZ14: =Pay_Items!D10 -> Markings Removal | BA14: =IF(AZ14="","N/A",VLOOKUP(AZ14,CHOOSE({1,2},Table2[Pay Item Description],Table2[Units]),2,0)) -> S.F. | BB14: ='Maintenance Policies'!D26*$C$8 -> 15000 | BC14: =IF(AZ14="","N/A",VLOOKUP(AZ14,CHOOSE({1,2},Table2[Pay Item Description],Table2[Unit Cost]),2,0)) -> 0.77777778 | BD14: =BC14*BB14 -> 11666.667 | BF14: 2 | BG14: =IF(BH14="",0,VLOOKUP(BH14,CHOOSE({1,2},Table2[Pay Item Description],Table2[Pay Item No.]),2,0)) -> P-101-5.2a | BH14: =Pay_Items!D6 -> Crack Repair (Type I), Asphalt | BI14: =IF(BH14="","N/A",VLOOKUP(BH14,CHOOSE({1,2},Table2[Pay Item Description],Table2[Units]),2,0)) -> L.F. | BJ14: ='Maintenance Policies'!D29*($C$5*9) -> 24000.12 | BK14: =IF(BH14="","N/A",VLOOKUP(BH14,CHOOSE({1,2},Table2[Pay Item Description],Table2[Unit Cost]),2,0)) -> 4 | BL14: =BK14*BJ14 -> 96000.48
A15: 3 | B15: =IF(C15="",0,VLOOKUP(C15,CHOOSE({1,2},Table2[Pay Item Description],Table2[Pay Item No.]),2,0)) -> 0 | D15: =IF(C15="","N/A",VLOOKUP(C15,CHOOSE({1,2},Table2[Pay Item Description],Table2[Units]),2,0)) -> N/A | F15: =IF(C15="","N/A",VLOOKUP(C15,CHOOSE({1,2},Table2[Pay Item Description],Table2[Unit Cost]),2,0)) -> N/A | G15: =IF(B15<>0,F15*E15,0) -> 0 | J15: 3 | K15: =IF(L15="",0,VLOOKUP(L15,CHOOSE({1,2},Table2[Pay Item Description],Table2[Pay Item No.]),2,0)) -> P-620-5.1a | L15: =Pay_Items!D56 -> Markings (prep, markings, reflective media) | M15: =IF(L15="","N/A",VLOOKUP(L15,CHOOSE({1,2},Table2[Pay Item Description],Table2[Units]),2,0)) -> S.F. | N15: ='Maintenance Policies'!D11*$C$8 -> 15000 | O15: =IF(L15="","N/A",VLOOKUP(L15,CHOOSE({1,2},Table2[Pay Item Description],Table2[Unit Cost]),2,0)) -> 0.66666667 | P15: =O15*N15 -> 10000 | R15: 3 | S15: =IF(T15="",0,VLOOKUP(T15,CHOOSE({1,2},Table2[Pay Item Description],Table2[Pay Item No.]),2,0)) -> P-620-5.1a | T15: =Pay_Items!D56 -> Markings (prep, markings, reflective media) | U15: =Pay_Items!E56 -> S.F. | V15: ='Maintenance Policies'!D13*$C$8 -> 15000 | W15: =IF(T15="","N/A",VLOOKUP(T15,CHOOSE({1,2},Table2[Pay Item Description],Table2[Unit Cost]),2,0)) -> 0.66666667 | X15: =W15*V15 -> 10000 | Z15: 3 | AA15: =IF(AB15="",0,VLOOKUP(AB15,CHOOSE({1,2},Table2[Pay Item Description],Table2[Pay Item No.]),2,0)) -> P-608-8.1 | AB15: =C7 -> Emulsified Asphalt Surface Treatment | AC15: =IF(AB15="","N/A",VLOOKUP(AB15,CHOOSE({1,2},Table2[Pay Item Description],Table2[Units]),2,0)) -> S.Y. | AD15: ='Maintenance Policies'!D16*$C$5 -> 66667 | AE15: =IF(AB15="","N/A",VLOOKUP(AB15,CHOOSE({1,2},Table2[Pay Item Description],Table2[Unit Cost]),2,0)) -> 4 | AF15: =AE15*AD15 -> 266668 | AH15: 3 | AI15: =IF(AJ15="",0,VLOOKUP(AJ15,CHOOSE({1,2},Table2[Pay Item Description],Table2[Pay Item No.]),2,0)) -> P-608-8.1 | AJ15: =C7 -> Emulsified Asphalt Surface Treatment | AK15: =IF(AJ15="","N/A",VLOOKUP(AJ15,CHOOSE({1,2},Table2[Pay Item Description],Table2[Units]),2,0)) -> S.Y. | AL15: ='Maintenance Policies'!D20*$C$5 -> 66667 | AM15: =IF(AJ15="","N/A",VLOOKUP(AJ15,CHOOSE({1,2},Table2[Pay Item Description],Table2[Unit Cost]),2,0)) -> 4 | AN15: =AM15*AL15 -> 266668 | AP15: 3 | AQ15: =IF(AR15="",0,VLOOKUP(AR15,CHOOSE({1,2},Table2[Pay Item Description],Table2[Pay Item No.]),2,0)) -> P-401-8.1a | AR15: =Pay_Items!D37 -> Asphalt Surface Course | AS15: =IF(AR15="","N/A",VLOOKUP(AR15,CHOOSE({1,2},Table2[Pay Item Description],Table2[Units]),2,0)) -> TON | AT15: ='Maintenance Policies'!D22*$C$5*AQ6*AQ7/2000 -> 8000.04 | AU15: =IF(AR15="","N/A",VLOOKUP(AR15,CHOOSE({1,2},Table2[Pay Item Description],Table2[Unit Cost]),2,0)) -> 130 | AV15: =AU15*AT15 -> 1040005.2 | AX15: 3 | AY15: =IF(AZ15="",0,VLOOKUP(AZ15,CHOOSE({1,2},Table2[Pay Item Description],Table2[Pay Item No.]),2,0)) -> P-620-5.1a | AZ15: =Pay_Items!D56 -> Markings (prep, markings, reflective media) | BA15: =IF(AZ15="","N/A",VLOOKUP(AZ15,CHOOSE({1,2},Table2[Pay Item Description],Table2[Units]),2,0)) -> S.F. | BB15: ='Maintenance Policies'!D27*$C$8 -> 15000 | BC15: =IF(AZ15="","N/A",VLOOKUP(AZ15,CHOOSE({1,2},Table2[Pay Item Description],Table2[Unit Cost]),2,0)) -> 0.66666667 | BD15: =BC15*BB15 -> 10000 | BF15: 3 | BG15: =IF(BH15="",0,VLOOKUP(BH15,CHOOSE({1,2},Table2[Pay Item Description],Table2[Pay Item No.]),2,0)) -> P-608-8.1 | BH15: =C7 -> Emulsified Asphalt Surface Treatment | BI15: =IF(BH15="","N/A",VLOOKUP(BH15,CHOOSE({1,2},Table2[Pay Item Description],Table2[Units]),2,0)) -> S.Y. | BJ15: ='Maintenance Policies'!D30*$C$5 -> 66667 | BK15: =IF(BH15="","N/A",VLOOKUP(BH15,CHOOSE({1,2},Table2[Pay Item Description],Table2[Unit Cost]),2,0)) -> 4 | BL15: =BK15*BJ15 -> 266668
A16: 4 | B16: =IF(C16="",0,VLOOKUP(C16,CHOOSE({1,2},Table2[Pay Item Description],Table2[Pay Item No.]),2,0)) -> 0 | D16: =IF(C16="","N/A",VLOOKUP(C16,CHOOSE({1,2},Table2[Pay Item Description],Table2[Units]),2,0)) -> N/A | F16: =IF(C16="","N/A",VLOOKUP(C16,CHOOSE({1,2},Table2[Pay Item Description],Table2[Unit Cost]),2,0)) -> N/A | G16: =IF(B16<>0,F16*E16,0) -> 0 | O16: Subtotal | P16: =SUM(P13:P15) -> 288334.67 | W16: Subtotal | X16: =SUM(X13:X15) -> 288334.67 | Z16: 4 | AA16: =IF(AB16="",0,VLOOKUP(AB16,CHOOSE({1,2},Table2[Pay Item Description],Table2[Pay Item No.]),2,0)) -> P-101-5.3 | AB16: =Pay_Items!D10 -> Markings Removal | AC16: =IF(AB16="","N/A",VLOOKUP(AB16,CHOOSE({1,2},Table2[Pay Item Description],Table2[Units]),2,0)) -> S.F. | AD16: ='Maintenance Policies'!D16*$C$8 -> 15000 | AE16: =IF(AB16="","N/A",VLOOKUP(AB16,CHOOSE({1,2},Table2[Pay Item Description],Table2[Unit Cost]),2,0)) -> 0.77777778 | AF16: =AE16*AD16 -> 11666.667 | AH16: 4 | AI16: =IF(AJ16="",0,VLOOKUP(AJ16,CHOOSE({1,2},Table2[Pay Item Description],Table2[Pay Item No.]),2,0)) -> P-101-5.3 | AJ16: =Pay_Items!D10 -> Markings Removal | AK16: =IF(AJ16="","N/A",VLOOKUP(AJ16,CHOOSE({1,2},Table2[Pay Item Description],Table2[Units]),2,0)) -> S.F. | AL16: ='Maintenance Policies'!D20*$C$8 -> 15000 | AM16: =IF(AJ16="","N/A",VLOOKUP(AJ16,CHOOSE({1,2},Table2[Pay Item Description],Table2[Unit Cost]),2,0)) -> 0.77777778 | AN16: =AM16*AL16 -> 11666.667 | AP16: 4 | AQ16: =IF(AR16="",0,VLOOKUP(AR16,CHOOSE({1,2},Table2[Pay Item Description],Table2[Pay Item No.]),2,0)) -> P-101-5.2a | AR16: =Pay_Items!D6 -> Crack Repair (Type I), Asphalt | AS16: =IF(AR16="","N/A",VLOOKUP(AR16,CHOOSE({1,2},Table2[Pay Item Description],Table2[Units]),2,0)) -> L.F. | AT16: ='Maintenance Policies'!D23*($C$5*9) -> 9000.045 | AU16: =IF(AR16="","N/A",VLOOKUP(AR16,CHOOSE({1,2},Table2[Pay Item Description],Table2[Unit Cost]),2,0)) -> 4 | AV16: =AU16*AT16 -> 36000.18 | BC16: Subtotal | BD16: =SUM(BD13:BD15) -> 288334.67 | BF16: 4 | BG16: =IF(BH16="",0,VLOOKUP(BH16,CHOOSE({1,2},Table2[Pay Item Description],Table2[Pay Item No.]),2,0)) -> P-101-5.3 | BH16: =Pay_Items!D10 -> Markings Removal | BI16: =IF(BH16="","N/A",VLOOKUP(BH16,CHOOSE({1,2},Table2[Pay Item Description],Table2[Units]),2,0)) -> S.F. | BJ16: =C8 -> 15000 | BK16: =IF(BH16="","N/A",VLOOKUP(BH16,CHOOSE({1,2},Table2[Pay Item Description],Table2[Unit Cost]),2,0)) -> 0.77777778 | BL16: =BK16*BJ16 -> 11666.667
A17: 5 | B17: =IF(C17="",0,VLOOKUP(C17,CHOOSE({1,2},Table2[Pay Item Description],Table2[Pay Item No.]),2,0)) -> 0 | D17: =IF(C17="","N/A",VLOOKUP(C17,CHOOSE({1,2},Table2[Pay Item Description],Table2[Units]),2,0)) -> N/A | F17: =IF(C17="","N/A",VLOOKUP(C17,CHOOSE({1,2},Table2[Pay Item Description],Table2[Unit Cost]),2,0)) -> N/A | G17: =IF(B17<>0,F17*E17,0) -> 0 | L17: Mobilization | P17: =('General Information'!$D$36/100)*P16 -> 28833.467 | T17: Mobilization | X17: =('General Information'!$D$36/100)*X16 -> 28833.467 | Z17: 5 | AA17: =IF(AB17="",0,VLOOKUP(AB17,CHOOSE({1,2},Table2[Pay Item Description],Table2[Pay Item No.]),2,0)) -> P-620-5.1a | AB17: =Pay_Items!D56 -> Markings (prep, markings, reflective media) | AC17: =IF(AB17="","N/A",VLOOKUP(AB17,CHOOSE({1,2},Table2[Pay Item Description],Table2[Units]),2,0)) -> S.F. | AD17: ='Maintenance Policies'!D17*$C$8 -> 15000 | AE17: =IF(AB17="","N/A",VLOOKUP(AB17,CHOOSE({1,2},Table2[Pay Item Description],Table2[Unit Cost]),2,0)) -> 0.66666667 | AF17: =AE17*AD17 -> 10000 | AH17: 5 | AI17: =IF(AJ17="",0,VLOOKUP(AJ17,CHOOSE({1,2},Table2[Pay Item Description],Table2[Pay Item No.]),2,0)) -> P-620-5.1a | AJ17: =Pay_Items!D56 -> Markings (prep, markings, reflective media) | AK17: =IF(AJ17="","N/A",VLOOKUP(AJ17,CHOOSE({1,2},Table2[Pay Item Description],Table2[Units]),2,0)) -> S.F. | AL17: ='Maintenance Policies'!D21*$C$8 -> 15000 | AM17: =IF(AJ17="","N/A",VLOOKUP(AJ17,CHOOSE({1,2},Table2[Pay Item Description],Table2[Unit Cost]),2,0)) -> 0.66666667 | AN17: =AM17*AL17 -> 10000 | AP17: 5 | AQ17: =IF(AR17="",0,VLOOKUP(AR17,CHOOSE({1,2},Table2[Pay Item Description],Table2[Pay Item No.]),2,0)) -> P-101-5.4a | AR17: =Pay_Items!D11 -> Spall Repair, Asphalt | AS17: =IF(AR17="","N/A",VLOOKUP(AR17,CHOOSE({1,2},Table2[Pay Item Description],Table2[Units]),2,0)) -> S.F. | AT17: ='Maintenance Policies'!D24*($C$5*9) -> 3000.015 | AU17: =IF(AR17="","N/A",VLOOKUP(AR17,CHOOSE({1,2},Table2[Pay Item Description],Table2[Unit Cost]),2,0)) -> 8.5 | AV17: =AU17*AT17 -> 25500.127 | AZ17: Mobilization | BD17: =('General Information'!$D$36/100)*BD16 -> 28833.467 | BF17: 5 | BG17: =IF(BH17="",0,VLOOKUP(BH17,CHOOSE({1,2},Table2[Pay Item Description],Table2[Pay Item No.]),2,0)) -> P-620-5.1a | BH17: =Pay_Items!D56 -> Markings (prep, markings, reflective media) | BI17: =IF(BH17="","N/A",VLOOKUP(BH17,CHOOSE({1,2},Table2[Pay Item Description],Table2[Units]),2,0)) -> S.F. | BJ17: ='Maintenance Policies'!D31*$C$8 -> 15000 | BK17: =IF(BH17="","N/A",VLOOKUP(BH17,CHOOSE({1,2},Table2[Pay Item Description],Table2[Unit Cost]),2,0)) -> 0.66666667 | BL17: =BK17*BJ17 -> 10000
A18: 6 | B18: =IF(C18="",0,VLOOKUP(C18,CHOOSE({1,2},Table2[Pay Item Description],Table2[Pay Item No.]),2,0)) -> 0 | D18: =IF(C18="","N/A",VLOOKUP(C18,CHOOSE({1,2},Table2[Pay Item Description],Table2[Units]),2,0)) -> N/A | F18: =IF(C18="","N/A",VLOOKUP(C18,CHOOSE({1,2},Table2[Pay Item Description],Table2[Unit Cost]),2,0)) -> N/A | G18: =IF(B18<>0,F18*E18,0) -> 0 | L18: Engineering | P18: =('General Information'!$D$37/100)*P16 -> 14416.733 | T18: Engineering | X18: =('General Information'!$D$37/100)*X16 -> 14416.733 | AE18: Subtotal | AF18: =SUM(AF13:AF17) -> 404585.25 | AM18: Subtotal | AN18: =SUM(AN13:AN17) -> 423335.34 | AP18: 6 | AQ18: =IF(AR18="",0,VLOOKUP(AR18,CHOOSE({1,2},Table2[Pay Item Description],Table2[Pay Item No.]),2,0)) -> P-620-5.1a | AR18: =Pay_Items!D56 -> Markings (prep, markings, reflective media) | AS18: =IF(AR18="","N/A",VLOOKUP(AR18,CHOOSE({1,2},Table2[Pay Item Description],Table2[Units]),2,0)) -> S.F. | AT18: ='Maintenance Policies'!D25*$C$8 -> 15000 | AU18: =IF(AR18="","N/A",VLOOKUP(AR18,CHOOSE({1,2},Table2[Pay Item Description],Table2[Unit Cost]),2,0)) -> 0.66666667 | AV18: =AU18*AT18 -> 10000 | AZ18: Engineering | BD18: =('General Information'!$D$37/100)*BD16 -> 14416.733 | BK18: Subtotal | BL18: =SUM(BL13:BL17) -> 448085.47
A19: 7 | B19: =IF(C19="",0,VLOOKUP(C19,CHOOSE({1,2},Table2[Pay Item Description],Table2[Pay Item No.]),2,0)) -> 0 | D19: =IF(C19="","N/A",VLOOKUP(C19,CHOOSE({1,2},Table2[Pay Item Description],Table2[Units]),2,0)) -> N/A | F19: =IF(C19="","N/A",VLOOKUP(C19,CHOOSE({1,2},Table2[Pay Item Description],Table2[Unit Cost]),2,0)) -> N/A | G19: =IF(B19<>0,F19*E19,0) -> 0 | O19: Total | P19: =SUM(P16:P18) -> 331584.87 | W19: Total | X19: =SUM(X16:X18) -> 331584.87 | AB19: Mobilization | AF19: =('General Information'!$D$36/100)*AF18 -> 40458.525 | AJ19: Mobilization | AN19: =('General Information'!$D$36/100)*AN18 -> 42333.534 | AU19: Subtotal | AV19: =SUM(AV13:AV18) -> 1474840.7 | BC19: Total | BD19: =SUM(BD16:BD18) -> 331584.87 | BH19: Mobilization | BL19: =('General Information'!$D$36/100)*BL18 -> 44808.547
A20: 8 | B20: =IF(C20="",0,VLOOKUP(C20,CHOOSE({1,2},Table2[Pay Item Description],Table2[Pay Item No.]),2,0)) -> 0 | D20: =IF(C20="","N/A",VLOOKUP(C20,CHOOSE({1,2},Table2[Pay Item Description],Table2[Units]),2,0)) -> N/A | F20: =IF(C20="","N/A",VLOOKUP(C20,CHOOSE({1,2},Table2[Pay Item Description],Table2[Unit Cost]),2,0)) -> N/A | G20: =IF(B20<>0,F20*E20,0) -> 0 | AB20: Engineering | AF20: =('General Information'!$D$37/100)*AF18 -> 20229.262 | AJ20: Engineering | AN20: =('General Information'!$D$37/100)*AN18 -> 21166.767 | AR20: Mobilization | AV20: =('General Information'!$D$36/100)*AV19 -> 147484.07 | BH20: Engineering | BL20: =('General Information'!$D$37/100)*BL18 -> 22404.273
A21: 9 | B21: =IF(C21="",0,VLOOKUP(C21,CHOOSE({1,2},Table2[Pay Item Description],Table2[Pay Item No.]),2,0)) -> 0 | D21: =IF(C21="","N/A",VLOOKUP(C21,CHOOSE({1,2},Table2[Pay Item Description],Table2[Units]),2,0)) -> N/A | F21: =IF(C21="","N/A",VLOOKUP(C21,CHOOSE({1,2},Table2[Pay Item Description],Table2[Unit Cost]),2,0)) -> N/A | G21: =IF(B21<>0,F21*E21,0) -> 0 | AE21: Total | AF21: =SUM(AF18:AF20) -> 465273.04 | AM21: Total | AN21: =SUM(AN18:AN20) -> 486835.64 | AR21: Engineering | AV21: =('General Information'!$D$37/100)*AV19 -> 73742.033 | BK21: Total | BL21: =SUM(BL18:BL20) -> 515298.29
A22: 10 | B22: =IF(C22="",0,VLOOKUP(C22,CHOOSE({1,2},Table2[Pay Item Description],Table2[Pay Item No.]),2,0)) -> 0 | D22: =IF(C22="","N/A",VLOOKUP(C22,CHOOSE({1,2},Table2[Pay Item Description],Table2[Units]),2,0)) -> N/A | F22: =IF(C22="","N/A",VLOOKUP(C22,CHOOSE({1,2},Table2[Pay Item Description],Table2[Unit Cost]),2,0)) -> N/A | G22: =IF(B22<>0,F22*E22,0) -> 0 | AU22: Total | AV22: =SUM(AV19:AV21) -> 1696066.8
A24: Subtotal | G24: =SUM(G13:G22) -> 0
B25: Mobilization | G25: =('General Information'!$D$36/100)*G24 -> 0
B26: Engineering | G26: =('General Information'!$D$37/100)*G24 -> 0
A27: Total | G27: =SUM(G24:G26) -> 0
A32: Net Present Worth
A33: HMA Reconstruction - Alternative 1 | I33: Hidden
B35: Item | C35: Year Applied | D35: Actual Cost | E35: Discounted Cost
B36: Initial Construction | C36: =C6 -> 2028 | D36: =G27 -> 0 | E36: =D36 -> 0 | K36: Year | L36: Direct Cost | M36: Indirect Cost | N36: Total Discounted Cost
B37: Maintenance 1 | C37: ='Maintenance Policies'!E10 -> 4 | D37: =P19 -> 331584.87 | E37: =IF(C37>'General Information'!$D$33,0,D37/(1+('General Information'!$D$34/100))^C37) -> 294608.86 | K37: =C6 -> 2028 | L37: =IF(K37-$C$6>'General Information'!$D$33,0,IF(K37=$C$6,$D$36,0)+SUMIFS($D$37:$D$51,$C$37:$C$51,K37-$C$6,$B$37:$B$51,"<>*Indirect*")) -> 0 | M37: =IF(K37-$C$6>'General Information'!$D$33,0,SUMIFS($D$37:$D$51,$C$37:$C$51,K37-$C$6,$B$37:$B$51,"*Indirect*")) -> 0 | N37: =IF(K37-$C$6>'General Information'!$D$33,0,IF(K37=$C$6,$E$36,0)+SUMIF($C$37:$C$51,K37-$C$6,$E$37:$E$51)) -> 0
B38: Maintenance 1 Indirect Cost | C38: ='Maintenance Policies'!E10 -> 4 | D38: =F2*F4 -> 22675.73 | E38: =IF(C38>'General Information'!$D$33,0,D38/(1+('General Information'!$D$34/100))^C38) -> 20147.092 | K38: =K37+1 -> 2029 | L38: =IF(K38-$C$6>'General Information'!$D$33,0,IF(K38=$C$6,$D$36,0)+SUMIFS($D$37:$D$51,$C$37:$C$51,K38-$C$6,$B$37:$B$51,"<>*Indirect*")) -> 0 | M38: =IF(K38-$C$6>'General Information'!$D$33,0,SUMIFS($D$37:$D$51,$C$37:$C$51,K38-$C$6,$B$37:$B$51,"*Indirect*")) -> 0 | N38: =IF(K38-$C$6>'General Information'!$D$33,0,IF(K38=$C$6,$E$36,0)+SUMIF($C$37:$C$51,K38-$C$6,$E$37:$E$51)) -> 0
B39: Maintenance 2 | C39: ='Maintenance Policies'!E12 -> 8 | D39: =X19 -> 331584.87 | E39: =IF(C39>'General Information'!$D$33,0,D39/(1+('General Information'!$D$34/100))^C39) -> 261756.16 | K39: =K38+1 -> 2030 | L39: =IF(K39-$C$6>'General Information'!$D$33,0,IF(K39=$C$6,$D$36,0)+SUMIFS($D$37:$D$51,$C$37:$C$51,K39-$C$6,$B$37:$B$51,"<>*Indirect*")) -> 0 | M39: =IF(K39-$C$6>'General Information'!$D$33,0,SUMIFS($D$37:$D$51,$C$37:$C$51,K39-$C$6,$B$37:$B$51,"*Indirect*")) -> 0 | N39: =IF(K39-$C$6>'General Information'!$D$33,0,IF(K39=$C$6,$E$36,0)+SUMIF($C$37:$C$51,K39-$C$6,$E$37:$E$51)) -> 0
B40: Maintenance 2 Indirect Cost | C40: ='Maintenance Policies'!E12 -> 8 | D40: =F2*F5 -> 22675.73 | E40: =IF(C40>'General Information'!$D$33,0,D40/(1+('General Information'!$D$34/100))^C40) -> 17900.431 | K40: =K39+1 -> 2031 | L40: =IF(K40-$C$6>'General Information'!$D$33,0,IF(K40=$C$6,$D$36,0)+SUMIFS($D$37:$D$51,$C$37:$C$51,K40-$C$6,$B$37:$B$51,"<>*Indirect*")) -> 0 | M40: =IF(K40-$C$6>'General Information'!$D$33,0,SUMIFS($D$37:$D$51,$C$37:$C$51,K40-$C$6,$B$37:$B$51,"*Indirect*")) -> 0 | N40: =IF(K40-$C$6>'General Information'!$D$33,0,IF(K40=$C$6,$E$36,0)+SUMIF($C$37:$C$51,K40-$C$6,$E$37:$E$51)) -> 0
B41: Maintenance 3 | C41: ='Maintenance Policies'!E14 -> 12 | D41: =AF21 -> 465273.04 | E41: =IF(C41>'General Information'!$D$33,0,D41/(1+('General Information'!$D$34/100))^C41) -> 326333.15 | K41: =K40+1 -> 2032 | L41: =IF(K41-$C$6>'General Information'!$D$33,0,IF(K41=$C$6,$D$36,0)+SUMIFS($D$37:$D$51,$C$37:$C$51,K41-$C$6,$B$37:$B$51,"<>*Indirect*")) -> 331584.87 | M41: =IF(K41-$C$6>'General Information'!$D$33,0,SUMIFS($D$37:$D$51,$C$37:$C$51,K41-$C$6,$B$37:$B$51,"*Indirect*")) -> 22675.73 | N41: =IF(K41-$C$6>'General Information'!$D$33,0,IF(K41=$C$6,$E$36,0)+SUMIF($C$37:$C$51,K41-$C$6,$E$37:$E$51)) -> 314755.95
B42: Maintenance 3 Indirect Cost | C42: ='Maintenance Policies'!E14 -> 12 | D42: =F2*F6 -> 29154.51 | E42: =IF(C42>'General Information'!$D$33,0,D42/(1+('General Information'!$D$34/100))^C42) -> 20448.387 | K42: =K41+1 -> 2033 | L42: =IF(K42-$C$6>'General Information'!$D$33,0,IF(K42=$C$6,$D$36,0)+SUMIFS($D$37:$D$51,$C$37:$C$51,K42-$C$6,$B$37:$B$51,"<>*Indirect*")) -> 0 | M42: =IF(K42-$C$6>'General Information'!$D$33,0,SUMIFS($D$37:$D$51,$C$37:$C$51,K42-$C$6,$B$37:$B$51,"*Indirect*")) -> 0 | N42: =IF(K42-$C$6>'General Information'!$D$33,0,IF(K42=$C$6,$E$36,0)+SUMIF($C$37:$C$51,K42-$C$6,$E$37:$E$51)) -> 0
B43: Maintenance 4 | C43: ='Maintenance Policies'!E18 -> 16 | D43: =AN21 -> 486835.64 | E43: =IF(C43>'General Information'!$D$33,0,D43/(1+('General Information'!$D$34/100))^C43) -> 303379.88 | K43: =K42+1 -> 2034 | L43: =IF(K43-$C$6>'General Information'!$D$33,0,IF(K43=$C$6,$D$36,0)+SUMIFS($D$37:$D$51,$C$37:$C$51,K43-$C$6,$B$37:$B$51,"<>*Indirect*")) -> 0 | M43: =IF(K43-$C$6>'General Information'!$D$33,0,SUMIFS($D$37:$D$51,$C$37:$C$51,K43-$C$6,$B$37:$B$51,"*Indirect*")) -> 0 | N43: =IF(K43-$C$6>'General Information'!$D$33,0,IF(K43=$C$6,$E$36,0)+SUMIF($C$37:$C$51,K43-$C$6,$E$37:$E$51)) -> 0
B44: Maintenance 4 Indirect Cost | C44: ='Maintenance Policies'!E18 -> 16 | D44: =F2*F7 -> 29154.51 | E44: =IF(C44>'General Information'!$D$33,0,D44/(1+('General Information'!$D$34/100))^C44) -> 18168.127 | K44: =K43+1 -> 2035 | L44: =IF(K44-$C$6>'General Information'!$D$33,0,IF(K44=$C$6,$D$36,0)+SUMIFS($D$37:$D$51,$C$37:$C$51,K44-$C$6,$B$37:$B$51,"<>*Indirect*")) -> 0 | M44: =IF(K44-$C$6>'General Information'!$D$33,0,SUMIFS($D$37:$D$51,$C$37:$C$51,K44-$C$6,$B$37:$B$51,"*Indirect*")) -> 0 | N44: =IF(K44-$C$6>'General Information'!$D$33,0,IF(K44=$C$6,$E$36,0)+SUMIF($C$37:$C$51,K44-$C$6,$E$37:$E$51)) -> 0
B45: Rehabilitation 1 | C45: ='Maintenance Policies'!E22 -> 20 | D45: =AV22 -> 1696066.8 | E45: =IF(C45>'General Information'!$D$33,0,D45/(1+('General Information'!$D$34/100))^C45) -> 939071.04 | K45: =K44+1 -> 2036 | L45: =IF(K45-$C$6>'General Information'!$D$33,0,IF(K45=$C$6,$D$36,0)+SUMIFS($D$37:$D$51,$C$37:$C$51,K45-$C$6,$B$37:$B$51,"<>*Indirect*")) -> 331584.87 | M45: =IF(K45-$C$6>'General Information'!$D$33,0,SUMIFS($D$37:$D$51,$C$37:$C$51,K45-$C$6,$B$37:$B$51,"*Indirect*")) -> 22675.73 | N45: =IF(K45-$C$6>'General Information'!$D$33,0,IF(K45=$C$6,$E$36,0)+SUMIF($C$37:$C$51,K45-$C$6,$E$37:$E$51)) -> 279656.59
B46: Rehabilitation 1 Indirect Cost | C46: ='Maintenance Policies'!E22 -> 20 | D46: =F2*F8 -> 61548.41 | E46: =IF(C46>'General Information'!$D$33,0,D46/(1+('General Information'!$D$34/100))^C46) -> 34077.862 | K46: =K45+1 -> 2037 | L46: =IF(K46-$C$6>'General Information'!$D$33,0,IF(K46=$C$6,$D$36,0)+SUMIFS($D$37:$D$51,$C$37:$C$51,K46-$C$6,$B$37:$B$51,"<>*Indirect*")) -> 0 | M46: =IF(K46-$C$6>'General Information'!$D$33,0,SUMIFS($D$37:$D$51,$C$37:$C$51,K46-$C$6,$B$37:$B$51,"*Indirect*")) -> 0 | N46: =IF(K46-$C$6>'General Information'!$D$33,0,IF(K46=$C$6,$E$36,0)+SUMIF($C$37:$C$51,K46-$C$6,$E$37:$E$51)) -> 0
B47: Maintenance 5 | C47: ='Maintenance Policies'!E26 -> 24 | D47: =BD19 -> 331584.87 | E47: =IF(C47>'General Information'!$D$33,0,D47/(1+('General Information'!$D$34/100))^C47) -> 163117.78 | K47: =K46+1 -> 2038 | L47: =IF(K47-$C$6>'General Information'!$D$33,0,IF(K47=$C$6,$D$36,0)+SUMIFS($D$37:$D$51,$C$37:$C$51,K47-$C$6,$B$37:$B$51,"<>*Indirect*")) -> 0 | M47: =IF(K47-$C$6>'General Information'!$D$33,0,SUMIFS($D$37:$D$51,$C$37:$C$51,K47-$C$6,$B$37:$B$51,"*Indirect*")) -> 0 | N47: =IF(K47-$C$6>'General Information'!$D$33,0,IF(K47=$C$6,$E$36,0)+SUMIF($C$37:$C$51,K47-$C$6,$E$37:$E$51)) -> 0
B48: Maintenance 5 Indirect Cost | C48: ='Maintenance Policies'!E26 -> 24 | D48: =F2*F9 -> 22675.73 | E48: =IF(C48>'General Information'!$D$33,0,D48/(1+('General Information'!$D$34/100))^C48) -> 11154.957 | K48: =K47+1 -> 2039 | L48: =IF(K48-$C$6>'General Information'!$D$33,0,IF(K48=$C$6,$D$36,0)+SUMIFS($D$37:$D$51,$C$37:$C$51,K48-$C$6,$B$37:$B$51,"<>*Indirect*")) -> 0 | M48: =IF(K48-$C$6>'General Information'!$D$33,0,SUMIFS($D$37:$D$51,$C$37:$C$51,K48-$C$6,$B$37:$B$51,"*Indirect*")) -> 0 | N48: =IF(K48-$C$6>'General Information'!$D$33,0,IF(K48=$C$6,$E$36,0)+SUMIF($C$37:$C$51,K48-$C$6,$E$37:$E$51)) -> 0
B49: Maintenance 6 | C49: ='Maintenance Policies'!E28 -> 28 | D49: =BL21 -> 515298.29 | E49: =IF(C49>'General Information'!$D$33,0,D49/(1+('General Information'!$D$34/100))^C49) -> 225224.9 | K49: =K48+1 -> 2040 | L49: =IF(K49-$C$6>'General Information'!$D$33,0,IF(K49=$C$6,$D$36,0)+SUMIFS($D$37:$D$51,$C$37:$C$51,K49-$C$6,$B$37:$B$51,"<>*Indirect*")) -> 465273.04 | M49: =IF(K49-$C$6>'General Information'!$D$33,0,SUMIFS($D$37:$D$51,$C$37:$C$51,K49-$C$6,$B$37:$B$51,"*Indirect*")) -> 29154.51 | N49: =IF(K49-$C$6>'General Information'!$D$33,0,IF(K49=$C$6,$E$36,0)+SUMIF($C$37:$C$51,K49-$C$6,$E$37:$E$51)) -> 346781.53
B50: Maintenance 6 Indirect Cost | C50: ='Maintenance Policies'!E28 -> 28 | D50: =F2*F10 -> 29154.51 | E50: =IF(C50>'General Information'!$D$33,0,D50/(1+('General Information'!$D$34/100))^C50) -> 12742.759 | K50: =K49+1 -> 2041 | L50: =IF(K50-$C$6>'General Information'!$D$33,0,IF(K50=$C$6,$D$36,0)+SUMIFS($D$37:$D$51,$C$37:$C$51,K50-$C$6,$B$37:$B$51,"<>*Indirect*")) -> 0 | M50: =IF(K50-$C$6>'General Information'!$D$33,0,SUMIFS($D$37:$D$51,$C$37:$C$51,K50-$C$6,$B$37:$B$51,"*Indirect*")) -> 0 | N50: =IF(K50-$C$6>'General Information'!$D$33,0,IF(K50=$C$6,$E$36,0)+SUMIF($C$37:$C$51,K50-$C$6,$E$37:$E$51)) -> 0
B51: Salvage | C51: ='General Information'!D33 -> 30 | D51: =-'Maintenance Policies'!D32*AV22 -> -212008.34 | E51: =IF(C51>'General Information'!$D$33,0,D51/(1+('General Information'!$D$34/100))^C51) -> -87344.631 | K51: =K50+1 -> 2042 | L51: =IF(K51-$C$6>'General Information'!$D$33,0,IF(K51=$C$6,$D$36,0)+SUMIFS($D$37:$D$51,$C$37:$C$51,K51-$C$6,$B$37:$B$51,"<>*Indirect*")) -> 0 | M51: =IF(K51-$C$6>'General Information'!$D$33,0,SUMIFS($D$37:$D$51,$C$37:$C$51,K51-$C$6,$B$37:$B$51,"*Indirect*")) -> 0 | N51: =IF(K51-$C$6>'General Information'!$D$33,0,IF(K51=$C$6,$E$36,0)+SUMIF($C$37:$C$51,K51-$C$6,$E$37:$E$51)) -> 0
B52: Net Present Worth | E52: =SUM(E36:E51) -> 2560786.7 | K52: =K51+1 -> 2043 | L52: =IF(K52-$C$6>'General Information'!$D$33,0,IF(K52=$C$6,$D$36,0)+SUMIFS($D$37:$D$51,$C$37:$C$51,K52-$C$6,$B$37:$B$51,"<>*Indirect*")) -> 0 | M52: =IF(K52-$C$6>'General Information'!$D$33,0,SUMIFS($D$37:$D$51,$C$37:$C$51,K52-$C$6,$B$37:$B$51,"*Indirect*")) -> 0 | N52: =IF(K52-$C$6>'General Information'!$D$33,0,IF(K52=$C$6,$E$36,0)+SUMIF($C$37:$C$51,K52-$C$6,$E$37:$E$51)) -> 0
K53: =K52+1 -> 2044 | L53: =IF(K53-$C$6>'General Information'!$D$33,0,IF(K53=$C$6,$D$36,0)+SUMIFS($D$37:$D$51,$C$37:$C$51,K53-$C$6,$B$37:$B$51,"<>*Indirect*")) -> 486835.64 | M53: =IF(K53-$C$6>'General Information'!$D$33,0,SUMIFS($D$37:$D$51,$C$37:$C$51,K53-$C$6,$B$37:$B$51,"*Indirect*")) -> 29154.51 | N53: =IF(K53-$C$6>'General Information'!$D$33,0,IF(K53=$C$6,$E$36,0)+SUMIF($C$37:$C$51,K53-$C$6,$E$37:$E$51)) -> 321548
K54: =K53+1 -> 2045 | L54: =IF(K54-$C$6>'General Information'!$D$33,0,IF(K54=$C$6,$D$36,0)+SUMIFS($D$37:$D$51,$C$37:$C$51,K54-$C$6,$B$37:$B$51,"<>*Indirect*")) -> 0 | M54: =IF(K54-$C$6>'General Information'!$D$33,0,SUMIFS($D$37:$D$51,$C$37:$C$51,K54-$C$6,$B$37:$B$51,"*Indirect*")) -> 0 | N54: =IF(K54-$C$6>'General Information'!$D$33,0,IF(K54=$C$6,$E$36,0)+SUMIF($C$37:$C$51,K54-$C$6,$E$37:$E$51)) -> 0
K55: =K54+1 -> 2046 | L55: =IF(K55-$C$6>'General Information'!$D$33,0,IF(K55=$C$6,$D$36,0)+SUMIFS($D$37:$D$51,$C$37:$C$51,K55-$C$6,$B$37:$B$51,"<>*Indirect*")) -> 0 | M55: =IF(K55-$C$6>'General Information'!$D$33,0,SUMIFS($D$37:$D$51,$C$37:$C$51,K55-$C$6,$B$37:$B$51,"*Indirect*")) -> 0 | N55: =IF(K55-$C$6>'General Information'!$D$33,0,IF(K55=$C$6,$E$36,0)+SUMIF($C$37:$C$51,K55-$C$6,$E$37:$E$51)) -> 0
K56: =K55+1 -> 2047 | L56: =IF(K56-$C$6>'General Information'!$D$33,0,IF(K56=$C$6,$D$36,0)+SUMIFS($D$37:$D$51,$C$37:$C$51,K56-$C$6,$B$37:$B$51,"<>*Indirect*")) -> 0 | M56: =IF(K56-$C$6>'General Information'!$D$33,0,SUMIFS($D$37:$D$51,$C$37:$C$51,K56-$C$6,$B$37:$B$51,"*Indirect*")) -> 0 | N56: =IF(K56-$C$6>'General Information'!$D$33,0,IF(K56=$C$6,$E$36,0)+SUMIF($C$37:$C$51,K56-$C$6,$E$37:$E$51)) -> 0
K57: =K56+1 -> 2048 | L57: =IF(K57-$C$6>'General Information'!$D$33,0,IF(K57=$C$6,$D$36,0)+SUMIFS($D$37:$D$51,$C$37:$C$51,K57-$C$6,$B$37:$B$51,"<>*Indirect*")) -> 1696066.8 | M57: =IF(K57-$C$6>'General Information'!$D$33,0,SUMIFS($D$37:$D$51,$C$37:$C$51,K57-$C$6,$B$37:$B$51,"*Indirect*")) -> 61548.41 | N57: =IF(K57-$C$6>'General Information'!$D$33,0,IF(K57=$C$6,$E$36,0)+SUMIF($C$37:$C$51,K57-$C$6,$E$37:$E$51)) -> 973148.9
K58: =K57+1 -> 2049 | L58: =IF(K58-$C$6>'General Information'!$D$33,0,IF(K58=$C$6,$D$36,0)+SUMIFS($D$37:$D$51,$C$37:$C$51,K58-$C$6,$B$37:$B$51,"<>*Indirect*")) -> 0 | M58: =IF(K58-$C$6>'General Information'!$D$33,0,SUMIFS($D$37:$D$51,$C$37:$C$51,K58-$C$6,$B$37:$B$51,"*Indirect*")) -> 0 | N58: =IF(K58-$C$6>'General Information'!$D$33,0,IF(K58=$C$6,$E$36,0)+SUMIF($C$37:$C$51,K58-$C$6,$E$37:$E$51)) -> 0
K59: =K58+1 -> 2050 | L59: =IF(K59-$C$6>'General Information'!$D$33,0,IF(K59=$C$6,$D$36,0)+SUMIFS($D$37:$D$51,$C$37:$C$51,K59-$C$6,$B$37:$B$51,"<>*Indirect*")) -> 0 | M59: =IF(K59-$C$6>'General Information'!$D$33,0,SUMIFS($D$37:$D$51,$C$37:$C$51,K59-$C$6,$B$37:$B$51,"*Indirect*")) -> 0 | N59: =IF(K59-$C$6>'General Information'!$D$33,0,IF(K59=$C$6,$E$36,0)+SUMIF($C$37:$C$51,K59-$C$6,$E$37:$E$51)) -> 0
K60: =K59+1 -> 2051 | L60: =IF(K60-$C$6>'General Information'!$D$33,0,IF(K60=$C$6,$D$36,0)+SUMIFS($D$37:$D$51,$C$37:$C$51,K60-$C$6,$B$37:$B$51,"<>*Indirect*")) -> 0 | M60: =IF(K60-$C$6>'General Information'!$D$33,0,SUMIFS($D$37:$D$51,$C$37:$C$51,K60-$C$6,$B$37:$B$51,"*Indirect*")) -> 0 | N60: =IF(K60-$C$6>'General Information'!$D$33,0,IF(K60=$C$6,$E$36,0)+SUMIF($C$37:$C$51,K60-$C$6,$E$37:$E$51)) -> 0
K61: =K60+1 -> 2052 | L61: =IF(K61-$C$6>'General Information'!$D$33,0,IF(K61=$C$6,$D$36,0)+SUMIFS($D$37:$D$51,$C$37:$C$51,K61-$C$6,$B$37:$B$51,"<>*Indirect*")) -> 331584.87 | M61: =IF(K61-$C$6>'General Information'!$D$33,0,SUMIFS($D$37:$D$51,$C$37:$C$51,K61-$C$6,$B$37:$B$51,"*Indirect*")) -> 22675.73 | N61: =IF(K61-$C$6>'General Information'!$D$33,0,IF(K61=$C$6,$E$36,0)+SUMIF($C$37:$C$51,K61-$C$6,$E$37:$E$51)) -> 174272.74
K62: =K61+1 -> 2053 | L62: =IF(K62-$C$6>'General Information'!$D$33,0,IF(K62=$C$6,$D$36,0)+SUMIFS($D$37:$D$51,$C$37:$C$51,K62-$C$6,$B$37:$B$51,"<>*Indirect*")) -> 0 | M62: =IF(K62-$C$6>'General Information'!$D$33,0,SUMIFS($D$37:$D$51,$C$37:$C$51,K62-$C$6,$B$37:$B$51,"*Indirect*")) -> 0 | N62: =IF(K62-$C$6>'General Information'!$D$33,0,IF(K62=$C$6,$E$36,0)+SUMIF($C$37:$C$51,K62-$C$6,$E$37:$E$51)) -> 0
K63: =K62+1 -> 2054 | L63: =IF(K63-$C$6>'General Information'!$D$33,0,IF(K63=$C$6,$D$36,0)+SUMIFS($D$37:$D$51,$C$37:$C$51,K63-$C$6,$B$37:$B$51,"<>*Indirect*")) -> 0 | M63: =IF(K63-$C$6>'General Information'!$D$33,0,SUMIFS($D$37:$D$51,$C$37:$C$51,K63-$C$6,$B$37:$B$51,"*Indirect*")) -> 0 | N63: =IF(K63-$C$6>'General Information'!$D$33,0,IF(K63=$C$6,$E$36,0)+SUMIF($C$37:$C$51,K63-$C$6,$E$37:$E$51)) -> 0
K64: =K63+1 -> 2055 | L64: =IF(K64-$C$6>'General Information'!$D$33,0,IF(K64=$C$6,$D$36,0)+SUMIFS($D$37:$D$51,$C$37:$C$51,K64-$C$6,$B$37:$B$51,"<>*Indirect*")) -> 0 | M64: =IF(K64-$C$6>'General Information'!$D$33,0,SUMIFS($D$37:$D$51,$C$37:$C$51,K64-$C$6,$B$37:$B$51,"*Indirect*")) -> 0 | N64: =IF(K64-$C$6>'General Information'!$D$33,0,IF(K64=$C$6,$E$36,0)+SUMIF($C$37:$C$51,K64-$C$6,$E$37:$E$51)) -> 0
... K67: =K66+1 -> 2058 | L67: =IF(K67-$C$6>'General Information'!$D$33,0,IF(K67=$C$6,$D$36,0)+SUMIFS($D$37:$D$51,$C$37:$C$51,K67-$C$6,$B$37:$B$51,"<>*Indirect*")) -> -212008.34 | M67: =IF(K67-$C$6>'General Information'!$D$33,0,SUMIFS($D$37:$D$51,$C$37:$C$51,K67-$C$6,$B$37:$B$51,"*Indirect*")) -> 0 | N67: =IF(K67-$C$6>'General Information'!$D$33,0,IF(K67=$C$6,$E$36,0)+SUMIF($C$37:$C$51,K67-$C$6,$E$37:$E$51)) -> -87344.631

Sheet RevenueData
A1: FAA ID | B1: 100LL Fuel Sales | C1: Jet-A Fuel Sales | D1: Transient Tie-downs | E1: Itinerant Hangar Storage | F1: Tenant Fuel Flowage Fee | G1: Business Tenant Revenue | H1: Other Revenue Sources
A2: MKL | B2: 946.42 | C2: 7293.08 | D2: 60.53 | E2: 3 | F2: 94.64 | G2: 108.27 | H2: Office Rent, Enterprise Concessionaire, Interest
A3: SRB | B3: 794.52 | C3: 2153.43 | D3: 13.7 | E3: 1101.37 | F3: 26.3 | G3: 254.8 | H3: $-
A4: MBT | B4: 4939.57 | C4: 1517.81 | D4: 30 | E4: 10 | F4: $- | G4: 2344 | H4: $-
A5: NQA | B5: 592 | C5: 1410 | D5: 1 | E5: 7 | F5: $- | G5: 2250 | H5: 2031
A6: DKX | B6: 2630 | C6: 1044 | D6: 42 | E6: 15 | F6: $- | G6: 110 | H6: 2862
A7: SYI | B7: 1924.14 | C7: 923.66 | D7: $- | E7: $- | F7: $- | G7: 27397.26 | H7: 571.58
A8: GCY | B8: 1000 | C8: 725 | D8: 10 | E8: 5 | F8: 40 | G8: NA | H8: 20
A9: THA | B9: 635.26 | C9: 279 | D9: $- | E9: $- | F9: $- | G9: $- | H9: 25
A10: GKT | B10: 1660.27 | C10: 3427.4 | D10: 3.5 | E10: 350 | F10: $- | G10: $- | H10: $-
A11: JWN | B11: 8400 | C11: 70000 | D11: 1000 | E11: $- | F11: 625 | G11: $- | H11: 9215
A12: MOR | B12: 4604 | C12: 4057 | D12: $- | E12: $- | F12: 140.4 | G12: $- | H12: $-
A13: MQY | B13: 4939.57 | C13: 1517.81 | D13: 30 | E13: 10 | F13: $- | G13: 2344 | H13: $-
A14: RZR | B14: 794 | C14: 2431 | D14: 300 | E14: 150 | F14: 100 | G14: 300 | H14: 25
A15: XNX | B15: 5.26 | C15: 76.71 | D15: 600 airport and 16,389 FBO | E15: $175k for airport and FBO $260,000 | F15: $0.08 flowage per gallon | G15: $6 million FBO revenues. $50,000 revenue share with FBO | H15: $5,000 utlities reimbursements
A16: M91 | B16: 727 | C16: 388 | D16: 6 | E16: $- | F16: $- | G16: 368 | H16: 569
A17: CKV | B17: 1184.59 | C17: 1267.07 | D17: 120 | E17: 667.73 | F17: $- | G17: $- | H17: $-
A18: M54 | B18: 3rd party has fuel contract…revenue captured in tenant flowage fee. | D18: $- | E18: $- | F18: 71.88 | G18: 915.33 | H18: 40.6

Sheet TMP(NewHMA)
I1: Hidden
A2: Initial Construction Costs: | J2: Maintenance 1 | R2: Maintenance 2 | Z2: Maintenance 3 | AH2: Maintenance 4 | AP2: Rehabilitation 1 | AX2: Maintenance 5 | BF2: Maintenance 6
A4: Pavement Type: | C4: New HMA
A5: Mainline Pavement Area: | C5: ='General Information'!D26 -> 66667 | D5: S.Y.
A6: Initial Construction Year: | C6: ='General Information'!D25 -> 2028 | AP6: Mill and overlay: | AQ6: 2 | AR6: inches
A7: Asphalt Surface Treatment Type: | C7: Emulsified Asphalt Surface Treatment | D7: Select alternative treatment, if planned. | AP7: Asphalt: | AQ7: 120 | AR7: lbs/SY-in
A8: Markings Area: | C8: ='General Information'!D28 -> 15000 | D8: S.F.
AP9: Tack Coat Application | AQ9: 0.1 | AR9: gal/S.Y.
A12: Item No. | B12: Pay Item | C12: Description | D12: Unit | E12: Qty | F12: Unit Cost | G12: Item Cost | J12: Item No. | K12: Pay Item | L12: Description | M12: Unit | N12: Qty | O12: Unit Cost | P12: Item Cost | R12: Item No. | S12: Pay Item | T12: Description | U12: Unit | V12: Qty | W12: Unit Cost | X12: Item Cost | Z12: Item No. | AA12: Pay Item | AB12: Description | AC12: Unit | AD12: Qty | AE12: Unit Cost | AF12: Item Cost | AH12: Item No. | AI12: Pay Item | AJ12: Description | AK12: Unit | AL12: Qty | AM12: Unit Cost | AN12: Item Cost | AP12: Item No. | AQ12: Pay Item | AR12: Description | AS12: Unit | AT12: Qty | AU12: Unit Cost | AV12: Item Cost | AX12: Item No. | AY12: Pay Item | AZ12: Description | BA12: Unit | BB12: Qty | BC12: Unit Cost | BD12: Item Cost | BF12: Item No. | BG12: Pay Item | BH12: Description | BI12: Unit | BJ12: Qty | BK12: Unit Cost | BL12: Item Cost
A13: 1 | B13: =IF(C13="",0,VLOOKUP(C13,CHOOSE({1,2},Table2[Pay Item Description],Table2[Pay Item No.]),2,0)) -> 0 | D13: =IF(C13="","N/A",VLOOKUP(C13,CHOOSE({1,2},Table2[Pay Item Description],Table2[Units]),2,0)) -> N/A | F13: =IF(C13="","N/A",VLOOKUP(C13,CHOOSE({1,2},Table2[Pay Item Description],Table2[Unit Cost]),2,0)) -> N/A | G13: =IF(B13<>0,F13*E13,0) -> 0 | J13: 1 | K13: =IF(L13="",0,VLOOKUP(L13,CHOOSE({1,2},Table2[Pay Item Description],Table2[Pay Item No.]),2,0)) -> P-608-8.1 | L13: =C7 -> Emulsified Asphalt Surface Treatment | M13: =VLOOKUP(L13,CHOOSE({1,2},Table2[Pay Item Description],Table2[Units]),2,0) -> S.Y. | N13: ='Maintenance Policies'!D10*$C$5 -> 66667 | O13: =IF(L13="","N/A",VLOOKUP(L13,CHOOSE({1,2},Table2[Pay Item Description],Table2[Unit Cost]),2,0)) -> 4 | P13: =O13*N13 -> 266668 | R13: 1 | S13: =IF(T13="",0,VLOOKUP(T13,CHOOSE({1,2},Table2[Pay Item Description],Table2[Pay Item No.]),2,0)) -> P-608-8.1 | T13: =C7 -> Emulsified Asphalt Surface Treatment | U13: =VLOOKUP(T13,CHOOSE({1,2},Table2[Pay Item Description],Table2[Units]),2,0) -> S.Y. | V13: ='Maintenance Policies'!D12*$C$5 -> 66667 | W13: =IF(T13="","N/A",VLOOKUP(T13,CHOOSE({1,2},Table2[Pay Item Description],Table2[Unit Cost]),2,0)) -> 4 | X13: =W13*V13 -> 266668 | Z13: 1 | AA13: =IF(AB13="",0,VLOOKUP(AB13,CHOOSE({1,2},Table2[Pay Item Description],Table2[Pay Item No.]),2,0)) -> P-101-5.4a | AB13: =Pay_Items!D11 -> Spall Repair, Asphalt | AC13: =IF(AB13="","N/A",VLOOKUP(AB13,CHOOSE({1,2},Table2[Pay Item Description],Table2[Units]),2,0)) -> S.F. | AD13: ='Maintenance Policies'!D14*($C$5*9) -> 4500.0225 | AE13: =IF(AB13="","N/A",VLOOKUP(AB13,CHOOSE({1,2},Table2[Pay Item Description],Table2[Unit Cost]),2,0)) -> 8.5 | AF13: =AE13*AD13 -> 38250.191 | AH13: 1 | AI13: =IF(AJ13="",0,VLOOKUP(AJ13,CHOOSE({1,2},Table2[Pay Item Description],Table2[Pay Item No.]),2,0)) -> P-101-5.4a | AJ13: =Pay_Items!D11 -> Spall Repair, Asphalt | AK13: =IF(AJ13="","N/A",VLOOKUP(AJ13,CHOOSE({1,2},Table2[Pay Item Description],Table2[Units]),2,0)) -> S.F. | AL13: ='Maintenance Policies'!D18*($C$5*9) -> 6000.03 | AM13: =IF(AJ13="","N/A",VLOOKUP(AJ13,CHOOSE({1,2},Table2[Pay Item Description],Table2[Unit Cost]),2,0)) -> 8.5 | AN13: =AM13*AL13 -> 51000.255 | AP13: 1 | AQ13: =IF(AR13="",0,VLOOKUP(AR13,CHOOSE({1,2},Table2[Pay Item Description],Table2[Pay Item No.]),2,0)) -> P-101-5.6 | AR13: =Pay_Items!D16 -> Cold Milling | AS13: =IF(AR13="","N/A",VLOOKUP(AR13,CHOOSE({1,2},Table2[Pay Item Description],Table2[Units]),2,0)) -> S.Y. | AT13: ='Maintenance Policies'!D22*$C$5 -> 66667 | AU13: =IF(AR13="","N/A",VLOOKUP(AR13,CHOOSE({1,2},Table2[Pay Item Description],Table2[Unit Cost]),2,0)) -> 5 | AV13: =AU13*AT13 -> 333335 | AX13: 1 | AY13: =IF(AZ13="",0,VLOOKUP(AZ13,CHOOSE({1,2},Table2[Pay Item Description],Table2[Pay Item No.]),2,0)) -> P-608-8.1 | AZ13: =C7 -> Emulsified Asphalt Surface Treatment | BA13: =IF(AZ13="","N/A",VLOOKUP(AZ13,CHOOSE({1,2},Table2[Pay Item Description],Table2[Units]),2,0)) -> S.Y. | BB13: ='Maintenance Policies'!D26*$C$5 -> 66667 | BC13: =IF(AZ13="","N/A",VLOOKUP(AZ13,CHOOSE({1,2},Table2[Pay Item Description],Table2[Unit Cost]),2,0)) -> 4 | BD13: =BC13*BB13 -> 266668 | BF13: 1 | BG13: =IF(BH13="",0,VLOOKUP(BH13,CHOOSE({1,2},Table2[Pay Item Description],Table2[Pay Item No.]),2,0)) -> P-101-5.4a | BH13: =Pay_Items!D11 -> Spall Repair, Asphalt | BI13: =IF(BH13="","N/A",VLOOKUP(BH13,CHOOSE({1,2},Table2[Pay Item Description],Table2[Units]),2,0)) -> S.F. | BJ13: ='Maintenance Policies'!D28*($C$5*9) -> 7500.0375 | BK13: =IF(BH13="","N/A",VLOOKUP(BH13,CHOOSE({1,2},Table2[Pay Item Description],Table2[Unit Cost]),2,0)) -> 8.5 | BL13: =BK13*BJ13 -> 63750.319
A14: 2 | B14: =IF(C14="",0,VLOOKUP(C14,CHOOSE({1,2},Table2[Pay Item Description],Table2[Pay Item No.]),2,0)) -> 0 | D14: =IF(C14="","N/A",VLOOKUP(C14,CHOOSE({1,2},Table2[Pay Item Description],Table2[Units]),2,0)) -> N/A | F14: =IF(C14="","N/A",VLOOKUP(C14,CHOOSE({1,2},Table2[Pay Item Description],Table2[Unit Cost]),2,0)) -> N/A | G14: =IF(B14<>0,F14*E14,0) -> 0 | J14: 2 | K14: =IF(L14="",0,VLOOKUP(L14,CHOOSE({1,2},Table2[Pay Item Description],Table2[Pay Item No.]),2,0)) -> P-101-5.3 | L14: =Pay_Items!D10 -> Markings Removal | M14: =IF(L14="","N/A",VLOOKUP(L14,CHOOSE({1,2},Table2[Pay Item Description],Table2[Units]),2,0)) -> S.F. | N14: ='Maintenance Policies'!D10*$C$8 -> 15000 | O14: =IF(L14="","N/A",VLOOKUP(L14,CHOOSE({1,2},Table2[Pay Item Description],Table2[Unit Cost]),2,0)) -> 0.77777778 | P14: =O14*N14 -> 11666.667 | R14: 2 | S14: =IF(T14="",0,VLOOKUP(T14,CHOOSE({1,2},Table2[Pay Item Description],Table2[Pay Item No.]),2,0)) -> P-101-5.3 | T14: =Pay_Items!D10 -> Markings Removal | U14: =IF(T14="","N/A",VLOOKUP(T14,CHOOSE({1,2},Table2[Pay Item Description],Table2[Units]),2,0)) -> S.F. | V14: ='Maintenance Policies'!D12*$C$8 -> 15000 | W14: =IF(T14="","N/A",VLOOKUP(T14,CHOOSE({1,2},Table2[Pay Item Description],Table2[Unit Cost]),2,0)) -> 0.77777778 | X14: =W14*V14 -> 11666.667 | Z14: 2 | AA14: =IF(AB14="",0,VLOOKUP(AB14,CHOOSE({1,2},Table2[Pay Item Description],Table2[Pay Item No.]),2,0)) -> P-101-5.2a | AB14: =Pay_Items!D6 -> Crack Repair (Type I), Asphalt | AC14: =IF(AB14="","N/A",VLOOKUP(AB14,CHOOSE({1,2},Table2[Pay Item Description],Table2[Units]),2,0)) -> L.F. | AD14: ='Maintenance Policies'!D15*($C$5*9) -> 19500.097 | AE14: =IF(AB14="","N/A",VLOOKUP(AB14,CHOOSE({1,2},Table2[Pay Item Description],Table2[Unit Cost]),2,0)) -> 4 | AF14: =AE14*AD14 -> 78000.39 | AH14: 2 | AI14: =IF(AJ14="",0,VLOOKUP(AJ14,CHOOSE({1,2},Table2[Pay Item Description],Table2[Pay Item No.]),2,0)) -> P-101-5.2a | AJ14: =Pay_Items!D6 -> Crack Repair (Type I), Asphalt | AK14: =IF(AJ14="","N/A",VLOOKUP(AJ14,CHOOSE({1,2},Table2[Pay Item Description],Table2[Units]),2,0)) -> L.F. | AL14: ='Maintenance Policies'!D19*($C$5*9) -> 21000.105 | AM14: =IF(AJ14="","N/A",VLOOKUP(AJ14,CHOOSE({1,2},Table2[Pay Item Description],Table2[Unit Cost]),2,0)) -> 4 | AN14: =AM14*AL14 -> 84000.42 | AP14: 2 | AQ14: =IF(AR14="",0,VLOOKUP(AR14,CHOOSE({1,2},Table2[Pay Item Description],Table2[Pay Item No.]),2,0)) -> P-603-5.1 | AR14: =Pay_Items!D54 -> Emulsified Asphalt Tack Coat | AS14: =IF(AR14="","N/A",VLOOKUP(AR14,CHOOSE({1,2},Table2[Pay Item Description],Table2[Units]),2,0)) -> GAL | AT14: ='Maintenance Policies'!D22*$C$5*AQ9 -> 6666.7 | AU14: =IF(AR14="","N/A",VLOOKUP(AR14,CHOOSE({1,2},Table2[Pay Item Description],Table2[Unit Cost]),2,0)) -> 4.5 | AV14: =AU14*AT14 -> 30000.15 | AX14: 2 | AY14: =IF(AZ14="",0,VLOOKUP(AZ14,CHOOSE({1,2},Table2[Pay Item Description],Table2[Pay Item No.]),2,0)) -> P-101-5.3 | AZ14: =Pay_Items!D10 -> Markings Removal | BA14: =IF(AZ14="","N/A",VLOOKUP(AZ14,CHOOSE({1,2},Table2[Pay Item Description],Table2[Units]),2,0)) -> S.F. | BB14: ='Maintenance Policies'!D26*$C$8 -> 15000 | BC14: =IF(AZ14="","N/A",VLOOKUP(AZ14,CHOOSE({1,2},Table2[Pay Item Description],Table2[Unit Cost]),2,0)) -> 0.77777778 | BD14: =BC14*BB14 -> 11666.667 | BF14: 2 | BG14: =IF(BH14="",0,VLOOKUP(BH14,CHOOSE({1,2},Table2[Pay Item Description],Table2[Pay Item No.]),2,0)) -> P-101-5.2a | BH14: =Pay_Items!D6 -> Crack Repair (Type I), Asphalt | BI14: =IF(BH14="","N/A",VLOOKUP(BH14,CHOOSE({1,2},Table2[Pay Item Description],Table2[Units]),2,0)) -> L.F. | BJ14: ='Maintenance Policies'!D29*($C$5*9) -> 24000.12 | BK14: =IF(BH14="","N/A",VLOOKUP(BH14,CHOOSE({1,2},Table2[Pay Item Description],Table2[Unit Cost]),2,0)) -> 4 | BL14: =BK14*BJ14 -> 96000.48
A15: 3 | B15: =IF(C15="",0,VLOOKUP(C15,CHOOSE({1,2},Table2[Pay Item Description],Table2[Pay Item No.]),2,0)) -> 0 | D15: =IF(C15="","N/A",VLOOKUP(C15,CHOOSE({1,2},Table2[Pay Item Description],Table2[Units]),2,0)) -> N/A | F15: =IF(C15="","N/A",VLOOKUP(C15,CHOOSE({1,2},Table2[Pay Item Description],Table2[Unit Cost]),2,0)) -> N/A | G15: =IF(B15<>0,F15*E15,0) -> 0 | J15: 3 | K15: =IF(L15="",0,VLOOKUP(L15,CHOOSE({1,2},Table2[Pay Item Description],Table2[Pay Item No.]),2,0)) -> P-620-5.1a | L15: =Pay_Items!D56 -> Markings (prep, markings, reflective media) | M15: =IF(L15="","N/A",VLOOKUP(L15,CHOOSE({1,2},Table2[Pay Item Description],Table2[Units]),2,0)) -> S.F. | N15: ='Maintenance Policies'!D11*$C$8 -> 15000 | O15: =IF(L15="","N/A",VLOOKUP(L15,CHOOSE({1,2},Table2[Pay Item Description],Table2[Unit Cost]),2,0)) -> 0.66666667 | P15: =O15*N15 -> 10000 | R15: 3 | S15: =IF(T15="",0,VLOOKUP(T15,CHOOSE({1,2},Table2[Pay Item Description],Table2[Pay Item No.]),2,0)) -> P-620-5.1a | T15: =Pay_Items!D56 -> Markings (prep, markings, reflective media) | U15: =Pay_Items!E56 -> S.F. | V15: ='Maintenance Policies'!D13*$C$8 -> 15000 | W15: =IF(T15="","N/A",VLOOKUP(T15,CHOOSE({1,2},Table2[Pay Item Description],Table2[Unit Cost]),2,0)) -> 0.66666667 | X15: =W15*V15 -> 10000 | Z15: 3 | AA15: =IF(AB15="",0,VLOOKUP(AB15,CHOOSE({1,2},Table2[Pay Item Description],Table2[Pay Item No.]),2,0)) -> P-608-8.1 | AB15: =C7 -> Emulsified Asphalt Surface Treatment | AC15: =IF(AB15="","N/A",VLOOKUP(AB15,CHOOSE({1,2},Table2[Pay Item Description],Table2[Units]),2,0)) -> S.Y. | AD15: ='Maintenance Policies'!D16*$C$5 -> 66667 | AE15: =IF(AB15="","N/A",VLOOKUP(AB15,CHOOSE({1,2},Table2[Pay Item Description],Table2[Unit Cost]),2,0)) -> 4 | AF15: =AE15*AD15 -> 266668 | AH15: 3 | AI15: =IF(AJ15="",0,VLOOKUP(AJ15,CHOOSE({1,2},Table2[Pay Item Description],Table2[Pay Item No.]),2,0)) -> P-608-8.1 | AJ15: =C7 -> Emulsified Asphalt Surface Treatment | AK15: =IF(AJ15="","N/A",VLOOKUP(AJ15,CHOOSE({1,2},Table2[Pay Item Description],Table2[Units]),2,0)) -> S.Y. | AL15: ='Maintenance Policies'!D20*$C$5 -> 66667 | AM15: =IF(AJ15="","N/A",VLOOKUP(AJ15,CHOOSE({1,2},Table2[Pay Item Description],Table2[Unit Cost]),2,0)) -> 4 | AN15: =AM15*AL15 -> 266668 | AP15: 3 | AQ15: =IF(AR15="",0,VLOOKUP(AR15,CHOOSE({1,2},Table2[Pay Item Description],Table2[Pay Item No.]),2,0)) -> P-401-8.1a | AR15: =Pay_Items!D37 -> Asphalt Surface Course | AS15: =IF(AR15="","N/A",VLOOKUP(AR15,CHOOSE({1,2},Table2[Pay Item Description],Table2[Units]),2,0)) -> TON | AT15: ='Maintenance Policies'!D22*$C$5*AQ6*AQ7/2000 -> 8000.04 | AU15: =IF(AR15="","N/A",VLOOKUP(AR15,CHOOSE({1,2},Table2[Pay Item Description],Table2[Unit Cost]),2,0)) -> 130 | AV15: =AU15*AT15 -> 1040005.2 | AX15: 3 | AY15: =IF(AZ15="",0,VLOOKUP(AZ15,CHOOSE({1,2},Table2[Pay Item Description],Table2[Pay Item No.]),2,0)) -> P-620-5.1a | AZ15: =Pay_Items!D56 -> Markings (prep, markings, reflective media) | BA15: =IF(AZ15="","N/A",VLOOKUP(AZ15,CHOOSE({1,2},Table2[Pay Item Description],Table2[Units]),2,0)) -> S.F. | BB15: ='Maintenance Policies'!D27*$C$8 -> 15000 | BC15: =IF(AZ15="","N/A",VLOOKUP(AZ15,CHOOSE({1,2},Table2[Pay Item Description],Table2[Unit Cost]),2,0)) -> 0.66666667 | BD15: =BC15*BB15 -> 10000 | BF15: 3 | BG15: =IF(BH15="",0,VLOOKUP(BH15,CHOOSE({1,2},Table2[Pay Item Description],Table2[Pay Item No.]),2,0)) -> P-608-8.1 | BH15: =C7 -> Emulsified Asphalt Surface Treatment | BI15: =IF(BH15="","N/A",VLOOKUP(BH15,CHOOSE({1,2},Table2[Pay Item Description],Table2[Units]),2,0)) -> S.Y. | BJ15: ='Maintenance Policies'!D30*$C$5 -> 66667 | BK15: =IF(BH15="","N/A",VLOOKUP(BH15,CHOOSE({1,2},Table2[Pay Item Description],Table2[Unit Cost]),2,0)) -> 4 | BL15: =BK15*BJ15 -> 266668
A16: 4 | B16: =IF(C16="",0,VLOOKUP(C16,CHOOSE({1,2},Table2[Pay Item Description],Table2[Pay Item No.]),2,0)) -> 0 | D16: =IF(C16="","N/A",VLOOKUP(C16,CHOOSE({1,2},Table2[Pay Item Description],Table2[Units]),2,0)) -> N/A | F16: =IF(C16="","N/A",VLOOKUP(C16,CHOOSE({1,2},Table2[Pay Item Description],Table2[Unit Cost]),2,0)) -> N/A | G16: =IF(B16<>0,F16*E16,0) -> 0 | O16: Subtotal | P16: =SUM(P13:P15) -> 288334.67 | W16: Subtotal | X16: =SUM(X13:X15) -> 288334.67 | Z16: 4 | AA16: =IF(AB16="",0,VLOOKUP(AB16,CHOOSE({1,2},Table2[Pay Item Description],Table2[Pay Item No.]),2,0)) -> P-101-5.3 | AB16: =Pay_Items!D10 -> Markings Removal | AC16: =IF(AB16="","N/A",VLOOKUP(AB16,CHOOSE({1,2},Table2[Pay Item Description],Table2[Units]),2,0)) -> S.F. | AD16: ='Maintenance Policies'!D16*$C$8 -> 15000 | AE16: =IF(AB16="","N/A",VLOOKUP(AB16,CHOOSE({1,2},Table2[Pay Item Description],Table2[Unit Cost]),2,0)) -> 0.77777778 | AF16: =AE16*AD16 -> 11666.667 | AH16: 4 | AI16: =IF(AJ16="",0,VLOOKUP(AJ16,CHOOSE({1,2},Table2[Pay Item Description],Table2[Pay Item No.]),2,0)) -> P-101-5.3 | AJ16: =Pay_Items!D10 -> Markings Removal | AK16: =IF(AJ16="","N/A",VLOOKUP(AJ16,CHOOSE({1,2},Table2[Pay Item Description],Table2[Units]),2,0)) -> S.F. | AL16: ='Maintenance Policies'!D20*$C$8 -> 15000 | AM16: =IF(AJ16="","N/A",VLOOKUP(AJ16,CHOOSE({1,2},Table2[Pay Item Description],Table2[Unit Cost]),2,0)) -> 0.77777778 | AN16: =AM16*AL16 -> 11666.667 | AP16: 4 | AQ16: =IF(AR16="",0,VLOOKUP(AR16,CHOOSE({1,2},Table2[Pay Item Description],Table2[Pay Item No.]),2,0)) -> P-101-5.2a | AR16: =Pay_Items!D6 -> Crack Repair (Type I), Asphalt | AS16: =IF(AR16="","N/A",VLOOKUP(AR16,CHOOSE({1,2},Table2[Pay Item Description],Table2[Units]),2,0)) -> L.F. | AT16: ='Maintenance Policies'!D23*($C$5*9) -> 9000.045 | AU16: =IF(AR16="","N/A",VLOOKUP(AR16,CHOOSE({1,2},Table2[Pay Item Description],Table2[Unit Cost]),2,0)) -> 4 | AV16: =AU16*AT16 -> 36000.18 | BC16: Subtotal | BD16: =SUM(BD13:BD15) -> 288334.67 | BF16: 4 | BG16: =IF(BH16="",0,VLOOKUP(BH16,CHOOSE({1,2},Table2[Pay Item Description],Table2[Pay Item No.]),2,0)) -> P-101-5.3 | BH16: =Pay_Items!D10 -> Markings Removal | BI16: =IF(BH16="","N/A",VLOOKUP(BH16,CHOOSE({1,2},Table2[Pay Item Description],Table2[Units]),2,0)) -> S.F. | BJ16: =C8 -> 15000 | BK16: =IF(BH16="","N/A",VLOOKUP(BH16,CHOOSE({1,2},Table2[Pay Item Description],Table2[Unit Cost]),2,0)) -> 0.77777778 | BL16: =BK16*BJ16 -> 11666.667
A17: 5 | B17: =IF(C17="",0,VLOOKUP(C17,CHOOSE({1,2},Table2[Pay Item Description],Table2[Pay Item No.]),2,0)) -> 0 | D17: =IF(C17="","N/A",VLOOKUP(C17,CHOOSE({1,2},Table2[Pay Item Description],Table2[Units]),2,0)) -> N/A | F17: =IF(C17="","N/A",VLOOKUP(C17,CHOOSE({1,2},Table2[Pay Item Description],Table2[Unit Cost]),2,0)) -> N/A | G17: =IF(B17<>0,F17*E17,0) -> 0 | L17: Mobilization | P17: =('General Information'!$D$36/100)*P16 -> 28833.467 | T17: Mobilization | X17: =('General Information'!$D$36/100)*X16 -> 28833.467 | Z17: 5 | AA17: =IF(AB17="",0,VLOOKUP(AB17,CHOOSE({1,2},Table2[Pay Item Description],Table2[Pay Item No.]),2,0)) -> P-620-5.1a | AB17: =Pay_Items!D56 -> Markings (prep, markings, reflective media) | AC17: =IF(AB17="","N/A",VLOOKUP(AB17,CHOOSE({1,2},Table2[Pay Item Description],Table2[Units]),2,0)) -> S.F. | AD17: ='Maintenance Policies'!D17*$C$8 -> 15000 | AE17: =IF(AB17="","N/A",VLOOKUP(AB17,CHOOSE({1,2},Table2[Pay Item Description],Table2[Unit Cost]),2,0)) -> 0.66666667 | AF17: =AE17*AD17 -> 10000 | AH17: 5 | AI17: =IF(AJ17="",0,VLOOKUP(AJ17,CHOOSE({1,2},Table2[Pay Item Description],Table2[Pay Item No.]),2,0)) -> P-620-5.1a | AJ17: =Pay_Items!D56 -> Markings (prep, markings, reflective media) | AK17: =IF(AJ17="","N/A",VLOOKUP(AJ17,CHOOSE({1,2},Table2[Pay Item Description],Table2[Units]),2,0)) -> S.F. | AL17: ='Maintenance Policies'!D21*$C$8 -> 15000 | AM17: =IF(AJ17="","N/A",VLOOKUP(AJ17,CHOOSE({1,2},Table2[Pay Item Description],Table2[Unit Cost]),2,0)) -> 0.66666667 | AN17: =AM17*AL17 -> 10000 | AP17: 5 | AQ17: =IF(AR17="",0,VLOOKUP(AR17,CHOOSE({1,2},Table2[Pay Item Description],Table2[Pay Item No.]),2,0)) -> P-101-5.4a | AR17: =Pay_Items!D11 -> Spall Repair, Asphalt | AS17: =IF(AR17="","N/A",VLOOKUP(AR17,CHOOSE({1,2},Table2[Pay Item Description],Table2[Units]),2,0)) -> S.F. | AT17: ='Maintenance Policies'!D24*($C$5*9) -> 3000.015 | AU17: =IF(AR17="","N/A",VLOOKUP(AR17,CHOOSE({1,2},Table2[Pay Item Description],Table2[Unit Cost]),2,0)) -> 8.5 | AV17: =AU17*AT17 -> 25500.127 | AZ17: Mobilization | BD17: =('General Information'!$D$36/100)*BD16 -> 28833.467 | BF17: 5 | BG17: =IF(BH17="",0,VLOOKUP(BH17,CHOOSE({1,2},Table2[Pay Item Description],Table2[Pay Item No.]),2,0)) -> P-620-5.1a | BH17: =Pay_Items!D56 -> Markings (prep, markings, reflective media) | BI17: =IF(BH17="","N/A",VLOOKUP(BH17,CHOOSE({1,2},Table2[Pay Item Description],Table2[Units]),2,0)) -> S.F. | BJ17: ='Maintenance Policies'!D31*$C$8 -> 15000 | BK17: =IF(BH17="","N/A",VLOOKUP(BH17,CHOOSE({1,2},Table2[Pay Item Description],Table2[Unit Cost]),2,0)) -> 0.66666667 | BL17: =BK17*BJ17 -> 10000
A18: 6 | B18: =IF(C18="",0,VLOOKUP(C18,CHOOSE({1,2},Table2[Pay Item Description],Table2[Pay Item No.]),2,0)) -> 0 | D18: =IF(C18="","N/A",VLOOKUP(C18,CHOOSE({1,2},Table2[Pay Item Description],Table2[Units]),2,0)) -> N/A | F18: =IF(C18="","N/A",VLOOKUP(C18,CHOOSE({1,2},Table2[Pay Item Description],Table2[Unit Cost]),2,0)) -> N/A | G18: =IF(B18<>0,F18*E18,0) -> 0 | L18: Engineering | P18: =('General Information'!$D$37/100)*P16 -> 14416.733 | T18: Engineering | X18: =('General Information'!$D$37/100)*X16 -> 14416.733 | AE18: Subtotal | AF18: =SUM(AF13:AF17) -> 404585.25 | AM18: Subtotal | AN18: =SUM(AN13:AN17) -> 423335.34 | AP18: 6 | AQ18: =IF(AR18="",0,VLOOKUP(AR18,CHOOSE({1,2},Table2[Pay Item Description],Table2[Pay Item No.]),2,0)) -> P-620-5.1a | AR18: =Pay_Items!D56 -> Markings (prep, markings, reflective media) | AS18: =IF(AR18="","N/A",VLOOKUP(AR18,CHOOSE({1,2},Table2[Pay Item Description],Table2[Units]),2,0)) -> S.F. | AT18: ='Maintenance Policies'!D25*$C$8 -> 15000 | AU18: =IF(AR18="","N/A",VLOOKUP(AR18,CHOOSE({1,2},Table2[Pay Item Description],Table2[Unit Cost]),2,0)) -> 0.66666667 | AV18: =AU18*AT18 -> 10000 | AZ18: Engineering | BD18: =('General Information'!$D$37/100)*BD16 -> 14416.733 | BK18: Subtotal | BL18: =SUM(BL13:BL17) -> 448085.47
A19: 7 | B19: =IF(C19="",0,VLOOKUP(C19,CHOOSE({1,2},Table2[Pay Item Description],Table2[Pay Item No.]),2,0)) -> 0 | D19: =IF(C19="","N/A",VLOOKUP(C19,CHOOSE({1,2},Table2[Pay Item Description],Table2[Units]),2,0)) -> N/A | F19: =IF(C19="","N/A",VLOOKUP(C19,CHOOSE({1,2},Table2[Pay Item Description],Table2[Unit Cost]),2,0)) -> N/A | G19: =IF(B19<>0,F19*E19,0) -> 0 | O19: Total | P19: =SUM(P16:P18) -> 331584.87 | W19: Total | X19: =SUM(X16:X18) -> 331584.87 | AB19: Mobilization | AF19: =('General Information'!$D$36/100)*AF18 -> 40458.525 | AJ19: Mobilization | AN19: =('General Information'!$D$36/100)*AN18 -> 42333.534 | AU19: Subtotal | AV19: =SUM(AV13:AV18) -> 1474840.7 | BC19: Total | BD19: =SUM(BD16:BD18) -> 331584.87 | BH19: Mobilization | BL19: =('General Information'!$D$36/100)*BL18 -> 44808.547
A20: 8 | B20: =IF(C20="",0,VLOOKUP(C20,CHOOSE({1,2},Table2[Pay Item Description],Table2[Pay Item No.]),2,0)) -> 0 | D20: =IF(C20="","N/A",VLOOKUP(C20,CHOOSE({1,2},Table2[Pay Item Description],Table2[Units]),2,0)) -> N/A | F20: =IF(C20="","N/A",VLOOKUP(C20,CHOOSE({1,2},Table2[Pay Item Description],Table2[Unit Cost]),2,0)) -> N/A | G20: =IF(B20<>0,F20*E20,0) -> 0 | AB20: Engineering | AF20: =('General Information'!$D$37/100)*AF18 -> 20229.262 | AJ20: Engineering | AN20: =('General Information'!$D$37/100)*AN18 -> 21166.767 | AR20: Mobilization | AV20: =('General Information'!$D$36/100)*AV19 -> 147484.07 | BH20: Engineering | BL20: =('General Information'!$D$37/100)*BL18 -> 22404.273
A21: 9 | B21: =IF(C21="",0,VLOOKUP(C21,CHOOSE({1,2},Table2[Pay Item Description],Table2[Pay Item No.]),2,0)) -> 0 | D21: =IF(C21="","N/A",VLOOKUP(C21,CHOOSE({1,2},Table2[Pay Item Description],Table2[Units]),2,0)) -> N/A | F21: =IF(C21="","N/A",VLOOKUP(C21,CHOOSE({1,2},Table2[Pay Item Description],Table2[Unit Cost]),2,0)) -> N/A | G21: =IF(B21<>0,F21*E21,0) -> 0 | AE21: Total | AF21: =SUM(AF18:AF20) -> 465273.04 | AM21: Total | AN21: =SUM(AN18:AN20) -> 486835.64 | AR21: Engineering | AV21: =('General Information'!$D$37/100)*AV19 -> 73742.033 | BK21: Total | BL21: =SUM(BL18:BL20) -> 515298.29
A22: 10 | B22: =IF(C22="",0,VLOOKUP(C22,CHOOSE({1,2},Table2[Pay Item Description],Table2[Pay Item No.]),2,0)) -> 0 | D22: =IF(C22="","N/A",VLOOKUP(C22,CHOOSE({1,2},Table2[Pay Item Description],Table2[Units]),2,0)) -> N/A | F22: =IF(C22="","N/A",VLOOKUP(C22,CHOOSE({1,2},Table2[Pay Item Description],Table2[Unit Cost]),2,0)) -> N/A | G22: =IF(B22<>0,F22*E22,0) -> 0 | AU22: Total | AV22: =SUM(AV19:AV21) -> 1696066.8
A24: Subtotal | G24: =SUM(G13:G22) -> 0
B25: Mobilization | G25: =('General Information'!$D$36/100)*G24 -> 0
B26: Engineering | G26: =('General Information'!$D$37/100)*G24 -> 0
A27: Total | G27: =SUM(G24:G26) -> 0
A32: Net Present Worth
A33: HMA Reconstruction - Alternative 1 | I33: Hidden
B35: Item | C35: Year Applied | D35: Actual Cost | E35: Discounted Cost
B36: Initial Construction | C36: =C6 -> 2028 | D36: =G27 -> 0 | E36: =D36 -> 0 | K36: Year | L36: Actual | M36: Discounted
B37: Maintenance 1 | C37: ='Maintenance Policies'!E10 -> 4 | D37: =P19 -> 331584.87 | E37: =IF(C37>'General Information'!$D$33,0,D37/(1+('General Information'!$D$34/100))^C37) -> 294608.86 | K37: =C6 -> 2028 | L37: =IF(K37-$C$6>'General Information'!$D$33,0,IF(K37=$C$6,$D$36,0)+SUMIF($C$37:$C$44,K37-$C$6,$D$37:$D$44)) -> 0 | M37: =IF(K37-$C$6>'General Information'!$D$33,0,IF(K37=$C$6,$E$36,0)+SUMIF($C$37:$C$44,K37-$C$6,$E$37:$E$44)) -> 0
B38: Maintenance 2 | C38: ='Maintenance Policies'!E12 -> 8 | D38: =X19 -> 331584.87 | E38: =IF(C38>'General Information'!$D$33,0,D38/(1+('General Information'!$D$34/100))^C38) -> 261756.16 | K38: =K37+1 -> 2029 | L38: =IF(K38-$C$6>'General Information'!$D$33,0,IF(K38=$C$6,$D$36,0)+SUMIF($C$37:$C$44,K38-$C$6,$D$37:$D$44)) -> 0 | M38: =IF(K38-$C$6>'General Information'!$D$33,0,IF(K38=$C$6,$E$36,0)+SUMIF($C$37:$C$44,K38-$C$6,$E$37:$E$44)) -> 0
B39: Maintenance 3 | C39: ='Maintenance Policies'!E14 -> 12 | D39: =AF21 -> 465273.04 | E39: =IF(C39>'General Information'!$D$33,0,D39/(1+('General Information'!$D$34/100))^C39) -> 326333.15 | K39: =K38+1 -> 2030 | L39: =IF(K39-$C$6>'General Information'!$D$33,0,IF(K39=$C$6,$D$36,0)+SUMIF($C$37:$C$44,K39-$C$6,$D$37:$D$44)) -> 0 | M39: =IF(K39-$C$6>'General Information'!$D$33,0,IF(K39=$C$6,$E$36,0)+SUMIF($C$37:$C$44,K39-$C$6,$E$37:$E$44)) -> 0
B40: Maintenance 4 | C40: ='Maintenance Policies'!E18 -> 16 | D40: =AN21 -> 486835.64 | E40: =IF(C40>'General Information'!$D$33,0,D40/(1+('General Information'!$D$34/100))^C40) -> 303379.88 | K40: =K39+1 -> 2031 | L40: =IF(K40-$C$6>'General Information'!$D$33,0,IF(K40=$C$6,$D$36,0)+SUMIF($C$37:$C$44,K40-$C$6,$D$37:$D$44)) -> 0 | M40: =IF(K40-$C$6>'General Information'!$D$33,0,IF(K40=$C$6,$E$36,0)+SUMIF($C$37:$C$44,K40-$C$6,$E$37:$E$44)) -> 0
B41: Rehabilitation 1 | C41: ='Maintenance Policies'!E22 -> 20 | D41: =AV22 -> 1696066.8 | E41: =IF(C41>'General Information'!$D$33,0,D41/(1+('General Information'!$D$34/100))^C41) -> 939071.04 | K41: =K40+1 -> 2032 | L41: =IF(K41-$C$6>'General Information'!$D$33,0,IF(K41=$C$6,$D$36,0)+SUMIF($C$37:$C$44,K41-$C$6,$D$37:$D$44)) -> 331584.87 | M41: =IF(K41-$C$6>'General Information'!$D$33,0,IF(K41=$C$6,$E$36,0)+SUMIF($C$37:$C$44,K41-$C$6,$E$37:$E$44)) -> 294608.86
B42: Maintenance 5 | C42: ='Maintenance Policies'!E26 -> 24 | D42: =BD19 -> 331584.87 | E42: =IF(C42>'General Information'!$D$33,0,D42/(1+('General Information'!$D$34/100))^C42) -> 163117.78 | K42: =K41+1 -> 2033 | L42: =IF(K42-$C$6>'General Information'!$D$33,0,IF(K42=$C$6,$D$36,0)+SUMIF($C$37:$C$44,K42-$C$6,$D$37:$D$44)) -> 0 | M42: =IF(K42-$C$6>'General Information'!$D$33,0,IF(K42=$C$6,$E$36,0)+SUMIF($C$37:$C$44,K42-$C$6,$E$37:$E$44)) -> 0
B43: Maintenance 6 | C43: ='Maintenance Policies'!E28 -> 28 | D43: =BL21 -> 515298.29 | E43: =IF(C43>'General Information'!$D$33,0,D43/(1+('General Information'!$D$34/100))^C43) -> 225224.9 | K43: =K42+1 -> 2034 | L43: =IF(K43-$C$6>'General Information'!$D$33,0,IF(K43=$C$6,$D$36,0)+SUMIF($C$37:$C$44,K43-$C$6,$D$37:$D$44)) -> 0 | M43: =IF(K43-$C$6>'General Information'!$D$33,0,IF(K43=$C$6,$E$36,0)+SUMIF($C$37:$C$44,K43-$C$6,$E$37:$E$44)) -> 0
B44: Salvage | C44: ='General Information'!D33 -> 30 | D44: =-'Maintenance Policies'!D32*AV22 -> -212008.34 | E44: =IF(C44>'General Information'!$D$33,0,D44/(1+('General Information'!$D$34/100))^C44) -> -87344.631 | K44: =K43+1 -> 2035 | L44: =IF(K44-$C$6>'General Information'!$D$33,0,IF(K44=$C$6,$D$36,0)+SUMIF($C$37:$C$44,K44-$C$6,$D$37:$D$44)) -> 0 | M44: =IF(K44-$C$6>'General Information'!$D$33,0,IF(K44=$C$6,$E$36,0)+SUMIF($C$37:$C$44,K44-$C$6,$E$37:$E$44)) -> 0
B45: Net Present Worth | E45: =SUM(E36:E44) -> 2426147.1 | K45: =K44+1 -> 2036 | L45: =IF(K45-$C$6>'General Information'!$D$33,0,IF(K45=$C$6,$D$36,0)+SUMIF($C$37:$C$44,K45-$C$6,$D$37:$D$44)) -> 331584.87 | M45: =IF(K45-$C$6>'General Information'!$D$33,0,IF(K45=$C$6,$E$36,0)+SUMIF($C$37:$C$44,K45-$C$6,$E$37:$E$44)) -> 261756.16
K46: =K45+1 -> 2037 | L46: =IF(K46-$C$6>'General Information'!$D$33,0,IF(K46=$C$6,$D$36,0)+SUMIF($C$37:$C$44,K46-$C$6,$D$37:$D$44)) -> 0 | M46: =IF(K46-$C$6>'General Information'!$D$33,0,IF(K46=$C$6,$E$36,0)+SUMIF($C$37:$C$44,K46-$C$6,$E$37:$E$44)) -> 0
K47: =K46+1 -> 2038 | L47: =IF(K47-$C$6>'General Information'!$D$33,0,IF(K47=$C$6,$D$36,0)+SUMIF($C$37:$C$44,K47-$C$6,$D$37:$D$44)) -> 0 | M47: =IF(K47-$C$6>'General Information'!$D$33,0,IF(K47=$C$6,$E$36,0)+SUMIF($C$37:$C$44,K47-$C$6,$E$37:$E$44)) -> 0
K48: =K47+1 -> 2039 | L48: =IF(K48-$C$6>'General Information'!$D$33,0,IF(K48=$C$6,$D$36,0)+SUMIF($C$37:$C$44,K48-$C$6,$D$37:$D$44)) -> 0 | M48: =IF(K48-$C$6>'General Information'!$D$33,0,IF(K48=$C$6,$E$36,0)+SUMIF($C$37:$C$44,K48-$C$6,$E$37:$E$44)) -> 0
K49: =K48+1 -> 2040 | L49: =IF(K49-$C$6>'General Information'!$D$33,0,IF(K49=$C$6,$D$36,0)+SUMIF($C$37:$C$44,K49-$C$6,$D$37:$D$44)) -> 465273.04 | M49: =IF(K49-$C$6>'General Information'!$D$33,0,IF(K49=$C$6,$E$36,0)+SUMIF($C$37:$C$44,K49-$C$6,$E$37:$E$44)) -> 326333.15
K50: =K49+1 -> 2041 | L50: =IF(K50-$C$6>'General Information'!$D$33,0,IF(K50=$C$6,$D$36,0)+SUMIF($C$37:$C$44,K50-$C$6,$D$37:$D$44)) -> 0 | M50: =IF(K50-$C$6>'General Information'!$D$33,0,IF(K50=$C$6,$E$36,0)+SUMIF($C$37:$C$44,K50-$C$6,$E$37:$E$44)) -> 0
K51: =K50+1 -> 2042 | L51: =IF(K51-$C$6>'General Information'!$D$33,0,IF(K51=$C$6,$D$36,0)+SUMIF($C$37:$C$44,K51-$C$6,$D$37:$D$44)) -> 0 | M51: =IF(K51-$C$6>'General Information'!$D$33,0,IF(K51=$C$6,$E$36,0)+SUMIF($C$37:$C$44,K51-$C$6,$E$37:$E$44)) -> 0
K52: =K51+1 -> 2043 | L52: =IF(K52-$C$6>'General Information'!$D$33,0,IF(K52=$C$6,$D$36,0)+SUMIF($C$37:$C$44,K52-$C$6,$D$37:$D$44)) -> 0 | M52: =IF(K52-$C$6>'General Information'!$D$33,0,IF(K52=$C$6,$E$36,0)+SUMIF($C$37:$C$44,K52-$C$6,$E$37:$E$44)) -> 0
K53: =K52+1 -> 2044 | L53: =IF(K53-$C$6>'General Information'!$D$33,0,IF(K53=$C$6,$D$36,0)+SUMIF($C$37:$C$44,K53-$C$6,$D$37:$D$44)) -> 486835.64 | M53: =IF(K53-$C$6>'General Information'!$D$33,0,IF(K53=$C$6,$E$36,0)+SUMIF($C$37:$C$44,K53-$C$6,$E$37:$E$44)) -> 303379.88
K54: =K53+1 -> 2045 | L54: =IF(K54-$C$6>'General Information'!$D$33,0,IF(K54=$C$6,$D$36,0)+SUMIF($C$37:$C$44,K54-$C$6,$D$37:$D$44)) -> 0 | M54: =IF(K54-$C$6>'General Information'!$D$33,0,IF(K54=$C$6,$E$36,0)+SUMIF($C$37:$C$44,K54-$C$6,$E$37:$E$44)) -> 0
K55: =K54+1 -> 2046 | L55: =IF(K55-$C$6>'General Information'!$D$33,0,IF(K55=$C$6,$D$36,0)+SUMIF($C$37:$C$44,K55-$C$6,$D$37:$D$44)) -> 0 | M55: =IF(K55-$C$6>'General Information'!$D$33,0,IF(K55=$C$6,$E$36,0)+SUMIF($C$37:$C$44,K55-$C$6,$E$37:$E$44)) -> 0
K56: =K55+1 -> 2047 | L56: =IF(K56-$C$6>'General Information'!$D$33,0,IF(K56=$C$6,$D$36,0)+SUMIF($C$37:$C$44,K56-$C$6,$D$37:$D$44)) -> 0 | M56: =IF(K56-$C$6>'General Information'!$D$33,0,IF(K56=$C$6,$E$36,0)+SUMIF($C$37:$C$44,K56-$C$6,$E$37:$E$44)) -> 0
K57: =K56+1 -> 2048 | L57: =IF(K57-$C$6>'General Information'!$D$33,0,IF(K57=$C$6,$D$36,0)+SUMIF($C$37:$C$44,K57-$C$6,$D$37:$D$44)) -> 1696066.8 | M57: =IF(K57-$C$6>'General Information'!$D$33,0,IF(K57=$C$6,$E$36,0)+SUMIF($C$37:$C$44,K57-$C$6,$E$37:$E$44)) -> 939071.04
... K67: =K66+1 -> 2058 | L67: =IF(K67-$C$6>'General Information'!$D$33,0,IF(K67=$C$6,$D$36,0)+SUMIF($C$37:$C$44,K67-$C$6,$D$37:$D$44)) -> -212008.34 | M67: =IF(K67-$C$6>'General Information'!$D$33,0,IF(K67=$C$6,$E$36,0)+SUMIF($C$37:$C$44,K67-$C$6,$E$37:$E$44)) -> -87344.631

Sheet TMP(NewPCC)
I1: Hidden
A2: Initial Construction Costs: | J2: Maintenance 1 | R2: Rehabilitation 1
A4: Pavement Type: | C4: New PCC
A5: Mainline Pavement Area: | C5: ='General Information'!D26 -> 66667 | D5: S.Y.
A6: Initial Construction Year: | C6: ='General Information'!D25 -> 2028
A7: Markings Area: | C7: ='General Information'!D28 -> 15000 | D7: S.F. | J7: No. of Slabs: | K7: =C5/((12.5*12.5)/9) -> 3840.0192
J8: Joint length: | K8: =K7*25+((K7/8)*12.5) -> 102000.51
A12: Item No. | B12: Pay Item | C12: Description | D12: Unit | E12: Qty | F12: Unit Cost | G12: Item Cost | J12: Item No. | K12: Pay Item | L12: Description | M12: Unit | N12: Qty | O12: Unit Cost | P12: Item Cost | R12: Item No. | S12: Pay Item | T12: Description | U12: Unit | V12: Qty | W12: Unit Cost | X12: Item Cost
A13: 1 | B13: =IF(C13="",0,VLOOKUP(C13,CHOOSE({1,2},Table2[Pay Item Description],Table2[Pay Item No.]),2,0)) -> 0 | D13: =IF(C13="","N/A",VLOOKUP(C13,CHOOSE({1,2},Table2[Pay Item Description],Table2[Units]),2,0)) -> N/A | F13: =IF(C13="","N/A",VLOOKUP(C13,CHOOSE({1,2},Table2[Pay Item Description],Table2[Unit Cost]),2,0)) -> N/A | G13: =IF(B13<>0,F13*E13,0) -> 0 | J13: 1 | K13: =IF(L13="",0,VLOOKUP(L13,CHOOSE({1,2},Table2[Pay Item Description],Table2[Pay Item No.]),2,0)) -> P-605-5.1a | L13: =Pay_Items!D55 -> Joint Clean and Reseal, Concrete | M13: =IF(L13="","N/A",VLOOKUP(L13,CHOOSE({1,2},Table2[Pay Item Description],Table2[Units]),2,0)) -> L.F. | N13: =K8*'Maintenance Policies'!D37 -> 102000.51 | O13: =IF(L13="","N/A",VLOOKUP(L13,CHOOSE({1,2},Table2[Pay Item Description],Table2[Unit Cost]),2,0)) -> 7 | P13: =O13*N13 -> 714003.57 | R13: 1 | S13: =IF(T13="",0,VLOOKUP(T13,CHOOSE({1,2},Table2[Pay Item Description],Table2[Pay Item No.]),2,0)) -> P-101-5.5c | T13: =Pay_Items!D15 -> Slab Replacement, Concrete | U13: =IF(T13="","N/A",VLOOKUP(T13,CHOOSE({1,2},Table2[Pay Item Description],Table2[Units]),2,0)) -> S.Y. | V13: ='Maintenance Policies'!D41*C5 -> 1333.34 | W13: =IF(T13="","N/A",VLOOKUP(T13,CHOOSE({1,2},Table2[Pay Item Description],Table2[Unit Cost]),2,0)) -> 100 | X13: =W13*V13 -> 133334
A14: 2 | B14: =IF(C14="",0,VLOOKUP(C14,CHOOSE({1,2},Table2[Pay Item Description],Table2[Pay Item No.]),2,0)) -> 0 | D14: =IF(C14="","N/A",VLOOKUP(C14,CHOOSE({1,2},Table2[Pay Item Description],Table2[Units]),2,0)) -> N/A | F14: =IF(C14="","N/A",VLOOKUP(C14,CHOOSE({1,2},Table2[Pay Item Description],Table2[Unit Cost]),2,0)) -> N/A | G14: =IF(B14<>0,F14*E14,0) -> 0 | J14: 2 | K14: =VLOOKUP(L14,CHOOSE({1,2},Table2[Pay Item Description],Table2[Pay Item No.]),2,0) -> P-101-5.2c | L14: =Pay_Items!D8 -> Crack Seal, Concrete | M14: =IF(L14="","N/A",VLOOKUP(L14,CHOOSE({1,2},Table2[Pay Item Description],Table2[Units]),2,0)) -> L.F. | N14: ='Maintenance Policies'!D38*(C5*9) -> 1500.0075 | O14: =IF(L14="","N/A",VLOOKUP(L14,CHOOSE({1,2},Table2[Pay Item Description],Table2[Unit Cost]),2,0)) -> 8 | P14: =O14*N14 -> 12000.06 | R14: 2 | S14: =VLOOKUP(T14,CHOOSE({1,2},Table2[Pay Item Description],Table2[Pay Item No.]),2,0) -> P-101-5.5b | T14: =Pay_Items!D14 -> Full-Depth Repair, Concrete | U14: =IF(T14="","N/A",VLOOKUP(T14,CHOOSE({1,2},Table2[Pay Item Description],Table2[Units]),2,0)) -> S.Y. | V14: ='Maintenance Policies'!D42*C5 -> 200.001 | W14: =IF(T14="","N/A",VLOOKUP(T14,CHOOSE({1,2},Table2[Pay Item Description],Table2[Unit Cost]),2,0)) -> 120 | X14: =W14*V14 -> 24000.12
A15: 3 | B15: =IF(C15="",0,VLOOKUP(C15,CHOOSE({1,2},Table2[Pay Item Description],Table2[Pay Item No.]),2,0)) -> 0 | D15: =IF(C15="","N/A",VLOOKUP(C15,CHOOSE({1,2},Table2[Pay Item Description],Table2[Units]),2,0)) -> N/A | F15: =IF(C15="","N/A",VLOOKUP(C15,CHOOSE({1,2},Table2[Pay Item Description],Table2[Unit Cost]),2,0)) -> N/A | G15: =IF(B15<>0,F15*E15,0) -> 0 | J15: 3 | K15: =VLOOKUP(L15,CHOOSE({1,2},Table2[Pay Item Description],Table2[Pay Item No.]),2,0) -> P-101-5.5a | L15: =Pay_Items!D13 -> Spall Repair, Concrete | M15: =IF(L15="","N/A",VLOOKUP(L15,CHOOSE({1,2},Table2[Pay Item Description],Table2[Units]),2,0)) -> S.F. | N15: ='Maintenance Policies'!D39*(C5*9) -> 780.0039 | O15: =IF(L15="","N/A",VLOOKUP(L15,CHOOSE({1,2},Table2[Pay Item Description],Table2[Unit Cost]),2,0)) -> 60 | P15: =O15*N15 -> 46800.234 | R15: 3 | S15: =VLOOKUP(T15,CHOOSE({1,2},Table2[Pay Item Description],Table2[Pay Item No.]),2,0) -> P-101-5.5a | T15: =Pay_Items!D13 -> Spall Repair, Concrete | U15: =IF(T15="","N/A",VLOOKUP(T15,CHOOSE({1,2},Table2[Pay Item Description],Table2[Units]),2,0)) -> S.F. | V15: ='Maintenance Policies'!D43*(C5*9) -> 780.0039 | W15: =IF(T15="","N/A",VLOOKUP(T15,CHOOSE({1,2},Table2[Pay Item Description],Table2[Unit Cost]),2,0)) -> 60 | X15: =W15*V15 -> 46800.234
A16: 4 | B16: =IF(C16="",0,VLOOKUP(C16,CHOOSE({1,2},Table2[Pay Item Description],Table2[Pay Item No.]),2,0)) -> 0 | D16: =IF(C16="","N/A",VLOOKUP(C16,CHOOSE({1,2},Table2[Pay Item Description],Table2[Units]),2,0)) -> N/A | F16: =IF(C16="","N/A",VLOOKUP(C16,CHOOSE({1,2},Table2[Pay Item Description],Table2[Unit Cost]),2,0)) -> N/A | G16: =IF(B16<>0,F16*E16,0) -> 0 | J16: 4 | K16: =VLOOKUP(L16,CHOOSE({1,2},Table2[Pay Item Description],Table2[Pay Item No.]),2,0) -> P-101-5.5b | L16: =Pay_Items!D14 -> Full-Depth Repair, Concrete | M16: =IF(L16="","N/A",VLOOKUP(L16,CHOOSE({1,2},Table2[Pay Item Description],Table2[Units]),2,0)) -> S.Y. | N16: ='Maintenance Policies'!D40*C5 -> 200.001 | O16: =IF(L16="","N/A",VLOOKUP(L16,CHOOSE({1,2},Table2[Pay Item Description],Table2[Unit Cost]),2,0)) -> 120 | P16: =O16*N16 -> 24000.12 | R16: 4 | S16: =VLOOKUP(T16,CHOOSE({1,2},Table2[Pay Item Description],Table2[Pay Item No.]),2,0) -> P-101-5.2c | T16: =Pay_Items!D8 -> Crack Seal, Concrete | U16: =IF(T16="","N/A",VLOOKUP(T16,CHOOSE({1,2},Table2[Pay Item Description],Table2[Units]),2,0)) -> L.F. | V16: ='Maintenance Policies'!D44*(C5*9) -> 1800.009 | W16: =IF(T16="","N/A",VLOOKUP(T16,CHOOSE({1,2},Table2[Pay Item Description],Table2[Unit Cost]),2,0)) -> 8 | X16: =W16*V16 -> 14400.072
A17: 5 | B17: =IF(C17="",0,VLOOKUP(C17,CHOOSE({1,2},Table2[Pay Item Description],Table2[Pay Item No.]),2,0)) -> 0 | D17: =IF(C17="","N/A",VLOOKUP(C17,CHOOSE({1,2},Table2[Pay Item Description],Table2[Units]),2,0)) -> N/A | F17: =IF(C17="","N/A",VLOOKUP(C17,CHOOSE({1,2},Table2[Pay Item Description],Table2[Unit Cost]),2,0)) -> N/A | G17: =IF(B17<>0,F17*E17,0) -> 0 | O17: Subtotal | P17: =SUM(P13:P16) -> 796803.98 | R17: 5 | S17: =VLOOKUP(T17,CHOOSE({1,2},Table2[Pay Item Description],Table2[Pay Item No.]),2,0) -> P-605-5.1a | T17: =Pay_Items!D55 -> Joint Clean and Reseal, Concrete | U17: =IF(T17="","N/A",VLOOKUP(T17,CHOOSE({1,2},Table2[Pay Item Description],Table2[Units]),2,0)) -> L.F. | V17: ='Maintenance Policies'!D45*K8 -> 102000.51 | W17: =IF(T17="","N/A",VLOOKUP(T17,CHOOSE({1,2},Table2[Pay Item Description],Table2[Unit Cost]),2,0)) -> 7 | X17: =W17*V17 -> 714003.57
A18: 6 | B18: =IF(C18="",0,VLOOKUP(C18,CHOOSE({1,2},Table2[Pay Item Description],Table2[Pay Item No.]),2,0)) -> 0 | D18: =IF(C18="","N/A",VLOOKUP(C18,CHOOSE({1,2},Table2[Pay Item Description],Table2[Units]),2,0)) -> N/A | F18: =IF(C18="","N/A",VLOOKUP(C18,CHOOSE({1,2},Table2[Pay Item Description],Table2[Unit Cost]),2,0)) -> N/A | G18: =IF(B18<>0,F18*E18,0) -> 0 | L18: Mobilization | P18: =('General Information'!$D$36/100)*P17 -> 79680.398 | W18: Subtotal | X18: =SUM(X13:X17) -> 932538
A19: 7 | B19: =IF(C19="",0,VLOOKUP(C19,CHOOSE({1,2},Table2[Pay Item Description],Table2[Pay Item No.]),2,0)) -> 0 | D19: =IF(C19="","N/A",VLOOKUP(C19,CHOOSE({1,2},Table2[Pay Item Description],Table2[Units]),2,0)) -> N/A | F19: =IF(C19="","N/A",VLOOKUP(C19,CHOOSE({1,2},Table2[Pay Item Description],Table2[Unit Cost]),2,0)) -> N/A | G19: =IF(B19<>0,F19*E19,0) -> 0 | L19: Engineering | P19: =('General Information'!$D$37/100)*P17 -> 39840.199 | T19: Mobilization | X19: =('General Information'!$D$36/100)*X18 -> 93253.8
A20: 8 | B20: =IF(C20="",0,VLOOKUP(C20,CHOOSE({1,2},Table2[Pay Item Description],Table2[Pay Item No.]),2,0)) -> 0 | D20: =IF(C20="","N/A",VLOOKUP(C20,CHOOSE({1,2},Table2[Pay Item Description],Table2[Units]),2,0)) -> N/A | F20: =IF(C20="","N/A",VLOOKUP(C20,CHOOSE({1,2},Table2[Pay Item Description],Table2[Unit Cost]),2,0)) -> N/A | G20: =IF(B20<>0,F20*E20,0) -> 0 | O20: Total | P20: =SUM(P17:P19) -> 916324.58 | T20: Engineering | X20: =('General Information'!$D$37/100)*X18 -> 46626.9
A21: 9 | B21: =IF(C21="",0,VLOOKUP(C21,CHOOSE({1,2},Table2[Pay Item Description],Table2[Pay Item No.]),2,0)) -> 0 | D21: =IF(C21="","N/A",VLOOKUP(C21,CHOOSE({1,2},Table2[Pay Item Description],Table2[Units]),2,0)) -> N/A | F21: =IF(C21="","N/A",VLOOKUP(C21,CHOOSE({1,2},Table2[Pay Item Description],Table2[Unit Cost]),2,0)) -> N/A | G21: =IF(B21<>0,F21*E21,0) -> 0 | W21: Total | X21: =SUM(X18:X20) -> 1072418.7
A22: 10 | B22: =IF(C22="",0,VLOOKUP(C22,CHOOSE({1,2},Table2[Pay Item Description],Table2[Pay Item No.]),2,0)) -> 0 | D22: =IF(C22="","N/A",VLOOKUP(C22,CHOOSE({1,2},Table2[Pay Item Description],Table2[Units]),2,0)) -> N/A | F22: =IF(C22="","N/A",VLOOKUP(C22,CHOOSE({1,2},Table2[Pay Item Description],Table2[Unit Cost]),2,0)) -> N/A | G22: =IF(B22<>0,F22*E22,0) -> 0
A24: Subtotal | G24: =SUM(G13:G22) -> 0
B25: Mobilization | G25: =('General Information'!$D$36/100)*G24 -> 0
B26: Engineering | G26: =('General Information'!$D$37/100)*G24 -> 0
A27: Total | G27: =SUM(G24:G26) -> 0
A33: Net Present Worth
A34: PCC Reconstruction - Alternative 2 | I34: Hidden
B36: Item | C36: Year Applied | D36: Actual Cost | E36: Discounted Cost
B37: Initial Construction | C37: =C6 -> 2028 | D37: =G27 -> 0 | E37: =D37 -> 0 | K37: Year | L37: Actual | M37: Discounted
B38: Maintenance 1 | C38: ='Maintenance Policies'!E37 -> 19 | D38: =P20 -> 916324.58 | E38: =IF(C38>'General Information'!$D$33,0,D38/(1+('General Information'!$D$34/100))^C38) -> 522567.1 | K38: =C6 -> 2028 | L38: =IF(K38-$C$6>'General Information'!$D$33,0,IF(K38=$C$6,$D$37,0)+SUMIF($C$38:$C$40,K38-$C$6,$D$38:$D$40)) -> 0 | M38: =IF(K38-$C$6>'General Information'!$D$33,0,IF(K38=$C$6,$E$37,0)+SUMIF($C$38:$C$40,K38-$C$6,$E$38:$E$40)) -> 0
B39: Rehabilitation 1 | C39: ='Maintenance Policies'!E41 -> 27 | D39: =X21 -> 1072418.7 | E39: =IF(C39>'General Information'!$D$33,0,D39/(1+('General Information'!$D$34/100))^C39) -> 482791.16 | K39: =K38+1 -> 2029 | L39: =IF(K39-$C$6>'General Information'!$D$33,0,IF(K39=$C$6,$D$37,0)+SUMIF($C$38:$C$40,K39-$C$6,$D$38:$D$40)) -> 0 | M39: =IF(K39-$C$6>'General Information'!$D$33,0,IF(K39=$C$6,$E$37,0)+SUMIF($C$38:$C$40,K39-$C$6,$E$38:$E$40)) -> 0
B40: Salvage | C40: ='General Information'!D33 -> 30 | D40: =-'Maintenance Policies'!D46*G27 -> 0 | E40: =IF(C40>'General Information'!$D$33,0,D40/(1+('General Information'!$D$34/100))^C40) -> 0 | K40: =K39+1 -> 2030 | L40: =IF(K40-$C$6>'General Information'!$D$33,0,IF(K40=$C$6,$D$37,0)+SUMIF($C$38:$C$40,K40-$C$6,$D$38:$D$40)) -> 0 | M40: =IF(K40-$C$6>'General Information'!$D$33,0,IF(K40=$C$6,$E$37,0)+SUMIF($C$38:$C$40,K40-$C$6,$E$38:$E$40)) -> 0
B41: Net Present Worth | E41: =SUM(E37:E40) -> 1005358.3 | K41: =K40+1 -> 2031 | L41: =IF(K41-$C$6>'General Information'!$D$33,0,IF(K41=$C$6,$D$37,0)+SUMIF($C$38:$C$40,K41-$C$6,$D$38:$D$40)) -> 0 | M41: =IF(K41-$C$6>'General Information'!$D$33,0,IF(K41=$C$6,$E$37,0)+SUMIF($C$38:$C$40,K41-$C$6,$E$38:$E$40)) -> 0
K42: =K41+1 -> 2032 | L42: =IF(K42-$C$6>'General Information'!$D$33,0,IF(K42=$C$6,$D$37,0)+SUMIF($C$38:$C$40,K42-$C$6,$D$38:$D$40)) -> 0 | M42: =IF(K42-$C$6>'General Information'!$D$33,0,IF(K42=$C$6,$E$37,0)+SUMIF($C$38:$C$40,K42-$C$6,$E$38:$E$40)) -> 0
K43: =K42+1 -> 2033 | L43: =IF(K43-$C$6>'General Information'!$D$33,0,IF(K43=$C$6,$D$37,0)+SUMIF($C$38:$C$40,K43-$C$6,$D$38:$D$40)) -> 0 | M43: =IF(K43-$C$6>'General Information'!$D$33,0,IF(K43=$C$6,$E$37,0)+SUMIF($C$38:$C$40,K43-$C$6,$E$38:$E$40)) -> 0
K44: =K43+1 -> 2034 | L44: =IF(K44-$C$6>'General Information'!$D$33,0,IF(K44=$C$6,$D$37,0)+SUMIF($C$38:$C$40,K44-$C$6,$D$38:$D$40)) -> 0 | M44: =IF(K44-$C$6>'General Information'!$D$33,0,IF(K44=$C$6,$E$37,0)+SUMIF($C$38:$C$40,K44-$C$6,$E$38:$E$40)) -> 0
K45: =K44+1 -> 2035 | L45: =IF(K45-$C$6>'General Information'!$D$33,0,IF(K45=$C$6,$D$37,0)+SUMIF($C$38:$C$40,K45-$C$6,$D$38:$D$40)) -> 0 | M45: =IF(K45-$C$6>'General Information'!$D$33,0,IF(K45=$C$6,$E$37,0)+SUMIF($C$38:$C$40,K45-$C$6,$E$38:$E$40)) -> 0
K46: =K45+1 -> 2036 | L46: =IF(K46-$C$6>'General Information'!$D$33,0,IF(K46=$C$6,$D$37,0)+SUMIF($C$38:$C$40,K46-$C$6,$D$38:$D$40)) -> 0 | M46: =IF(K46-$C$6>'General Information'!$D$33,0,IF(K46=$C$6,$E$37,0)+SUMIF($C$38:$C$40,K46-$C$6,$E$38:$E$40)) -> 0
K47: =K46+1 -> 2037 | L47: =IF(K47-$C$6>'General Information'!$D$33,0,IF(K47=$C$6,$D$37,0)+SUMIF($C$38:$C$40,K47-$C$6,$D$38:$D$40)) -> 0 | M47: =IF(K47-$C$6>'General Information'!$D$33,0,IF(K47=$C$6,$E$37,0)+SUMIF($C$38:$C$40,K47-$C$6,$E$38:$E$40)) -> 0
K48: =K47+1 -> 2038 | L48: =IF(K48-$C$6>'General Information'!$D$33,0,IF(K48=$C$6,$D$37,0)+SUMIF($C$38:$C$40,K48-$C$6,$D$38:$D$40)) -> 0 | M48: =IF(K48-$C$6>'General Information'!$D$33,0,IF(K48=$C$6,$E$37,0)+SUMIF($C$38:$C$40,K48-$C$6,$E$38:$E$40)) -> 0
K49: =K48+1 -> 2039 | L49: =IF(K49-$C$6>'General Information'!$D$33,0,IF(K49=$C$6,$D$37,0)+SUMIF($C$38:$C$40,K49-$C$6,$D$38:$D$40)) -> 0 | M49: =IF(K49-$C$6>'General Information'!$D$33,0,IF(K49=$C$6,$E$37,0)+SUMIF($C$38:$C$40,K49-$C$6,$E$38:$E$40)) -> 0
K50: =K49+1 -> 2040 | L50: =IF(K50-$C$6>'General Information'!$D$33,0,IF(K50=$C$6,$D$37,0)+SUMIF($C$38:$C$40,K50-$C$6,$D$38:$D$40)) -> 0 | M50: =IF(K50-$C$6>'General Information'!$D$33,0,IF(K50=$C$6,$E$37,0)+SUMIF($C$38:$C$40,K50-$C$6,$E$38:$E$40)) -> 0
K51: =K50+1 -> 2041 | L51: =IF(K51-$C$6>'General Information'!$D$33,0,IF(K51=$C$6,$D$37,0)+SUMIF($C$38:$C$40,K51-$C$6,$D$38:$D$40)) -> 0 | M51: =IF(K51-$C$6>'General Information'!$D$33,0,IF(K51=$C$6,$E$37,0)+SUMIF($C$38:$C$40,K51-$C$6,$E$38:$E$40)) -> 0
K52: =K51+1 -> 2042 | L52: =IF(K52-$C$6>'General Information'!$D$33,0,IF(K52=$C$6,$D$37,0)+SUMIF($C$38:$C$40,K52-$C$6,$D$38:$D$40)) -> 0 | M52: =IF(K52-$C$6>'General Information'!$D$33,0,IF(K52=$C$6,$E$37,0)+SUMIF($C$38:$C$40,K52-$C$6,$E$38:$E$40)) -> 0
K53: =K52+1 -> 2043 | L53: =IF(K53-$C$6>'General Information'!$D$33,0,IF(K53=$C$6,$D$37,0)+SUMIF($C$38:$C$40,K53-$C$6,$D$38:$D$40)) -> 0 | M53: =IF(K53-$C$6>'General Information'!$D$33,0,IF(K53=$C$6,$E$37,0)+SUMIF($C$38:$C$40,K53-$C$6,$E$38:$E$40)) -> 0
... K68: =K67+1 -> 2058 | L68: =IF(K68-$C$6>'General Information'!$D$33,0,IF(K68=$C$6,$D$37,0)+SUMIF($C$38:$C$40,K68-$C$6,$D$38:$D$40)) -> 0 | M68: =IF(K68-$C$6>'General Information'!$D$33,0,IF(K68=$C$6,$E$37,0)+SUMIF($C$38:$C$40,K68-$C$6,$E$38:$E$40)) -> 0

Sheet TMP(HMARehab)
I1: Hidden
A2: Initial Construction Costs: | J2: Maintenance 1 | R2: Maintenance 2 | Z2: Maintenance 3 | AH2: Rehabilitation 1 | AP2: Maintenance 4 | AX2: Maintenance 5 | BF2: Maintenance 6
A4: Pavement Type: | C4: HMA mill and overlay
A5: Mainline Pavement Area: | C5: ='General Information'!D26 -> 66667 | D5: S.Y.
A6: Initial Construction Year: | C6: ='General Information'!D25 -> 2028 | AH6: Mill and overlay: | AI6: 2 | AJ6: inches
A7: Asphalt Surface Treatment Type: | C7: Emulsified Asphalt Surface Treatment | D7: Select alternative treatment, if planned. | AH7: Asphalt: | AI7: 120 | AJ7: lbs/SY-in
A8: Markings Area: | C8: ='General Information'!D28 -> 15000 | D8: S.F.
AH9: Tack Coat Application | AI9: 0.07 | AJ9: gal/S.Y.
A12: Item No. | B12: Pay Item | C12: Description | D12: Unit | E12: Qty | F12: Unit Cost | G12: Item Cost | J12: Item No. | K12: Pay Item | L12: Description | M12: Unit | N12: Qty | O12: Unit Cost | P12: Item Cost | R12: Item No. | S12: Pay Item | T12: Description | U12: Unit | V12: Qty | W12: Unit Cost | X12: Item Cost | Z12: Item No. | AA12: Pay Item | AB12: Description | AC12: Unit | AD12: Qty | AE12: Unit Cost | AF12: Item Cost | AH12: Item No. | AI12: Pay Item | AJ12: Description | AK12: Unit | AL12: Qty | AM12: Unit Cost | AN12: Item Cost | AP12: Item No. | AQ12: Pay Item | AR12: Description | AS12: Unit | AT12: Qty | AU12: Unit Cost | AV12: Item Cost | AX12: Item No. | AY12: Pay Item | AZ12: Description | BA12: Unit | BB12: Qty | BC12: Unit Cost | BD12: Item Cost | BF12: Item No. | BG12: Pay Item | BH12: Description | BI12: Unit | BJ12: Qty | BK12: Unit Cost | BL12: Item Cost
A13: 1 | B13: =IF(C13="",0,VLOOKUP(C13,CHOOSE({1,2},Table2[Pay Item Description],Table2[Pay Item No.]),2,0)) -> 0 | D13: =IF(C13="","N/A",VLOOKUP(C13,CHOOSE({1,2},Table2[Pay Item Description],Table2[Units]),2,0)) -> N/A | E13: 0 | F13: =IF(C13="","N/A",VLOOKUP(C13,CHOOSE({1,2},Table2[Pay Item Description],Table2[Unit Cost]),2,0)) -> N/A | G13: =IF(B13<>0,F13*E13,0) -> 0 | J13: 1 | K13: =IF(L13="",0,VLOOKUP(L13,CHOOSE({1,2},Table2[Pay Item Description],Table2[Pay Item No.]),2,0)) -> P-608-8.1 | L13: =C7 -> Emulsified Asphalt Surface Treatment | M13: =IF(L13="","N/A",VLOOKUP(L13,CHOOSE({1,2},Table2[Pay Item Description],Table2[Units]),2,0)) -> S.Y. | N13: ='Maintenance Policies'!D51*$C$5 -> 66667 | O13: =IF(L13="","N/A",VLOOKUP(L13,CHOOSE({1,2},Table2[Pay Item Description],Table2[Unit Cost]),2,0)) -> 4 | P13: =O13*N13 -> 266668 | R13: 1 | S13: =IF(T13="",0,VLOOKUP(T13,CHOOSE({1,2},Table2[Pay Item Description],Table2[Pay Item No.]),2,0)) -> P-101-5.4a | T13: =Pay_Items!D11 -> Spall Repair, Asphalt | U13: =IF(T13="","N/A",VLOOKUP(T13,CHOOSE({1,2},Table2[Pay Item Description],Table2[Units]),2,0)) -> S.F. | V13: ='Maintenance Policies'!D53*($C$5*9) -> 7500.0375 | W13: =IF(T13="","N/A",VLOOKUP(T13,CHOOSE({1,2},Table2[Pay Item Description],Table2[Unit Cost]),2,0)) -> 8.5 | X13: =W13*V13 -> 63750.319 | Z13: 1 | AA13: =IF(AB13="",0,VLOOKUP(AB13,CHOOSE({1,2},Table2[Pay Item Description],Table2[Pay Item No.]),2,0)) -> P-608-8.1 | AB13: =C7 -> Emulsified Asphalt Surface Treatment | AC13: =IF(AB13="","N/A",VLOOKUP(AB13,CHOOSE({1,2},Table2[Pay Item Description],Table2[Units]),2,0)) -> S.Y. | AD13: ='Maintenance Policies'!D57*$C$5 -> 66667 | AE13: =IF(AB13="","N/A",VLOOKUP(AB13,CHOOSE({1,2},Table2[Pay Item Description],Table2[Unit Cost]),2,0)) -> 4 | AF13: =AE13*AD13 -> 266668 | AH13: 1 | AI13: =IF(AJ13="",0,VLOOKUP(AJ13,CHOOSE({1,2},Table2[Pay Item Description],Table2[Pay Item No.]),2,0)) -> P-101-5.6 | AJ13: Cold Milling | AK13: =IF(AJ13="","N/A",VLOOKUP(AJ13,CHOOSE({1,2},Table2[Pay Item Description],Table2[Units]),2,0)) -> S.Y. | AL13: ='Maintenance Policies'!D59*$C$5 -> 66667 | AM13: =IF(AJ13="","N/A",VLOOKUP(AJ13,CHOOSE({1,2},Table2[Pay Item Description],Table2[Unit Cost]),2,0)) -> 5 | AN13: =AM13*AL13 -> 333335 | AP13: 1 | AQ13: =IF(AR13="",0,VLOOKUP(AR13,CHOOSE({1,2},Table2[Pay Item Description],Table2[Pay Item No.]),2,0)) -> P-608-8.1 | AR13: =C7 -> Emulsified Asphalt Surface Treatment | AS13: =IF(AR13="","N/A",VLOOKUP(AR13,CHOOSE({1,2},Table2[Pay Item Description],Table2[Units]),2,0)) -> S.Y. | AT13: ='Maintenance Policies'!D63*$C$5 -> 66667 | AU13: =IF(AR13="","N/A",VLOOKUP(AR13,CHOOSE({1,2},Table2[Pay Item Description],Table2[Unit Cost]),2,0)) -> 4 | AV13: =AU13*AT13 -> 266668 | AX13: 1 | AY13: =IF(AZ13="",0,VLOOKUP(AZ13,CHOOSE({1,2},Table2[Pay Item Description],Table2[Pay Item No.]),2,0)) -> P-101-5.4a | AZ13: Spall Repair, Asphalt | BA13: =IF(AZ13="","N/A",VLOOKUP(AZ13,CHOOSE({1,2},Table2[Pay Item Description],Table2[Units]),2,0)) -> S.F. | BB13: ='Maintenance Policies'!D65*($C$5*9) -> 7500.0375 | BC13: =IF(AZ13="","N/A",VLOOKUP(AZ13,CHOOSE({1,2},Table2[Pay Item Description],Table2[Unit Cost]),2,0)) -> 8.5 | BD13: =BC13*BB13 -> 63750.319 | BF13: 1 | BG13: =IF(BH13="",0,VLOOKUP(BH13,CHOOSE({1,2},Table2[Pay Item Description],Table2[Pay Item No.]),2,0)) -> P-608-8.1 | BH13: =C7 -> Emulsified Asphalt Surface Treatment | BI13: =IF(BH13="","N/A",VLOOKUP(BH13,CHOOSE({1,2},Table2[Pay Item Description],Table2[Units]),2,0)) -> S.Y. | BJ13: ='Maintenance Policies'!D69*$C$5 -> 66667 | BK13: =IF(BH13="","N/A",VLOOKUP(BH13,CHOOSE({1,2},Table2[Pay Item Description],Table2[Unit Cost]),2,0)) -> 4 | BL13: =BK13*BJ13 -> 266668
A14: 2 | B14: =IF(C14="",0,VLOOKUP(C14,CHOOSE({1,2},Table2[Pay Item Description],Table2[Pay Item No.]),2,0)) -> 0 | D14: =IF(C14="","N/A",VLOOKUP(C14,CHOOSE({1,2},Table2[Pay Item Description],Table2[Units]),2,0)) -> N/A | E14: 0 | F14: =IF(C14="","N/A",VLOOKUP(C14,CHOOSE({1,2},Table2[Pay Item Description],Table2[Unit Cost]),2,0)) -> N/A | G14: =IF(B14<>0,F14*E14,0) -> 0 | J14: 2 | K14: =IF(L14="",0,VLOOKUP(L14,CHOOSE({1,2},Table2[Pay Item Description],Table2[Pay Item No.]),2,0)) -> P-101-5.3 | L14: Markings Removal | M14: =IF(L14="","N/A",VLOOKUP(L14,CHOOSE({1,2},Table2[Pay Item Description],Table2[Units]),2,0)) -> S.F. | N14: ='Maintenance Policies'!D52*$C$8 -> 15000 | O14: =IF(L14="","N/A",VLOOKUP(L14,CHOOSE({1,2},Table2[Pay Item Description],Table2[Unit Cost]),2,0)) -> 0.77777778 | P14: =O14*N14 -> 11666.667 | R14: 2 | S14: =IF(T14="",0,VLOOKUP(T14,CHOOSE({1,2},Table2[Pay Item Description],Table2[Pay Item No.]),2,0)) -> P-101-5.2a | T14: =Pay_Items!D6 -> Crack Repair (Type I), Asphalt | U14: =IF(T14="","N/A",VLOOKUP(T14,CHOOSE({1,2},Table2[Pay Item Description],Table2[Units]),2,0)) -> L.F. | V14: ='Maintenance Policies'!D54*($C$5*9) -> 24000.12 | W14: =IF(T14="","N/A",VLOOKUP(T14,CHOOSE({1,2},Table2[Pay Item Description],Table2[Unit Cost]),2,0)) -> 4 | X14: =W14*V14 -> 96000.48 | Z14: 2 | AA14: =IF(AB14="",0,VLOOKUP(AB14,CHOOSE({1,2},Table2[Pay Item Description],Table2[Pay Item No.]),2,0)) -> P-101-5.3 | AB14: Markings Removal | AC14: =IF(AB14="","N/A",VLOOKUP(AB14,CHOOSE({1,2},Table2[Pay Item Description],Table2[Units]),2,0)) -> S.F. | AD14: ='Maintenance Policies'!D58*$C$8 -> 15000 | AE14: =IF(AB14="","N/A",VLOOKUP(AB14,CHOOSE({1,2},Table2[Pay Item Description],Table2[Unit Cost]),2,0)) -> 0.77777778 | AF14: =AE14*AD14 -> 11666.667 | AH14: 2 | AI14: =IF(AJ14="",0,VLOOKUP(AJ14,CHOOSE({1,2},Table2[Pay Item Description],Table2[Pay Item No.]),2,0)) -> P-603-5.1 | AJ14: Emulsified Asphalt Tack Coat | AK14: =IF(AJ14="","N/A",VLOOKUP(AJ14,CHOOSE({1,2},Table2[Pay Item Description],Table2[Units]),2,0)) -> GAL | AL14: ='Maintenance Policies'!D59*$C$5*AI9 -> 4666.69 | AM14: =IF(AJ14="","N/A",VLOOKUP(AJ14,CHOOSE({1,2},Table2[Pay Item Description],Table2[Unit Cost]),2,0)) -> 4.5 | AN14: =AM14*AL14 -> 21000.105 | AP14: 2 | AQ14: =IF(AR14="",0,VLOOKUP(AR14,CHOOSE({1,2},Table2[Pay Item Description],Table2[Pay Item No.]),2,0)) -> P-101-5.3 | AR14: Markings Removal | AS14: =IF(AR14="","N/A",VLOOKUP(AR14,CHOOSE({1,2},Table2[Pay Item Description],Table2[Units]),2,0)) -> S.F. | AT14: ='Maintenance Policies'!D64*$C$8 -> 15000 | AU14: =IF(AR14="","N/A",VLOOKUP(AR14,CHOOSE({1,2},Table2[Pay Item Description],Table2[Unit Cost]),2,0)) -> 0.77777778 | AV14: =AU14*AT14 -> 11666.667 | AX14: 2 | AY14: =IF(AZ14="",0,VLOOKUP(AZ14,CHOOSE({1,2},Table2[Pay Item Description],Table2[Pay Item No.]),2,0)) -> P-101-5.2a | AZ14: Crack Repair (Type I), Asphalt | BA14: =IF(AZ14="","N/A",VLOOKUP(AZ14,CHOOSE({1,2},Table2[Pay Item Description],Table2[Units]),2,0)) -> L.F. | BB14: ='Maintenance Policies'!D66*($C$5*9) -> 24000.12 | BC14: =IF(AZ14="","N/A",VLOOKUP(AZ14,CHOOSE({1,2},Table2[Pay Item Description],Table2[Unit Cost]),2,0)) -> 4 | BD14: =BC14*BB14 -> 96000.48 | BF14: 2 | BG14: =IF(BH14="",0,VLOOKUP(BH14,CHOOSE({1,2},Table2[Pay Item Description],Table2[Pay Item No.]),2,0)) -> P-101-5.3 | BH14: Markings Removal | BI14: =IF(BH14="","N/A",VLOOKUP(BH14,CHOOSE({1,2},Table2[Pay Item Description],Table2[Units]),2,0)) -> S.F. | BJ14: ='Maintenance Policies'!D70*$C$8 -> 15000 | BK14: =IF(BH14="","N/A",VLOOKUP(BH14,CHOOSE({1,2},Table2[Pay Item Description],Table2[Unit Cost]),2,0)) -> 0.77777778 | BL14: =BK14*BJ14 -> 11666.667
A15: 3 | B15: =IF(C15="",0,VLOOKUP(C15,CHOOSE({1,2},Table2[Pay Item Description],Table2[Pay Item No.]),2,0)) -> 0 | D15: =IF(C15="","N/A",VLOOKUP(C15,CHOOSE({1,2},Table2[Pay Item Description],Table2[Units]),2,0)) -> N/A | E15: 0 | F15: =IF(C15="","N/A",VLOOKUP(C15,CHOOSE({1,2},Table2[Pay Item Description],Table2[Unit Cost]),2,0)) -> N/A | G15: =IF(B15<>0,F15*E15,0) -> 0 | J15: 3 | K15: =IF(L15="",0,VLOOKUP(L15,CHOOSE({1,2},Table2[Pay Item Description],Table2[Pay Item No.]),2,0)) -> P-620-5.1a | L15: Markings (prep, markings, reflective media) | M15: =IF(L15="","N/A",VLOOKUP(L15,CHOOSE({1,2},Table2[Pay Item Description],Table2[Units]),2,0)) -> S.F. | N15: ='Maintenance Policies'!D52*$C$8 -> 15000 | O15: =IF(L15="","N/A",VLOOKUP(L15,CHOOSE({1,2},Table2[Pay Item Description],Table2[Unit Cost]),2,0)) -> 0.66666667 | P15: =O15*N15 -> 10000 | R15: 3 | S15: =IF(T15="",0,VLOOKUP(T15,CHOOSE({1,2},Table2[Pay Item Description],Table2[Pay Item No.]),2,0)) -> P-608-8.1 | T15: =C7 -> Emulsified Asphalt Surface Treatment | U15: =IF(T15="","N/A",VLOOKUP(T15,CHOOSE({1,2},Table2[Pay Item Description],Table2[Units]),2,0)) -> S.Y. | V15: ='Maintenance Policies'!D55*$C$5 -> 66667 | W15: =IF(T15="","N/A",VLOOKUP(T15,CHOOSE({1,2},Table2[Pay Item Description],Table2[Unit Cost]),2,0)) -> 4 | X15: =W15*V15 -> 266668 | Z15: 3 | AA15: =IF(AB15="",0,VLOOKUP(AB15,CHOOSE({1,2},Table2[Pay Item Description],Table2[Pay Item No.]),2,0)) -> P-620-5.1a | AB15: Markings (prep, markings, reflective media) | AC15: =IF(AB15="","N/A",VLOOKUP(AB15,CHOOSE({1,2},Table2[Pay Item Description],Table2[Units]),2,0)) -> S.F. | AD15: ='Maintenance Policies'!D58*$C$8 -> 15000 | AE15: =IF(AB15="","N/A",VLOOKUP(AB15,CHOOSE({1,2},Table2[Pay Item Description],Table2[Unit Cost]),2,0)) -> 0.66666667 | AF15: =AE15*AD15 -> 10000 | AH15: 3 | AI15: =IF(AJ15="",0,VLOOKUP(AJ15,CHOOSE({1,2},Table2[Pay Item Description],Table2[Pay Item No.]),2,0)) -> P-401-8.1a | AJ15: Asphalt Surface Course | AK15: =IF(AJ15="","N/A",VLOOKUP(AJ15,CHOOSE({1,2},Table2[Pay Item Description],Table2[Units]),2,0)) -> TON | AL15: ='Maintenance Policies'!D59*$C$5*AI6*AI7/2000 -> 8000.04 | AM15: =IF(AJ15="","N/A",VLOOKUP(AJ15,CHOOSE({1,2},Table2[Pay Item Description],Table2[Unit Cost]),2,0)) -> 130 | AN15: =AM15*AL15 -> 1040005.2 | AP15: 3 | AQ15: =IF(AR15="",0,VLOOKUP(AR15,CHOOSE({1,2},Table2[Pay Item Description],Table2[Pay Item No.]),2,0)) -> P-620-5.1a | AR15: Markings (prep, markings, reflective media) | AS15: =IF(AR15="","N/A",VLOOKUP(AR15,CHOOSE({1,2},Table2[Pay Item Description],Table2[Units]),2,0)) -> S.F. | AT15: ='Maintenance Policies'!D64*$C$8 -> 15000 | AU15: =IF(AR15="","N/A",VLOOKUP(AR15,CHOOSE({1,2},Table2[Pay Item Description],Table2[Unit Cost]),2,0)) -> 0.66666667 | AV15: =AU15*AT15 -> 10000 | AX15: 3 | AY15: =IF(AZ15="",0,VLOOKUP(AZ15,CHOOSE({1,2},Table2[Pay Item Description],Table2[Pay Item No.]),2,0)) -> P-608-8.1 | AZ15: =C7 -> Emulsified Asphalt Surface Treatment | BA15: =IF(AZ15="","N/A",VLOOKUP(AZ15,CHOOSE({1,2},Table2[Pay Item Description],Table2[Units]),2,0)) -> S.Y. | BB15: ='Maintenance Policies'!D67*$C$5 -> 66667 | BC15: =IF(AZ15="","N/A",VLOOKUP(AZ15,CHOOSE({1,2},Table2[Pay Item Description],Table2[Unit Cost]),2,0)) -> 4 | BD15: =BC15*BB15 -> 266668 | BF15: 3 | BG15: =IF(BH15="",0,VLOOKUP(BH15,CHOOSE({1,2},Table2[Pay Item Description],Table2[Pay Item No.]),2,0)) -> P-620-5.1a | BH15: Markings (prep, markings, reflective media) | BI15: =IF(BH15="","N/A",VLOOKUP(BH15,CHOOSE({1,2},Table2[Pay Item Description],Table2[Units]),2,0)) -> S.F. | BJ15: ='Maintenance Policies'!D70*$C$8 -> 15000 | BK15: =IF(BH15="","N/A",VLOOKUP(BH15,CHOOSE({1,2},Table2[Pay Item Description],Table2[Unit Cost]),2,0)) -> 0.66666667 | BL15: =BK15*BJ15 -> 10000
A16: 4 | B16: =IF(C16="",0,VLOOKUP(C16,CHOOSE({1,2},Table2[Pay Item Description],Table2[Pay Item No.]),2,0)) -> 0 | D16: =IF(C16="","N/A",VLOOKUP(C16,CHOOSE({1,2},Table2[Pay Item Description],Table2[Units]),2,0)) -> N/A | E16: 0 | F16: =IF(C16="","N/A",VLOOKUP(C16,CHOOSE({1,2},Table2[Pay Item Description],Table2[Unit Cost]),2,0)) -> N/A | G16: =IF(B16<>0,F16*E16,0) -> 0 | O16: Subtotal | P16: =SUM(P13:P15) -> 288334.67 | R16: 4 | S16: =IF(T16="",0,VLOOKUP(T16,CHOOSE({1,2},Table2[Pay Item Description],Table2[Pay Item No.]),2,0)) -> P-101-5.3 | T16: =Pay_Items!D10 -> Markings Removal | U16: =IF(T16="","N/A",VLOOKUP(T16,CHOOSE({1,2},Table2[Pay Item Description],Table2[Units]),2,0)) -> S.F. | V16: ='Maintenance Policies'!D56*$C$8 -> 15000 | W16: =IF(T16="","N/A",VLOOKUP(T16,CHOOSE({1,2},Table2[Pay Item Description],Table2[Unit Cost]),2,0)) -> 0.77777778 | X16: =W16*V16 -> 11666.667 | AE16: Subtotal | AF16: =SUM(AF13:AF15) -> 288334.67 | AH16: 4 | AI16: =IF(AJ16="",0,VLOOKUP(AJ16,CHOOSE({1,2},Table2[Pay Item Description],Table2[Pay Item No.]),2,0)) -> P-101-5.2a | AJ16: Crack Repair (Type I), Asphalt | AK16: =IF(AJ16="","N/A",VLOOKUP(AJ16,CHOOSE({1,2},Table2[Pay Item Description],Table2[Units]),2,0)) -> L.F. | AL16: ='Maintenance Policies'!D60*($C$5*9) -> 9000.045 | AM16: =IF(AJ16="","N/A",VLOOKUP(AJ16,CHOOSE({1,2},Table2[Pay Item Description],Table2[Unit Cost]),2,0)) -> 4 | AN16: =AM16*AL16 -> 36000.18 | AU16: Subtotal | AV16: =SUM(AV13:AV15) -> 288334.67 | AX16: 4 | AY16: =IF(AZ16="",0,VLOOKUP(AZ16,CHOOSE({1,2},Table2[Pay Item Description],Table2[Pay Item No.]),2,0)) -> P-101-5.3 | AZ16: Markings Removal | BA16: =IF(AZ16="","N/A",VLOOKUP(AZ16,CHOOSE({1,2},Table2[Pay Item Description],Table2[Units]),2,0)) -> S.F. | BB16: ='Maintenance Policies'!D68*$C$8 -> 15000 | BC16: =IF(AZ16="","N/A",VLOOKUP(AZ16,CHOOSE({1,2},Table2[Pay Item Description],Table2[Unit Cost]),2,0)) -> 0.77777778 | BD16: =BC16*BB16 -> 11666.667 | BK16: Subtotal | BL16: =SUM(BL13:BL15) -> 288334.67
A17: 5 | B17: =IF(C17="",0,VLOOKUP(C17,CHOOSE({1,2},Table2[Pay Item Description],Table2[Pay Item No.]),2,0)) -> 0 | D17: =IF(C17="","N/A",VLOOKUP(C17,CHOOSE({1,2},Table2[Pay Item Description],Table2[Units]),2,0)) -> N/A | E17: 0 | F17: =IF(C17="","N/A",VLOOKUP(C17,CHOOSE({1,2},Table2[Pay Item Description],Table2[Unit Cost]),2,0)) -> N/A | G17: =IF(B17<>0,F17*E17,0) -> 0 | L17: Mobilization | P17: =('General Information'!$D$36/100)*P16 -> 28833.467 | R17: 5 | S17: =IF(T17="",0,VLOOKUP(T17,CHOOSE({1,2},Table2[Pay Item Description],Table2[Pay Item No.]),2,0)) -> P-620-5.1a | T17: =Pay_Items!D56 -> Markings (prep, markings, reflective media) | U17: =IF(T17="","N/A",VLOOKUP(T17,CHOOSE({1,2},Table2[Pay Item Description],Table2[Units]),2,0)) -> S.F. | V17: ='Maintenance Policies'!D56*$C$8 -> 15000 | W17: =IF(T17="","N/A",VLOOKUP(T17,CHOOSE({1,2},Table2[Pay Item Description],Table2[Unit Cost]),2,0)) -> 0.66666667 | X17: =W17*V17 -> 10000 | AB17: Mobilization | AF17: =('General Information'!$D$36/100)*AF16 -> 28833.467 | AH17: 5 | AI17: =IF(AJ17="",0,VLOOKUP(AJ17,CHOOSE({1,2},Table2[Pay Item Description],Table2[Pay Item No.]),2,0)) -> P-101-5.4a | AJ17: Spall Repair, Asphalt | AK17: =IF(AJ17="","N/A",VLOOKUP(AJ17,CHOOSE({1,2},Table2[Pay Item Description],Table2[Units]),2,0)) -> S.F. | AL17: ='Maintenance Policies'!D61*($C$5*9) -> 3000.015 | AM17: =IF(AJ17="","N/A",VLOOKUP(AJ17,CHOOSE({1,2},Table2[Pay Item Description],Table2[Unit Cost]),2,0)) -> 8.5 | AN17: =AM17*AL17 -> 25500.127 | AR17: Mobilization | AV17: =('General Information'!$D$36/100)*AV16 -> 28833.467 | AX17: 5 | AY17: =IF(AZ17="",0,VLOOKUP(AZ17,CHOOSE({1,2},Table2[Pay Item Description],Table2[Pay Item No.]),2,0)) -> P-620-5.1a | AZ17: Markings (prep, markings, reflective media) | BA17: =IF(AZ17="","N/A",VLOOKUP(AZ17,CHOOSE({1,2},Table2[Pay Item Description],Table2[Units]),2,0)) -> S.F. | BB17: ='Maintenance Policies'!D68*$C$8 -> 15000 | BC17: =IF(AZ17="","N/A",VLOOKUP(AZ17,CHOOSE({1,2},Table2[Pay Item Description],Table2[Unit Cost]),2,0)) -> 0.66666667 | BD17: =BC17*BB17 -> 10000 | BH17: Mobilization | BL17: =('General Information'!$D$36/100)*BL16 -> 28833.467
A18: 6 | B18: =IF(C18="",0,VLOOKUP(C18,CHOOSE({1,2},Table2[Pay Item Description],Table2[Pay Item No.]),2,0)) -> 0 | D18: =IF(C18="","N/A",VLOOKUP(C18,CHOOSE({1,2},Table2[Pay Item Description],Table2[Units]),2,0)) -> N/A | E18: 0 | F18: =IF(C18="","N/A",VLOOKUP(C18,CHOOSE({1,2},Table2[Pay Item Description],Table2[Unit Cost]),2,0)) -> N/A | G18: =IF(B18<>0,F18*E18,0) -> 0 | L18: Engineering | P18: =('General Information'!$D$37/100)*P16 -> 14416.733 | W18: Subtotal | X18: =SUM(X13:X17) -> 448085.47 | AB18: Engineering | AF18: =('General Information'!$D$37/100)*AF16 -> 14416.733 | AH18: 6 | AI18: =IF(AJ18="",0,VLOOKUP(AJ18,CHOOSE({1,2},Table2[Pay Item Description],Table2[Pay Item No.]),2,0)) -> P-620-5.1a | AJ18: Markings (prep, markings, reflective media) | AK18: =IF(AJ18="","N/A",VLOOKUP(AJ18,CHOOSE({1,2},Table2[Pay Item Description],Table2[Units]),2,0)) -> S.F. | AL18: ='Maintenance Policies'!D62*$C$8 -> 15000 | AM18: =IF(AJ18="","N/A",VLOOKUP(AJ18,CHOOSE({1,2},Table2[Pay Item Description],Table2[Unit Cost]),2,0)) -> 0.66666667 | AN18: =AM18*AL18 -> 10000 | AR18: Engineering | AV18: =('General Information'!$D$37/100)*AV16 -> 14416.733 | BC18: Subtotal | BD18: =SUM(BD13:BD17) -> 448085.47 | BH18: Engineering | BL18: =('General Information'!$D$37/100)*BL16 -> 14416.733
A19: 7 | B19: =IF(C19="",0,VLOOKUP(C19,CHOOSE({1,2},Table2[Pay Item Description],Table2[Pay Item No.]),2,0)) -> 0 | D19: =IF(C19="","N/A",VLOOKUP(C19,CHOOSE({1,2},Table2[Pay Item Description],Table2[Units]),2,0)) -> N/A | E19: 0 | F19: =IF(C19="","N/A",VLOOKUP(C19,CHOOSE({1,2},Table2[Pay Item Description],Table2[Unit Cost]),2,0)) -> N/A | G19: =IF(B19<>0,F19*E19,0) -> 0 | O19: Total | P19: =SUM(P16:P18) -> 331584.87 | T19: Mobilization | X19: =('General Information'!$D$36/100)*X18 -> 44808.547 | AE19: Total | AF19: =SUM(AF16:AF18) -> 331584.87 | AM19: Subtotal | AN19: =SUM(AN13:AN18) -> 1465840.6 | AU19: Total | AV19: =SUM(AV16:AV18) -> 331584.87 | AZ19: Mobilization | BD19: =('General Information'!$D$36/100)*BD18 -> 44808.547 | BK19: Total | BL19: =SUM(BL16:BL18) -> 331584.87
A20: 8 | B20: =IF(C20="",0,VLOOKUP(C20,CHOOSE({1,2},Table2[Pay Item Description],Table2[Pay Item No.]),2,0)) -> 0 | D20: =IF(C20="","N/A",VLOOKUP(C20,CHOOSE({1,2},Table2[Pay Item Description],Table2[Units]),2,0)) -> N/A | E20: 0 | F20: =IF(C20="","N/A",VLOOKUP(C20,CHOOSE({1,2},Table2[Pay Item Description],Table2[Unit Cost]),2,0)) -> N/A | G20: =IF(B20<>0,F20*E20,0) -> 0 | T20: Engineering | X20: =('General Information'!$D$37/100)*X18 -> 22404.273 | AJ20: Mobilization | AN20: =('General Information'!$D$36/100)*AN19 -> 146584.06 | AZ20: Engineering | BD20: =('General Information'!$D$37/100)*BD18 -> 22404.273
A21: 9 | B21: =IF(C21="",0,VLOOKUP(C21,CHOOSE({1,2},Table2[Pay Item Description],Table2[Pay Item No.]),2,0)) -> 0 | D21: =IF(C21="","N/A",VLOOKUP(C21,CHOOSE({1,2},Table2[Pay Item Description],Table2[Units]),2,0)) -> N/A | E21: 0 | F21: =IF(C21="","N/A",VLOOKUP(C21,CHOOSE({1,2},Table2[Pay Item Description],Table2[Unit Cost]),2,0)) -> N/A | G21: =IF(B21<>0,F21*E21,0) -> 0 | W21: Total | X21: =SUM(X18:X20) -> 515298.29 | AJ21: Engineering | AN21: =('General Information'!$D$37/100)*AN19 -> 73292.031 | BC21: Total | BD21: =SUM(BD18:BD20) -> 515298.29
A22: 10 | B22: =IF(C22="",0,VLOOKUP(C22,CHOOSE({1,2},Table2[Pay Item Description],Table2[Pay Item No.]),2,0)) -> 0 | D22: =IF(C22="","N/A",VLOOKUP(C22,CHOOSE({1,2},Table2[Pay Item Description],Table2[Units]),2,0)) -> N/A | E22: 0 | F22: =IF(C22="","N/A",VLOOKUP(C22,CHOOSE({1,2},Table2[Pay Item Description],Table2[Unit Cost]),2,0)) -> N/A | G22: =IF(B22<>0,F22*E22,0) -> 0 | AM22: Total | AN22: =SUM(AN19:AN21) -> 1685716.7
A24: Subtotal | G24: =SUM(G13:G22) -> 0
B25: Mobilization | G25: =('General Information'!$D$36/100)*G24 -> 0
B26: Engineering | G26: =('General Information'!$D$37/100)*G24 -> 0
A27: Total | G27: =SUM(G24:G26) -> 0
A32: Net Present Worth
A33: HMA Mill and Overlay - Alternative 3 | I33: Hidden
B35: Item | C35: Year Applied | D35: Actual Cost | E35: Discounted Cost
B36: Initial Construction | C36: =C6 -> 2028 | D36: =G27 -> 0 | E36: =D36 -> 0 | K36: Year | L36: Actual | M36: Discounted
B37: Maintenance 1 | C37: ='Maintenance Policies'!E51 -> 4 | D37: =P19 -> 331584.87 | E37: =IF(C37>'General Information'!$D$33,0,D37/(1+('General Information'!$D$34/100))^C37) -> 294608.86 | K37: =C6 -> 2028 | L37: =IF(K37-$C$6>'General Information'!$D$33,0,IF(K37=$C$6,$D$36,0)+SUMIF($C$37:$C$44,K37-$C$6,$D$37:$D$44)) -> 0 | M37: =IF(K37-$C$6>'General Information'!$D$33,0,IF(K37=$C$6,$E$36,0)+SUMIF($C$37:$C$44,K37-$C$6,$E$37:$E$44)) -> 0
B38: Maintenance 2 | C38: ='Maintenance Policies'!E53 -> 8 | D38: =X21 -> 515298.29 | E38: =IF(C38>'General Information'!$D$33,0,D38/(1+('General Information'!$D$34/100))^C38) -> 406781.22 | K38: =K37+1 -> 2029 | L38: =IF(K38-$C$6>'General Information'!$D$33,0,IF(K38=$C$6,$D$36,0)+SUMIF($C$37:$C$44,K38-$C$6,$D$37:$D$44)) -> 0 | M38: =IF(K38-$C$6>'General Information'!$D$33,0,IF(K38=$C$6,$E$36,0)+SUMIF($C$37:$C$44,K38-$C$6,$E$37:$E$44)) -> 0
B39: Maintenance 3 | C39: ='Maintenance Policies'!E57 -> 12 | D39: =AF19 -> 331584.87 | E39: =IF(C39>'General Information'!$D$33,0,D39/(1+('General Information'!$D$34/100))^C39) -> 232566.95 | K39: =K38+1 -> 2030 | L39: =IF(K39-$C$6>'General Information'!$D$33,0,IF(K39=$C$6,$D$36,0)+SUMIF($C$37:$C$44,K39-$C$6,$D$37:$D$44)) -> 0 | M39: =IF(K39-$C$6>'General Information'!$D$33,0,IF(K39=$C$6,$E$36,0)+SUMIF($C$37:$C$44,K39-$C$6,$E$37:$E$44)) -> 0
B40: Rehabilitation 1 | C40: ='Maintenance Policies'!E59 -> 16 | D40: =AN22 -> 1685716.7 | E40: =IF(C40>'General Information'!$D$33,0,D40/(1+('General Information'!$D$34/100))^C40) -> 1050482.9 | K40: =K39+1 -> 2031 | L40: =IF(K40-$C$6>'General Information'!$D$33,0,IF(K40=$C$6,$D$36,0)+SUMIF($C$37:$C$44,K40-$C$6,$D$37:$D$44)) -> 0 | M40: =IF(K40-$C$6>'General Information'!$D$33,0,IF(K40=$C$6,$E$36,0)+SUMIF($C$37:$C$44,K40-$C$6,$E$37:$E$44)) -> 0
B41: Maintenance 4 | C41: ='Maintenance Policies'!E63 -> 20 | D41: =AV19 -> 331584.87 | E41: =IF(C41>'General Information'!$D$33,0,D41/(1+('General Information'!$D$34/100))^C41) -> 183590.5 | K41: =K40+1 -> 2032 | L41: =IF(K41-$C$6>'General Information'!$D$33,0,IF(K41=$C$6,$D$36,0)+SUMIF($C$37:$C$44,K41-$C$6,$D$37:$D$44)) -> 331584.87 | M41: =IF(K41-$C$6>'General Information'!$D$33,0,IF(K41=$C$6,$E$36,0)+SUMIF($C$37:$C$44,K41-$C$6,$E$37:$E$44)) -> 294608.86
B42: Maintenance 5 | C42: ='Maintenance Policies'!E65 -> 24 | D42: =BD21 -> 515298.29 | E42: =IF(C42>'General Information'!$D$33,0,D42/(1+('General Information'!$D$34/100))^C42) -> 253492.61 | K42: =K41+1 -> 2033 | L42: =IF(K42-$C$6>'General Information'!$D$33,0,IF(K42=$C$6,$D$36,0)+SUMIF($C$37:$C$44,K42-$C$6,$D$37:$D$44)) -> 0 | M42: =IF(K42-$C$6>'General Information'!$D$33,0,IF(K42=$C$6,$E$36,0)+SUMIF($C$37:$C$44,K42-$C$6,$E$37:$E$44)) -> 0
B43: Maintenance 6 | C43: ='Maintenance Policies'!E69 -> 28 | D43: =BL19 -> 331584.87 | E43: =IF(C43>'General Information'!$D$33,0,D43/(1+('General Information'!$D$34/100))^C43) -> 144928.04 | K43: =K42+1 -> 2034 | L43: =IF(K43-$C$6>'General Information'!$D$33,0,IF(K43=$C$6,$D$36,0)+SUMIF($C$37:$C$44,K43-$C$6,$D$37:$D$44)) -> 0 | M43: =IF(K43-$C$6>'General Information'!$D$33,0,IF(K43=$C$6,$E$36,0)+SUMIF($C$37:$C$44,K43-$C$6,$E$37:$E$44)) -> 0
B44: Salvage | C44: ='General Information'!D33 -> 30 | D44: =-'Maintenance Policies'!D71*AN22 -> 0 | E44: =IF(C44>'General Information'!$D$33,0,D44/(1+('General Information'!$D$34/100))^C44) -> 0 | K44: =K43+1 -> 2035 | L44: =IF(K44-$C$6>'General Information'!$D$33,0,IF(K44=$C$6,$D$36,0)+SUMIF($C$37:$C$44,K44-$C$6,$D$37:$D$44)) -> 0 | M44: =IF(K44-$C$6>'General Information'!$D$33,0,IF(K44=$C$6,$E$36,0)+SUMIF($C$37:$C$44,K44-$C$6,$E$37:$E$44)) -> 0
B45: Net Present Worth | E45: =SUM(E36:E44) -> 2566451.1 | K45: =K44+1 -> 2036 | L45: =IF(K45-$C$6>'General Information'!$D$33,0,IF(K45=$C$6,$D$36,0)+SUMIF($C$37:$C$44,K45-$C$6,$D$37:$D$44)) -> 515298.29 | M45: =IF(K45-$C$6>'General Information'!$D$33,0,IF(K45=$C$6,$E$36,0)+SUMIF($C$37:$C$44,K45-$C$6,$E$37:$E$44)) -> 406781.22
K46: =K45+1 -> 2037 | L46: =IF(K46-$C$6>'General Information'!$D$33,0,IF(K46=$C$6,$D$36,0)+SUMIF($C$37:$C$44,K46-$C$6,$D$37:$D$44)) -> 0 | M46: =IF(K46-$C$6>'General Information'!$D$33,0,IF(K46=$C$6,$E$36,0)+SUMIF($C$37:$C$44,K46-$C$6,$E$37:$E$44)) -> 0
K47: =K46+1 -> 2038 | L47: =IF(K47-$C$6>'General Information'!$D$33,0,IF(K47=$C$6,$D$36,0)+SUMIF($C$37:$C$44,K47-$C$6,$D$37:$D$44)) -> 0 | M47: =IF(K47-$C$6>'General Information'!$D$33,0,IF(K47=$C$6,$E$36,0)+SUMIF($C$37:$C$44,K47-$C$6,$E$37:$E$44)) -> 0
K48: =K47+1 -> 2039 | L48: =IF(K48-$C$6>'General Information'!$D$33,0,IF(K48=$C$6,$D$36,0)+SUMIF($C$37:$C$44,K48-$C$6,$D$37:$D$44)) -> 0 | M48: =IF(K48-$C$6>'General Information'!$D$33,0,IF(K48=$C$6,$E$36,0)+SUMIF($C$37:$C$44,K48-$C$6,$E$37:$E$44)) -> 0
K49: =K48+1 -> 2040 | L49: =IF(K49-$C$6>'General Information'!$D$33,0,IF(K49=$C$6,$D$36,0)+SUMIF($C$37:$C$44,K49-$C$6,$D$37:$D$44)) -> 331584.87 | M49: =IF(K49-$C$6>'General Information'!$D$33,0,IF(K49=$C$6,$E$36,0)+SUMIF($C$37:$C$44,K49-$C$6,$E$37:$E$44)) -> 232566.95
K50: =K49+1 -> 2041 | L50: =IF(K50-$C$6>'General Information'!$D$33,0,IF(K50=$C$6,$D$36,0)+SUMIF($C$37:$C$44,K50-$C$6,$D$37:$D$44)) -> 0 | M50: =IF(K50-$C$6>'General Information'!$D$33,0,IF(K50=$C$6,$E$36,0)+SUMIF($C$37:$C$44,K50-$C$6,$E$37:$E$44)) -> 0
K51: =K50+1 -> 2042 | L51: =IF(K51-$C$6>'General Information'!$D$33,0,IF(K51=$C$6,$D$36,0)+SUMIF($C$37:$C$44,K51-$C$6,$D$37:$D$44)) -> 0 | M51: =IF(K51-$C$6>'General Information'!$D$33,0,IF(K51=$C$6,$E$36,0)+SUMIF($C$37:$C$44,K51-$C$6,$E$37:$E$44)) -> 0
K52: =K51+1 -> 2043 | L52: =IF(K52-$C$6>'General Information'!$D$33,0,IF(K52=$C$6,$D$36,0)+SUMIF($C$37:$C$44,K52-$C$6,$D$37:$D$44)) -> 0 | M52: =IF(K52-$C$6>'General Information'!$D$33,0,IF(K52=$C$6,$E$36,0)+SUMIF($C$37:$C$44,K52-$C$6,$E$37:$E$44)) -> 0
K53: =K52+1 -> 2044 | L53: =IF(K53-$C$6>'General Information'!$D$33,0,IF(K53=$C$6,$D$36,0)+SUMIF($C$37:$C$44,K53-$C$6,$D$37:$D$44)) -> 1685716.7 | M53: =IF(K53-$C$6>'General Information'!$D$33,0,IF(K53=$C$6,$E$36,0)+SUMIF($C$37:$C$44,K53-$C$6,$E$37:$E$44)) -> 1050482.9
K54: =K53+1 -> 2045 | L54: =IF(K54-$C$6>'General Information'!$D$33,0,IF(K54=$C$6,$D$36,0)+SUMIF($C$37:$C$44,K54-$C$6,$D$37:$D$44)) -> 0 | M54: =IF(K54-$C$6>'General Information'!$D$33,0,IF(K54=$C$6,$E$36,0)+SUMIF($C$37:$C$44,K54-$C$6,$E$37:$E$44)) -> 0
K55: =K54+1 -> 2046 | L55: =IF(K55-$C$6>'General Information'!$D$33,0,IF(K55=$C$6,$D$36,0)+SUMIF($C$37:$C$44,K55-$C$6,$D$37:$D$44)) -> 0 | M55: =IF(K55-$C$6>'General Information'!$D$33,0,IF(K55=$C$6,$E$36,0)+SUMIF($C$37:$C$44,K55-$C$6,$E$37:$E$44)) -> 0
K56: =K55+1 -> 2047 | L56: =IF(K56-$C$6>'General Information'!$D$33,0,IF(K56=$C$6,$D$36,0)+SUMIF($C$37:$C$44,K56-$C$6,$D$37:$D$44)) -> 0 | M56: =IF(K56-$C$6>'General Information'!$D$33,0,IF(K56=$C$6,$E$36,0)+SUMIF($C$37:$C$44,K56-$C$6,$E$37:$E$44)) -> 0
K57: =K56+1 -> 2048 | L57: =IF(K57-$C$6>'General Information'!$D$33,0,IF(K57=$C$6,$D$36,0)+SUMIF($C$37:$C$44,K57-$C$6,$D$37:$D$44)) -> 331584.87 | M57: =IF(K57-$C$6>'General Information'!$D$33,0,IF(K57=$C$6,$E$36,0)+SUMIF($C$37:$C$44,K57-$C$6,$E$37:$E$44)) -> 183590.5
... K67: =K66+1 -> 2058 | L67: =IF(K67-$C$6>'General Information'!$D$33,0,IF(K67=$C$6,$D$36,0)+SUMIF($C$37:$C$44,K67-$C$6,$D$37:$D$44)) -> 0 | M67: =IF(K67-$C$6>'General Information'!$D$33,0,IF(K67=$C$6,$E$36,0)+SUMIF($C$37:$C$44,K67-$C$6,$E$37:$E$44)) -> 0

Sheet TMP(PCCRehab)
A1: Coming soon.
E45: I

Sheet Summary
A1: =HYPERLINK("#'General Information'!D9","◄ General Information") -> ◄ General Information | B1: =HYPERLINK("#Instructions!B9","Instructions") -> Instructions | G1: LCCA SUMMARY | W1: CHART DATA (calculated automatically from the table on the left; do not edit)
G2: Everything from this column onward calculates from the alternative worksheets and updates by itself. Columns A:E and "Chart 1" are written by the Alternative Setup form as before.
A3: Alternative | B3: Name | C3: Initial Construction | D3: Present Worth | E3: Alternative Description | G3: Worksheet | H3: Alternative | I3: Type | J3: Initial construction | K3: Maintenance PW | L3: Rehabilitation PW | M3: Lost revenue PW | N3: Salvage PW | O3: Net present worth | P3: vs. lowest NPW | Q3: Closure days in period | R3: Runway availability | W3: Present worth by category
A4: Alt 1 | B4: Alternative 1 | C4: ='Alt 1 (New HMA)'!G27 -> 7268437 | D4: ='Alt 1 (New HMA)'!E52 -> 9829223.7 | E4: New HMA | G4: =IF(INDEX(Database!$D:$D,4)="","",INDEX(Database!$D:$D,4)) -> Alt 1 (New HMA) | H4: =IF($G4="","",INDEX(Database!$A:$A,4)) -> Alternative 1 | I4: =IF($G4="","",INDEX(Database!$B:$B,4)) -> HMA-New | J4: =IF($G4="","",IFERROR(INDEX(INDIRECT("'"&$G4&"'!$G$1:$G$70"),MATCH("Total",INDIRECT("'"&$G4&"'!$A$1:$A$70"),0)),0)) -> 7268437 | K4: =IF($G4="","",IFERROR(SUMIFS(INDIRECT("'"&$G4&"'!$E$37:$E$52"),INDIRECT("'"&$G4&"'!$B$37:$B$52"),"Maintenance*",INDIRECT("'"&$G4&"'!$B$37:$B$52"),"<>*Indirect*"),0)) -> 1574420.7 | L4: =IF($G4="","",IFERROR(SUMIFS(INDIRECT("'"&$G4&"'!$E$37:$E$52"),INDIRECT("'"&$G4&"'!$B$37:$B$52"),"Rehabilitation*",INDIRECT("'"&$G4&"'!$B$37:$B$52"),"<>*Indirect*"),0)) -> 939071.04 | M4: =IF($G4="","",IFERROR(SUMIFS(INDIRECT("'"&$G4&"'!$E$37:$E$52"),INDIRECT("'"&$G4&"'!$B$37:$B$52"),"*Indirect*"),0)) -> 134639.61 | N4: =IF($G4="","",IFERROR(SUMIFS(INDIRECT("'"&$G4&"'!$E$37:$E$52"),INDIRECT("'"&$G4&"'!$B$37:$B$52"),"Salvage*"),0)) -> -87344.631 | O4: =IF($G4="","",IFERROR(INDEX(INDIRECT("'"&$G4&"'!$E$1:$E$70"),MATCH("Net Present Worth",INDIRECT("'"&$G4&"'!$B$1:$B$70"),0)),0)) -> 9829223.7 | P4: =IF($G4="","",O4-MIN($O$4:$O$7)) -> 648621.5 | Q4: =IF($G4="","",IF(IFERROR(INDIRECT("'"&$G4&"'!$F$2"),0)>0,SUM($AG$41:$AG$71),IFERROR(SUM(INDIRECT("'"&$G4&"'!$F$4:$F$10")),0))) -> 67 | R4: =IF($G4="","",1-Q4/('General Information'!$D$33*365)) -> 0.99388128 | W4: Category | X4: =IF($H$4="","Alt "&1,$H$4) -> Alternative 1 | Y4: =IF($H$5="","Alt "&2,$H$5) -> Alternative 2 | Z4: =IF($H$6="","Alt "&3,$H$6) -> Alt 3 | AA4: =IF($H$7="","Alt "&4,$H$7) -> Alt 4
A5: Alt 2 | B5: Alternative 2 | C5: ='Alt 2 (New PCC)'!G27 -> 9062465.8 | D5: ='Alt 2 (New PCC)'!E43 -> 9180602.2 | E5: New PCC | G5: =IF(INDEX(Database!$D:$D,5)="","",INDEX(Database!$D:$D,5)) -> Alt 2 (New PCC) | H5: =IF($G5="","",INDEX(Database!$A:$A,5)) -> Alternative 2 | I5: =IF($G5="","",INDEX(Database!$B:$B,5)) -> PCC-New | J5: =IF($G5="","",IFERROR(INDEX(INDIRECT("'"&$G5&"'!$G$1:$G$70"),MATCH("Total",INDIRECT("'"&$G5&"'!$A$1:$A$70"),0)),0)) -> 9062465.8 | K5: =IF($G5="","",IFERROR(SUMIFS(INDIRECT("'"&$G5&"'!$E$37:$E$52"),INDIRECT("'"&$G5&"'!$B$37:$B$52"),"Maintenance*",INDIRECT("'"&$G5&"'!$B$37:$B$52"),"<>*Indirect*"),0)) -> 522567.1 | L5: =IF($G5="","",IFERROR(SUMIFS(INDIRECT("'"&$G5&"'!$E$37:$E$52"),INDIRECT("'"&$G5&"'!$B$37:$B$52"),"Rehabilitation*",INDIRECT("'"&$G5&"'!$B$37:$B$52"),"<>*Indirect*"),0)) -> 482791.16 | M5: =IF($G5="","",IFERROR(SUMIFS(INDIRECT("'"&$G5&"'!$E$37:$E$52"),INDIRECT("'"&$G5&"'!$B$37:$B$52"),"*Indirect*"),0)) -> 46182.209 | N5: =IF($G5="","",IFERROR(SUMIFS(INDIRECT("'"&$G5&"'!$E$37:$E$52"),INDIRECT("'"&$G5&"'!$B$37:$B$52"),"Salvage*"),0)) -> -933403.97 | O5: =IF($G5="","",IFERROR(INDEX(INDIRECT("'"&$G5&"'!$E$1:$E$70"),MATCH("Net Present Worth",INDIRECT("'"&$G5&"'!$B$1:$B$70"),0)),0)) -> 9180602.2 | P5: =IF($G5="","",O5-MIN($O$4:$O$7)) -> 0 | Q5: =IF($G5="","",IF(IFERROR(INDIRECT("'"&$G5&"'!$F$2"),0)>0,SUM($AH$41:$AH$71),IFERROR(SUM(INDIRECT("'"&$G5&"'!$F$4:$F$10")),0))) -> 29 | R5: =IF($G5="","",1-Q5/('General Information'!$D$33*365)) -> 0.9973516 | W5: Initial construction | X5: =IF(J4="",0,J4) -> 7268437 | Y5: =IF(J5="",0,J5) -> 9062465.8 | Z5: =IF(J6="",0,J6) -> 0 | AA5: =IF(J7="",0,J7) -> 0
G6: =IF(INDEX(Database!$D:$D,6)="","",INDEX(Database!$D:$D,6)) | H6: =IF($G6="","",INDEX(Database!$A:$A,6)) | I6: =IF($G6="","",INDEX(Database!$B:$B,6)) | J6: =IF($G6="","",IFERROR(INDEX(INDIRECT("'"&$G6&"'!$G$1:$G$70"),MATCH("Total",INDIRECT("'"&$G6&"'!$A$1:$A$70"),0)),0)) | K6: =IF($G6="","",IFERROR(SUMIFS(INDIRECT("'"&$G6&"'!$E$37:$E$52"),INDIRECT("'"&$G6&"'!$B$37:$B$52"),"Maintenance*",INDIRECT("'"&$G6&"'!$B$37:$B$52"),"<>*Indirect*"),0)) | L6: =IF($G6="","",IFERROR(SUMIFS(INDIRECT("'"&$G6&"'!$E$37:$E$52"),INDIRECT("'"&$G6&"'!$B$37:$B$52"),"Rehabilitation*",INDIRECT("'"&$G6&"'!$B$37:$B$52"),"<>*Indirect*"),0)) | M6: =IF($G6="","",IFERROR(SUMIFS(INDIRECT("'"&$G6&"'!$E$37:$E$52"),INDIRECT("'"&$G6&"'!$B$37:$B$52"),"*Indirect*"),0)) | N6: =IF($G6="","",IFERROR(SUMIFS(INDIRECT("'"&$G6&"'!$E$37:$E$52"),INDIRECT("'"&$G6&"'!$B$37:$B$52"),"Salvage*"),0)) | O6: =IF($G6="","",IFERROR(INDEX(INDIRECT("'"&$G6&"'!$E$1:$E$70"),MATCH("Net Present Worth",INDIRECT("'"&$G6&"'!$B$1:$B$70"),0)),0)) | P6: =IF($G6="","",O6-MIN($O$4:$O$7)) | Q6: =IF($G6="","",IF(IFERROR(INDIRECT("'"&$G6&"'!$F$2"),0)>0,SUM($AI$41:$AI$71),IFERROR(SUM(INDIRECT("'"&$G6&"'!$F$4:$F$10")),0))) | R6: =IF($G6="","",1-Q6/('General Information'!$D$33*365)) | W6: Maintenance | X6: =IF(K4="",0,K4) -> 1574420.7 | Y6: =IF(K5="",0,K5) -> 522567.1 | Z6: =IF(K6="",0,K6) -> 0 | AA6: =IF(K7="",0,K7) -> 0
G7: =IF(INDEX(Database!$D:$D,7)="","",INDEX(Database!$D:$D,7)) | H7: =IF($G7="","",INDEX(Database!$A:$A,7)) | I7: =IF($G7="","",INDEX(Database!$B:$B,7)) | J7: =IF($G7="","",IFERROR(INDEX(INDIRECT("'"&$G7&"'!$G$1:$G$70"),MATCH("Total",INDIRECT("'"&$G7&"'!$A$1:$A$70"),0)),0)) | K7: =IF($G7="","",IFERROR(SUMIFS(INDIRECT("'"&$G7&"'!$E$37:$E$52"),INDIRECT("'"&$G7&"'!$B$37:$B$52"),"Maintenance*",INDIRECT("'"&$G7&"'!$B$37:$B$52"),"<>*Indirect*"),0)) | L7: =IF($G7="","",IFERROR(SUMIFS(INDIRECT("'"&$G7&"'!$E$37:$E$52"),INDIRECT("'"&$G7&"'!$B$37:$B$52"),"Rehabilitation*",INDIRECT("'"&$G7&"'!$B$37:$B$52"),"<>*Indirect*"),0)) | M7: =IF($G7="","",IFERROR(SUMIFS(INDIRECT("'"&$G7&"'!$E$37:$E$52"),INDIRECT("'"&$G7&"'!$B$37:$B$52"),"*Indirect*"),0)) | N7: =IF($G7="","",IFERROR(SUMIFS(INDIRECT("'"&$G7&"'!$E$37:$E$52"),INDIRECT("'"&$G7&"'!$B$37:$B$52"),"Salvage*"),0)) | O7: =IF($G7="","",IFERROR(INDEX(INDIRECT("'"&$G7&"'!$E$1:$E$70"),MATCH("Net Present Worth",INDIRECT("'"&$G7&"'!$B$1:$B$70"),0)),0)) | P7: =IF($G7="","",O7-MIN($O$4:$O$7)) | Q7: =IF($G7="","",IF(IFERROR(INDIRECT("'"&$G7&"'!$F$2"),0)>0,SUM($AJ$41:$AJ$71),IFERROR(SUM(INDIRECT("'"&$G7&"'!$F$4:$F$10")),0))) | R7: =IF($G7="","",1-Q7/('General Information'!$D$33*365)) | W7: Rehabilitation | X7: =IF(L4="",0,L4) -> 939071.04 | Y7: =IF(L5="",0,L5) -> 482791.16 | Z7: =IF(L6="",0,L6) -> 0 | AA7: =IF(L7="",0,L7) -> 0
W8: Lost revenue | X8: =IF(M4="",0,M4) -> 134639.61 | Y8: =IF(M5="",0,M5) -> 46182.209 | Z8: =IF(M6="",0,M6) -> 0 | AA8: =IF(M7="",0,M7) -> 0
G9: =IF(COUNT($O$4:$O$7)=0,"No alternatives yet. Go to General Information and click Alternative Setup.","Lowest present worth: "&INDEX($H$4:$H$7,MATCH(MIN($O$4:$O$7),$O$4:$O$7,0))&IF(COUNT($O$4:$O$7)<2," | only one alternative so far",IF(SMALL($O$4:$O$7,2)=MIN($O$4:$O$7)," | tied with the next alternative"," | margin to next: "&TEXT(SMALL($O$4:$O$7,2)-MIN($O$4:$O$7),"$#,##0")))&" | "&'General Information'!$D$34&"% over "&'General Information'!$D$33&" years | lost revenue: "&'General Information'!$D$38) -> Lowest present worth: Alternative 2 | margin to next: $648,621 | 3% over 30 years | lost revenue: Yes | W9: Salvage | X9: =IF(N4="",0,N4) -> -87344.631 | Y9: =IF(N5="",0,N5) -> -933403.97 | Z9: =IF(N6="",0,N6) -> 0 | AA9: =IF(N7="",0,N7) -> 0
G10: =IF(COUNT($O$4:$O$7)<2,"",IF(INDEX($H$4:$H$7,MATCH(MIN($O$4:$O$7),$O$4:$O$7,0))=INDEX($H$4:$H$7,MATCH(MIN($X$32:$AA$32),$X$32:$AA$32,0)),"The same alternative is lowest at the FAA AIP rate of 7%.","At the FAA AIP rate of 7% the lowest-cost alternative changes: see chart 2.")) -> At the FAA AIP rate of 7% the lowest-cost alternative changes: see chart 2. | W10: Net present worth vs. discount rate
W11: Rate (%) | X11: =X$4 -> Alternative 1 | Y11: =Y$4 -> Alternative 2 | Z11: =Z$4 -> Alt 3 | AA11: =AA$4 -> Alt 4
G12: CHARTS | W12: 2 | X12: =IF($G$4="",0,IFERROR($J$4+SUMPRODUCT((INDIRECT("'"&$G$4&"'!$C$37:$C$52")<='General Information'!$D$33)*INDIRECT("'"&$G$4&"'!$D$37:$D$52")/(1+$W12/100)^INDIRECT("'"&$G$4&"'!$C$37:$C$52")),0)) -> 10262553 | Y12: =IF($G$5="",0,IFERROR($J$5+SUMPRODUCT((INDIRECT("'"&$G$5&"'!$C$37:$C$52")<='General Information'!$D$33)*INDIRECT("'"&$G$5&"'!$D$37:$D$52")/(1+$W12/100)^INDIRECT("'"&$G$5&"'!$C$37:$C$52")),0)) -> 9127262.7 | Z12: =IF($G$6="",0,IFERROR($J$6+SUMPRODUCT((INDIRECT("'"&$G$6&"'!$C$37:$C$52")<='General Information'!$D$33)*INDIRECT("'"&$G$6&"'!$D$37:$D$52")/(1+$W12/100)^INDIRECT("'"&$G$6&"'!$C$37:$C$52")),0)) -> 0 | AA12: =IF($G$7="",0,IFERROR($J$7+SUMPRODUCT((INDIRECT("'"&$G$7&"'!$C$37:$C$52")<='General Information'!$D$33)*INDIRECT("'"&$G$7&"'!$D$37:$D$52")/(1+$W12/100)^INDIRECT("'"&$G$7&"'!$C$37:$C$52")),0)) -> 0
W13: 2.25 | X13: =IF($G$4="",0,IFERROR($J$4+SUMPRODUCT((INDIRECT("'"&$G$4&"'!$C$37:$C$52")<='General Information'!$D$33)*INDIRECT("'"&$G$4&"'!$D$37:$D$52")/(1+$W13/100)^INDIRECT("'"&$G$4&"'!$C$37:$C$52")),0)) -> 10146265 | Y13: =IF($G$5="",0,IFERROR($J$5+SUMPRODUCT((INDIRECT("'"&$G$5&"'!$C$37:$C$52")<='General Information'!$D$33)*INDIRECT("'"&$G$5&"'!$D$37:$D$52")/(1+$W13/100)^INDIRECT("'"&$G$5&"'!$C$37:$C$52")),0)) -> 9143740.6 | Z13: =IF($G$6="",0,IFERROR($J$6+SUMPRODUCT((INDIRECT("'"&$G$6&"'!$C$37:$C$52")<='General Information'!$D$33)*INDIRECT("'"&$G$6&"'!$D$37:$D$52")/(1+$W13/100)^INDIRECT("'"&$G$6&"'!$C$37:$C$52")),0)) -> 0 | AA13: =IF($G$7="",0,IFERROR($J$7+SUMPRODUCT((INDIRECT("'"&$G$7&"'!$C$37:$C$52")<='General Information'!$D$33)*INDIRECT("'"&$G$7&"'!$D$37:$D$52")/(1+$W13/100)^INDIRECT("'"&$G$7&"'!$C$37:$C$52")),0)) -> 0
W14: 2.5 | X14: =IF($G$4="",0,IFERROR($J$4+SUMPRODUCT((INDIRECT("'"&$G$4&"'!$C$37:$C$52")<='General Information'!$D$33)*INDIRECT("'"&$G$4&"'!$D$37:$D$52")/(1+$W14/100)^INDIRECT("'"&$G$4&"'!$C$37:$C$52")),0)) -> 10035470 | Y14: =IF($G$5="",0,IFERROR($J$5+SUMPRODUCT((INDIRECT("'"&$G$5&"'!$C$37:$C$52")<='General Information'!$D$33)*INDIRECT("'"&$G$5&"'!$D$37:$D$52")/(1+$W14/100)^INDIRECT("'"&$G$5&"'!$C$37:$C$52")),0)) -> 9157977.8 | Z14: =IF($G$6="",0,IFERROR($J$6+SUMPRODUCT((INDIRECT("'"&$G$6&"'!$C$37:$C$52")<='General Information'!$D$33)*INDIRECT("'"&$G$6&"'!$D$37:$D$52")/(1+$W14/100)^INDIRECT("'"&$G$6&"'!$C$37:$C$52")),0)) -> 0 | AA14: =IF($G$7="",0,IFERROR($J$7+SUMPRODUCT((INDIRECT("'"&$G$7&"'!$C$37:$C$52")<='General Information'!$D$33)*INDIRECT("'"&$G$7&"'!$D$37:$D$52")/(1+$W14/100)^INDIRECT("'"&$G$7&"'!$C$37:$C$52")),0)) -> 0
W15: 2.75 | X15: =IF($G$4="",0,IFERROR($J$4+SUMPRODUCT((INDIRECT("'"&$G$4&"'!$C$37:$C$52")<='General Information'!$D$33)*INDIRECT("'"&$G$4&"'!$D$37:$D$52")/(1+$W15/100)^INDIRECT("'"&$G$4&"'!$C$37:$C$52")),0)) -> 9929881.1 | Y15: =IF($G$5="",0,IFERROR($J$5+SUMPRODUCT((INDIRECT("'"&$G$5&"'!$C$37:$C$52")<='General Information'!$D$33)*INDIRECT("'"&$G$5&"'!$D$37:$D$52")/(1+$W15/100)^INDIRECT("'"&$G$5&"'!$C$37:$C$52")),0)) -> 9170197.4 | Z15: =IF($G$6="",0,IFERROR($J$6+SUMPRODUCT((INDIRECT("'"&$G$6&"'!$C$37:$C$52")<='General Information'!$D$33)*INDIRECT("'"&$G$6&"'!$D$37:$D$52")/(1+$W15/100)^INDIRECT("'"&$G$6&"'!$C$37:$C$52")),0)) -> 0 | AA15: =IF($G$7="",0,IFERROR($J$7+SUMPRODUCT((INDIRECT("'"&$G$7&"'!$C$37:$C$52")<='General Information'!$D$33)*INDIRECT("'"&$G$7&"'!$D$37:$D$52")/(1+$W15/100)^INDIRECT("'"&$G$7&"'!$C$37:$C$52")),0)) -> 0
W16: 3 | X16: =IF($G$4="",0,IFERROR($J$4+SUMPRODUCT((INDIRECT("'"&$G$4&"'!$C$37:$C$52")<='General Information'!$D$33)*INDIRECT("'"&$G$4&"'!$D$37:$D$52")/(1+$W16/100)^INDIRECT("'"&$G$4&"'!$C$37:$C$52")),0)) -> 9829223.7 | Y16: =IF($G$5="",0,IFERROR($J$5+SUMPRODUCT((INDIRECT("'"&$G$5&"'!$C$37:$C$52")<='General Information'!$D$33)*INDIRECT("'"&$G$5&"'!$D$37:$D$52")/(1+$W16/100)^INDIRECT("'"&$G$5&"'!$C$37:$C$52")),0)) -> 9180602.2 | Z16: =IF($G$6="",0,IFERROR($J$6+SUMPRODUCT((INDIRECT("'"&$G$6&"'!$C$37:$C$52")<='General Information'!$D$33)*INDIRECT("'"&$G$6&"'!$D$37:$D$52")/(1+$W16/100)^INDIRECT("'"&$G$6&"'!$C$37:$C$52")),0)) -> 0 | AA16: =IF($G$7="",0,IFERROR($J$7+SUMPRODUCT((INDIRECT("'"&$G$7&"'!$C$37:$C$52")<='General Information'!$D$33)*INDIRECT("'"&$G$7&"'!$D$37:$D$52")/(1+$W16/100)^INDIRECT("'"&$G$7&"'!$C$37:$C$52")),0)) -> 0
W17: 3.25 | X17: =IF($G$4="",0,IFERROR($J$4+SUMPRODUCT((INDIRECT("'"&$G$4&"'!$C$37:$C$52")<='General Information'!$D$33)*INDIRECT("'"&$G$4&"'!$D$37:$D$52")/(1+$W17/100)^INDIRECT("'"&$G$4&"'!$C$37:$C$52")),0)) -> 9733241 | Y17: =IF($G$5="",0,IFERROR($J$5+SUMPRODUCT((INDIRECT("'"&$G$5&"'!$C$37:$C$52")<='General Information'!$D$33)*INDIRECT("'"&$G$5&"'!$D$37:$D$52")/(1+$W17/100)^INDIRECT("'"&$G$5&"'!$C$37:$C$52")),0)) -> 9189376.6 | Z17: =IF($G$6="",0,IFERROR($J$6+SUMPRODUCT((INDIRECT("'"&$G$6&"'!$C$37:$C$52")<='General Information'!$D$33)*INDIRECT("'"&$G$6&"'!$D$37:$D$52")/(1+$W17/100)^INDIRECT("'"&$G$6&"'!$C$37:$C$52")),0)) -> 0 | AA17: =IF($G$7="",0,IFERROR($J$7+SUMPRODUCT((INDIRECT("'"&$G$7&"'!$C$37:$C$52")<='General Information'!$D$33)*INDIRECT("'"&$G$7&"'!$D$37:$D$52")/(1+$W17/100)^INDIRECT("'"&$G$7&"'!$C$37:$C$52")),0)) -> 0
W18: 3.5 | X18: =IF($G$4="",0,IFERROR($J$4+SUMPRODUCT((INDIRECT("'"&$G$4&"'!$C$37:$C$52")<='General Information'!$D$33)*INDIRECT("'"&$G$4&"'!$D$37:$D$52")/(1+$W18/100)^INDIRECT("'"&$G$4&"'!$C$37:$C$52")),0)) -> 9641689.9 | Y18: =IF($G$5="",0,IFERROR($J$5+SUMPRODUCT((INDIRECT("'"&$G$5&"'!$C$37:$C$52")<='General Information'!$D$33)*INDIRECT("'"&$G$5&"'!$D$37:$D$52")/(1+$W18/100)^INDIRECT("'"&$G$5&"'!$C$37:$C$52")),0)) -> 9196687.7 | Z18: =IF($G$6="",0,IFERROR($J$6+SUMPRODUCT((INDIRECT("'"&$G$6&"'!$C$37:$C$52")<='General Information'!$D$33)*INDIRECT("'"&$G$6&"'!$D$37:$D$52")/(1+$W18/100)^INDIRECT("'"&$G$6&"'!$C$37:$C$52")),0)) -> 0 | AA18: =IF($G$7="",0,IFERROR($J$7+SUMPRODUCT((INDIRECT("'"&$G$7&"'!$C$37:$C$52")<='General Information'!$D$33)*INDIRECT("'"&$G$7&"'!$D$37:$D$52")/(1+$W18/100)^INDIRECT("'"&$G$7&"'!$C$37:$C$52")),0)) -> 0
W19: 3.75 | X19: =IF($G$4="",0,IFERROR($J$4+SUMPRODUCT((INDIRECT("'"&$G$4&"'!$C$37:$C$52")<='General Information'!$D$33)*INDIRECT("'"&$G$4&"'!$D$37:$D$52")/(1+$W19/100)^INDIRECT("'"&$G$4&"'!$C$37:$C$52")),0)) -> 9554341.1 | Y19: =IF($G$5="",0,IFERROR($J$5+SUMPRODUCT((INDIRECT("'"&$G$5&"'!$C$37:$C$52")<='General Information'!$D$33)*INDIRECT("'"&$G$5&"'!$D$37:$D$52")/(1+$W19/100)^INDIRECT("'"&$G$5&"'!$C$37:$C$52")),0)) -> 9202687.7 | Z19: =IF($G$6="",0,IFERROR($J$6+SUMPRODUCT((INDIRECT("'"&$G$6&"'!$C$37:$C$52")<='General Information'!$D$33)*INDIRECT("'"&$G$6&"'!$D$37:$D$52")/(1+$W19/100)^INDIRECT("'"&$G$6&"'!$C$37:$C$52")),0)) -> 0 | AA19: =IF($G$7="",0,IFERROR($J$7+SUMPRODUCT((INDIRECT("'"&$G$7&"'!$C$37:$C$52")<='General Information'!$D$33)*INDIRECT("'"&$G$7&"'!$D$37:$D$52")/(1+$W19/100)^INDIRECT("'"&$G$7&"'!$C$37:$C$52")),0)) -> 0
W20: 4 | X20: =IF($G$4="",0,IFERROR($J$4+SUMPRODUCT((INDIRECT("'"&$G$4&"'!$C$37:$C$52")<='General Information'!$D$33)*INDIRECT("'"&$G$4&"'!$D$37:$D$52")/(1+$W20/100)^INDIRECT("'"&$G$4&"'!$C$37:$C$52")),0)) -> 9470978.4 | Y20: =IF($G$5="",0,IFERROR($J$5+SUMPRODUCT((INDIRECT("'"&$G$5&"'!$C$37:$C$52")<='General Information'!$D$33)*INDIRECT("'"&$G$5&"'!$D$37:$D$52")/(1+$W20/100)^INDIRECT("'"&$G$5&"'!$C$37:$C$52")),0)) -> 9207514.5 | Z20: =IF($G$6="",0,IFERROR($J$6+SUMPRODUCT((INDIRECT("'"&$G$6&"'!$C$37:$C$52")<='General Information'!$D$33)*INDIRECT("'"&$G$6&"'!$D$37:$D$52")/(1+$W20/100)^INDIRECT("'"&$G$6&"'!$C$37:$C$52")),0)) -> 0 | AA20: =IF($G$7="",0,IFERROR($J$7+SUMPRODUCT((INDIRECT("'"&$G$7&"'!$C$37:$C$52")<='General Information'!$D$33)*INDIRECT("'"&$G$7&"'!$D$37:$D$52")/(1+$W20/100)^INDIRECT("'"&$G$7&"'!$C$37:$C$52")),0)) -> 0
W21: 4.25 | X21: =IF($G$4="",0,IFERROR($J$4+SUMPRODUCT((INDIRECT("'"&$G$4&"'!$C$37:$C$52")<='General Information'!$D$33)*INDIRECT("'"&$G$4&"'!$D$37:$D$52")/(1+$W21/100)^INDIRECT("'"&$G$4&"'!$C$37:$C$52")),0)) -> 9391397.3 | Y21: =IF($G$5="",0,IFERROR($J$5+SUMPRODUCT((INDIRECT("'"&$G$5&"'!$C$37:$C$52")<='General Information'!$D$33)*INDIRECT("'"&$G$5&"'!$D$37:$D$52")/(1+$W21/100)^INDIRECT("'"&$G$5&"'!$C$37:$C$52")),0)) -> 9211293.3 | Z21: =IF($G$6="",0,IFERROR($J$6+SUMPRODUCT((INDIRECT("'"&$G$6&"'!$C$37:$C$52")<='General Information'!$D$33)*INDIRECT("'"&$G$6&"'!$D$37:$D$52")/(1+$W21/100)^INDIRECT("'"&$G$6&"'!$C$37:$C$52")),0)) -> 0 | AA21: =IF($G$7="",0,IFERROR($J$7+SUMPRODUCT((INDIRECT("'"&$G$7&"'!$C$37:$C$52")<='General Information'!$D$33)*INDIRECT("'"&$G$7&"'!$D$37:$D$52")/(1+$W21/100)^INDIRECT("'"&$G$7&"'!$C$37:$C$52")),0)) -> 0
W22: 4.5 | X22: =IF($G$4="",0,IFERROR($J$4+SUMPRODUCT((INDIRECT("'"&$G$4&"'!$C$37:$C$52")<='General Information'!$D$33)*INDIRECT("'"&$G$4&"'!$D$37:$D$52")/(1+$W22/100)^INDIRECT("'"&$G$4&"'!$C$37:$C$52")),0)) -> 9315404.8 | Y22: =IF($G$5="",0,IFERROR($J$5+SUMPRODUCT((INDIRECT("'"&$G$5&"'!$C$37:$C$52")<='General Information'!$D$33)*INDIRECT("'"&$G$5&"'!$D$37:$D$52")/(1+$W22/100)^INDIRECT("'"&$G$5&"'!$C$37:$C$52")),0)) -> 9214137.5 | Z22: =IF($G$6="",0,IFERROR($J$6+SUMPRODUCT((INDIRECT("'"&$G$6&"'!$C$37:$C$52")<='General Information'!$D$33)*INDIRECT("'"&$G$6&"'!$D$37:$D$52")/(1+$W22/100)^INDIRECT("'"&$G$6&"'!$C$37:$C$52")),0)) -> 0 | AA22: =IF($G$7="",0,IFERROR($J$7+SUMPRODUCT((INDIRECT("'"&$G$7&"'!$C$37:$C$52")<='General Information'!$D$33)*INDIRECT("'"&$G$7&"'!$D$37:$D$52")/(1+$W22/100)^INDIRECT("'"&$G$7&"'!$C$37:$C$52")),0)) -> 0
W23: 4.75 | X23: =IF($G$4="",0,IFERROR($J$4+SUMPRODUCT((INDIRECT("'"&$G$4&"'!$C$37:$C$52")<='General Information'!$D$33)*INDIRECT("'"&$G$4&"'!$D$37:$D$52")/(1+$W23/100)^INDIRECT("'"&$G$4&"'!$C$37:$C$52")),0)) -> 9242818.6 | Y23: =IF($G$5="",0,IFERROR($J$5+SUMPRODUCT((INDIRECT("'"&$G$5&"'!$C$37:$C$52")<='General Information'!$D$33)*INDIRECT("'"&$G$5&"'!$D$37:$D$52")/(1+$W23/100)^INDIRECT("'"&$G$5&"'!$C$37:$C$52")),0)) -> 9216150.2 | Z23: =IF($G$6="",0,IFERROR($J$6+SUMPRODUCT((INDIRECT("'"&$G$6&"'!$C$37:$C$52")<='General Information'!$D$33)*INDIRECT("'"&$G$6&"'!$D$37:$D$52")/(1+$W23/100)^INDIRECT("'"&$G$6&"'!$C$37:$C$52")),0)) -> 0 | AA23: =IF($G$7="",0,IFERROR($J$7+SUMPRODUCT((INDIRECT("'"&$G$7&"'!$C$37:$C$52")<='General Information'!$D$33)*INDIRECT("'"&$G$7&"'!$D$37:$D$52")/(1+$W23/100)^INDIRECT("'"&$G$7&"'!$C$37:$C$52")),0)) -> 0
W24: 5 | X24: =IF($G$4="",0,IFERROR($J$4+SUMPRODUCT((INDIRECT("'"&$G$4&"'!$C$37:$C$52")<='General Information'!$D$33)*INDIRECT("'"&$G$4&"'!$D$37:$D$52")/(1+$W24/100)^INDIRECT("'"&$G$4&"'!$C$37:$C$52")),0)) -> 9173466.4 | Y24: =IF($G$5="",0,IFERROR($J$5+SUMPRODUCT((INDIRECT("'"&$G$5&"'!$C$37:$C$52")<='General Information'!$D$33)*INDIRECT("'"&$G$5&"'!$D$37:$D$52")/(1+$W24/100)^INDIRECT("'"&$G$5&"'!$C$37:$C$52")),0)) -> 9217424.5 | Z24: =IF($G$6="",0,IFERROR($J$6+SUMPRODUCT((INDIRECT("'"&$G$6&"'!$C$37:$C$52")<='General Information'!$D$33)*INDIRECT("'"&$G$6&"'!$D$37:$D$52")/(1+$W24/100)^INDIRECT("'"&$G$6&"'!$C$37:$C$52")),0)) -> 0 | AA24: =IF($G$7="",0,IFERROR($J$7+SUMPRODUCT((INDIRECT("'"&$G$7&"'!$C$37:$C$52")<='General Information'!$D$33)*INDIRECT("'"&$G$7&"'!$D$37:$D$52")/(1+$W24/100)^INDIRECT("'"&$G$7&"'!$C$37:$C$52")),0)) -> 0
... W36: 8 | X36: =IF($G$4="",0,IFERROR($J$4+SUMPRODUCT((INDIRECT("'"&$G$4&"'!$C$37:$C$52")<='General Information'!$D$33)*INDIRECT("'"&$G$4&"'!$D$37:$D$52")/(1+$W36/100)^INDIRECT("'"&$G$4&"'!$C$37:$C$52")),0)) -> 8542182.2 | Y36: =IF($G$5="",0,IFERROR($J$5+SUMPRODUCT((INDIRECT("'"&$G$5&"'!$C$37:$C$52")<='General Information'!$D$33)*INDIRECT("'"&$G$5&"'!$D$37:$D$52")/(1+$W36/100)^INDIRECT("'"&$G$5&"'!$C$37:$C$52")),0)) -> 9199102.1 | Z36: =IF($G$6="",0,IFERROR($J$6+SUMPRODUCT((INDIRECT("'"&$G$6&"'!$C$37:$C$52")<='General Information'!$D$33)*INDIRECT("'"&$G$6&"'!$D$37:$D$52")/(1+$W36/100)^INDIRECT("'"&$G$6&"'!$C$37:$C$52")),0)) -> 0 | AA36: =IF($G$7="",0,IFERROR($J$7+SUMPRODUCT((INDIRECT("'"&$G$7&"'!$C$37:$C$52")<='General Information'!$D$33)*INDIRECT("'"&$G$7&"'!$D$37:$D$52")/(1+$W36/100)^INDIRECT("'"&$G$7&"'!$C$37:$C$52")),0)) -> 0
W39: By calendar year: spend (undiscounted), cumulative discounted cost, closure days
W40: Year | X40: Calendar year | Y40: =X$4&" spend" -> Alternative 1 spend | Z40: =Y$4&" spend" -> Alternative 2 spend | AA40: =Z$4&" spend" -> Alt 3 spend | AB40: =AA$4&" spend" -> Alt 4 spend | AC40: =X$4&" cumulative PW" -> Alternative 1 cumulative PW | AD40: =Y$4&" cumulative PW" -> Alternative 2 cumulative PW | AE40: =Z$4&" cumulative PW" -> Alt 3 cumulative PW | AF40: =AA$4&" cumulative PW" -> Alt 4 cumulative PW | AG40: =X$4&" closure days" -> Alternative 1 closure days | AH40: =Y$4&" closure days" -> Alternative 2 closure days | AI40: =Z$4&" closure days" -> Alt 3 closure days | AJ40: =AA$4&" closure days" -> Alt 4 closure days
W41: 0 | X41: ='General Information'!$D$25+W41 -> 2028 | Y41: =IF($G$4="",0,IF(W41>'General Information'!$D$33,0,IF(W41=0,$J$4,IFERROR(SUMIF(INDIRECT("'"&$G$4&"'!$C$37:$C$52"),W41,INDIRECT("'"&$G$4&"'!$D$37:$D$52")),0)))) -> 7268437 | Z41: =IF($G$5="",0,IF(W41>'General Information'!$D$33,0,IF(W41=0,$J$5,IFERROR(SUMIF(INDIRECT("'"&$G$5&"'!$C$37:$C$52"),W41,INDIRECT("'"&$G$5&"'!$D$37:$D$52")),0)))) -> 9062465.8 | AA41: =IF($G$6="",0,IF(W41>'General Information'!$D$33,0,IF(W41=0,$J$6,IFERROR(SUMIF(INDIRECT("'"&$G$6&"'!$C$37:$C$52"),W41,INDIRECT("'"&$G$6&"'!$D$37:$D$52")),0)))) -> 0 | AB41: =IF($G$7="",0,IF(W41>'General Information'!$D$33,0,IF(W41=0,$J$7,IFERROR(SUMIF(INDIRECT("'"&$G$7&"'!$C$37:$C$52"),W41,INDIRECT("'"&$G$7&"'!$D$37:$D$52")),0)))) -> 0 | AC41: =IF($G$4="",0,IF(W41>'General Information'!$D$33,0,IF(W41=0,$J$4,IFERROR(SUMIF(INDIRECT("'"&$G$4&"'!$C$37:$C$52"),W41,INDIRECT("'"&$G$4&"'!$E$37:$E$52")),0)))) -> 7268437 | AD41: =IF($G$5="",0,IF(W41>'General Information'!$D$33,0,IF(W41=0,$J$5,IFERROR(SUMIF(INDIRECT("'"&$G$5&"'!$C$37:$C$52"),W41,INDIRECT("'"&$G$5&"'!$E$37:$E$52")),0)))) -> 9062465.8 | AE41: =IF($G$6="",0,IF(W41>'General Information'!$D$33,0,IF(W41=0,$J$6,IFERROR(SUMIF(INDIRECT("'"&$G$6&"'!$C$37:$C$52"),W41,INDIRECT("'"&$G$6&"'!$E$37:$E$52")),0)))) -> 0 | AF41: =IF($G$7="",0,IF(W41>'General Information'!$D$33,0,IF(W41=0,$J$7,IFERROR(SUMIF(INDIRECT("'"&$G$7&"'!$C$37:$C$52"),W41,INDIRECT("'"&$G$7&"'!$E$37:$E$52")),0)))) -> 0 | AG41: =IF($G$4="",0,IF(W41>'General Information'!$D$33,0,IFERROR(SUMIFS(INDIRECT("'"&$G$4&"'!$D$37:$D$52"),INDIRECT("'"&$G$4&"'!$C$37:$C$52"),W41,INDIRECT("'"&$G$4&"'!$B$37:$B$52"),"*Indirect*")/INDIRECT("'"&$G$4&"'!$F$2"),0))) -> 0 | AH41: =IF($G$5="",0,IF(W41>'General Information'!$D$33,0,IFERROR(SUMIFS(INDIRECT("'"&$G$5&"'!$D$37:$D$52"),INDIRECT("'"&$G$5&"'!$C$37:$C$52"),W41,INDIRECT("'"&$G$5&"'!$B$37:$B$52"),"*Indirect*")/INDIRECT("'"&$G$5&"'!$F$2"),0))) -> 0 | AI41: =IF($G$6="",0,IF(W41>'General Information'!$D$33,0,IFERROR(SUMIFS(INDIRECT("'"&$G$6&"'!$D$37:$D$52"),INDIRECT("'"&$G$6&"'!$C$37:$C$52"),W41,INDIRECT("'"&$G$6&"'!$B$37:$B$52"),"*Indirect*")/INDIRECT("'"&$G$6&"'!$F$2"),0))) -> 0 | AJ41: =IF($G$7="",0,IF(W41>'General Information'!$D$33,0,IFERROR(SUMIFS(INDIRECT("'"&$G$7&"'!$D$37:$D$52"),INDIRECT("'"&$G$7&"'!$C$37:$C$52"),W41,INDIRECT("'"&$G$7&"'!$B$37:$B$52"),"*Indirect*")/INDIRECT("'"&$G$7&"'!$F$2"),0))) -> 0
W42: 1 | X42: ='General Information'!$D$25+W42 -> 2029 | Y42: =IF($G$4="",0,IF(W42>'General Information'!$D$33,0,IF(W42=0,$J$4,IFERROR(SUMIF(INDIRECT("'"&$G$4&"'!$C$37:$C$52"),W42,INDIRECT("'"&$G$4&"'!$D$37:$D$52")),0)))) -> 0 | Z42: =IF($G$5="",0,IF(W42>'General Information'!$D$33,0,IF(W42=0,$J$5,IFERROR(SUMIF(INDIRECT("'"&$G$5&"'!$C$37:$C$52"),W42,INDIRECT("'"&$G$5&"'!$D$37:$D$52")),0)))) -> 0 | AA42: =IF($G$6="",0,IF(W42>'General Information'!$D$33,0,IF(W42=0,$J$6,IFERROR(SUMIF(INDIRECT("'"&$G$6&"'!$C$37:$C$52"),W42,INDIRECT("'"&$G$6&"'!$D$37:$D$52")),0)))) -> 0 | AB42: =IF($G$7="",0,IF(W42>'General Information'!$D$33,0,IF(W42=0,$J$7,IFERROR(SUMIF(INDIRECT("'"&$G$7&"'!$C$37:$C$52"),W42,INDIRECT("'"&$G$7&"'!$D$37:$D$52")),0)))) -> 0 | AC42: =IF($G$4="",0,AC41+IF(W42>'General Information'!$D$33,0,IF(W42=0,$J$4,IFERROR(SUMIF(INDIRECT("'"&$G$4&"'!$C$37:$C$52"),W42,INDIRECT("'"&$G$4&"'!$E$37:$E$52")),0)))) -> 7268437 | AD42: =IF($G$5="",0,AD41+IF(W42>'General Information'!$D$33,0,IF(W42=0,$J$5,IFERROR(SUMIF(INDIRECT("'"&$G$5&"'!$C$37:$C$52"),W42,INDIRECT("'"&$G$5&"'!$E$37:$E$52")),0)))) -> 9062465.8 | AE42: =IF($G$6="",0,AE41+IF(W42>'General Information'!$D$33,0,IF(W42=0,$J$6,IFERROR(SUMIF(INDIRECT("'"&$G$6&"'!$C$37:$C$52"),W42,INDIRECT("'"&$G$6&"'!$E$37:$E$52")),0)))) -> 0 | AF42: =IF($G$7="",0,AF41+IF(W42>'General Information'!$D$33,0,IF(W42=0,$J$7,IFERROR(SUMIF(INDIRECT("'"&$G$7&"'!$C$37:$C$52"),W42,INDIRECT("'"&$G$7&"'!$E$37:$E$52")),0)))) -> 0 | AG42: =IF($G$4="",0,IF(W42>'General Information'!$D$33,0,IFERROR(SUMIFS(INDIRECT("'"&$G$4&"'!$D$37:$D$52"),INDIRECT("'"&$G$4&"'!$C$37:$C$52"),W42,INDIRECT("'"&$G$4&"'!$B$37:$B$52"),"*Indirect*")/INDIRECT("'"&$G$4&"'!$F$2"),0))) -> 0 | AH42: =IF($G$5="",0,IF(W42>'General Information'!$D$33,0,IFERROR(SUMIFS(INDIRECT("'"&$G$5&"'!$D$37:$D$52"),INDIRECT("'"&$G$5&"'!$C$37:$C$52"),W42,INDIRECT("'"&$G$5&"'!$B$37:$B$52"),"*Indirect*")/INDIRECT("'"&$G$5&"'!$F$2"),0))) -> 0 | AI42: =IF($G$6="",0,IF(W42>'General Information'!$D$33,0,IFERROR(SUMIFS(INDIRECT("'"&$G$6&"'!$D$37:$D$52"),INDIRECT("'"&$G$6&"'!$C$37:$C$52"),W42,INDIRECT("'"&$G$6&"'!$B$37:$B$52"),"*Indirect*")/INDIRECT("'"&$G$6&"'!$F$2"),0))) -> 0 | AJ42: =IF($G$7="",0,IF(W42>'General Information'!$D$33,0,IFERROR(SUMIFS(INDIRECT("'"&$G$7&"'!$D$37:$D$52"),INDIRECT("'"&$G$7&"'!$C$37:$C$52"),W42,INDIRECT("'"&$G$7&"'!$B$37:$B$52"),"*Indirect*")/INDIRECT("'"&$G$7&"'!$F$2"),0))) -> 0
W43: 2 | X43: ='General Information'!$D$25+W43 -> 2030 | Y43: =IF($G$4="",0,IF(W43>'General Information'!$D$33,0,IF(W43=0,$J$4,IFERROR(SUMIF(INDIRECT("'"&$G$4&"'!$C$37:$C$52"),W43,INDIRECT("'"&$G$4&"'!$D$37:$D$52")),0)))) -> 0 | Z43: =IF($G$5="",0,IF(W43>'General Information'!$D$33,0,IF(W43=0,$J$5,IFERROR(SUMIF(INDIRECT("'"&$G$5&"'!$C$37:$C$52"),W43,INDIRECT("'"&$G$5&"'!$D$37:$D$52")),0)))) -> 0 | AA43: =IF($G$6="",0,IF(W43>'General Information'!$D$33,0,IF(W43=0,$J$6,IFERROR(SUMIF(INDIRECT("'"&$G$6&"'!$C$37:$C$52"),W43,INDIRECT("'"&$G$6&"'!$D$37:$D$52")),0)))) -> 0 | AB43: =IF($G$7="",0,IF(W43>'General Information'!$D$33,0,IF(W43=0,$J$7,IFERROR(SUMIF(INDIRECT("'"&$G$7&"'!$C$37:$C$52"),W43,INDIRECT("'"&$G$7&"'!$D$37:$D$52")),0)))) -> 0 | AC43: =IF($G$4="",0,AC42+IF(W43>'General Information'!$D$33,0,IF(W43=0,$J$4,IFERROR(SUMIF(INDIRECT("'"&$G$4&"'!$C$37:$C$52"),W43,INDIRECT("'"&$G$4&"'!$E$37:$E$52")),0)))) -> 7268437 | AD43: =IF($G$5="",0,AD42+IF(W43>'General Information'!$D$33,0,IF(W43=0,$J$5,IFERROR(SUMIF(INDIRECT("'"&$G$5&"'!$C$37:$C$52"),W43,INDIRECT("'"&$G$5&"'!$E$37:$E$52")),0)))) -> 9062465.8 | AE43: =IF($G$6="",0,AE42+IF(W43>'General Information'!$D$33,0,IF(W43=0,$J$6,IFERROR(SUMIF(INDIRECT("'"&$G$6&"'!$C$37:$C$52"),W43,INDIRECT("'"&$G$6&"'!$E$37:$E$52")),0)))) -> 0 | AF43: =IF($G$7="",0,AF42+IF(W43>'General Information'!$D$33,0,IF(W43=0,$J$7,IFERROR(SUMIF(INDIRECT("'"&$G$7&"'!$C$37:$C$52"),W43,INDIRECT("'"&$G$7&"'!$E$37:$E$52")),0)))) -> 0 | AG43: =IF($G$4="",0,IF(W43>'General Information'!$D$33,0,IFERROR(SUMIFS(INDIRECT("'"&$G$4&"'!$D$37:$D$52"),INDIRECT("'"&$G$4&"'!$C$37:$C$52"),W43,INDIRECT("'"&$G$4&"'!$B$37:$B$52"),"*Indirect*")/INDIRECT("'"&$G$4&"'!$F$2"),0))) -> 0 | AH43: =IF($G$5="",0,IF(W43>'General Information'!$D$33,0,IFERROR(SUMIFS(INDIRECT("'"&$G$5&"'!$D$37:$D$52"),INDIRECT("'"&$G$5&"'!$C$37:$C$52"),W43,INDIRECT("'"&$G$5&"'!$B$37:$B$52"),"*Indirect*")/INDIRECT("'"&$G$5&"'!$F$2"),0))) -> 0 | AI43: =IF($G$6="",0,IF(W43>'General Information'!$D$33,0,IFERROR(SUMIFS(INDIRECT("'"&$G$6&"'!$D$37:$D$52"),INDIRECT("'"&$G$6&"'!$C$37:$C$52"),W43,INDIRECT("'"&$G$6&"'!$B$37:$B$52"),"*Indirect*")/INDIRECT("'"&$G$6&"'!$F$2"),0))) -> 0 | AJ43: =IF($G$7="",0,IF(W43>'General Information'!$D$33,0,IFERROR(SUMIFS(INDIRECT("'"&$G$7&"'!$D$37:$D$52"),INDIRECT("'"&$G$7&"'!$C$37:$C$52"),W43,INDIRECT("'"&$G$7&"'!$B$37:$B$52"),"*Indirect*")/INDIRECT("'"&$G$7&"'!$F$2"),0))) -> 0
W44: 3 | X44: ='General Information'!$D$25+W44 -> 2031 | Y44: =IF($G$4="",0,IF(W44>'General Information'!$D$33,0,IF(W44=0,$J$4,IFERROR(SUMIF(INDIRECT("'"&$G$4&"'!$C$37:$C$52"),W44,INDIRECT("'"&$G$4&"'!$D$37:$D$52")),0)))) -> 0 | Z44: =IF($G$5="",0,IF(W44>'General Information'!$D$33,0,IF(W44=0,$J$5,IFERROR(SUMIF(INDIRECT("'"&$G$5&"'!$C$37:$C$52"),W44,INDIRECT("'"&$G$5&"'!$D$37:$D$52")),0)))) -> 0 | AA44: =IF($G$6="",0,IF(W44>'General Information'!$D$33,0,IF(W44=0,$J$6,IFERROR(SUMIF(INDIRECT("'"&$G$6&"'!$C$37:$C$52"),W44,INDIRECT("'"&$G$6&"'!$D$37:$D$52")),0)))) -> 0 | AB44: =IF($G$7="",0,IF(W44>'General Information'!$D$33,0,IF(W44=0,$J$7,IFERROR(SUMIF(INDIRECT("'"&$G$7&"'!$C$37:$C$52"),W44,INDIRECT("'"&$G$7&"'!$D$37:$D$52")),0)))) -> 0 | AC44: =IF($G$4="",0,AC43+IF(W44>'General Information'!$D$33,0,IF(W44=0,$J$4,IFERROR(SUMIF(INDIRECT("'"&$G$4&"'!$C$37:$C$52"),W44,INDIRECT("'"&$G$4&"'!$E$37:$E$52")),0)))) -> 7268437 | AD44: =IF($G$5="",0,AD43+IF(W44>'General Information'!$D$33,0,IF(W44=0,$J$5,IFERROR(SUMIF(INDIRECT("'"&$G$5&"'!$C$37:$C$52"),W44,INDIRECT("'"&$G$5&"'!$E$37:$E$52")),0)))) -> 9062465.8 | AE44: =IF($G$6="",0,AE43+IF(W44>'General Information'!$D$33,0,IF(W44=0,$J$6,IFERROR(SUMIF(INDIRECT("'"&$G$6&"'!$C$37:$C$52"),W44,INDIRECT("'"&$G$6&"'!$E$37:$E$52")),0)))) -> 0 | AF44: =IF($G$7="",0,AF43+IF(W44>'General Information'!$D$33,0,IF(W44=0,$J$7,IFERROR(SUMIF(INDIRECT("'"&$G$7&"'!$C$37:$C$52"),W44,INDIRECT("'"&$G$7&"'!$E$37:$E$52")),0)))) -> 0 | AG44: =IF($G$4="",0,IF(W44>'General Information'!$D$33,0,IFERROR(SUMIFS(INDIRECT("'"&$G$4&"'!$D$37:$D$52"),INDIRECT("'"&$G$4&"'!$C$37:$C$52"),W44,INDIRECT("'"&$G$4&"'!$B$37:$B$52"),"*Indirect*")/INDIRECT("'"&$G$4&"'!$F$2"),0))) -> 0 | AH44: =IF($G$5="",0,IF(W44>'General Information'!$D$33,0,IFERROR(SUMIFS(INDIRECT("'"&$G$5&"'!$D$37:$D$52"),INDIRECT("'"&$G$5&"'!$C$37:$C$52"),W44,INDIRECT("'"&$G$5&"'!$B$37:$B$52"),"*Indirect*")/INDIRECT("'"&$G$5&"'!$F$2"),0))) -> 0 | AI44: =IF($G$6="",0,IF(W44>'General Information'!$D$33,0,IFERROR(SUMIFS(INDIRECT("'"&$G$6&"'!$D$37:$D$52"),INDIRECT("'"&$G$6&"'!$C$37:$C$52"),W44,INDIRECT("'"&$G$6&"'!$B$37:$B$52"),"*Indirect*")/INDIRECT("'"&$G$6&"'!$F$2"),0))) -> 0 | AJ44: =IF($G$7="",0,IF(W44>'General Information'!$D$33,0,IFERROR(SUMIFS(INDIRECT("'"&$G$7&"'!$D$37:$D$52"),INDIRECT("'"&$G$7&"'!$C$37:$C$52"),W44,INDIRECT("'"&$G$7&"'!$B$37:$B$52"),"*Indirect*")/INDIRECT("'"&$G$7&"'!$F$2"),0))) -> 0
W45: 4 | X45: ='General Information'!$D$25+W45 -> 2032 | Y45: =IF($G$4="",0,IF(W45>'General Information'!$D$33,0,IF(W45=0,$J$4,IFERROR(SUMIF(INDIRECT("'"&$G$4&"'!$C$37:$C$52"),W45,INDIRECT("'"&$G$4&"'!$D$37:$D$52")),0)))) -> 354260.6 | Z45: =IF($G$5="",0,IF(W45>'General Information'!$D$33,0,IF(W45=0,$J$5,IFERROR(SUMIF(INDIRECT("'"&$G$5&"'!$C$37:$C$52"),W45,INDIRECT("'"&$G$5&"'!$D$37:$D$52")),0)))) -> 0 | AA45: =IF($G$6="",0,IF(W45>'General Information'!$D$33,0,IF(W45=0,$J$6,IFERROR(SUMIF(INDIRECT("'"&$G$6&"'!$C$37:$C$52"),W45,INDIRECT("'"&$G$6&"'!$D$37:$D$52")),0)))) -> 0 | AB45: =IF($G$7="",0,IF(W45>'General Information'!$D$33,0,IF(W45=0,$J$7,IFERROR(SUMIF(INDIRECT("'"&$G$7&"'!$C$37:$C$52"),W45,INDIRECT("'"&$G$7&"'!$D$37:$D$52")),0)))) -> 0 | AC45: =IF($G$4="",0,AC44+IF(W45>'General Information'!$D$33,0,IF(W45=0,$J$4,IFERROR(SUMIF(INDIRECT("'"&$G$4&"'!$C$37:$C$52"),W45,INDIRECT("'"&$G$4&"'!$E$37:$E$52")),0)))) -> 7583193 | AD45: =IF($G$5="",0,AD44+IF(W45>'General Information'!$D$33,0,IF(W45=0,$J$5,IFERROR(SUMIF(INDIRECT("'"&$G$5&"'!$C$37:$C$52"),W45,INDIRECT("'"&$G$5&"'!$E$37:$E$52")),0)))) -> 9062465.8 | AE45: =IF($G$6="",0,AE44+IF(W45>'General Information'!$D$33,0,IF(W45=0,$J$6,IFERROR(SUMIF(INDIRECT("'"&$G$6&"'!$C$37:$C$52"),W45,INDIRECT("'"&$G$6&"'!$E$37:$E$52")),0)))) -> 0 | AF45: =IF($G$7="",0,AF44+IF(W45>'General Information'!$D$33,0,IF(W45=0,$J$7,IFERROR(SUMIF(INDIRECT("'"&$G$7&"'!$C$37:$C$52"),W45,INDIRECT("'"&$G$7&"'!$E$37:$E$52")),0)))) -> 0 | AG45: =IF($G$4="",0,IF(W45>'General Information'!$D$33,0,IFERROR(SUMIFS(INDIRECT("'"&$G$4&"'!$D$37:$D$52"),INDIRECT("'"&$G$4&"'!$C$37:$C$52"),W45,INDIRECT("'"&$G$4&"'!$B$37:$B$52"),"*Indirect*")/INDIRECT("'"&$G$4&"'!$F$2"),0))) -> 7 | AH45: =IF($G$5="",0,IF(W45>'General Information'!$D$33,0,IFERROR(SUMIFS(INDIRECT("'"&$G$5&"'!$D$37:$D$52"),INDIRECT("'"&$G$5&"'!$C$37:$C$52"),W45,INDIRECT("'"&$G$5&"'!$B$37:$B$52"),"*Indirect*")/INDIRECT("'"&$G$5&"'!$F$2"),0))) -> 0 | AI45: =IF($G$6="",0,IF(W45>'General Information'!$D$33,0,IFERROR(SUMIFS(INDIRECT("'"&$G$6&"'!$D$37:$D$52"),INDIRECT("'"&$G$6&"'!$C$37:$C$52"),W45,INDIRECT("'"&$G$6&"'!$B$37:$B$52"),"*Indirect*")/INDIRECT("'"&$G$6&"'!$F$2"),0))) -> 0 | AJ45: =IF($G$7="",0,IF(W45>'General Information'!$D$33,0,IFERROR(SUMIFS(INDIRECT("'"&$G$7&"'!$D$37:$D$52"),INDIRECT("'"&$G$7&"'!$C$37:$C$52"),W45,INDIRECT("'"&$G$7&"'!$B$37:$B$52"),"*Indirect*")/INDIRECT("'"&$G$7&"'!$F$2"),0))) -> 0
W46: 5 | X46: ='General Information'!$D$25+W46 -> 2033 | Y46: =IF($G$4="",0,IF(W46>'General Information'!$D$33,0,IF(W46=0,$J$4,IFERROR(SUMIF(INDIRECT("'"&$G$4&"'!$C$37:$C$52"),W46,INDIRECT("'"&$G$4&"'!$D$37:$D$52")),0)))) -> 0 | Z46: =IF($G$5="",0,IF(W46>'General Information'!$D$33,0,IF(W46=0,$J$5,IFERROR(SUMIF(INDIRECT("'"&$G$5&"'!$C$37:$C$52"),W46,INDIRECT("'"&$G$5&"'!$D$37:$D$52")),0)))) -> 0 | AA46: =IF($G$6="",0,IF(W46>'General Information'!$D$33,0,IF(W46=0,$J$6,IFERROR(SUMIF(INDIRECT("'"&$G$6&"'!$C$37:$C$52"),W46,INDIRECT("'"&$G$6&"'!$D$37:$D$52")),0)))) -> 0 | AB46: =IF($G$7="",0,IF(W46>'General Information'!$D$33,0,IF(W46=0,$J$7,IFERROR(SUMIF(INDIRECT("'"&$G$7&"'!$C$37:$C$52"),W46,INDIRECT("'"&$G$7&"'!$D$37:$D$52")),0)))) -> 0 | AC46: =IF($G$4="",0,AC45+IF(W46>'General Information'!$D$33,0,IF(W46=0,$J$4,IFERROR(SUMIF(INDIRECT("'"&$G$4&"'!$C$37:$C$52"),W46,INDIRECT("'"&$G$4&"'!$E$37:$E$52")),0)))) -> 7583193 | AD46: =IF($G$5="",0,AD45+IF(W46>'General Information'!$D$33,0,IF(W46=0,$J$5,IFERROR(SUMIF(INDIRECT("'"&$G$5&"'!$C$37:$C$52"),W46,INDIRECT("'"&$G$5&"'!$E$37:$E$52")),0)))) -> 9062465.8 | AE46: =IF($G$6="",0,AE45+IF(W46>'General Information'!$D$33,0,IF(W46=0,$J$6,IFERROR(SUMIF(INDIRECT("'"&$G$6&"'!$C$37:$C$52"),W46,INDIRECT("'"&$G$6&"'!$E$37:$E$52")),0)))) -> 0 | AF46: =IF($G$7="",0,AF45+IF(W46>'General Information'!$D$33,0,IF(W46=0,$J$7,IFERROR(SUMIF(INDIRECT("'"&$G$7&"'!$C$37:$C$52"),W46,INDIRECT("'"&$G$7&"'!$E$37:$E$52")),0)))) -> 0 | AG46: =IF($G$4="",0,IF(W46>'General Information'!$D$33,0,IFERROR(SUMIFS(INDIRECT("'"&$G$4&"'!$D$37:$D$52"),INDIRECT("'"&$G$4&"'!$C$37:$C$52"),W46,INDIRECT("'"&$G$4&"'!$B$37:$B$52"),"*Indirect*")/INDIRECT("'"&$G$4&"'!$F$2"),0))) -> 0 | AH46: =IF($G$5="",0,IF(W46>'General Information'!$D$33,0,IFERROR(SUMIFS(INDIRECT("'"&$G$5&"'!$D$37:$D$52"),INDIRECT("'"&$G$5&"'!$C$37:$C$52"),W46,INDIRECT("'"&$G$5&"'!$B$37:$B$52"),"*Indirect*")/INDIRECT("'"&$G$5&"'!$F$2"),0))) -> 0 | AI46: =IF($G$6="",0,IF(W46>'General Information'!$D$33,0,IFERROR(SUMIFS(INDIRECT("'"&$G$6&"'!$D$37:$D$52"),INDIRECT("'"&$G$6&"'!$C$37:$C$52"),W46,INDIRECT("'"&$G$6&"'!$B$37:$B$52"),"*Indirect*")/INDIRECT("'"&$G$6&"'!$F$2"),0))) -> 0 | AJ46: =IF($G$7="",0,IF(W46>'General Information'!$D$33,0,IFERROR(SUMIFS(INDIRECT("'"&$G$7&"'!$D$37:$D$52"),INDIRECT("'"&$G$7&"'!$C$37:$C$52"),W46,INDIRECT("'"&$G$7&"'!$B$37:$B$52"),"*Indirect*")/INDIRECT("'"&$G$7&"'!$F$2"),0))) -> 0
W47: 6 | X47: ='General Information'!$D$25+W47 -> 2034 | Y47: =IF($G$4="",0,IF(W47>'General Information'!$D$33,0,IF(W47=0,$J$4,IFERROR(SUMIF(INDIRECT("'"&$G$4&"'!$C$37:$C$52"),W47,INDIRECT("'"&$G$4&"'!$D$37:$D$52")),0)))) -> 0 | Z47: =IF($G$5="",0,IF(W47>'General Information'!$D$33,0,IF(W47=0,$J$5,IFERROR(SUMIF(INDIRECT("'"&$G$5&"'!$C$37:$C$52"),W47,INDIRECT("'"&$G$5&"'!$D$37:$D$52")),0)))) -> 0 | AA47: =IF($G$6="",0,IF(W47>'General Information'!$D$33,0,IF(W47=0,$J$6,IFERROR(SUMIF(INDIRECT("'"&$G$6&"'!$C$37:$C$52"),W47,INDIRECT("'"&$G$6&"'!$D$37:$D$52")),0)))) -> 0 | AB47: =IF($G$7="",0,IF(W47>'General Information'!$D$33,0,IF(W47=0,$J$7,IFERROR(SUMIF(INDIRECT("'"&$G$7&"'!$C$37:$C$52"),W47,INDIRECT("'"&$G$7&"'!$D$37:$D$52")),0)))) -> 0 | AC47: =IF($G$4="",0,AC46+IF(W47>'General Information'!$D$33,0,IF(W47=0,$J$4,IFERROR(SUMIF(INDIRECT("'"&$G$4&"'!$C$37:$C$52"),W47,INDIRECT("'"&$G$4&"'!$E$37:$E$52")),0)))) -> 7583193 | AD47: =IF($G$5="",0,AD46+IF(W47>'General Information'!$D$33,0,IF(W47=0,$J$5,IFERROR(SUMIF(INDIRECT("'"&$G$5&"'!$C$37:$C$52"),W47,INDIRECT("'"&$G$5&"'!$E$37:$E$52")),0)))) -> 9062465.8 | AE47: =IF($G$6="",0,AE46+IF(W47>'General Information'!$D$33,0,IF(W47=0,$J$6,IFERROR(SUMIF(INDIRECT("'"&$G$6&"'!$C$37:$C$52"),W47,INDIRECT("'"&$G$6&"'!$E$37:$E$52")),0)))) -> 0 | AF47: =IF($G$7="",0,AF46+IF(W47>'General Information'!$D$33,0,IF(W47=0,$J$7,IFERROR(SUMIF(INDIRECT("'"&$G$7&"'!$C$37:$C$52"),W47,INDIRECT("'"&$G$7&"'!$E$37:$E$52")),0)))) -> 0 | AG47: =IF($G$4="",0,IF(W47>'General Information'!$D$33,0,IFERROR(SUMIFS(INDIRECT("'"&$G$4&"'!$D$37:$D$52"),INDIRECT("'"&$G$4&"'!$C$37:$C$52"),W47,INDIRECT("'"&$G$4&"'!$B$37:$B$52"),"*Indirect*")/INDIRECT("'"&$G$4&"'!$F$2"),0))) -> 0 | AH47: =IF($G$5="",0,IF(W47>'General Information'!$D$33,0,IFERROR(SUMIFS(INDIRECT("'"&$G$5&"'!$D$37:$D$52"),INDIRECT("'"&$G$5&"'!$C$37:$C$52"),W47,INDIRECT("'"&$G$5&"'!$B$37:$B$52"),"*Indirect*")/INDIRECT("'"&$G$5&"'!$F$2"),0))) -> 0 | AI47: =IF($G$6="",0,IF(W47>'General Information'!$D$33,0,IFERROR(SUMIFS(INDIRECT("'"&$G$6&"'!$D$37:$D$52"),INDIRECT("'"&$G$6&"'!$C$37:$C$52"),W47,INDIRECT("'"&$G$6&"'!$B$37:$B$52"),"*Indirect*")/INDIRECT("'"&$G$6&"'!$F$2"),0))) -> 0 | AJ47: =IF($G$7="",0,IF(W47>'General Information'!$D$33,0,IFERROR(SUMIFS(INDIRECT("'"&$G$7&"'!$D$37:$D$52"),INDIRECT("'"&$G$7&"'!$C$37:$C$52"),W47,INDIRECT("'"&$G$7&"'!$B$37:$B$52"),"*Indirect*")/INDIRECT("'"&$G$7&"'!$F$2"),0))) -> 0
W48: 7 | X48: ='General Information'!$D$25+W48 -> 2035 | Y48: =IF($G$4="",0,IF(W48>'General Information'!$D$33,0,IF(W48=0,$J$4,IFERROR(SUMIF(INDIRECT("'"&$G$4&"'!$C$37:$C$52"),W48,INDIRECT("'"&$G$4&"'!$D$37:$D$52")),0)))) -> 0 | Z48: =IF($G$5="",0,IF(W48>'General Information'!$D$33,0,IF(W48=0,$J$5,IFERROR(SUMIF(INDIRECT("'"&$G$5&"'!$C$37:$C$52"),W48,INDIRECT("'"&$G$5&"'!$D$37:$D$52")),0)))) -> 0 | AA48: =IF($G$6="",0,IF(W48>'General Information'!$D$33,0,IF(W48=0,$J$6,IFERROR(SUMIF(INDIRECT("'"&$G$6&"'!$C$37:$C$52"),W48,INDIRECT("'"&$G$6&"'!$D$37:$D$52")),0)))) -> 0 | AB48: =IF($G$7="",0,IF(W48>'General Information'!$D$33,0,IF(W48=0,$J$7,IFERROR(SUMIF(INDIRECT("'"&$G$7&"'!$C$37:$C$52"),W48,INDIRECT("'"&$G$7&"'!$D$37:$D$52")),0)))) -> 0 | AC48: =IF($G$4="",0,AC47+IF(W48>'General Information'!$D$33,0,IF(W48=0,$J$4,IFERROR(SUMIF(INDIRECT("'"&$G$4&"'!$C$37:$C$52"),W48,INDIRECT("'"&$G$4&"'!$E$37:$E$52")),0)))) -> 7583193 | AD48: =IF($G$5="",0,AD47+IF(W48>'General Information'!$D$33,0,IF(W48=0,$J$5,IFERROR(SUMIF(INDIRECT("'"&$G$5&"'!$C$37:$C$52"),W48,INDIRECT("'"&$G$5&"'!$E$37:$E$52")),0)))) -> 9062465.8 | AE48: =IF($G$6="",0,AE47+IF(W48>'General Information'!$D$33,0,IF(W48=0,$J$6,IFERROR(SUMIF(INDIRECT("'"&$G$6&"'!$C$37:$C$52"),W48,INDIRECT("'"&$G$6&"'!$E$37:$E$52")),0)))) -> 0 | AF48: =IF($G$7="",0,AF47+IF(W48>'General Information'!$D$33,0,IF(W48=0,$J$7,IFERROR(SUMIF(INDIRECT("'"&$G$7&"'!$C$37:$C$52"),W48,INDIRECT("'"&$G$7&"'!$E$37:$E$52")),0)))) -> 0 | AG48: =IF($G$4="",0,IF(W48>'General Information'!$D$33,0,IFERROR(SUMIFS(INDIRECT("'"&$G$4&"'!$D$37:$D$52"),INDIRECT("'"&$G$4&"'!$C$37:$C$52"),W48,INDIRECT("'"&$G$4&"'!$B$37:$B$52"),"*Indirect*")/INDIRECT("'"&$G$4&"'!$F$2"),0))) -> 0 | AH48: =IF($G$5="",0,IF(W48>'General Information'!$D$33,0,IFERROR(SUMIFS(INDIRECT("'"&$G$5&"'!$D$37:$D$52"),INDIRECT("'"&$G$5&"'!$C$37:$C$52"),W48,INDIRECT("'"&$G$5&"'!$B$37:$B$52"),"*Indirect*")/INDIRECT("'"&$G$5&"'!$F$2"),0))) -> 0 | AI48: =IF($G$6="",0,IF(W48>'General Information'!$D$33,0,IFERROR(SUMIFS(INDIRECT("'"&$G$6&"'!$D$37:$D$52"),INDIRECT("'"&$G$6&"'!$C$37:$C$52"),W48,INDIRECT("'"&$G$6&"'!$B$37:$B$52"),"*Indirect*")/INDIRECT("'"&$G$6&"'!$F$2"),0))) -> 0 | AJ48: =IF($G$7="",0,IF(W48>'General Information'!$D$33,0,IFERROR(SUMIFS(INDIRECT("'"&$G$7&"'!$D$37:$D$52"),INDIRECT("'"&$G$7&"'!$C$37:$C$52"),W48,INDIRECT("'"&$G$7&"'!$B$37:$B$52"),"*Indirect*")/INDIRECT("'"&$G$7&"'!$F$2"),0))) -> 0
W49: 8 | X49: ='General Information'!$D$25+W49 -> 2036 | Y49: =IF($G$4="",0,IF(W49>'General Information'!$D$33,0,IF(W49=0,$J$4,IFERROR(SUMIF(INDIRECT("'"&$G$4&"'!$C$37:$C$52"),W49,INDIRECT("'"&$G$4&"'!$D$37:$D$52")),0)))) -> 354260.6 | Z49: =IF($G$5="",0,IF(W49>'General Information'!$D$33,0,IF(W49=0,$J$5,IFERROR(SUMIF(INDIRECT("'"&$G$5&"'!$C$37:$C$52"),W49,INDIRECT("'"&$G$5&"'!$D$37:$D$52")),0)))) -> 0 | AA49: =IF($G$6="",0,IF(W49>'General Information'!$D$33,0,IF(W49=0,$J$6,IFERROR(SUMIF(INDIRECT("'"&$G$6&"'!$C$37:$C$52"),W49,INDIRECT("'"&$G$6&"'!$D$37:$D$52")),0)))) -> 0 | AB49: =IF($G$7="",0,IF(W49>'General Information'!$D$33,0,IF(W49=0,$J$7,IFERROR(SUMIF(INDIRECT("'"&$G$7&"'!$C$37:$C$52"),W49,INDIRECT("'"&$G$7&"'!$D$37:$D$52")),0)))) -> 0 | AC49: =IF($G$4="",0,AC48+IF(W49>'General Information'!$D$33,0,IF(W49=0,$J$4,IFERROR(SUMIF(INDIRECT("'"&$G$4&"'!$C$37:$C$52"),W49,INDIRECT("'"&$G$4&"'!$E$37:$E$52")),0)))) -> 7862849.5 | AD49: =IF($G$5="",0,AD48+IF(W49>'General Information'!$D$33,0,IF(W49=0,$J$5,IFERROR(SUMIF(INDIRECT("'"&$G$5&"'!$C$37:$C$52"),W49,INDIRECT("'"&$G$5&"'!$E$37:$E$52")),0)))) -> 9062465.8 | AE49: =IF($G$6="",0,AE48+IF(W49>'General Information'!$D$33,0,IF(W49=0,$J$6,IFERROR(SUMIF(INDIRECT("'"&$G$6&"'!$C$37:$C$52"),W49,INDIRECT("'"&$G$6&"'!$E$37:$E$52")),0)))) -> 0 | AF49: =IF($G$7="",0,AF48+IF(W49>'General Information'!$D$33,0,IF(W49=0,$J$7,IFERROR(SUMIF(INDIRECT("'"&$G$7&"'!$C$37:$C$52"),W49,INDIRECT("'"&$G$7&"'!$E$37:$E$52")),0)))) -> 0 | AG49: =IF($G$4="",0,IF(W49>'General Information'!$D$33,0,IFERROR(SUMIFS(INDIRECT("'"&$G$4&"'!$D$37:$D$52"),INDIRECT("'"&$G$4&"'!$C$37:$C$52"),W49,INDIRECT("'"&$G$4&"'!$B$37:$B$52"),"*Indirect*")/INDIRECT("'"&$G$4&"'!$F$2"),0))) -> 7 | AH49: =IF($G$5="",0,IF(W49>'General Information'!$D$33,0,IFERROR(SUMIFS(INDIRECT("'"&$G$5&"'!$D$37:$D$52"),INDIRECT("'"&$G$5&"'!$C$37:$C$52"),W49,INDIRECT("'"&$G$5&"'!$B$37:$B$52"),"*Indirect*")/INDIRECT("'"&$G$5&"'!$F$2"),0))) -> 0 | AI49: =IF($G$6="",0,IF(W49>'General Information'!$D$33,0,IFERROR(SUMIFS(INDIRECT("'"&$G$6&"'!$D$37:$D$52"),INDIRECT("'"&$G$6&"'!$C$37:$C$52"),W49,INDIRECT("'"&$G$6&"'!$B$37:$B$52"),"*Indirect*")/INDIRECT("'"&$G$6&"'!$F$2"),0))) -> 0 | AJ49: =IF($G$7="",0,IF(W49>'General Information'!$D$33,0,IFERROR(SUMIFS(INDIRECT("'"&$G$7&"'!$D$37:$D$52"),INDIRECT("'"&$G$7&"'!$C$37:$C$52"),W49,INDIRECT("'"&$G$7&"'!$B$37:$B$52"),"*Indirect*")/INDIRECT("'"&$G$7&"'!$F$2"),0))) -> 0
W50: 9 | X50: ='General Information'!$D$25+W50 -> 2037 | Y50: =IF($G$4="",0,IF(W50>'General Information'!$D$33,0,IF(W50=0,$J$4,IFERROR(SUMIF(INDIRECT("'"&$G$4&"'!$C$37:$C$52"),W50,INDIRECT("'"&$G$4&"'!$D$37:$D$52")),0)))) -> 0 | Z50: =IF($G$5="",0,IF(W50>'General Information'!$D$33,0,IF(W50=0,$J$5,IFERROR(SUMIF(INDIRECT("'"&$G$5&"'!$C$37:$C$52"),W50,INDIRECT("'"&$G$5&"'!$D$37:$D$52")),0)))) -> 0 | AA50: =IF($G$6="",0,IF(W50>'General Information'!$D$33,0,IF(W50=0,$J$6,IFERROR(SUMIF(INDIRECT("'"&$G$6&"'!$C$37:$C$52"),W50,INDIRECT("'"&$G$6&"'!$D$37:$D$52")),0)))) -> 0 | AB50: =IF($G$7="",0,IF(W50>'General Information'!$D$33,0,IF(W50=0,$J$7,IFERROR(SUMIF(INDIRECT("'"&$G$7&"'!$C$37:$C$52"),W50,INDIRECT("'"&$G$7&"'!$D$37:$D$52")),0)))) -> 0 | AC50: =IF($G$4="",0,AC49+IF(W50>'General Information'!$D$33,0,IF(W50=0,$J$4,IFERROR(SUMIF(INDIRECT("'"&$G$4&"'!$C$37:$C$52"),W50,INDIRECT("'"&$G$4&"'!$E$37:$E$52")),0)))) -> 7862849.5 | AD50: =IF($G$5="",0,AD49+IF(W50>'General Information'!$D$33,0,IF(W50=0,$J$5,IFERROR(SUMIF(INDIRECT("'"&$G$5&"'!$C$37:$C$52"),W50,INDIRECT("'"&$G$5&"'!$E$37:$E$52")),0)))) -> 9062465.8 | AE50: =IF($G$6="",0,AE49+IF(W50>'General Information'!$D$33,0,IF(W50=0,$J$6,IFERROR(SUMIF(INDIRECT("'"&$G$6&"'!$C$37:$C$52"),W50,INDIRECT("'"&$G$6&"'!$E$37:$E$52")),0)))) -> 0 | AF50: =IF($G$7="",0,AF49+IF(W50>'General Information'!$D$33,0,IF(W50=0,$J$7,IFERROR(SUMIF(INDIRECT("'"&$G$7&"'!$C$37:$C$52"),W50,INDIRECT("'"&$G$7&"'!$E$37:$E$52")),0)))) -> 0 | AG50: =IF($G$4="",0,IF(W50>'General Information'!$D$33,0,IFERROR(SUMIFS(INDIRECT("'"&$G$4&"'!$D$37:$D$52"),INDIRECT("'"&$G$4&"'!$C$37:$C$52"),W50,INDIRECT("'"&$G$4&"'!$B$37:$B$52"),"*Indirect*")/INDIRECT("'"&$G$4&"'!$F$2"),0))) -> 0 | AH50: =IF($G$5="",0,IF(W50>'General Information'!$D$33,0,IFERROR(SUMIFS(INDIRECT("'"&$G$5&"'!$D$37:$D$52"),INDIRECT("'"&$G$5&"'!$C$37:$C$52"),W50,INDIRECT("'"&$G$5&"'!$B$37:$B$52"),"*Indirect*")/INDIRECT("'"&$G$5&"'!$F$2"),0))) -> 0 | AI50: =IF($G$6="",0,IF(W50>'General Information'!$D$33,0,IFERROR(SUMIFS(INDIRECT("'"&$G$6&"'!$D$37:$D$52"),INDIRECT("'"&$G$6&"'!$C$37:$C$52"),W50,INDIRECT("'"&$G$6&"'!$B$37:$B$52"),"*Indirect*")/INDIRECT("'"&$G$6&"'!$F$2"),0))) -> 0 | AJ50: =IF($G$7="",0,IF(W50>'General Information'!$D$33,0,IFERROR(SUMIFS(INDIRECT("'"&$G$7&"'!$D$37:$D$52"),INDIRECT("'"&$G$7&"'!$C$37:$C$52"),W50,INDIRECT("'"&$G$7&"'!$B$37:$B$52"),"*Indirect*")/INDIRECT("'"&$G$7&"'!$F$2"),0))) -> 0
W51: 10 | X51: ='General Information'!$D$25+W51 -> 2038 | Y51: =IF($G$4="",0,IF(W51>'General Information'!$D$33,0,IF(W51=0,$J$4,IFERROR(SUMIF(INDIRECT("'"&$G$4&"'!$C$37:$C$52"),W51,INDIRECT("'"&$G$4&"'!$D$37:$D$52")),0)))) -> 0 | Z51: =IF($G$5="",0,IF(W51>'General Information'!$D$33,0,IF(W51=0,$J$5,IFERROR(SUMIF(INDIRECT("'"&$G$5&"'!$C$37:$C$52"),W51,INDIRECT("'"&$G$5&"'!$D$37:$D$52")),0)))) -> 0 | AA51: =IF($G$6="",0,IF(W51>'General Information'!$D$33,0,IF(W51=0,$J$6,IFERROR(SUMIF(INDIRECT("'"&$G$6&"'!$C$37:$C$52"),W51,INDIRECT("'"&$G$6&"'!$D$37:$D$52")),0)))) -> 0 | AB51: =IF($G$7="",0,IF(W51>'General Information'!$D$33,0,IF(W51=0,$J$7,IFERROR(SUMIF(INDIRECT("'"&$G$7&"'!$C$37:$C$52"),W51,INDIRECT("'"&$G$7&"'!$D$37:$D$52")),0)))) -> 0 | AC51: =IF($G$4="",0,AC50+IF(W51>'General Information'!$D$33,0,IF(W51=0,$J$4,IFERROR(SUMIF(INDIRECT("'"&$G$4&"'!$C$37:$C$52"),W51,INDIRECT("'"&$G$4&"'!$E$37:$E$52")),0)))) -> 7862849.5 | AD51: =IF($G$5="",0,AD50+IF(W51>'General Information'!$D$33,0,IF(W51=0,$J$5,IFERROR(SUMIF(INDIRECT("'"&$G$5&"'!$C$37:$C$52"),W51,INDIRECT("'"&$G$5&"'!$E$37:$E$52")),0)))) -> 9062465.8 | AE51: =IF($G$6="",0,AE50+IF(W51>'General Information'!$D$33,0,IF(W51=0,$J$6,IFERROR(SUMIF(INDIRECT("'"&$G$6&"'!$C$37:$C$52"),W51,INDIRECT("'"&$G$6&"'!$E$37:$E$52")),0)))) -> 0 | AF51: =IF($G$7="",0,AF50+IF(W51>'General Information'!$D$33,0,IF(W51=0,$J$7,IFERROR(SUMIF(INDIRECT("'"&$G$7&"'!$C$37:$C$52"),W51,INDIRECT("'"&$G$7&"'!$E$37:$E$52")),0)))) -> 0 | AG51: =IF($G$4="",0,IF(W51>'General Information'!$D$33,0,IFERROR(SUMIFS(INDIRECT("'"&$G$4&"'!$D$37:$D$52"),INDIRECT("'"&$G$4&"'!$C$37:$C$52"),W51,INDIRECT("'"&$G$4&"'!$B$37:$B$52"),"*Indirect*")/INDIRECT("'"&$G$4&"'!$F$2"),0))) -> 0 | AH51: =IF($G$5="",0,IF(W51>'General Information'!$D$33,0,IFERROR(SUMIFS(INDIRECT("'"&$G$5&"'!$D$37:$D$52"),INDIRECT("'"&$G$5&"'!$C$37:$C$52"),W51,INDIRECT("'"&$G$5&"'!$B$37:$B$52"),"*Indirect*")/INDIRECT("'"&$G$5&"'!$F$2"),0))) -> 0 | AI51: =IF($G$6="",0,IF(W51>'General Information'!$D$33,0,IFERROR(SUMIFS(INDIRECT("'"&$G$6&"'!$D$37:$D$52"),INDIRECT("'"&$G$6&"'!$C$37:$C$52"),W51,INDIRECT("'"&$G$6&"'!$B$37:$B$52"),"*Indirect*")/INDIRECT("'"&$G$6&"'!$F$2"),0))) -> 0 | AJ51: =IF($G$7="",0,IF(W51>'General Information'!$D$33,0,IFERROR(SUMIFS(INDIRECT("'"&$G$7&"'!$D$37:$D$52"),INDIRECT("'"&$G$7&"'!$C$37:$C$52"),W51,INDIRECT("'"&$G$7&"'!$B$37:$B$52"),"*Indirect*")/INDIRECT("'"&$G$7&"'!$F$2"),0))) -> 0
