Workbook

Sheet TMP(NewPCC)_IndirectCost
A1: =HYPERLINK("#'General Information'!D9","◄ General Information") -> ◄ General Information | C1: =HYPERLINK("#Summary!G1","Summary") -> Summary | D1: =$A$34 -> PCC Reconstruction - Alternative 2 | I1: Hidden
A2: Initial Construction Costs: | E2: Average Daily Revenue: | F2: =IF('General Information'!$D$38="Yes",SUMIF(RevenueData!$A:$A,'General Information'!$D$10,RevenueData!$B:$B)+SUMIF(RevenueData!$A:$A,'General Information'!$D$10,RevenueData!$C:$C)+SUMIF(RevenueData!$A:$A,'General Information'!$D$10,RevenueData!$D:$D)+SUMIF(RevenueData!$A:$A,'General Information'!$D$10,RevenueData!$E:$E)+SUMIF(RevenueData!$A:$A,'General Information'!$D$10,RevenueData!$F:$F)+SUMIF(RevenueData!$A:$A,'General Information'!$D$10,RevenueData!$G:$G)+SUMIF(RevenueData!$A:$A,'General Information'!$D$10,RevenueData!$H:$H),0) -> 5441.17 | G2: =IF(AND('General Information'!$D$38="Yes",F2=0),"No revenue data for this airport - lost revenue set to $0. Contact Aeronautics.","") | J2: Maintenance 1 | R2: Rehabilitation 1
A3: STEP 4 of 5 · The quantities for this alternative. Grey cells are yours: C4 to C7 project data (filled from General Information), F4 and F5 closure days, C13 to C22 pay items and E13 to E22 quantities. Everything else calculates. Unit costs come from Pay_Items, and C11 picks which division they are priced from.
A4: Pavement Type: | C4: New PCC | E4: Maintenance 1 Duration (Days) | F4: =ROUNDUP(C5*550/(50*100/9)/10000,0)+ROUNDUP(C5*'Maintenance Policies'!D38/10000,0)+ROUNDUP(C5*'Maintenance Policies'!D39/5000,0)+ROUNDUP(C5*'Maintenance Policies'!D40/5000,0) -> 8
A5: Mainline Pavement Area: | C5: ='General Information'!D26 -> 45883 | D5: S.Y. | E5: Rehabilitation 1 Duration (Days) | F5: =ROUNDUP(C5*550/(50*100/9)/10000,0)+ROUNDUP(C5*'Maintenance Policies'!D44/10000,0)+ROUNDUP(C5*'Maintenance Policies'!D43/5000,0)+ROUNDUP(C5*'Maintenance Policies'!D42/5000,0)+ROUNDUP(C5*'Maintenance Policies'!D41/1000,0)+7 -> 16
A6: Initial Construction Year: | C6: ='General Information'!D25 -> 2028
A7: Markings Area: | C7: ='General Information'!D28 -> 12000 | D7: S.F. | J7: No. of Slabs: | K7: =C5/((12.5*12.5)/9) -> 2642.8608
J8: Joint length: | K8: =K7*25+((K7/8)*12.5) -> 70200.99
I10: Price column: 1 Regular, 2 Middle, 3 West, 4 East
B11: Price from: | C11: Regular | D11: =IF(OR($C$11="Regular",$C$11=""),"Regular is the statewide Unit Cost column on Pay_Items.","Prices from the "&$C$11&" column on Pay_Items: "&SUM($I$13:$I$22)&" of "&COUNT($I$13:$I$22)&" pay items used here have a "&$C$11&" cost, the rest fall back to Unit Cost.") -> Regular is the statewide Unit Cost column on Pay_Items. | I11: =IFERROR(MATCH($C$11,PriceSources,0),1) -> 1
A12: Item No. | B12: Pay Item | C12: Description | D12: Unit | E12: Qty | F12: Unit Cost | G12: Item Cost | J12: Item No. | K12: Pay Item | L12: Description | M12: Unit | N12: Qty | O12: Unit Cost | P12: Item Cost | R12: Item No. | S12: Pay Item | T12: Description | U12: Unit | V12: Qty | W12: Unit Cost | X12: Item Cost
A13: 1 | B13: =IF(C13="","",VLOOKUP(C13,CHOOSE({1,2},Table2[Pay Item Description],Table2[Pay Item No.]),2,0)) | D13: =IF(C13="","N/A",VLOOKUP(C13,CHOOSE({1,2},Table2[Pay Item Description],Table2[Units]),2,0)) -> N/A | F13: =IF(C13="","N/A",IF(INDEX(UnitCostGrid,MATCH(C13,PayItemKeys,0),$I$11)="",INDEX(UnitCostGrid,MATCH(C13,PayItemKeys,0),1),INDEX(UnitCostGrid,MATCH(C13,PayItemKeys,0),$I$11))) -> N/A | G13: =IF(C13="",0,F13*E13) -> 0 | I13: =IF(C13="","",IF(INDEX(UnitCostGrid,MATCH(C13,PayItemKeys,0),$I$11)="",0,1)) | J13: 1 | K13: =IF(L13="",0,VLOOKUP(L13,CHOOSE({1,2},Table2[Pay Item Description],Table2[Pay Item No.]),2,0)) -> P-605-5.1a | L13: =Pay_Items!D55 -> Joint Clean and Reseal, Concrete | M13: =IF(L13="","N/A",VLOOKUP(L13,CHOOSE({1,2},Table2[Pay Item Description],Table2[Units]),2,0)) -> L.F. | N13: =K8*'Maintenance Policies'!D37 -> 70200.99 | O13: =IF(L13="","N/A",IF(INDEX(UnitCostGrid,MATCH(L13,PayItemKeys,0),$I$11)="",INDEX(UnitCostGrid,MATCH(L13,PayItemKeys,0),1),INDEX(UnitCostGrid,MATCH(L13,PayItemKeys,0),$I$11))) -> 7 | P13: =O13*N13 -> 491406.93 | R13: 1 | S13: =IF(T13="",0,VLOOKUP(T13,CHOOSE({1,2},Table2[Pay Item Description],Table2[Pay Item No.]),2,0)) -> P-101-5.5c | T13: =Pay_Items!D15 -> Slab Replacement, Concrete | U13: =IF(T13="","N/A",VLOOKUP(T13,CHOOSE({1,2},Table2[Pay Item Description],Table2[Units]),2,0)) -> S.Y. | V13: ='Maintenance Policies'!D41*C5 -> 917.66 | W13: =IF(T13="","N/A",IF(INDEX(UnitCostGrid,MATCH(T13,PayItemKeys,0),$I$11)="",INDEX(UnitCostGrid,MATCH(T13,PayItemKeys,0),1),INDEX(UnitCostGrid,MATCH(T13,PayItemKeys,0),$I$11))) -> 100 | X13: =W13*V13 -> 91766
A14: 2 | B14: =IF(C14="","",VLOOKUP(C14,CHOOSE({1,2},Table2[Pay Item Description],Table2[Pay Item No.]),2,0)) | D14: =IF(C14="","N/A",VLOOKUP(C14,CHOOSE({1,2},Table2[Pay Item Description],Table2[Units]),2,0)) -> N/A | F14: =IF(C14="","N/A",IF(INDEX(UnitCostGrid,MATCH(C14,PayItemKeys,0),$I$11)="",INDEX(UnitCostGrid,MATCH(C14,PayItemKeys,0),1),INDEX(UnitCostGrid,MATCH(C14,PayItemKeys,0),$I$11))) -> N/A | G14: =IF(C14="",0,F14*E14) -> 0 | I14: =IF(C14="","",IF(INDEX(UnitCostGrid,MATCH(C14,PayItemKeys,0),$I$11)="",0,1)) | J14: 2 | K14: =VLOOKUP(L14,CHOOSE({1,2},Table2[Pay Item Description],Table2[Pay Item No.]),2,0) -> P-101-5.2c | L14: =Pay_Items!D8 -> Crack Seal, Concrete | M14: =IF(L14="","N/A",VLOOKUP(L14,CHOOSE({1,2},Table2[Pay Item Description],Table2[Units]),2,0)) -> L.F. | N14: ='Maintenance Policies'!D38*(C5*9) -> 1032.3675 | O14: =IF(L14="","N/A",IF(INDEX(UnitCostGrid,MATCH(L14,PayItemKeys,0),$I$11)="",INDEX(UnitCostGrid,MATCH(L14,PayItemKeys,0),1),INDEX(UnitCostGrid,MATCH(L14,PayItemKeys,0),$I$11))) -> 8 | P14: =O14*N14 -> 8258.94 | R14: 2 | S14: =VLOOKUP(T14,CHOOSE({1,2},Table2[Pay Item Description],Table2[Pay Item No.]),2,0) -> P-101-5.5b | T14: =Pay_Items!D14 -> Full-Depth Repair, Concrete | U14: =IF(T14="","N/A",VLOOKUP(T14,CHOOSE({1,2},Table2[Pay Item Description],Table2[Units]),2,0)) -> S.Y. | V14: ='Maintenance Policies'!D42*C5 -> 137.649 | W14: =IF(T14="","N/A",IF(INDEX(UnitCostGrid,MATCH(T14,PayItemKeys,0),$I$11)="",INDEX(UnitCostGrid,MATCH(T14,PayItemKeys,0),1),INDEX(UnitCostGrid,MATCH(T14,PayItemKeys,0),$I$11))) -> 120 | X14: =W14*V14 -> 16517.88
A15: 3 | B15: =IF(C15="","",VLOOKUP(C15,CHOOSE({1,2},Table2[Pay Item Description],Table2[Pay Item No.]),2,0)) | D15: =IF(C15="","N/A",VLOOKUP(C15,CHOOSE({1,2},Table2[Pay Item Description],Table2[Units]),2,0)) -> N/A | F15: =IF(C15="","N/A",IF(INDEX(UnitCostGrid,MATCH(C15,PayItemKeys,0),$I$11)="",INDEX(UnitCostGrid,MATCH(C15,PayItemKeys,0),1),INDEX(UnitCostGrid,MATCH(C15,PayItemKeys,0),$I$11))) -> N/A | G15: =IF(C15="",0,F15*E15) -> 0 | I15: =IF(C15="","",IF(INDEX(UnitCostGrid,MATCH(C15,PayItemKeys,0),$I$11)="",0,1)) | J15: 3 | K15: =VLOOKUP(L15,CHOOSE({1,2},Table2[Pay Item Description],Table2[Pay Item No.]),2,0) -> P-101-5.5a | L15: =Pay_Items!D13 -> Spall Repair, Concrete | M15: =IF(L15="","N/A",VLOOKUP(L15,CHOOSE({1,2},Table2[Pay Item Description],Table2[Units]),2,0)) -> S.F. | N15: ='Maintenance Policies'!D39*(C5*9) -> 536.8311 | O15: =IF(L15="","N/A",IF(INDEX(UnitCostGrid,MATCH(L15,PayItemKeys,0),$I$11)="",INDEX(UnitCostGrid,MATCH(L15,PayItemKeys,0),1),INDEX(UnitCostGrid,MATCH(L15,PayItemKeys,0),$I$11))) -> 60 | P15: =O15*N15 -> 32209.866 | R15: 3 | S15: =VLOOKUP(T15,CHOOSE({1,2},Table2[Pay Item Description],Table2[Pay Item No.]),2,0) -> P-101-5.5a | T15: =Pay_Items!D13 -> Spall Repair, Concrete | U15: =IF(T15="","N/A",VLOOKUP(T15,CHOOSE({1,2},Table2[Pay Item Description],Table2[Units]),2,0)) -> S.F. | V15: ='Maintenance Policies'!D43*(C5*9) -> 536.8311 | W15: =IF(T15="","N/A",IF(INDEX(UnitCostGrid,MATCH(T15,PayItemKeys,0),$I$11)="",INDEX(UnitCostGrid,MATCH(T15,PayItemKeys,0),1),INDEX(UnitCostGrid,MATCH(T15,PayItemKeys,0),$I$11))) -> 60 | X15: =W15*V15 -> 32209.866
A16: 4 | B16: =IF(C16="","",VLOOKUP(C16,CHOOSE({1,2},Table2[Pay Item Description],Table2[Pay Item No.]),2,0)) | D16: =IF(C16="","N/A",VLOOKUP(C16,CHOOSE({1,2},Table2[Pay Item Description],Table2[Units]),2,0)) -> N/A | F16: =IF(C16="","N/A",IF(INDEX(UnitCostGrid,MATCH(C16,PayItemKeys,0),$I$11)="",INDEX(UnitCostGrid,MATCH(C16,PayItemKeys,0),1),INDEX(UnitCostGrid,MATCH(C16,PayItemKeys,0),$I$11))) -> N/A | G16: =IF(C16="",0,F16*E16) -> 0 | I16: =IF(C16="","",IF(INDEX(UnitCostGrid,MATCH(C16,PayItemKeys,0),$I$11)="",0,1)) | J16: 4 | K16: =VLOOKUP(L16,CHOOSE({1,2},Table2[Pay Item Description],Table2[Pay Item No.]),2,0) -> P-101-5.5b | L16: =Pay_Items!D14 -> Full-Depth Repair, Concrete | M16: =IF(L16="","N/A",VLOOKUP(L16,CHOOSE({1,2},Table2[Pay Item Description],Table2[Units]),2,0)) -> S.Y. | N16: ='Maintenance Policies'!D40*C5 -> 137.649 | O16: =IF(L16="","N/A",IF(INDEX(UnitCostGrid,MATCH(L16,PayItemKeys,0),$I$11)="",INDEX(UnitCostGrid,MATCH(L16,PayItemKeys,0),1),INDEX(UnitCostGrid,MATCH(L16,PayItemKeys,0),$I$11))) -> 120 | P16: =O16*N16 -> 16517.88 | R16: 4 | S16: =VLOOKUP(T16,CHOOSE({1,2},Table2[Pay Item Description],Table2[Pay Item No.]),2,0) -> P-101-5.2c | T16: =Pay_Items!D8 -> Crack Seal, Concrete | U16: =IF(T16="","N/A",VLOOKUP(T16,CHOOSE({1,2},Table2[Pay Item Description],Table2[Units]),2,0)) -> L.F. | V16: ='Maintenance Policies'!D44*(C5*9) -> 1238.841 | W16: =IF(T16="","N/A",IF(INDEX(UnitCostGrid,MATCH(T16,PayItemKeys,0),$I$11)="",INDEX(UnitCostGrid,MATCH(T16,PayItemKeys,0),1),INDEX(UnitCostGrid,MATCH(T16,PayItemKeys,0),$I$11))) -> 8 | X16: =W16*V16 -> 9910.728
A17: 5 | B17: =IF(C17="","",VLOOKUP(C17,CHOOSE({1,2},Table2[Pay Item Description],Table2[Pay Item No.]),2,0)) | D17: =IF(C17="","N/A",VLOOKUP(C17,CHOOSE({1,2},Table2[Pay Item Description],Table2[Units]),2,0)) -> N/A | F17: =IF(C17="","N/A",IF(INDEX(UnitCostGrid,MATCH(C17,PayItemKeys,0),$I$11)="",INDEX(UnitCostGrid,MATCH(C17,PayItemKeys,0),1),INDEX(UnitCostGrid,MATCH(C17,PayItemKeys,0),$I$11))) -> N/A | G17: =IF(C17="",0,F17*E17) -> 0 | I17: =IF(C17="","",IF(INDEX(UnitCostGrid,MATCH(C17,PayItemKeys,0),$I$11)="",0,1)) | O17: Subtotal | P17: =SUM(P13:P16) -> 548393.62 | R17: 5 | S17: =VLOOKUP(T17,CHOOSE({1,2},Table2[Pay Item Description],Table2[Pay Item No.]),2,0) -> P-605-5.1a | T17: =Pay_Items!D55 -> Joint Clean and Reseal, Concrete | U17: =IF(T17="","N/A",VLOOKUP(T17,CHOOSE({1,2},Table2[Pay Item Description],Table2[Units]),2,0)) -> L.F. | V17: ='Maintenance Policies'!D45*K8 -> 70200.99 | W17: =IF(T17="","N/A",IF(INDEX(UnitCostGrid,MATCH(T17,PayItemKeys,0),$I$11)="",INDEX(UnitCostGrid,MATCH(T17,PayItemKeys,0),1),INDEX(UnitCostGrid,MATCH(T17,PayItemKeys,0),$I$11))) -> 7 | X17: =W17*V17 -> 491406.93
A18: 6 | B18: =IF(C18="","",VLOOKUP(C18,CHOOSE({1,2},Table2[Pay Item Description],Table2[Pay Item No.]),2,0)) | D18: =IF(C18="","N/A",VLOOKUP(C18,CHOOSE({1,2},Table2[Pay Item Description],Table2[Units]),2,0)) -> N/A | F18: =IF(C18="","N/A",IF(INDEX(UnitCostGrid,MATCH(C18,PayItemKeys,0),$I$11)="",INDEX(UnitCostGrid,MATCH(C18,PayItemKeys,0),1),INDEX(UnitCostGrid,MATCH(C18,PayItemKeys,0),$I$11))) -> N/A | G18: =IF(C18="",0,F18*E18) -> 0 | I18: =IF(C18="","",IF(INDEX(UnitCostGrid,MATCH(C18,PayItemKeys,0),$I$11)="",0,1)) | L18: Mobilization | P18: =('General Information'!$D$36/100)*P17 -> 54839.362 | W18: Subtotal | X18: =SUM(X13:X17) -> 641811.4
A19: 7 | B19: =IF(C19="","",VLOOKUP(C19,CHOOSE({1,2},Table2[Pay Item Description],Table2[Pay Item No.]),2,0)) | D19: =IF(C19="","N/A",VLOOKUP(C19,CHOOSE({1,2},Table2[Pay Item Description],Table2[Units]),2,0)) -> N/A | F19: =IF(C19="","N/A",IF(INDEX(UnitCostGrid,MATCH(C19,PayItemKeys,0),$I$11)="",INDEX(UnitCostGrid,MATCH(C19,PayItemKeys,0),1),INDEX(UnitCostGrid,MATCH(C19,PayItemKeys,0),$I$11))) -> N/A | G19: =IF(C19="",0,F19*E19) -> 0 | I19: =IF(C19="","",IF(INDEX(UnitCostGrid,MATCH(C19,PayItemKeys,0),$I$11)="",0,1)) | L19: Engineering | P19: =('General Information'!$D$37/100)*P17 -> 27419.681 | T19: Mobilization | X19: =('General Information'!$D$36/100)*X18 -> 64181.14
A20: 8 | B20: =IF(C20="","",VLOOKUP(C20,CHOOSE({1,2},Table2[Pay Item Description],Table2[Pay Item No.]),2,0)) | D20: =IF(C20="","N/A",VLOOKUP(C20,CHOOSE({1,2},Table2[Pay Item Description],Table2[Units]),2,0)) -> N/A | F20: =IF(C20="","N/A",IF(INDEX(UnitCostGrid,MATCH(C20,PayItemKeys,0),$I$11)="",INDEX(UnitCostGrid,MATCH(C20,PayItemKeys,0),1),INDEX(UnitCostGrid,MATCH(C20,PayItemKeys,0),$I$11))) -> N/A | G20: =IF(C20="",0,F20*E20) -> 0 | I20: =IF(C20="","",IF(INDEX(UnitCostGrid,MATCH(C20,PayItemKeys,0),$I$11)="",0,1)) | O20: Total | P20: =SUM(P17:P19) -> 630652.66 | T20: Engineering | X20: =('General Information'!$D$37/100)*X18 -> 32090.57
A21: 9 | B21: =IF(C21="","",VLOOKUP(C21,CHOOSE({1,2},Table2[Pay Item Description],Table2[Pay Item No.]),2,0)) | D21: =IF(C21="","N/A",VLOOKUP(C21,CHOOSE({1,2},Table2[Pay Item Description],Table2[Units]),2,0)) -> N/A | F21: =IF(C21="","N/A",IF(INDEX(UnitCostGrid,MATCH(C21,PayItemKeys,0),$I$11)="",INDEX(UnitCostGrid,MATCH(C21,PayItemKeys,0),1),INDEX(UnitCostGrid,MATCH(C21,PayItemKeys,0),$I$11))) -> N/A | G21: =IF(C21="",0,F21*E21) -> 0 | I21: =IF(C21="","",IF(INDEX(UnitCostGrid,MATCH(C21,PayItemKeys,0),$I$11)="",0,1)) | W21: Total | X21: =SUM(X18:X20) -> 738083.11
A22: 10 | B22: =IF(C22="","",VLOOKUP(C22,CHOOSE({1,2},Table2[Pay Item Description],Table2[Pay Item No.]),2,0)) | D22: =IF(C22="","N/A",VLOOKUP(C22,CHOOSE({1,2},Table2[Pay Item Description],Table2[Units]),2,0)) -> N/A | F22: =IF(C22="","N/A",IF(INDEX(UnitCostGrid,MATCH(C22,PayItemKeys,0),$I$11)="",INDEX(UnitCostGrid,MATCH(C22,PayItemKeys,0),1),INDEX(UnitCostGrid,MATCH(C22,PayItemKeys,0),$I$11))) -> N/A | G22: =IF(C22="",0,F22*E22) -> 0 | I22: =IF(C22="","",IF(INDEX(UnitCostGrid,MATCH(C22,PayItemKeys,0),$I$11)="",0,1))
A24: Subtotal | G24: =SUM(G13:G22) -> 0
B25: Mobilization | G25: =('General Information'!$D$36/100)*G24 -> 0
B26: Engineering | G26: =('General Information'!$D$37/100)*G24 -> 0
A27: Total | G27: =SUM(G24:G26) -> 0
A33: Net Present Worth
A34: PCC Reconstruction - Alternative 2 | I34: Hidden
B36: Item | C36: Year Applied | D36: Actual Cost | E36: Discounted Cost
B37: Initial Construction | C37: =C6 -> 2028 | D37: =G27 -> 0 | E37: =D37 -> 0 | K37: Year | L37: Direct Cost | M37: Indirect Cost | N37: Total Discounted Cost
B38: Maintenance 1 | C38: ='Maintenance Policies'!E37 -> 19 | D38: =P20 -> 630652.66 | E38: =IF(C38>'General Information'!$D$33,0,D38/(1+('General Information'!$D$34/100))^C38) -> 359652.4 | K38: =C6 -> 2028 | L38: =IF(K38-$C$6>'General Information'!$D$33,0,IF(K38=$C$6,$D$37,0)+SUMIFS($D$38:$D$42,$C$38:$C$42,K38-$C$6,$B$38:$B$42,"<>*Indirect*")) -> 0 | M38: =IF(K38-$C$6>'General Information'!$D$33,0,SUMIFS($D$38:$D$42,$C$38:$C$42,K38-$C$6,$B$38:$B$42,"*Indirect*")) -> 0 | N38: =IF(K38-$C$6>'General Information'!$D$33,0,IF(K38=$C$6,$E$37,0)+SUMIF($C$38:$C$42,K38-$C$6,$E$38:$E$42)) -> 0
B39: Maintenance 1 Indirect Cost | C39: ='Maintenance Policies'!E37 -> 19 | D39: =F2*F4 -> 43529.36 | E39: =IF(C39>'General Information'!$D$33,0,D39/(1+('General Information'!$D$34/100))^C39) -> 24824.186 | K39: =K38+1 -> 2029 | L39: =IF(K39-$C$6>'General Information'!$D$33,0,IF(K39=$C$6,$D$37,0)+SUMIFS($D$38:$D$42,$C$38:$C$42,K39-$C$6,$B$38:$B$42,"<>*Indirect*")) -> 0 | M39: =IF(K39-$C$6>'General Information'!$D$33,0,SUMIFS($D$38:$D$42,$C$38:$C$42,K39-$C$6,$B$38:$B$42,"*Indirect*")) -> 0 | N39: =IF(K39-$C$6>'General Information'!$D$33,0,IF(K39=$C$6,$E$37,0)+SUMIF($C$38:$C$42,K39-$C$6,$E$38:$E$42)) -> 0
B40: Rehabilitation 1 | C40: ='Maintenance Policies'!E41 -> 27 | D40: =X21 -> 738083.11 | E40: =IF(C40>'General Information'!$D$33,0,D40/(1+('General Information'!$D$34/100))^C40) -> 332276.94 | K40: =K39+1 -> 2030 | L40: =IF(K40-$C$6>'General Information'!$D$33,0,IF(K40=$C$6,$D$37,0)+SUMIFS($D$38:$D$42,$C$38:$C$42,K40-$C$6,$B$38:$B$42,"<>*Indirect*")) -> 0 | M40: =IF(K40-$C$6>'General Information'!$D$33,0,SUMIFS($D$38:$D$42,$C$38:$C$42,K40-$C$6,$B$38:$B$42,"*Indirect*")) -> 0 | N40: =IF(K40-$C$6>'General Information'!$D$33,0,IF(K40=$C$6,$E$37,0)+SUMIF($C$38:$C$42,K40-$C$6,$E$38:$E$42)) -> 0
B41: Rehabilitation 1 Indirect Cost | C41: ='Maintenance Policies'!E41 -> 27 | D41: =F2*F5 -> 87058.72 | E41: =IF(C41>'General Information'!$D$33,0,D41/(1+('General Information'!$D$34/100))^C41) -> 39192.883 | K41: =K40+1 -> 2031 | L41: =IF(K41-$C$6>'General Information'!$D$33,0,IF(K41=$C$6,$D$37,0)+SUMIFS($D$38:$D$42,$C$38:$C$42,K41-$C$6,$B$38:$B$42,"<>*Indirect*")) -> 0 | M41: =IF(K41-$C$6>'General Information'!$D$33,0,SUMIFS($D$38:$D$42,$C$38:$C$42,K41-$C$6,$B$38:$B$42,"*Indirect*")) -> 0 | N41: =IF(K41-$C$6>'General Information'!$D$33,0,IF(K41=$C$6,$E$37,0)+SUMIF($C$38:$C$42,K41-$C$6,$E$38:$E$42)) -> 0
B42: Salvage | C42: ='General Information'!D33 -> 30 | D42: =-'Maintenance Policies'!D46*G27 -> 0 | E42: =IF(C42>'General Information'!$D$33,0,D42/(1+('General Information'!$D$34/100))^C42) -> 0 | K42: =K41+1 -> 2032 | L42: =IF(K42-$C$6>'General Information'!$D$33,0,IF(K42=$C$6,$D$37,0)+SUMIFS($D$38:$D$42,$C$38:$C$42,K42-$C$6,$B$38:$B$42,"<>*Indirect*")) -> 0 | M42: =IF(K42-$C$6>'General Information'!$D$33,0,SUMIFS($D$38:$D$42,$C$38:$C$42,K42-$C$6,$B$38:$B$42,"*Indirect*")) -> 0 | N42: =IF(K42-$C$6>'General Information'!$D$33,0,IF(K42=$C$6,$E$37,0)+SUMIF($C$38:$C$42,K42-$C$6,$E$38:$E$42)) -> 0
B43: Net Present Worth | E43: =SUM(E37:E42) -> 755946.41 | K43: =K42+1 -> 2033 | L43: =IF(K43-$C$6>'General Information'!$D$33,0,IF(K43=$C$6,$D$37,0)+SUMIFS($D$38:$D$42,$C$38:$C$42,K43-$C$6,$B$38:$B$42,"<>*Indirect*")) -> 0 | M43: =IF(K43-$C$6>'General Information'!$D$33,0,SUMIFS($D$38:$D$42,$C$38:$C$42,K43-$C$6,$B$38:$B$42,"*Indirect*")) -> 0 | N43: =IF(K43-$C$6>'General Information'!$D$33,0,IF(K43=$C$6,$E$37,0)+SUMIF($C$38:$C$42,K43-$C$6,$E$38:$E$42)) -> 0
K44: =K43+1 -> 2034 | L44: =IF(K44-$C$6>'General Information'!$D$33,0,IF(K44=$C$6,$D$37,0)+SUMIFS($D$38:$D$42,$C$38:$C$42,K44-$C$6,$B$38:$B$42,"<>*Indirect*")) -> 0 | M44: =IF(K44-$C$6>'General Information'!$D$33,0,SUMIFS($D$38:$D$42,$C$38:$C$42,K44-$C$6,$B$38:$B$42,"*Indirect*")) -> 0 | N44: =IF(K44-$C$6>'General Information'!$D$33,0,IF(K44=$C$6,$E$37,0)+SUMIF($C$38:$C$42,K44-$C$6,$E$38:$E$42)) -> 0
K45: =K44+1 -> 2035 | L45: =IF(K45-$C$6>'General Information'!$D$33,0,IF(K45=$C$6,$D$37,0)+SUMIFS($D$38:$D$42,$C$38:$C$42,K45-$C$6,$B$38:$B$42,"<>*Indirect*")) -> 0 | M45: =IF(K45-$C$6>'General Information'!$D$33,0,SUMIFS($D$38:$D$42,$C$38:$C$42,K45-$C$6,$B$38:$B$42,"*Indirect*")) -> 0 | N45: =IF(K45-$C$6>'General Information'!$D$33,0,IF(K45=$C$6,$E$37,0)+SUMIF($C$38:$C$42,K45-$C$6,$E$38:$E$42)) -> 0
K46: =K45+1 -> 2036 | L46: =IF(K46-$C$6>'General Information'!$D$33,0,IF(K46=$C$6,$D$37,0)+SUMIFS($D$38:$D$42,$C$38:$C$42,K46-$C$6,$B$38:$B$42,"<>*Indirect*")) -> 0 | M46: =IF(K46-$C$6>'General Information'!$D$33,0,SUMIFS($D$38:$D$42,$C$38:$C$42,K46-$C$6,$B$38:$B$42,"*Indirect*")) -> 0 | N46: =IF(K46-$C$6>'General Information'!$D$33,0,IF(K46=$C$6,$E$37,0)+SUMIF($C$38:$C$42,K46-$C$6,$E$38:$E$42)) -> 0
K47: =K46+1 -> 2037 | L47: =IF(K47-$C$6>'General Information'!$D$33,0,IF(K47=$C$6,$D$37,0)+SUMIFS($D$38:$D$42,$C$38:$C$42,K47-$C$6,$B$38:$B$42,"<>*Indirect*")) -> 0 | M47: =IF(K47-$C$6>'General Information'!$D$33,0,SUMIFS($D$38:$D$42,$C$38:$C$42,K47-$C$6,$B$38:$B$42,"*Indirect*")) -> 0 | N47: =IF(K47-$C$6>'General Information'!$D$33,0,IF(K47=$C$6,$E$37,0)+SUMIF($C$38:$C$42,K47-$C$6,$E$38:$E$42)) -> 0
K48: =K47+1 -> 2038 | L48: =IF(K48-$C$6>'General Information'!$D$33,0,IF(K48=$C$6,$D$37,0)+SUMIFS($D$38:$D$42,$C$38:$C$42,K48-$C$6,$B$38:$B$42,"<>*Indirect*")) -> 0 | M48: =IF(K48-$C$6>'General Information'!$D$33,0,SUMIFS($D$38:$D$42,$C$38:$C$42,K48-$C$6,$B$38:$B$42,"*Indirect*")) -> 0 | N48: =IF(K48-$C$6>'General Information'!$D$33,0,IF(K48=$C$6,$E$37,0)+SUMIF($C$38:$C$42,K48-$C$6,$E$38:$E$42)) -> 0
K49: =K48+1 -> 2039 | L49: =IF(K49-$C$6>'General Information'!$D$33,0,IF(K49=$C$6,$D$37,0)+SUMIFS($D$38:$D$42,$C$38:$C$42,K49-$C$6,$B$38:$B$42,"<>*Indirect*")) -> 0 | M49: =IF(K49-$C$6>'General Information'!$D$33,0,SUMIFS($D$38:$D$42,$C$38:$C$42,K49-$C$6,$B$38:$B$42,"*Indirect*")) -> 0 | N49: =IF(K49-$C$6>'General Information'!$D$33,0,IF(K49=$C$6,$E$37,0)+SUMIF($C$38:$C$42,K49-$C$6,$E$38:$E$42)) -> 0
K50: =K49+1 -> 2040 | L50: =IF(K50-$C$6>'General Information'!$D$33,0,IF(K50=$C$6,$D$37,0)+SUMIFS($D$38:$D$42,$C$38:$C$42,K50-$C$6,$B$38:$B$42,"<>*Indirect*")) -> 0 | M50: =IF(K50-$C$6>'General Information'!$D$33,0,SUMIFS($D$38:$D$42,$C$38:$C$42,K50-$C$6,$B$38:$B$42,"*Indirect*")) -> 0 | N50: =IF(K50-$C$6>'General Information'!$D$33,0,IF(K50=$C$6,$E$37,0)+SUMIF($C$38:$C$42,K50-$C$6,$E$38:$E$42)) -> 0
K51: =K50+1 -> 2041 | L51: =IF(K51-$C$6>'General Information'!$D$33,0,IF(K51=$C$6,$D$37,0)+SUMIFS($D$38:$D$42,$C$38:$C$42,K51-$C$6,$B$38:$B$42,"<>*Indirect*")) -> 0 | M51: =IF(K51-$C$6>'General Information'!$D$33,0,SUMIFS($D$38:$D$42,$C$38:$C$42,K51-$C$6,$B$38:$B$42,"*Indirect*")) -> 0 | N51: =IF(K51-$C$6>'General Information'!$D$33,0,IF(K51=$C$6,$E$37,0)+SUMIF($C$38:$C$42,K51-$C$6,$E$38:$E$42)) -> 0
K52: =K51+1 -> 2042 | L52: =IF(K52-$C$6>'General Information'!$D$33,0,IF(K52=$C$6,$D$37,0)+SUMIFS($D$38:$D$42,$C$38:$C$42,K52-$C$6,$B$38:$B$42,"<>*Indirect*")) -> 0 | M52: =IF(K52-$C$6>'General Information'!$D$33,0,SUMIFS($D$38:$D$42,$C$38:$C$42,K52-$C$6,$B$38:$B$42,"*Indirect*")) -> 0 | N52: =IF(K52-$C$6>'General Information'!$D$33,0,IF(K52=$C$6,$E$37,0)+SUMIF($C$38:$C$42,K52-$C$6,$E$38:$E$42)) -> 0
K53: =K52+1 -> 2043 | L53: =IF(K53-$C$6>'General Information'!$D$33,0,IF(K53=$C$6,$D$37,0)+SUMIFS($D$38:$D$42,$C$38:$C$42,K53-$C$6,$B$38:$B$42,"<>*Indirect*")) -> 0 | M53: =IF(K53-$C$6>'General Information'!$D$33,0,SUMIFS($D$38:$D$42,$C$38:$C$42,K53-$C$6,$B$38:$B$42,"*Indirect*")) -> 0 | N53: =IF(K53-$C$6>'General Information'!$D$33,0,IF(K53=$C$6,$E$37,0)+SUMIF($C$38:$C$42,K53-$C$6,$E$38:$E$42)) -> 0
K54: =K53+1 -> 2044 | L54: =IF(K54-$C$6>'General Information'!$D$33,0,IF(K54=$C$6,$D$37,0)+SUMIFS($D$38:$D$42,$C$38:$C$42,K54-$C$6,$B$38:$B$42,"<>*Indirect*")) -> 0 | M54: =IF(K54-$C$6>'General Information'!$D$33,0,SUMIFS($D$38:$D$42,$C$38:$C$42,K54-$C$6,$B$38:$B$42,"*Indirect*")) -> 0 | N54: =IF(K54-$C$6>'General Information'!$D$33,0,IF(K54=$C$6,$E$37,0)+SUMIF($C$38:$C$42,K54-$C$6,$E$38:$E$42)) -> 0
K55: =K54+1 -> 2045 | L55: =IF(K55-$C$6>'General Information'!$D$33,0,IF(K55=$C$6,$D$37,0)+SUMIFS($D$38:$D$42,$C$38:$C$42,K55-$C$6,$B$38:$B$42,"<>*Indirect*")) -> 0 | M55: =IF(K55-$C$6>'General Information'!$D$33,0,SUMIFS($D$38:$D$42,$C$38:$C$42,K55-$C$6,$B$38:$B$42,"*Indirect*")) -> 0 | N55: =IF(K55-$C$6>'General Information'!$D$33,0,IF(K55=$C$6,$E$37,0)+SUMIF($C$38:$C$42,K55-$C$6,$E$38:$E$42)) -> 0
... K68: =K67+1 -> 2058 | L68: =IF(K68-$C$6>'General Information'!$D$33,0,IF(K68=$C$6,$D$37,0)+SUMIFS($D$38:$D$42,$C$38:$C$42,K68-$C$6,$B$38:$B$42,"<>*Indirect*")) -> 0 | M68: =IF(K68-$C$6>'General Information'!$D$33,0,SUMIFS($D$38:$D$42,$C$38:$C$42,K68-$C$6,$B$38:$B$42,"*Indirect*")) -> 0 | N68: =IF(K68-$C$6>'General Information'!$D$33,0,IF(K68=$C$6,$E$37,0)+SUMIF($C$38:$C$42,K68-$C$6,$E$38:$E$42)) -> 0

Sheet Overview
B1: =HYPERLINK("#'General Information'!D9","◄ General Information") -> ◄ General Information | E1: =HYPERLINK("#Summary!G1","Summary") -> Summary | G1: Overview
B2: STEP 1 of 5 · What the framework does and the rules behind it. Read this and Instructions, then go to General Information.
B4: A life-cycle cost analysis compares alternatives over their whole life, not their first bill.
B5: You describe two or more ways to build the same runway. The workbook prices each one from the TDOT pay-item list, adds the maintenance and rehabilitation each will need over the analysis period, discounts it all to today’s money, and reports which costs least in present worth.
B8: What you provide | F8: What the workbook adds | J8: What you get
B9: • The airport and the runway | F9: • Unit costs by division | J9: • Net present worth per option
B10: • Pavement areas and markings | F10: • Maintenance and rehabilitation timing | J10: • Equivalent annual cost
B11: • Two or more alternatives | F11: • Salvage on remaining life | J11: • Sensitivity to the discount rate
B12: • Quantities per pay item | F12: • Lost revenue during closures | J12: • Eight charts and a comparison
B14: THE RULES BEHIND IT
B15: =IF('General Information'!$D$33="","30",'General Information'!$D$33)&" years" -> 30 years | E15: =IF('General Information'!$D$34="","3",'General Information'!$D$34)&"%" -> 3% | H15: =IF('General Information'!$D$36="","10",'General Information'!$D$36)&" / "&IF('General Information'!$D$37="","5",'General Information'!$D$37)&"%" -> 10 / 5% | K15: Remaining life
B16: analysis period, live from General Information D33 | E16: discount rate, D34; FAA follows OMB Circular A-94 | H16: mobilization and engineering, D36 and D37 | K16: salvage basis: remaining life over expected life (AAPTP, FAA)
B18: HOW A STUDY RUNS
B19: =HYPERLINK("#Instructions!B1","1 Overview & Instructions") -> 1 Overview & Instructions | E19: =HYPERLINK("#'General Information'!D9","2 General Information") -> 2 General Information | G19: =HYPERLINK("#Pay_Items!A1","3 Pay Items") -> 3 Pay Items | I19: =HYPERLINK("#'General Information'!D9","4 Alternatives") -> 4 Alternatives | K19: =HYPERLINK("#Summary!G1","5 Summary") -> 5 Summary
B21: TDOT Aeronautics Division | H21: Before you start
B22: 7335 Centennial Boulevard | H22: Enable macros and ActiveX when Excel asks. The Alternative Setup form and the pay-item pickers need them. If the yellow bar does not appear, check Trust Center › ActiveX Settings and restart Excel.
B23: Nashville, Tennessee 37209
B24: 615-741-3208
B25: tn.gov/tdot/aeronautics.html
B27: BACKGROUND

Sheet Instructions
B1: =HYPERLINK("#'General Information'!D9","◄ General Information") -> ◄ General Information | E1: =HYPERLINK("#Summary!G1","Summary") -> Summary | G1: Instructions
B2: STEP 1 of 5 · How to run an analysis, start to finish. When you are ready, go to General Information and fill in the grey cells.
B4: First, enable content.
B5: Macros and ActiveX must be on, or the Alternative Setup form and the pay-item pickers will not run. Trust Center › ActiveX Settings, then restart Excel.
B7: Set the study up | H7: Run it
B8: 1 | C8: Fill in General Information | H8: 4 | I8: Add each alternative
C9: Pick the airport from the dropdown and the ID, city, county and region fill themselves. Then the runway areas and the LCCA parameters, D9 to D39. The amber banner lists whatever is still missing. | I9: Back on General Information, click Alternative Setup. Name it, choose the pavement type, and the form builds a worksheet for it. Enter quantities against the pay items there.
B12: 2 | C12: Check the unit costs on Pay_Items | H12: 5 | I12: Read the Summary
C13: Every alternative is priced from that sheet, and the grey Unit Cost column is the one to edit. An item that ships with no cost prices at zero. | I13: It updates by itself. The banner names the lowest present worth; the two key plots show why it wins and whether it still wins at other discount rates.
B16: 3 | C16: Review the maintenance policies | H16: 6 | I16: Start the next study
C17: Four tables set what each pavement type gets done to it and in which year. They are live: a rate or a year changed there moves every alternative of that type. | I17: The + New Study button saves a cleared copy wherever you choose, with every input blank and every alternative removed. The study you have open is untouched.
B21: Grey means yours | F21: Where to look things up | J21: If a number looks wrong
B22: A grey cell is one you type in. | F22: Typical Values: the usual ranges, with sources. | J22: Check the Unit Cost column first, then the year a policy is applied.
B23: Everything else calculates: leave it alone. | F23: Method: every formula as it stands in the sheet. | J23: Both feed every alternative of that pavement type at once.
B26: THE ORIGINAL STEP-BY-STEP NOTES

Sheet General Information
C1: General Information | D1: STEP 2 of 5 · fill in the grey cells, D9 to D39.
B2: Saves a fresh copy for the next study. This file stays as is. | F2: HOW TO USE THIS WORKBOOK
F3: 1. Overview and Instructions: what the framework does and the rules behind it. 2. General Information (this sheet): fill in the grey cells, D9 to D39. 3. Pay_Items: check the unit costs your alternatives will be priced from. 4. Alternative Setup: add each alternative, then enter its quantities on the sheet it creates. 5. Summary: read the comparison. It updates by itself. Grey cells are yours; white cells calculate. Typical Values has the usual ranges, Method every formula.
B4: 1 Overview › 2 General Information › 3 Pay Items › 4 Alternatives › 5 Summary
K7: Hidden
B8: Airport information | L8: Name | M8: ID | N8: City | O8: County | P8: Region | Q8: Owner | S8: Branch Use
C9: Airport Name: | D9: Gatlinburg-Pigeon Forge Airport | F9: =IF(LEN(IF(D9="","Airport Name, ","")&IF(D25="","Construction Year, ","")&IF(D26="","Mainline Area, ","")&IF(D28="","Markings Area, ","")&IF(D33="","Analysis Period, ","")&IF(D34="","Discount Rate, ",""))=0,"All required inputs are filled. Next: click Alternative Setup.","Still needed: "&LEFT(IF(D9="","Airport Name, ","")&IF(D25="","Construction Year, ","")&IF(D26="","Mainline Area, ","")&IF(D28="","Markings Area, ","")&IF(D33="","Analysis Period, ","")&IF(D34="","Discount Rate, ",""),LEN(IF(D9="","Airport Name, ","")&IF(D25="","Construction Year, ","")&IF(D26="","Mainline Area, ","")&IF(D28="","Markings Area, ","")&IF(D33="","Analysis Period, ","")&IF(D34="","Discount Rate, ",""))-2)) -> All required inputs are filled. Next: click Alternative Setup. | N9: N/A | O9: N/A
C10: Airport ID: | D10: =IF(D9="","N/A",VLOOKUP(Airport_Name,Table17[],2)) -> GKT | L10: Abernathy Field | M10: GZS | N10: Pulaski | O10: Giles | P10: Middle | S10: Runway
C11: City: | D11: =IF(D9="","N/A",VLOOKUP(Airport_Name,Table17[],3)) -> Sevierville | L11: Arnold Field | M11: M31 | N11: Halls | O11: Lauderdale | P11: West | S11: Taxiway
C12: County: | D12: =IF(D9="","N/A",VLOOKUP(Airport_Name,Table17[],4)) -> Sevier | L12: Beech River Regional Airport | M12: PVE | N12: Lexington/Parsons | O12: Henderson | P12: West | S12: Apron
C13: State Region: | D13: =IF(D9="","N/A",VLOOKUP(Airport_Name,Table17[],5)) -> East | L13: Benton County Airport | M13: 0M4 | N13: Camden | O13: Benton | P13: West
C14: Design Consultant: | D14: ARA | L14: Bomar Field-Shelbyville Municipal Airport | M14: SYI | N14: Shelbyville | O14: Bedford | P14: Middle
C15: Project Number: | D15: 6101 | L15: Carroll County Airport | M15: HZD | N15: Huntingdon | O15: Carroll | P15: West | S15: Markings Type
C16: Project Name: | D16: Runway 10-28 Reconstruction | L16: Centerville Municipal Airport | M16: GHM | N16: Centerville | O16: Hickman | P16: Middle
C17: Date of LCCA: | L17: Charles W. Baker Field | M17: 2M8 | N17: Millington | O17: Shelby | P17: West | S17: Reflective
L18: Chilhowee Gliderport | M18: 92A | N18: Benton | O18: Polk | P18: East | S18: Non-Reflective
L19: Cleveland Regional Jetport | M19: RZR | N19: Cleveland | O19: Bradley | P19: East
B20: Project and pavement | L20: Collegedale Municipal Airport | M20: FGU | N20: Collegedale | O20: Hamilton | P20: East
C21: Branch Type: | D21: Runway | L21: Colonel Tommy C. Stiner-Campbell County Airport | M21: JAU | N21: Jacksboro | O21: Campbell | P21: East | S21: Weight Category
C22: Branch Name: | D22: Runway 10-28 | L22: Covington Municipal Airport | M22: M04 | N22: Covington | O22: Tipton | P22: West
C23: Project Type: | D23: Reconstruction | L23: Crossville Memorial Airport/Whitson Field | M23: CSV | N23: Crossville | O23: Cumberland | P23: East | S23: < 60,000 lbs
C24: Project Description: | D24: Full-depth reconstruction, 5,506 x 75 ft, no paved shoulders | L24: Dallas Bay Skypark Airport | M24: 1A0 | N24: Chattanooga | O24: Hamilton | P24: East | S24: > 60,000 to < 100,000 lbs
C25: Initial Construction Year: | D25: 2028 | F25: Construction year; the analysis period starts here. | L25: Dickson Municipal Airport | M25: M02 | N25: Dickson | O25: Dickson | P25: Middle | S25: > 100,000 lbs
C26: Mainline Area, S.Y.: | D26: 45883 | F26: Length x width / 9. TN GA: 4,000-6,000 ft x 75-100 ft wide. | L26: Dyersburg Municipal Airport | M26: DYR | N26: Dyersburg | O26: Dyer | P26: West
C27: Shoulder Area, S.Y.: | D27: 0 | F27: Paved shoulders only; usually 0 at TN GA airports. | L27: Elizabethton Municipal Airport | M27: 0A9 | N27: Elizabethton | O27: Carter | P27: East
C28: Markings, S.F.: | D28: 12000 | F28: About 2,000-3,000 SF per 1,000 ft of runway. | L28: Ellington Airport | M28: LUG | N28: Lewisburg | O28: Marshall | P28: Middle
C29: Markings, Type: | D29: Reflective | L29: Everett-Stewart Airport | M29: UCY | N29: Union City | O29: Obion | P29: West
L30: Fayette County Airport | M30: FYE | N30: Somerville | O30: Fayette | P30: West
L31: Fayetteville Municipal Airport | M31: FYM | N31: Fayetteville | O31: Lincoln | P31: Middle
B32: LCCA parameters | L32: Franklin County Airport | M32: UOS | N32: Sewanee | O32: Franklin | P32: Middle
C33: Analysis Period, years: | D33: 30 | F33: TDOT policy 30 years; FAA leaves the period to the engineer. | L33: Gatlinburg-Pigeon Forge Airport | M33: GKT | N33: Sevierville | O33: Sevier | P33: East
C34: Discount Rate, percent: | D34: 3 | F34: TDOT 3%. FAA uses the OMB A-94 real rate, 2.0% in 2026. | L34: General Dewitt Spain Airport | M34: M01 | N34: Memphis | O34: Shelby | P34: West
C35: Salvage Value, $: | F35: Remaining service life at the end of the analysis period; computed on Maintenance Policies. | L35: Gibson County Airport | M35: TGC | N35: Trenton | O35: Gibson | P35: West
C36: Mobilization, percent: | D36: 10 | F36: Percent of pay items; workbook default 10. | L36: Greeneville-Green County Municipal Airport | M36: GCY | N36: Greeneville | O36: Greene | P36: East
C37: Engineering, percent: | D37: 5 | F37: Percent of pay items; now applied to initial construction too. | L37: Hassell-Carroll Field | M37: M29 | N37: Clifton | O37: Wayne | P37: Middle
C38: Account Indirect Cost (Yes/No) | D38: Yes | F38: Yes counts lost revenue during closures (17 airports have data). | L38: Hawkins County Airport | M38: RVN | N38: Rogersville | O38: Hawkins | P38: East
C39: Airport Daily Revenue | D39: =IF(D38<>"Yes","",IF(COUNTIF(RevenueData!$A:$A,$D$10)=0,"Missing Airport Revenue",SUMIF(RevenueData!$A:$A,$D$10,RevenueData!$B:$B)+SUMIF(RevenueData!$A:$A,$D$10,RevenueData!$C:$C)+SUMIF(RevenueData!$A:$A,$D$10,RevenueData!$D:$D)+SUMIF(RevenueData!$A:$A,$D$10,RevenueData!$E:$E)+SUMIF(RevenueData!$A:$A,$D$10,RevenueData!$F:$F)+SUMIF(RevenueData!$A:$A,$D$10,RevenueData!$G:$G)+SUMIF(RevenueData!$A:$A,$D$10,RevenueData!$H:$H))) -> 5441.17 | L39: Henry County Airport | M39: PHT | N39: Paris | O39: Henry | P39: West
L40: Houston County Airport | M40: M93 | N40: McKinnon | O40: Houston | P40: Middle
B41: Alternative Setup | L41: Humboldt Municipal Airport | M41: M53 | N41: Humboldt | O41: Gibson | P41: West
L42: Humphreys County Airport | M42: 0M5 | N42: Waverly | O42: Humphreys | P42: Middle
B43: Where to go next | L43: Jackson County Airport | M43: 1A7 | N43: Gainesboro | O43: Jackson | P43: Middle
B44: LCCA Summary: | D44: =HYPERLINK("#Summary!G1","View Summary ►") -> View Summary ► | L44: James Tucker-Perry County Airport | M44: M15 | N44: Linden | O44: Perry | P44: Middle
B45: Typical input values: | D45: =HYPERLINK("#'Typical Values'!A1","Typical Values ►") -> Typical Values ► | L45: Jamestown Municipal Airport | M45: 2A1 | N45: Jamestown | O45: Fentress | P45: Middle
B46: How it is calculated: | D46: =HYPERLINK("#Method!A1","Method ►") -> Method ► | L46: John A. Baker Field | M46: 0M3 | N46: Hohenwald | O46: Lewis | P46: Middle
B47: Unit costs: | D47: =HYPERLINK("#Pay_Items!A1","Pay_Items ►") -> Pay_Items ► | L47: John C. Tune Airport | M47: JWN | N47: Nashville | O47: Davidson | P47: Middle
B48: Maintenance policies: | D48: =HYPERLINK("#'Maintenance Policies'!C2","Maintenance Policies ►") -> Maintenance Policies ► | L48: Johnson City Airport | M48: 0A4 | N48: Johnson City | O48: Washington | P48: East
L49: Johnson County Airport | M49: 6A4 | N49: Mountain City | O49: Johnson | P49: East
L50: Knoxville Downtown Island Airport | M50: DKX | N50: Knoxville | O50: Knox | P50: East
L51: Lafayette Municipal Airport | M51: 3M7 | N51: Lafayette | O51: Macon | P51: Middle
L52: Lawrenceburg-Lawrence County Airport | M52: 2M2 | N52: Lawrenceburg | O52: Lawrence | P52: Middle
L53: Lebanon Municipal Airport | M53: M54 | N53: Lebanon | O53: Wilson | P53: Middle
L54: Livingston Municipal Airport | M54: 8A3 | N54: Livingston | O54: Overton | P54: Middle
L55: Lovell Field | M55: CHA | N55: Chattanooga | O55: Hamilton | P55: East
L56: Marion County Airport-Brown Field | M56: APT | N56: Jasper | O56: Marion | P56: East
L57: Mark Anton Airport | M57: 2A0 | N57: Dayton | O57: Rhea | P57: East
L58: Martin Campbell Field | M58: 1A3 | N58: Copperhill | O58: Polk | P58: East
L59: Maury County Airport | M59: MRC | N59: Columbia | O59: Maury | P59: Middle
L60: McGhee Tyson Airport | M60: TYS | N60: Knoxville | O60: Blount | P60: East
... L88: Wolf River | M88: 54M | N88: Rossville | O88: Fayette | P88: West

Sheet Pay_Items
A1: =HYPERLINK("#'General Information'!D9","◄ General Information") -> ◄ General Information | B1: =HYPERLINK("#Summary!G1","Summary") -> Summary | C1: Pay Items | D1: =IF(COUNTBLANK($F$4:$F$59)=0,"Every pay item carries a unit cost.",COUNTBLANK($F$4:$F$59)&" of "&COUNTA($D$4:$D$59)&" pay items carry no unit cost, flagged amber below.") -> 28 of 56 pay items carry no unit cost, flagged amber below. | F1: STEP 3 of 5 | G1: Average Pay Item Unit Cost
A2: Division | B2: Division Type | C2: Pay Item No. | D2: Pay Item Description | E2: Units | F2: Unit Cost | G2: Middle | H2: West | I2: East | J2: Notes
B3: Default | E3: N/A | F3: N/A
A4: Part 3 – Sitework | B4: Sitework | C4: P-101-5.1a | D4: Pavement Removal, Asphalt | E4: S.Y. | F4: 4.2 | J4: Thickness adjustment or multiple
B5: Sitework | C5: P-101-5.1b | D5: Pavement Removal, Concrete | E5: S.Y. | J5: Thickness adjustment or multiple
B6: Sitework | C6: P-101-5.2a | D6: Crack Repair (Type I), Asphalt | E6: L.F. | F6: 4
B7: Sitework | C7: P-101-5.2b | D7: Crack Repair (Type II), Asphalt | E7: L.F. | F7: 6.5
B8: Sitework | C8: P-101-5.2c | D8: Crack Seal, Concrete | E8: L.F. | F8: 8
B9: Sitework | C9: P-101-5.2d | D9: Crack Repair, Concrete | E9: L.F. | F9: 8.5
B10: Sitework | C10: P-101-5.3 | D10: Markings Removal | E10: S.F. | F10: =7/9 -> 0.77777778
B11: Sitework | C11: P-101-5.4a | D11: Spall Repair, Asphalt | E11: S.F. | F11: 8.5 | J11: Thickness adjustment or multiple
B12: Sitework | C12: P-101-5.4b | D12: Full-Depth Repair, Asphalt | E12: S.F. | J12: Assumed Section: 4-inch HMA; 4-inch P-209
B13: Sitework | C13: P-101-5.5a | D13: Spall Repair, Concrete | E13: S.F. | F13: 60 | J13: Thickness adjustment or multiple
B14: Sitework | C14: P-101-5.5b | D14: Full-Depth Repair, Concrete | E14: S.Y. | F14: 120 | J14: Thickness adjustment or multiple
B15: Sitework | C15: P-101-5.5c | D15: Slab Replacement, Concrete | E15: S.Y. | F15: 100
B16: Sitework | C16: P-101-5.6 | D16: Cold Milling | E16: S.Y. | F16: =10/2 -> 5 | J16: Thickness adjustment or multiple
B17: Sitework | C17: P-152-4.1 | D17: Unclassified Excavation | E17: C.Y. | F17: 12
B18: Sitework | C18: P-152-4.2 | D18: Embankment In-Place | E18: C.Y.
B19: Sitework | C19: P-154-5.1 | D19: Subbase Course | E19: C.Y. | F19: 55
B20: Sitework | C20: P-154-5.2 | D20: Separation Geotextile (P-154) | E20: S.Y.
B21: Sitework | C21: P-155-8.1 | D21: Lime Treated subgrade | E21: S.Y. | F21: 10 | J21: Thickness adjustment or multiple
B22: Sitework | C22: P-156-8.1 | D22: Cement-Treated Subgrade | E22: S.Y. | J22: Thickness adjustment or multiple
B23: Sitework | C23: P-157-8.1a | D23: Cement Kiln Dust-Treated Subgrade | E23: S.Y. | J23: Thickness adjustment or multiple
B24: Sitework | C24: P-157-8.1b | D24: Lime Kiln Dust-Treated Subgrade | E24: S.Y. | J24: Thickness adjustment or multiple
B25: Sitework | C25: P-158-8.1 | D25: Fly Ash-Treated Subgrade | E25: S.Y. | J25: Thickness adjustment or multiple
A26: Part 4 – Base Courses | B26: Base Course | C26: P-207-5.1 | D26: In-Place Full Depth Reclamation (FDR) Recycled Asphalt Aggregate Base Course | E26: S.Y. | J26: Thickness adjustment or multiple
B27: Base Course | C27: P-208-5.1 | D27: Aggregate Base Course | E27: C.Y.
B28: Base Course | C28: P-208-5.2 | D28: Separation Geotextile (P-208) | E28: S.Y.
B29: Base Course | C29: P-209-5.1 | D29: Crushed Aggregate Base Course | E29: C.Y. | F29: 65
B30: Base Course | C30: P-209-5.2 | D30: Separation Geotextile (P-209) | E30: S.Y.
B31: Base Course | C31: P-219-5.1 | D31: Recycled Concrete Aggregate Base Course | E31: C.Y.
B32: Base Course | C32: P-219-5.2 | D32: Separation Geotextile (P-219) | E32: S.Y.
B33: Base Course | C33: P-220-6.1 | D33: Cement-Treated Soil Base Course | E33: S.Y. | J33: Thickness adjustment or multiple
A34: Part 5 – Stabilized Base Courses | B34: Stabilized Base Course | C34: P-304-8.1 | D34: Cement-Treated Base Course | E34: C.Y. | J34: If S.Y., then thickness adjustment
B35: Stabilized Base Course | C35: P-306-8.1 | D35: Lean Concrete Base Course | E35: C.Y. | J35: If S.Y., then thickness adjustment
B36: Stabilized Base Course | C36: P-307-7.1 | D36: Cement-Treated Permeable Base Course (CTPB) | E36: C.Y. | J36: If S.Y., then thickness adjustment
A37: Part 6 – Flexible Pavements | B37: Flexible Pavement | C37: P-401-8.1a | D37: Asphalt Surface Course | E37: TON | F37: 130
B38: Flexible Pavement | C38: P-401-8.1b | D38: Asphalt Base Course | E38: TON | F38: 120
B39: Flexible Pavement | C39: P-401-8.1c | D39: Asphalt Leveling Course | E39: TON | F39: 110
B40: Flexible Pavement | C40: P-403-8.1a | D40: Asphalt Mixture Surface Course | E40: TON
B41: Flexible Pavement | C41: P-403-8.1b | D41: Asphalt Mixture Base Course | E41: TON
B42: Flexible Pavement | C42: P-403-8.1c | D42: Asphalt Mixture Leveling Course | E42: TON
B43: Flexible Pavement | C43: P-407-X.1 | D43: Asphalt-Treated Permeable Base Course (ATPB) | E43: TON
A44: Part 7 – Rigid Pavement | B44: Cement Concrete | C44: P-501-8.1a | D44: Concrete Pavement, 5-inch | E44: S.Y. | F44: 79 | J44: Thickness adjustment or multiple
B45: Cement Concrete | C45: P-501-8.1b | D45: Concrete Pavement, 6-inch | E45: S.Y. | F45: 82 | J45: Thickness adjustment or multiple
B46: Cement Concrete | C46: P-501-8.1c | D46: Concrete Pavement, 9-inch | E46: S.Y. | F46: 85 | J46: Thickness adjustment or multiple
B47: Cement Concrete | C47: P-501-8.1d | D47: Concrete Pavement, 11-inch | E47: S.Y. | F47: 91 | J47: Thickness adjustment or multiple
A48: Part 8 – Surface Treatments | B48: Surface Treatment | C48: P-608-8.1 | D48: Emulsified Asphalt Surface Treatment | E48: S.Y. | F48: 4
B49: Surface Treatment | C49: P-623-8.1 | D49: Emulsified Asphalt Spray Seal Coat | E49: S.Y. | F49: 5
B50: Surface Treatment | C50: P-626-6.1 | D50: Emulsified Asphalt Slurry Seal Surface Treatment | E50: S.Y. | F50: 7
B51: Surface Treatment | C51: P-629-8.1 | D51: Thermoplastic Coal Tar Emulsion Surface Treatment | E51: S.Y.
B52: Surface Treatment | C52: P-630-7.1a | D52: Refined Coal Tar Emulsion Without Additives, Slurry Seal Surface Treatment | E52: S.Y.
B53: Surface Treatment | C53: P-631-7.1b | D53: Refined Coal Tar Emulsion With Additives, Slurry Seal Surface Treatment | E53: S.Y.
A54: Part 9 – Miscellaneous | B54: Tack Coat | C54: P-603-5.1 | D54: Emulsified Asphalt Tack Coat | E54: GAL | F54: 4.5 | J54: Assume 0.1 gal/SY for mill and overlay
B55: Joint Sealant | C55: P-605-5.1a | D55: Joint Clean and Reseal, Concrete | E55: L.F. | F55: 7 | J55: Assume 12.5x12.5 slabs for these GA pavements
B56: Marking | C56: P-620-5.1a | D56: Markings (prep, markings, reflective media) | E56: S.F. | F56: =6/9 -> 0.66666667
B57: Marking | C57: P-620-5.1b | D57: Markings (prep, markings, non-reflective media) | E57: S.F.
B58: Grooving | C58: P-621-5.1A | D58: Grooving, Asphalt | E58: S.Y.
B59: Grooving | C59: P-621-5.1B | D59: Grooving, Concrete | E59: S.Y.
A61: Every alternative worksheet prices its quantities from the Unit Cost column above, by looking up the pay item description. Change a cost here and every alternative reprices when the workbook recalculates.
A62: The Middle, West and East columns under "Average Pay Item Unit Cost" are the division averages. Each alternative worksheet picks one of them in C11, and any cell left blank there is priced from Unit Cost instead. They ship empty, so until they are filled every division prices the same.
A63: An item with no unit cost prices at $0. The Unit Cost column flags those in amber: fill one in before entering a quantity against it.
A64: Typical ranges and the published sources behind these costs are on the Typical Values sheet.

Sheet Database
A1: Alternative List
A3: Name | B3: Type | C3: Description | D3: Alt Worksheet Name
A4: Alternative 1 | B4: HMA-New | C4: New HMA | D4: Alt 1 (New HMA)
A5: Alternative 2 | B5: PCC-New | C5: New PCC | D5: Alt 2 (New PCC)
A6: Alternative 3 | B6: PCC-New | C6: New PCC | D6: Alt 3 (New PCC)

Sheet Maintenance Policies
B1: =HYPERLINK("#'General Information'!D9","◄ General Information") -> ◄ General Information | C1: =HYPERLINK("#Summary!G1","Summary") -> Summary
B2: Maintenance & Rehabilitation Policies
B3: This sheet is live. Every alternative reads its Rate and Year Applied straight from these four tables, so a year moved here moves that event on every alternative of that type and every number on the Summary. The grey cells are the ones to edit.
B4: Rate is the share of the quantity the activity covers: 1 is the whole mainline area, the whole markings area or the whole joint length. Year Applied counts years after construction, and an event past the analysis period drops to zero.
B5: Table 1 drives a New HMA alternative, Table 2 a New PCC alternative, Table 3 an HMA overlay and Table 4 a PCC rehabilitation.
B6: Rehabilitation | C6: Salvage credit | D6: No salvage | E6: Closure days come from Typical Values, not this sheet.
B8: Table 1. New HMA maintenance policies.
B9: Asphalt Maintenance | C9: Maintenance Item | D9: Rate | E9: Year Applied | F9: Asset life (yrs)
B10: Maintenance 1 | C10: Surface treatment, SYD | D10: 1 | E10: 4
C11: Paint markings, SFT | D11: 1
B12: Maintenance 2 | C12: Surface treatment, SYD | D12: 1 | E12: 8
C13: Paint markings, SFT | D13: 1
B14: Maintenance 3 | C14: Patching: 0.75% of area | D14: 0.0075 | E14: 12
C15: Crack sealing: 3.25% of area as linear feet | D15: 0.0325
C16: Surface treatment: 100% of area | D16: 1
C17: Paint markings: 100% of markings | D17: 1
B18: Maintenance 4 | C18: Patching: 1.00% of area | D18: 0.01 | E18: 16
C19: Crack sealing: 3.50% of area as linear feet | D19: 0.035
C20: Surface treatment: 100% of area | D20: 1
C21: Paint markings: 100% of markings | D21: 1
B22: Rehabilitation 1 | C22: Mill and overlay: 4-inch cold mill, tack coat, and asphalt overlay | D22: 1 | E22: 20
C23: Pre-overlay crack repair: 1.5% of area as linear feet | D23: 0.015
C24: Pre-overlay patching: 0.5% of area | D24: 0.005
C25: Paint markings: 100% of markings | D25: 1
B26: Maintenance 5 | C26: Surface treatment: 100% of area | D26: 1 | E26: 24
C27: Paint markings: 100% of markings | D27: 1
B28: Maintenance 6 | C28: Patching: 1.25% of area | D28: 0.0125 | E28: 28
C29: Crack sealing: 4.0% of area as linear feet | D29: 0.04
C30: Surface treatment: 100% of area | D30: 1
C31: Paint markings: 100% of markings | D31: 1
B32: Salvage | C32: ="Salvage value: "&TEXT(D32*F32,"0.#")&" of 16 years left on the mill and overlay"&" placed in year "&E22&" ("&TEXT(D32,"0.0%")&" of its cost) at the "&'General Information'!$D$33&"-year analysis period" -> Salvage value: 6 of 16 years left on the mill and overlay placed in year 20 (37.5% of its cost) at the 30-year analysis period | D32: =IF(E22>'General Information'!$D$33,0,MAX(0,MIN(1,(E22+F32-'General Information'!$D$33)/F32))) -> 0.375 | E32: ='General Information'!$D$33 -> 30 | F32: 16
B35: Table 2. New PCC maintenance policies.
B36: Concrete Maintenance | C36: Maintenance Item | D36: Rate | E36: Year Applied | F36: Asset life (yrs)
B37: Maintenance 1 | C37: Joint resealing: 100% of joints | D37: 1 | E37: 19
C38: Crack sealing: 0.25% of area as linear feet | D38: 0.0025
C39: Partial-depth patching: 0.13% of area | D39: 0.0013
C40: Full-depth patching: 0.30% of area | D40: 0.003
B41: Rehabilitation 1 | C41: Slab replacements: 2% of area | D41: 0.02 | E41: 27
C42: Full-depth patching: 0.30% of area | D42: 0.003
C43: Partial-depth patching: 0.13% of area | D43: 0.0013
C44: Crack sealing: 0.30% of area as linear feet | D44: 0.003
C45: Joint sealing: 100% of joints | D45: 1
B46: Salvage | C46: ="Salvage value: "&TEXT(D46*F46,"0.#")&" of 40 years left on the initial construction"&" ("&TEXT(D46,"0.0%")&" of its cost) at the "&'General Information'!$D$33&"-year analysis period" -> Salvage value: 10 of 40 years left on the initial construction (25.0% of its cost) at the 30-year analysis period | D46: =MAX(0,MIN(1,(0+F46-'General Information'!$D$33)/F46)) -> 0.25 | E46: ='General Information'!$D$33 -> 30 | F46: 40
B49: Table 3. First HMA Overlay maintenance policies.
B50: Asphalt Maintenance | C50: Maintenance Item | D50: Rate | E50: Year Applied | F50: Asset life (yrs)
B51: Maintenance 1 | C51: Surface treatment: 100% of area | D51: 1 | E51: 4
C52: Paint markings: 100% of markings | D52: 1
B53: Maintenance 2 | C53: Patching: 1.25% of area | D53: 0.0125 | E53: 8
C54: Crack sealing: 4.0% of area as linear feet | D54: 0.04
C55: Surface treatment: 100% of area | D55: 1
C56: Paint markings: 100% of markings | D56: 1
B57: Maintenance 3 | C57: Surface treatment, SYD | D57: 1 | E57: 12
C58: Paint markings, SFT | D58: 1
B59: Rehabilitation 2 | C59: Mill and overlay: 4-inch cold mill, tack coat, and asphalt overlay | D59: 1 | E59: 16
C60: Pre-overlay crack repair: 2% of area as linear feet | D60: 0.015
C61: Pre-overlay patching: 1% of area | D61: 0.005
C62: Paint markings: 100% of markings | D62: 1
B63: Maintenance 4 | C63: Surface treatment: 100% of area | D63: 1 | E63: 20
C64: Paint markings: 100% of markings | D64: 1
B65: Maintenance 5 | C65: Patching: 1.25% of area | D65: 0.0125 | E65: 24
C66: Crack sealing: 4.0% of area as linear feet | D66: 0.04
C67: Surface treatment: 100% of area | D67: 1
C68: Paint markings: 100% of markings | D68: 1
B69: Maintenance 6 | C69: Surface treatment: 100% of area | D69: 1 | E69: 28
C70: Paint markings: 100% of markings | D70: 1
B71: Salvage | C71: Salvage value: Need for reconstruction (zero salvage) | D71: 0 | E71: ='General Information'!$D$33 -> 30
B74: Table 4. PCC rehabilitation maintenance policies.
B75: Concrete Maintenance | C75: Maintenance Item | D75: Rate | E75: Year Applied | F75: Asset life (yrs)
B76: Maintenance 1 | C76: Joint resealing: 100% of joints | D76: 1 | E76: 15
C77: Crack sealing: 0.35% of area as linear feet | D77: 0.0035
C78: Partial-depth patching: 0.2% of area | D78: 0.002
C79: Full-depth patching: 0.30% of area | D79: 0.003
B80: Rehabilitation 1 | C80: Slab replacements: 5% of area | D80: 0.05 | E80: 25
C81: Full-depth patching: 0.30% of area | D81: 0.003
C82: Partial-depth patching: 0.15% of area | D82: 0.0015
C83: Crack sealing: 0.30% of area as linear feet | D83: 0.003
C84: Joint sealing: 100% of joints | D84: 1
B85: Salvage | C85: Salvage value: Need for reconstruction (zero salvage) | D85: 0 | E85: ='General Information'!$D$33 -> 30

Sheet TMP(NewHMA)_IndirectCost
A1: =HYPERLINK("#'General Information'!D9","◄ General Information") -> ◄ General Information | C1: =HYPERLINK("#Summary!G1","Summary") -> Summary | D1: =$A$33 -> HMA Reconstruction - Alternative 1 | I1: Hidden
A2: Initial Construction Costs: | E2: Average Daily Revenue: | F2: =IF('General Information'!$D$38="Yes",SUMIF(RevenueData!$A:$A,'General Information'!$D$10,RevenueData!$B:$B)+SUMIF(RevenueData!$A:$A,'General Information'!$D$10,RevenueData!$C:$C)+SUMIF(RevenueData!$A:$A,'General Information'!$D$10,RevenueData!$D:$D)+SUMIF(RevenueData!$A:$A,'General Information'!$D$10,RevenueData!$E:$E)+SUMIF(RevenueData!$A:$A,'General Information'!$D$10,RevenueData!$F:$F)+SUMIF(RevenueData!$A:$A,'General Information'!$D$10,RevenueData!$G:$G)+SUMIF(RevenueData!$A:$A,'General Information'!$D$10,RevenueData!$H:$H),0) -> 5441.17 | G2: =IF(AND('General Information'!$D$38="Yes",F2=0),"No revenue data for this airport - lost revenue set to $0. Contact Aeronautics.","") | J2: Maintenance 1 | R2: Maintenance 2 | Z2: Maintenance 3 | AH2: Maintenance 4 | AP2: Rehabilitation 1 | AX2: Maintenance 5 | BF2: Maintenance 6
A3: STEP 4 of 5 · The quantities for this alternative. Grey cells are yours: C4 to C8 project data (filled from General Information), F4 to F10 closure days, C13 to C22 pay items and E13 to E22 quantities. Everything else calculates. Unit costs come from Pay_Items, and C11 picks which division they are priced from.
A4: Pavement Type: | C4: New HMA | E4: Maintenance 1 Duration (Days) | F4: =ROUNDUP((C5/15000),0)+ROUNDUP((C8/20000),0)+ROUNDUP((C8/50000),0) -> 6
A5: Mainline Pavement Area: | C5: ='General Information'!D26 -> 45883 | D5: S.Y. | E5: Maintenance 2 Duration (Days) | F5: =ROUNDUP((C5/15000),0)+ROUNDUP((C8/20000),0)+ROUNDUP((C8/50000),0) -> 6
A6: Initial Construction Year: | C6: ='General Information'!D25 -> 2028 | E6: Maintenance 3 Duration (Days) | F6: =ROUNDUP((C5/15000),0)+ROUNDUP((C8/20000),0)+ROUNDUP((C8/50000),0)+ROUNDUP((C5*'Maintenance Policies'!D15/10000),0)+ROUNDUP((C5*'Maintenance Policies'!D14/5000),0) -> 8 | AP6: Mill and overlay: | AQ6: 2 | AR6: inches
A7: Asphalt Surface Treatment Type: | C7: Emulsified Asphalt Surface Treatment | D7: Select alternative treatment, if planned. | E7: Maintenance 4 Duration (Days) | F7: =ROUNDUP((C5/15000),0)+ROUNDUP((C8/20000),0)+ROUNDUP((C8/50000),0)+ROUNDUP((C5*'Maintenance Policies'!D18/10000),0)+ROUNDUP((C5*'Maintenance Policies'!D19/5000),0) -> 8 | AP7: Asphalt: | AQ7: 120 | AR7: lbs/SY-in
A8: Markings Area: | C8: ='General Information'!D28 -> 12000 | D8: S.F. | E8: Rehabilitation 1 Duration (Days) | F8: =ROUNDUP((C5/3800),0)+ROUNDUP((C8/50000),0) -> 14
E9: Maintenance 5 Duration (Days) | F9: =ROUNDUP((C5/15000),0)+ROUNDUP((C8/20000),0)+ROUNDUP((C8/50000),0) -> 6 | AP9: Tack Coat Application | AQ9: 0.1 | AR9: gal/S.Y.
E10: Maintenance 6 Duration (Days) | F10: =ROUNDUP((C5/15000),0)+ROUNDUP((C8/20000),0)+ROUNDUP((C8/50000),0)+ROUNDUP((C5*'Maintenance Policies'!D28/10000),0)+ROUNDUP((C5*'Maintenance Policies'!D29/5000),0) -> 8 | I10: Price column: 1 Regular, 2 Middle, 3 West, 4 East
B11: Price from: | C11: Regular | D11: =IF(OR($C$11="Regular",$C$11=""),"Regular is the statewide Unit Cost column on Pay_Items.","Prices from the "&$C$11&" column on Pay_Items: "&SUM($I$13:$I$22)&" of "&COUNT($I$13:$I$22)&" pay items used here have a "&$C$11&" cost, the rest fall back to Unit Cost.") -> Regular is the statewide Unit Cost column on Pay_Items. | I11: =IFERROR(MATCH($C$11,PriceSources,0),1) -> 1
A12: Item No. | B12: Pay Item | C12: Description | D12: Unit | E12: Qty | F12: Unit Cost | G12: Item Cost | J12: Item No. | K12: Pay Item | L12: Description | M12: Unit | N12: Qty | O12: Unit Cost | P12: Item Cost | R12: Item No. | S12: Pay Item | T12: Description | U12: Unit | V12: Qty | W12: Unit Cost | X12: Item Cost | Z12: Item No. | AA12: Pay Item | AB12: Description | AC12: Unit | AD12: Qty | AE12: Unit Cost | AF12: Item Cost | AH12: Item No. | AI12: Pay Item | AJ12: Description | AK12: Unit | AL12: Qty | AM12: Unit Cost | AN12: Item Cost | AP12: Item No. | AQ12: Pay Item | AR12: Description | AS12: Unit | AT12: Qty | AU12: Unit Cost | AV12: Item Cost | AX12: Item No. | AY12: Pay Item | AZ12: Description | BA12: Unit | BB12: Qty | BC12: Unit Cost | BD12: Item Cost | BF12: Item No. | BG12: Pay Item | BH12: Description | BI12: Unit | BJ12: Qty | BK12: Unit Cost | BL12: Item Cost
A13: 1 | B13: =IF(C13="","",VLOOKUP(C13,CHOOSE({1,2},Table2[Pay Item Description],Table2[Pay Item No.]),2,0)) | D13: =IF(C13="","N/A",VLOOKUP(C13,CHOOSE({1,2},Table2[Pay Item Description],Table2[Units]),2,0)) -> N/A | F13: =IF(C13="","N/A",IF(INDEX(UnitCostGrid,MATCH(C13,PayItemKeys,0),$I$11)="",INDEX(UnitCostGrid,MATCH(C13,PayItemKeys,0),1),INDEX(UnitCostGrid,MATCH(C13,PayItemKeys,0),$I$11))) -> N/A | G13: =IF(C13="",0,F13*E13) -> 0 | I13: =IF(C13="","",IF(INDEX(UnitCostGrid,MATCH(C13,PayItemKeys,0),$I$11)="",0,1)) | J13: 1 | K13: =IF(L13="",0,VLOOKUP(L13,CHOOSE({1,2},Table2[Pay Item Description],Table2[Pay Item No.]),2,0)) -> P-608-8.1 | L13: =C7 -> Emulsified Asphalt Surface Treatment | M13: =VLOOKUP(L13,CHOOSE({1,2},Table2[Pay Item Description],Table2[Units]),2,0) -> S.Y. | N13: ='Maintenance Policies'!D10*$C$5 -> 45883 | O13: =IF(L13="","N/A",IF(INDEX(UnitCostGrid,MATCH(L13,PayItemKeys,0),$I$11)="",INDEX(UnitCostGrid,MATCH(L13,PayItemKeys,0),1),INDEX(UnitCostGrid,MATCH(L13,PayItemKeys,0),$I$11))) -> 4 | P13: =O13*N13 -> 183532 | R13: 1 | S13: =IF(T13="",0,VLOOKUP(T13,CHOOSE({1,2},Table2[Pay Item Description],Table2[Pay Item No.]),2,0)) -> P-608-8.1 | T13: =C7 -> Emulsified Asphalt Surface Treatment | U13: =VLOOKUP(T13,CHOOSE({1,2},Table2[Pay Item Description],Table2[Units]),2,0) -> S.Y. | V13: ='Maintenance Policies'!D12*$C$5 -> 45883 | W13: =IF(T13="","N/A",IF(INDEX(UnitCostGrid,MATCH(T13,PayItemKeys,0),$I$11)="",INDEX(UnitCostGrid,MATCH(T13,PayItemKeys,0),1),INDEX(UnitCostGrid,MATCH(T13,PayItemKeys,0),$I$11))) -> 4 | X13: =W13*V13 -> 183532 | Z13: 1 | AA13: =IF(AB13="",0,VLOOKUP(AB13,CHOOSE({1,2},Table2[Pay Item Description],Table2[Pay Item No.]),2,0)) -> P-101-5.4a | AB13: =Pay_Items!D11 -> Spall Repair, Asphalt | AC13: =IF(AB13="","N/A",VLOOKUP(AB13,CHOOSE({1,2},Table2[Pay Item Description],Table2[Units]),2,0)) -> S.F. | AD13: ='Maintenance Policies'!D14*($C$5*9) -> 3097.1025 | AE13: =IF(AB13="","N/A",IF(INDEX(UnitCostGrid,MATCH(AB13,PayItemKeys,0),$I$11)="",INDEX(UnitCostGrid,MATCH(AB13,PayItemKeys,0),1),INDEX(UnitCostGrid,MATCH(AB13,PayItemKeys,0),$I$11))) -> 8.5 | AF13: =AE13*AD13 -> 26325.371 | AH13: 1 | AI13: =IF(AJ13="",0,VLOOKUP(AJ13,CHOOSE({1,2},Table2[Pay Item Description],Table2[Pay Item No.]),2,0)) -> P-101-5.4a | AJ13: =Pay_Items!D11 -> Spall Repair, Asphalt | AK13: =IF(AJ13="","N/A",VLOOKUP(AJ13,CHOOSE({1,2},Table2[Pay Item Description],Table2[Units]),2,0)) -> S.F. | AL13: ='Maintenance Policies'!D18*($C$5*9) -> 4129.47 | AM13: =IF(AJ13="","N/A",IF(INDEX(UnitCostGrid,MATCH(AJ13,PayItemKeys,0),$I$11)="",INDEX(UnitCostGrid,MATCH(AJ13,PayItemKeys,0),1),INDEX(UnitCostGrid,MATCH(AJ13,PayItemKeys,0),$I$11))) -> 8.5 | AN13: =AM13*AL13 -> 35100.495 | AP13: 1 | AQ13: =IF(AR13="",0,VLOOKUP(AR13,CHOOSE({1,2},Table2[Pay Item Description],Table2[Pay Item No.]),2,0)) -> P-101-5.6 | AR13: =Pay_Items!D16 -> Cold Milling | AS13: =IF(AR13="","N/A",VLOOKUP(AR13,CHOOSE({1,2},Table2[Pay Item Description],Table2[Units]),2,0)) -> S.Y. | AT13: ='Maintenance Policies'!D22*$C$5 -> 45883 | AU13: =IF(AR13="","N/A",IF(INDEX(UnitCostGrid,MATCH(AR13,PayItemKeys,0),$I$11)="",INDEX(UnitCostGrid,MATCH(AR13,PayItemKeys,0),1),INDEX(UnitCostGrid,MATCH(AR13,PayItemKeys,0),$I$11))) -> 5 | AV13: =AU13*AT13 -> 229415 | AX13: 1 | AY13: =IF(AZ13="",0,VLOOKUP(AZ13,CHOOSE({1,2},Table2[Pay Item Description],Table2[Pay Item No.]),2,0)) -> P-608-8.1 | AZ13: =C7 -> Emulsified Asphalt Surface Treatment | BA13: =IF(AZ13="","N/A",VLOOKUP(AZ13,CHOOSE({1,2},Table2[Pay Item Description],Table2[Units]),2,0)) -> S.Y. | BB13: ='Maintenance Policies'!D26*$C$5 -> 45883 | BC13: =IF(AZ13="","N/A",IF(INDEX(UnitCostGrid,MATCH(AZ13,PayItemKeys,0),$I$11)="",INDEX(UnitCostGrid,MATCH(AZ13,PayItemKeys,0),1),INDEX(UnitCostGrid,MATCH(AZ13,PayItemKeys,0),$I$11))) -> 4 | BD13: =BC13*BB13 -> 183532 | BF13: 1 | BG13: =IF(BH13="",0,VLOOKUP(BH13,CHOOSE({1,2},Table2[Pay Item Description],Table2[Pay Item No.]),2,0)) -> P-101-5.4a | BH13: =Pay_Items!D11 -> Spall Repair, Asphalt | BI13: =IF(BH13="","N/A",VLOOKUP(BH13,CHOOSE({1,2},Table2[Pay Item Description],Table2[Units]),2,0)) -> S.F. | BJ13: ='Maintenance Policies'!D28*($C$5*9) -> 5161.8375 | BK13: =IF(BH13="","N/A",IF(INDEX(UnitCostGrid,MATCH(BH13,PayItemKeys,0),$I$11)="",INDEX(UnitCostGrid,MATCH(BH13,PayItemKeys,0),1),INDEX(UnitCostGrid,MATCH(BH13,PayItemKeys,0),$I$11))) -> 8.5 | BL13: =BK13*BJ13 -> 43875.619
A14: 2 | B14: =IF(C14="","",VLOOKUP(C14,CHOOSE({1,2},Table2[Pay Item Description],Table2[Pay Item No.]),2,0)) | D14: =IF(C14="","N/A",VLOOKUP(C14,CHOOSE({1,2},Table2[Pay Item Description],Table2[Units]),2,0)) -> N/A | F14: =IF(C14="","N/A",IF(INDEX(UnitCostGrid,MATCH(C14,PayItemKeys,0),$I$11)="",INDEX(UnitCostGrid,MATCH(C14,PayItemKeys,0),1),INDEX(UnitCostGrid,MATCH(C14,PayItemKeys,0),$I$11))) -> N/A | G14: =IF(C14="",0,F14*E14) -> 0 | I14: =IF(C14="","",IF(INDEX(UnitCostGrid,MATCH(C14,PayItemKeys,0),$I$11)="",0,1)) | J14: 2 | K14: =IF(L14="",0,VLOOKUP(L14,CHOOSE({1,2},Table2[Pay Item Description],Table2[Pay Item No.]),2,0)) -> P-101-5.3 | L14: =Pay_Items!D10 -> Markings Removal | M14: =IF(L14="","N/A",VLOOKUP(L14,CHOOSE({1,2},Table2[Pay Item Description],Table2[Units]),2,0)) -> S.F. | N14: ='Maintenance Policies'!D10*$C$8 -> 12000 | O14: =IF(L14="","N/A",IF(INDEX(UnitCostGrid,MATCH(L14,PayItemKeys,0),$I$11)="",INDEX(UnitCostGrid,MATCH(L14,PayItemKeys,0),1),INDEX(UnitCostGrid,MATCH(L14,PayItemKeys,0),$I$11))) -> 0.77777778 | P14: =O14*N14 -> 9333.3333 | R14: 2 | S14: =IF(T14="",0,VLOOKUP(T14,CHOOSE({1,2},Table2[Pay Item Description],Table2[Pay Item No.]),2,0)) -> P-101-5.3 | T14: =Pay_Items!D10 -> Markings Removal | U14: =IF(T14="","N/A",VLOOKUP(T14,CHOOSE({1,2},Table2[Pay Item Description],Table2[Units]),2,0)) -> S.F. | V14: ='Maintenance Policies'!D12*$C$8 -> 12000 | W14: =IF(T14="","N/A",IF(INDEX(UnitCostGrid,MATCH(T14,PayItemKeys,0),$I$11)="",INDEX(UnitCostGrid,MATCH(T14,PayItemKeys,0),1),INDEX(UnitCostGrid,MATCH(T14,PayItemKeys,0),$I$11))) -> 0.77777778 | X14: =W14*V14 -> 9333.3333 | Z14: 2 | AA14: =IF(AB14="",0,VLOOKUP(AB14,CHOOSE({1,2},Table2[Pay Item Description],Table2[Pay Item No.]),2,0)) -> P-101-5.2a | AB14: =Pay_Items!D6 -> Crack Repair (Type I), Asphalt | AC14: =IF(AB14="","N/A",VLOOKUP(AB14,CHOOSE({1,2},Table2[Pay Item Description],Table2[Units]),2,0)) -> L.F. | AD14: ='Maintenance Policies'!D15*($C$5*9) -> 13420.778 | AE14: =IF(AB14="","N/A",IF(INDEX(UnitCostGrid,MATCH(AB14,PayItemKeys,0),$I$11)="",INDEX(UnitCostGrid,MATCH(AB14,PayItemKeys,0),1),INDEX(UnitCostGrid,MATCH(AB14,PayItemKeys,0),$I$11))) -> 4 | AF14: =AE14*AD14 -> 53683.11 | AH14: 2 | AI14: =IF(AJ14="",0,VLOOKUP(AJ14,CHOOSE({1,2},Table2[Pay Item Description],Table2[Pay Item No.]),2,0)) -> P-101-5.2a | AJ14: =Pay_Items!D6 -> Crack Repair (Type I), Asphalt | AK14: =IF(AJ14="","N/A",VLOOKUP(AJ14,CHOOSE({1,2},Table2[Pay Item Description],Table2[Units]),2,0)) -> L.F. | AL14: ='Maintenance Policies'!D19*($C$5*9) -> 14453.145 | AM14: =IF(AJ14="","N/A",IF(INDEX(UnitCostGrid,MATCH(AJ14,PayItemKeys,0),$I$11)="",INDEX(UnitCostGrid,MATCH(AJ14,PayItemKeys,0),1),INDEX(UnitCostGrid,MATCH(AJ14,PayItemKeys,0),$I$11))) -> 4 | AN14: =AM14*AL14 -> 57812.58 | AP14: 2 | AQ14: =IF(AR14="",0,VLOOKUP(AR14,CHOOSE({1,2},Table2[Pay Item Description],Table2[Pay Item No.]),2,0)) -> P-603-5.1 | AR14: =Pay_Items!D54 -> Emulsified Asphalt Tack Coat | AS14: =IF(AR14="","N/A",VLOOKUP(AR14,CHOOSE({1,2},Table2[Pay Item Description],Table2[Units]),2,0)) -> GAL | AT14: ='Maintenance Policies'!D22*$C$5*AQ9 -> 4588.3 | AU14: =IF(AR14="","N/A",IF(INDEX(UnitCostGrid,MATCH(AR14,PayItemKeys,0),$I$11)="",INDEX(UnitCostGrid,MATCH(AR14,PayItemKeys,0),1),INDEX(UnitCostGrid,MATCH(AR14,PayItemKeys,0),$I$11))) -> 4.5 | AV14: =AU14*AT14 -> 20647.35 | AX14: 2 | AY14: =IF(AZ14="",0,VLOOKUP(AZ14,CHOOSE({1,2},Table2[Pay Item Description],Table2[Pay Item No.]),2,0)) -> P-101-5.3 | AZ14: =Pay_Items!D10 -> Markings Removal | BA14: =IF(AZ14="","N/A",VLOOKUP(AZ14,CHOOSE({1,2},Table2[Pay Item Description],Table2[Units]),2,0)) -> S.F. | BB14: ='Maintenance Policies'!D26*$C$8 -> 12000 | BC14: =IF(AZ14="","N/A",IF(INDEX(UnitCostGrid,MATCH(AZ14,PayItemKeys,0),$I$11)="",INDEX(UnitCostGrid,MATCH(AZ14,PayItemKeys,0),1),INDEX(UnitCostGrid,MATCH(AZ14,PayItemKeys,0),$I$11))) -> 0.77777778 | BD14: =BC14*BB14 -> 9333.3333 | BF14: 2 | BG14: =IF(BH14="",0,VLOOKUP(BH14,CHOOSE({1,2},Table2[Pay Item Description],Table2[Pay Item No.]),2,0)) -> P-101-5.2a | BH14: =Pay_Items!D6 -> Crack Repair (Type I), Asphalt | BI14: =IF(BH14="","N/A",VLOOKUP(BH14,CHOOSE({1,2},Table2[Pay Item Description],Table2[Units]),2,0)) -> L.F. | BJ14: ='Maintenance Policies'!D29*($C$5*9) -> 16517.88 | BK14: =IF(BH14="","N/A",IF(INDEX(UnitCostGrid,MATCH(BH14,PayItemKeys,0),$I$11)="",INDEX(UnitCostGrid,MATCH(BH14,PayItemKeys,0),1),INDEX(UnitCostGrid,MATCH(BH14,PayItemKeys,0),$I$11))) -> 4 | BL14: =BK14*BJ14 -> 66071.52
A15: 3 | B15: =IF(C15="","",VLOOKUP(C15,CHOOSE({1,2},Table2[Pay Item Description],Table2[Pay Item No.]),2,0)) | D15: =IF(C15="","N/A",VLOOKUP(C15,CHOOSE({1,2},Table2[Pay Item Description],Table2[Units]),2,0)) -> N/A | F15: =IF(C15="","N/A",IF(INDEX(UnitCostGrid,MATCH(C15,PayItemKeys,0),$I$11)="",INDEX(UnitCostGrid,MATCH(C15,PayItemKeys,0),1),INDEX(UnitCostGrid,MATCH(C15,PayItemKeys,0),$I$11))) -> N/A | G15: =IF(C15="",0,F15*E15) -> 0 | I15: =IF(C15="","",IF(INDEX(UnitCostGrid,MATCH(C15,PayItemKeys,0),$I$11)="",0,1)) | J15: 3 | K15: =IF(L15="",0,VLOOKUP(L15,CHOOSE({1,2},Table2[Pay Item Description],Table2[Pay Item No.]),2,0)) -> P-620-5.1a | L15: =Pay_Items!D56 -> Markings (prep, markings, reflective media) | M15: =IF(L15="","N/A",VLOOKUP(L15,CHOOSE({1,2},Table2[Pay Item Description],Table2[Units]),2,0)) -> S.F. | N15: ='Maintenance Policies'!D11*$C$8 -> 12000 | O15: =IF(L15="","N/A",IF(INDEX(UnitCostGrid,MATCH(L15,PayItemKeys,0),$I$11)="",INDEX(UnitCostGrid,MATCH(L15,PayItemKeys,0),1),INDEX(UnitCostGrid,MATCH(L15,PayItemKeys,0),$I$11))) -> 0.66666667 | P15: =O15*N15 -> 8000 | R15: 3 | S15: =IF(T15="",0,VLOOKUP(T15,CHOOSE({1,2},Table2[Pay Item Description],Table2[Pay Item No.]),2,0)) -> P-620-5.1a | T15: =Pay_Items!D56 -> Markings (prep, markings, reflective media) | U15: =Pay_Items!E56 -> S.F. | V15: ='Maintenance Policies'!D13*$C$8 -> 12000 | W15: =IF(T15="","N/A",IF(INDEX(UnitCostGrid,MATCH(T15,PayItemKeys,0),$I$11)="",INDEX(UnitCostGrid,MATCH(T15,PayItemKeys,0),1),INDEX(UnitCostGrid,MATCH(T15,PayItemKeys,0),$I$11))) -> 0.66666667 | X15: =W15*V15 -> 8000 | Z15: 3 | AA15: =IF(AB15="",0,VLOOKUP(AB15,CHOOSE({1,2},Table2[Pay Item Description],Table2[Pay Item No.]),2,0)) -> P-608-8.1 | AB15: =C7 -> Emulsified Asphalt Surface Treatment | AC15: =IF(AB15="","N/A",VLOOKUP(AB15,CHOOSE({1,2},Table2[Pay Item Description],Table2[Units]),2,0)) -> S.Y. | AD15: ='Maintenance Policies'!D16*$C$5 -> 45883 | AE15: =IF(AB15="","N/A",IF(INDEX(UnitCostGrid,MATCH(AB15,PayItemKeys,0),$I$11)="",INDEX(UnitCostGrid,MATCH(AB15,PayItemKeys,0),1),INDEX(UnitCostGrid,MATCH(AB15,PayItemKeys,0),$I$11))) -> 4 | AF15: =AE15*AD15 -> 183532 | AH15: 3 | AI15: =IF(AJ15="",0,VLOOKUP(AJ15,CHOOSE({1,2},Table2[Pay Item Description],Table2[Pay Item No.]),2,0)) -> P-608-8.1 | AJ15: =C7 -> Emulsified Asphalt Surface Treatment | AK15: =IF(AJ15="","N/A",VLOOKUP(AJ15,CHOOSE({1,2},Table2[Pay Item Description],Table2[Units]),2,0)) -> S.Y. | AL15: ='Maintenance Policies'!D20*$C$5 -> 45883 | AM15: =IF(AJ15="","N/A",IF(INDEX(UnitCostGrid,MATCH(AJ15,PayItemKeys,0),$I$11)="",INDEX(UnitCostGrid,MATCH(AJ15,PayItemKeys,0),1),INDEX(UnitCostGrid,MATCH(AJ15,PayItemKeys,0),$I$11))) -> 4 | AN15: =AM15*AL15 -> 183532 | AP15: 3 | AQ15: =IF(AR15="",0,VLOOKUP(AR15,CHOOSE({1,2},Table2[Pay Item Description],Table2[Pay Item No.]),2,0)) -> P-401-8.1a | AR15: =Pay_Items!D37 -> Asphalt Surface Course | AS15: =IF(AR15="","N/A",VLOOKUP(AR15,CHOOSE({1,2},Table2[Pay Item Description],Table2[Units]),2,0)) -> TON | AT15: ='Maintenance Policies'!D22*$C$5*AQ6*AQ7/2000 -> 5505.96 | AU15: =IF(AR15="","N/A",IF(INDEX(UnitCostGrid,MATCH(AR15,PayItemKeys,0),$I$11)="",INDEX(UnitCostGrid,MATCH(AR15,PayItemKeys,0),1),INDEX(UnitCostGrid,MATCH(AR15,PayItemKeys,0),$I$11))) -> 130 | AV15: =AU15*AT15 -> 715774.8 | AX15: 3 | AY15: =IF(AZ15="",0,VLOOKUP(AZ15,CHOOSE({1,2},Table2[Pay Item Description],Table2[Pay Item No.]),2,0)) -> P-620-5.1a | AZ15: =Pay_Items!D56 -> Markings (prep, markings, reflective media) | BA15: =IF(AZ15="","N/A",VLOOKUP(AZ15,CHOOSE({1,2},Table2[Pay Item Description],Table2[Units]),2,0)) -> S.F. | BB15: ='Maintenance Policies'!D27*$C$8 -> 12000 | BC15: =IF(AZ15="","N/A",IF(INDEX(UnitCostGrid,MATCH(AZ15,PayItemKeys,0),$I$11)="",INDEX(UnitCostGrid,MATCH(AZ15,PayItemKeys,0),1),INDEX(UnitCostGrid,MATCH(AZ15,PayItemKeys,0),$I$11))) -> 0.66666667 | BD15: =BC15*BB15 -> 8000 | BF15: 3 | BG15: =IF(BH15="",0,VLOOKUP(BH15,CHOOSE({1,2},Table2[Pay Item Description],Table2[Pay Item No.]),2,0)) -> P-608-8.1 | BH15: =C7 -> Emulsified Asphalt Surface Treatment | BI15: =IF(BH15="","N/A",VLOOKUP(BH15,CHOOSE({1,2},Table2[Pay Item Description],Table2[Units]),2,0)) -> S.Y. | BJ15: ='Maintenance Policies'!D30*$C$5 -> 45883 | BK15: =IF(BH15="","N/A",IF(INDEX(UnitCostGrid,MATCH(BH15,PayItemKeys,0),$I$11)="",INDEX(UnitCostGrid,MATCH(BH15,PayItemKeys,0),1),INDEX(UnitCostGrid,MATCH(BH15,PayItemKeys,0),$I$11))) -> 4 | BL15: =BK15*BJ15 -> 183532
A16: 4 | B16: =IF(C16="","",VLOOKUP(C16,CHOOSE({1,2},Table2[Pay Item Description],Table2[Pay Item No.]),2,0)) | D16: =IF(C16="","N/A",VLOOKUP(C16,CHOOSE({1,2},Table2[Pay Item Description],Table2[Units]),2,0)) -> N/A | F16: =IF(C16="","N/A",IF(INDEX(UnitCostGrid,MATCH(C16,PayItemKeys,0),$I$11)="",INDEX(UnitCostGrid,MATCH(C16,PayItemKeys,0),1),INDEX(UnitCostGrid,MATCH(C16,PayItemKeys,0),$I$11))) -> N/A | G16: =IF(C16="",0,F16*E16) -> 0 | I16: =IF(C16="","",IF(INDEX(UnitCostGrid,MATCH(C16,PayItemKeys,0),$I$11)="",0,1)) | O16: Subtotal | P16: =SUM(P13:P15) -> 200865.33 | W16: Subtotal | X16: =SUM(X13:X15) -> 200865.33 | Z16: 4 | AA16: =IF(AB16="",0,VLOOKUP(AB16,CHOOSE({1,2},Table2[Pay Item Description],Table2[Pay Item No.]),2,0)) -> P-101-5.3 | AB16: =Pay_Items!D10 -> Markings Removal | AC16: =IF(AB16="","N/A",VLOOKUP(AB16,CHOOSE({1,2},Table2[Pay Item Description],Table2[Units]),2,0)) -> S.F. | AD16: ='Maintenance Policies'!D16*$C$8 -> 12000 | AE16: =IF(AB16="","N/A",IF(INDEX(UnitCostGrid,MATCH(AB16,PayItemKeys,0),$I$11)="",INDEX(UnitCostGrid,MATCH(AB16,PayItemKeys,0),1),INDEX(UnitCostGrid,MATCH(AB16,PayItemKeys,0),$I$11))) -> 0.77777778 | AF16: =AE16*AD16 -> 9333.3333 | AH16: 4 | AI16: =IF(AJ16="",0,VLOOKUP(AJ16,CHOOSE({1,2},Table2[Pay Item Description],Table2[Pay Item No.]),2,0)) -> P-101-5.3 | AJ16: =Pay_Items!D10 -> Markings Removal | AK16: =IF(AJ16="","N/A",VLOOKUP(AJ16,CHOOSE({1,2},Table2[Pay Item Description],Table2[Units]),2,0)) -> S.F. | AL16: ='Maintenance Policies'!D20*$C$8 -> 12000 | AM16: =IF(AJ16="","N/A",IF(INDEX(UnitCostGrid,MATCH(AJ16,PayItemKeys,0),$I$11)="",INDEX(UnitCostGrid,MATCH(AJ16,PayItemKeys,0),1),INDEX(UnitCostGrid,MATCH(AJ16,PayItemKeys,0),$I$11))) -> 0.77777778 | AN16: =AM16*AL16 -> 9333.3333 | AP16: 4 | AQ16: =IF(AR16="",0,VLOOKUP(AR16,CHOOSE({1,2},Table2[Pay Item Description],Table2[Pay Item No.]),2,0)) -> P-101-5.2a | AR16: =Pay_Items!D6 -> Crack Repair (Type I), Asphalt | AS16: =IF(AR16="","N/A",VLOOKUP(AR16,CHOOSE({1,2},Table2[Pay Item Description],Table2[Units]),2,0)) -> L.F. | AT16: ='Maintenance Policies'!D23*($C$5*9) -> 6194.205 | AU16: =IF(AR16="","N/A",IF(INDEX(UnitCostGrid,MATCH(AR16,PayItemKeys,0),$I$11)="",INDEX(UnitCostGrid,MATCH(AR16,PayItemKeys,0),1),INDEX(UnitCostGrid,MATCH(AR16,PayItemKeys,0),$I$11))) -> 4 | AV16: =AU16*AT16 -> 24776.82 | BC16: Subtotal | BD16: =SUM(BD13:BD15) -> 200865.33 | BF16: 4 | BG16: =IF(BH16="",0,VLOOKUP(BH16,CHOOSE({1,2},Table2[Pay Item Description],Table2[Pay Item No.]),2,0)) -> P-101-5.3 | BH16: =Pay_Items!D10 -> Markings Removal | BI16: =IF(BH16="","N/A",VLOOKUP(BH16,CHOOSE({1,2},Table2[Pay Item Description],Table2[Units]),2,0)) -> S.F. | BJ16: =C8 -> 12000 | BK16: =IF(BH16="","N/A",IF(INDEX(UnitCostGrid,MATCH(BH16,PayItemKeys,0),$I$11)="",INDEX(UnitCostGrid,MATCH(BH16,PayItemKeys,0),1),INDEX(UnitCostGrid,MATCH(BH16,PayItemKeys,0),$I$11))) -> 0.77777778 | BL16: =BK16*BJ16 -> 9333.3333
A17: 5 | B17: =IF(C17="","",VLOOKUP(C17,CHOOSE({1,2},Table2[Pay Item Description],Table2[Pay Item No.]),2,0)) | D17: =IF(C17="","N/A",VLOOKUP(C17,CHOOSE({1,2},Table2[Pay Item Description],Table2[Units]),2,0)) -> N/A | F17: =IF(C17="","N/A",IF(INDEX(UnitCostGrid,MATCH(C17,PayItemKeys,0),$I$11)="",INDEX(UnitCostGrid,MATCH(C17,PayItemKeys,0),1),INDEX(UnitCostGrid,MATCH(C17,PayItemKeys,0),$I$11))) -> N/A | G17: =IF(C17="",0,F17*E17) -> 0 | I17: =IF(C17="","",IF(INDEX(UnitCostGrid,MATCH(C17,PayItemKeys,0),$I$11)="",0,1)) | L17: Mobilization | P17: =('General Information'!$D$36/100)*P16 -> 20086.533 | T17: Mobilization | X17: =('General Information'!$D$36/100)*X16 -> 20086.533 | Z17: 5 | AA17: =IF(AB17="",0,VLOOKUP(AB17,CHOOSE({1,2},Table2[Pay Item Description],Table2[Pay Item No.]),2,0)) -> P-620-5.1a | AB17: =Pay_Items!D56 -> Markings (prep, markings, reflective media) | AC17: =IF(AB17="","N/A",VLOOKUP(AB17,CHOOSE({1,2},Table2[Pay Item Description],Table2[Units]),2,0)) -> S.F. | AD17: ='Maintenance Policies'!D17*$C$8 -> 12000 | AE17: =IF(AB17="","N/A",IF(INDEX(UnitCostGrid,MATCH(AB17,PayItemKeys,0),$I$11)="",INDEX(UnitCostGrid,MATCH(AB17,PayItemKeys,0),1),INDEX(UnitCostGrid,MATCH(AB17,PayItemKeys,0),$I$11))) -> 0.66666667 | AF17: =AE17*AD17 -> 8000 | AH17: 5 | AI17: =IF(AJ17="",0,VLOOKUP(AJ17,CHOOSE({1,2},Table2[Pay Item Description],Table2[Pay Item No.]),2,0)) -> P-620-5.1a | AJ17: =Pay_Items!D56 -> Markings (prep, markings, reflective media) | AK17: =IF(AJ17="","N/A",VLOOKUP(AJ17,CHOOSE({1,2},Table2[Pay Item Description],Table2[Units]),2,0)) -> S.F. | AL17: ='Maintenance Policies'!D21*$C$8 -> 12000 | AM17: =IF(AJ17="","N/A",IF(INDEX(UnitCostGrid,MATCH(AJ17,PayItemKeys,0),$I$11)="",INDEX(UnitCostGrid,MATCH(AJ17,PayItemKeys,0),1),INDEX(UnitCostGrid,MATCH(AJ17,PayItemKeys,0),$I$11))) -> 0.66666667 | AN17: =AM17*AL17 -> 8000 | AP17: 5 | AQ17: =IF(AR17="",0,VLOOKUP(AR17,CHOOSE({1,2},Table2[Pay Item Description],Table2[Pay Item No.]),2,0)) -> P-101-5.4a | AR17: =Pay_Items!D11 -> Spall Repair, Asphalt | AS17: =IF(AR17="","N/A",VLOOKUP(AR17,CHOOSE({1,2},Table2[Pay Item Description],Table2[Units]),2,0)) -> S.F. | AT17: ='Maintenance Policies'!D24*($C$5*9) -> 2064.735 | AU17: =IF(AR17="","N/A",IF(INDEX(UnitCostGrid,MATCH(AR17,PayItemKeys,0),$I$11)="",INDEX(UnitCostGrid,MATCH(AR17,PayItemKeys,0),1),INDEX(UnitCostGrid,MATCH(AR17,PayItemKeys,0),$I$11))) -> 8.5 | AV17: =AU17*AT17 -> 17550.248 | AZ17: Mobilization | BD17: =('General Information'!$D$36/100)*BD16 -> 20086.533 | BF17: 5 | BG17: =IF(BH17="",0,VLOOKUP(BH17,CHOOSE({1,2},Table2[Pay Item Description],Table2[Pay Item No.]),2,0)) -> P-620-5.1a | BH17: =Pay_Items!D56 -> Markings (prep, markings, reflective media) | BI17: =IF(BH17="","N/A",VLOOKUP(BH17,CHOOSE({1,2},Table2[Pay Item Description],Table2[Units]),2,0)) -> S.F. | BJ17: ='Maintenance Policies'!D31*$C$8 -> 12000 | BK17: =IF(BH17="","N/A",IF(INDEX(UnitCostGrid,MATCH(BH17,PayItemKeys,0),$I$11)="",INDEX(UnitCostGrid,MATCH(BH17,PayItemKeys,0),1),INDEX(UnitCostGrid,MATCH(BH17,PayItemKeys,0),$I$11))) -> 0.66666667 | BL17: =BK17*BJ17 -> 8000
A18: 6 | B18: =IF(C18="","",VLOOKUP(C18,CHOOSE({1,2},Table2[Pay Item Description],Table2[Pay Item No.]),2,0)) | D18: =IF(C18="","N/A",VLOOKUP(C18,CHOOSE({1,2},Table2[Pay Item Description],Table2[Units]),2,0)) -> N/A | F18: =IF(C18="","N/A",IF(INDEX(UnitCostGrid,MATCH(C18,PayItemKeys,0),$I$11)="",INDEX(UnitCostGrid,MATCH(C18,PayItemKeys,0),1),INDEX(UnitCostGrid,MATCH(C18,PayItemKeys,0),$I$11))) -> N/A | G18: =IF(C18="",0,F18*E18) -> 0 | I18: =IF(C18="","",IF(INDEX(UnitCostGrid,MATCH(C18,PayItemKeys,0),$I$11)="",0,1)) | L18: Engineering | P18: =('General Information'!$D$37/100)*P16 -> 10043.267 | T18: Engineering | X18: =('General Information'!$D$37/100)*X16 -> 10043.267 | AE18: Subtotal | AF18: =SUM(AF13:AF17) -> 280873.81 | AM18: Subtotal | AN18: =SUM(AN13:AN17) -> 293778.41 | AP18: 6 | AQ18: =IF(AR18="",0,VLOOKUP(AR18,CHOOSE({1,2},Table2[Pay Item Description],Table2[Pay Item No.]),2,0)) -> P-620-5.1a | AR18: =Pay_Items!D56 -> Markings (prep, markings, reflective media) | AS18: =IF(AR18="","N/A",VLOOKUP(AR18,CHOOSE({1,2},Table2[Pay Item Description],Table2[Units]),2,0)) -> S.F. | AT18: ='Maintenance Policies'!D25*$C$8 -> 12000 | AU18: =IF(AR18="","N/A",IF(INDEX(UnitCostGrid,MATCH(AR18,PayItemKeys,0),$I$11)="",INDEX(UnitCostGrid,MATCH(AR18,PayItemKeys,0),1),INDEX(UnitCostGrid,MATCH(AR18,PayItemKeys,0),$I$11))) -> 0.66666667 | AV18: =AU18*AT18 -> 8000 | AZ18: Engineering | BD18: =('General Information'!$D$37/100)*BD16 -> 10043.267 | BK18: Subtotal | BL18: =SUM(BL13:BL17) -> 310812.47
A19: 7 | B19: =IF(C19="","",VLOOKUP(C19,CHOOSE({1,2},Table2[Pay Item Description],Table2[Pay Item No.]),2,0)) | D19: =IF(C19="","N/A",VLOOKUP(C19,CHOOSE({1,2},Table2[Pay Item Description],Table2[Units]),2,0)) -> N/A | F19: =IF(C19="","N/A",IF(INDEX(UnitCostGrid,MATCH(C19,PayItemKeys,0),$I$11)="",INDEX(UnitCostGrid,MATCH(C19,PayItemKeys,0),1),INDEX(UnitCostGrid,MATCH(C19,PayItemKeys,0),$I$11))) -> N/A | G19: =IF(C19="",0,F19*E19) -> 0 | I19: =IF(C19="","",IF(INDEX(UnitCostGrid,MATCH(C19,PayItemKeys,0),$I$11)="",0,1)) | O19: Total | P19: =SUM(P16:P18) -> 230995.13 | W19: Total | X19: =SUM(X16:X18) -> 230995.13 | AB19: Mobilization | AF19: =('General Information'!$D$36/100)*AF18 -> 28087.381 | AJ19: Mobilization | AN19: =('General Information'!$D$36/100)*AN18 -> 29377.841 | AU19: Subtotal | AV19: =SUM(AV13:AV18) -> 1016164.2 | BC19: Total | BD19: =SUM(BD16:BD18) -> 230995.13 | BH19: Mobilization | BL19: =('General Information'!$D$36/100)*BL18 -> 31081.247
A20: 8 | B20: =IF(C20="","",VLOOKUP(C20,CHOOSE({1,2},Table2[Pay Item Description],Table2[Pay Item No.]),2,0)) | D20: =IF(C20="","N/A",VLOOKUP(C20,CHOOSE({1,2},Table2[Pay Item Description],Table2[Units]),2,0)) -> N/A | F20: =IF(C20="","N/A",IF(INDEX(UnitCostGrid,MATCH(C20,PayItemKeys,0),$I$11)="",INDEX(UnitCostGrid,MATCH(C20,PayItemKeys,0),1),INDEX(UnitCostGrid,MATCH(C20,PayItemKeys,0),$I$11))) -> N/A | G20: =IF(C20="",0,F20*E20) -> 0 | I20: =IF(C20="","",IF(INDEX(UnitCostGrid,MATCH(C20,PayItemKeys,0),$I$11)="",0,1)) | AB20: Engineering | AF20: =('General Information'!$D$37/100)*AF18 -> 14043.691 | AJ20: Engineering | AN20: =('General Information'!$D$37/100)*AN18 -> 14688.92 | AR20: Mobilization | AV20: =('General Information'!$D$36/100)*AV19 -> 101616.42 | BH20: Engineering | BL20: =('General Information'!$D$37/100)*BL18 -> 15540.624
A21: 9 | B21: =IF(C21="","",VLOOKUP(C21,CHOOSE({1,2},Table2[Pay Item Description],Table2[Pay Item No.]),2,0)) | D21: =IF(C21="","N/A",VLOOKUP(C21,CHOOSE({1,2},Table2[Pay Item Description],Table2[Units]),2,0)) -> N/A | F21: =IF(C21="","N/A",IF(INDEX(UnitCostGrid,MATCH(C21,PayItemKeys,0),$I$11)="",INDEX(UnitCostGrid,MATCH(C21,PayItemKeys,0),1),INDEX(UnitCostGrid,MATCH(C21,PayItemKeys,0),$I$11))) -> N/A | G21: =IF(C21="",0,F21*E21) -> 0 | I21: =IF(C21="","",IF(INDEX(UnitCostGrid,MATCH(C21,PayItemKeys,0),$I$11)="",0,1)) | AE21: Total | AF21: =SUM(AF18:AF20) -> 323004.89 | AM21: Total | AN21: =SUM(AN18:AN20) -> 337845.17 | AR21: Engineering | AV21: =('General Information'!$D$37/100)*AV19 -> 50808.211 | BK21: Total | BL21: =SUM(BL18:BL20) -> 357434.34
A22: 10 | B22: =IF(C22="","",VLOOKUP(C22,CHOOSE({1,2},Table2[Pay Item Description],Table2[Pay Item No.]),2,0)) | D22: =IF(C22="","N/A",VLOOKUP(C22,CHOOSE({1,2},Table2[Pay Item Description],Table2[Units]),2,0)) -> N/A | F22: =IF(C22="","N/A",IF(INDEX(UnitCostGrid,MATCH(C22,PayItemKeys,0),$I$11)="",INDEX(UnitCostGrid,MATCH(C22,PayItemKeys,0),1),INDEX(UnitCostGrid,MATCH(C22,PayItemKeys,0),$I$11))) -> N/A | G22: =IF(C22="",0,F22*E22) -> 0 | I22: =IF(C22="","",IF(INDEX(UnitCostGrid,MATCH(C22,PayItemKeys,0),$I$11)="",0,1)) | AU22: Total | AV22: =SUM(AV19:AV21) -> 1168588.9
A24: Subtotal | G24: =SUM(G13:G22) -> 0
B25: Mobilization | G25: =('General Information'!$D$36/100)*G24 -> 0
B26: Engineering | G26: =('General Information'!$D$37/100)*G24 -> 0
A27: Total | G27: =SUM(G24:G26) -> 0
A32: Net Present Worth
A33: HMA Reconstruction - Alternative 1 | I33: Hidden
B35: Item | C35: Year Applied | D35: Actual Cost | E35: Discounted Cost
B36: Initial Construction | C36: =C6 -> 2028 | D36: =G27 -> 0 | E36: =D36 -> 0 | K36: Year | L36: Direct Cost | M36: Indirect Cost | N36: Total Discounted Cost
B37: Maintenance 1 | C37: ='Maintenance Policies'!E10 -> 4 | D37: =P19 -> 230995.13 | E37: =IF(C37>'General Information'!$D$33,0,D37/(1+('General Information'!$D$34/100))^C37) -> 205236.18 | K37: =C6 -> 2028 | L37: =IF(K37-$C$6>'General Information'!$D$33,0,IF(K37=$C$6,$D$36,0)+SUMIFS($D$37:$D$51,$C$37:$C$51,K37-$C$6,$B$37:$B$51,"<>*Indirect*")) -> 0 | M37: =IF(K37-$C$6>'General Information'!$D$33,0,SUMIFS($D$37:$D$51,$C$37:$C$51,K37-$C$6,$B$37:$B$51,"*Indirect*")) -> 0 | N37: =IF(K37-$C$6>'General Information'!$D$33,0,IF(K37=$C$6,$E$36,0)+SUMIF($C$37:$C$51,K37-$C$6,$E$37:$E$51)) -> 0
B38: Maintenance 1 Indirect Cost | C38: ='Maintenance Policies'!E10 -> 4 | D38: =F2*F4 -> 32647.02 | E38: =IF(C38>'General Information'!$D$33,0,D38/(1+('General Information'!$D$34/100))^C38) -> 29006.454 | K38: =K37+1 -> 2029 | L38: =IF(K38-$C$6>'General Information'!$D$33,0,IF(K38=$C$6,$D$36,0)+SUMIFS($D$37:$D$51,$C$37:$C$51,K38-$C$6,$B$37:$B$51,"<>*Indirect*")) -> 0 | M38: =IF(K38-$C$6>'General Information'!$D$33,0,SUMIFS($D$37:$D$51,$C$37:$C$51,K38-$C$6,$B$37:$B$51,"*Indirect*")) -> 0 | N38: =IF(K38-$C$6>'General Information'!$D$33,0,IF(K38=$C$6,$E$36,0)+SUMIF($C$37:$C$51,K38-$C$6,$E$37:$E$51)) -> 0
B39: Maintenance 2 | C39: ='Maintenance Policies'!E12 -> 8 | D39: =X19 -> 230995.13 | E39: =IF(C39>'General Information'!$D$33,0,D39/(1+('General Information'!$D$34/100))^C39) -> 182349.69 | K39: =K38+1 -> 2030 | L39: =IF(K39-$C$6>'General Information'!$D$33,0,IF(K39=$C$6,$D$36,0)+SUMIFS($D$37:$D$51,$C$37:$C$51,K39-$C$6,$B$37:$B$51,"<>*Indirect*")) -> 0 | M39: =IF(K39-$C$6>'General Information'!$D$33,0,SUMIFS($D$37:$D$51,$C$37:$C$51,K39-$C$6,$B$37:$B$51,"*Indirect*")) -> 0 | N39: =IF(K39-$C$6>'General Information'!$D$33,0,IF(K39=$C$6,$E$36,0)+SUMIF($C$37:$C$51,K39-$C$6,$E$37:$E$51)) -> 0
B40: Maintenance 2 Indirect Cost | C40: ='Maintenance Policies'!E12 -> 8 | D40: =F2*F5 -> 32647.02 | E40: =IF(C40>'General Information'!$D$33,0,D40/(1+('General Information'!$D$34/100))^C40) -> 25771.859 | K40: =K39+1 -> 2031 | L40: =IF(K40-$C$6>'General Information'!$D$33,0,IF(K40=$C$6,$D$36,0)+SUMIFS($D$37:$D$51,$C$37:$C$51,K40-$C$6,$B$37:$B$51,"<>*Indirect*")) -> 0 | M40: =IF(K40-$C$6>'General Information'!$D$33,0,SUMIFS($D$37:$D$51,$C$37:$C$51,K40-$C$6,$B$37:$B$51,"*Indirect*")) -> 0 | N40: =IF(K40-$C$6>'General Information'!$D$33,0,IF(K40=$C$6,$E$36,0)+SUMIF($C$37:$C$51,K40-$C$6,$E$37:$E$51)) -> 0
B41: Maintenance 3 | C41: ='Maintenance Policies'!E14 -> 12 | D41: =AF21 -> 323004.89 | E41: =IF(C41>'General Information'!$D$33,0,D41/(1+('General Information'!$D$34/100))^C41) -> 226549.13 | K41: =K40+1 -> 2032 | L41: =IF(K41-$C$6>'General Information'!$D$33,0,IF(K41=$C$6,$D$36,0)+SUMIFS($D$37:$D$51,$C$37:$C$51,K41-$C$6,$B$37:$B$51,"<>*Indirect*")) -> 230995.13 | M41: =IF(K41-$C$6>'General Information'!$D$33,0,SUMIFS($D$37:$D$51,$C$37:$C$51,K41-$C$6,$B$37:$B$51,"*Indirect*")) -> 32647.02 | N41: =IF(K41-$C$6>'General Information'!$D$33,0,IF(K41=$C$6,$E$36,0)+SUMIF($C$37:$C$51,K41-$C$6,$E$37:$E$51)) -> 234242.64
B42: Maintenance 3 Indirect Cost | C42: ='Maintenance Policies'!E14 -> 12 | D42: =F2*F6 -> 43529.36 | E42: =IF(C42>'General Information'!$D$33,0,D42/(1+('General Information'!$D$34/100))^C42) -> 30530.617 | K42: =K41+1 -> 2033 | L42: =IF(K42-$C$6>'General Information'!$D$33,0,IF(K42=$C$6,$D$36,0)+SUMIFS($D$37:$D$51,$C$37:$C$51,K42-$C$6,$B$37:$B$51,"<>*Indirect*")) -> 0 | M42: =IF(K42-$C$6>'General Information'!$D$33,0,SUMIFS($D$37:$D$51,$C$37:$C$51,K42-$C$6,$B$37:$B$51,"*Indirect*")) -> 0 | N42: =IF(K42-$C$6>'General Information'!$D$33,0,IF(K42=$C$6,$E$36,0)+SUMIF($C$37:$C$51,K42-$C$6,$E$37:$E$51)) -> 0
B43: Maintenance 4 | C43: ='Maintenance Policies'!E18 -> 16 | D43: =AN21 -> 337845.17 | E43: =IF(C43>'General Information'!$D$33,0,D43/(1+('General Information'!$D$34/100))^C43) -> 210533.94 | K43: =K42+1 -> 2034 | L43: =IF(K43-$C$6>'General Information'!$D$33,0,IF(K43=$C$6,$D$36,0)+SUMIFS($D$37:$D$51,$C$37:$C$51,K43-$C$6,$B$37:$B$51,"<>*Indirect*")) -> 0 | M43: =IF(K43-$C$6>'General Information'!$D$33,0,SUMIFS($D$37:$D$51,$C$37:$C$51,K43-$C$6,$B$37:$B$51,"*Indirect*")) -> 0 | N43: =IF(K43-$C$6>'General Information'!$D$33,0,IF(K43=$C$6,$E$36,0)+SUMIF($C$37:$C$51,K43-$C$6,$E$37:$E$51)) -> 0
B44: Maintenance 4 Indirect Cost | C44: ='Maintenance Policies'!E18 -> 16 | D44: =F2*F7 -> 43529.36 | E44: =IF(C44>'General Information'!$D$33,0,D44/(1+('General Information'!$D$34/100))^C44) -> 27126.058 | K44: =K43+1 -> 2035 | L44: =IF(K44-$C$6>'General Information'!$D$33,0,IF(K44=$C$6,$D$36,0)+SUMIFS($D$37:$D$51,$C$37:$C$51,K44-$C$6,$B$37:$B$51,"<>*Indirect*")) -> 0 | M44: =IF(K44-$C$6>'General Information'!$D$33,0,SUMIFS($D$37:$D$51,$C$37:$C$51,K44-$C$6,$B$37:$B$51,"*Indirect*")) -> 0 | N44: =IF(K44-$C$6>'General Information'!$D$33,0,IF(K44=$C$6,$E$36,0)+SUMIF($C$37:$C$51,K44-$C$6,$E$37:$E$51)) -> 0
B45: Rehabilitation 1 | C45: ='Maintenance Policies'!E22 -> 20 | D45: =AV22 -> 1168588.9 | E45: =IF(C45>'General Information'!$D$33,0,D45/(1+('General Information'!$D$34/100))^C45) -> 647019.31 | K45: =K44+1 -> 2036 | L45: =IF(K45-$C$6>'General Information'!$D$33,0,IF(K45=$C$6,$D$36,0)+SUMIFS($D$37:$D$51,$C$37:$C$51,K45-$C$6,$B$37:$B$51,"<>*Indirect*")) -> 230995.13 | M45: =IF(K45-$C$6>'General Information'!$D$33,0,SUMIFS($D$37:$D$51,$C$37:$C$51,K45-$C$6,$B$37:$B$51,"*Indirect*")) -> 32647.02 | N45: =IF(K45-$C$6>'General Information'!$D$33,0,IF(K45=$C$6,$E$36,0)+SUMIF($C$37:$C$51,K45-$C$6,$E$37:$E$51)) -> 208121.55
B46: Rehabilitation 1 Indirect Cost | C46: ='Maintenance Policies'!E22 -> 20 | D46: =F2*F8 -> 76176.38 | E46: =IF(C46>'General Information'!$D$33,0,D46/(1+('General Information'!$D$34/100))^C46) -> 42177.015 | K46: =K45+1 -> 2037 | L46: =IF(K46-$C$6>'General Information'!$D$33,0,IF(K46=$C$6,$D$36,0)+SUMIFS($D$37:$D$51,$C$37:$C$51,K46-$C$6,$B$37:$B$51,"<>*Indirect*")) -> 0 | M46: =IF(K46-$C$6>'General Information'!$D$33,0,SUMIFS($D$37:$D$51,$C$37:$C$51,K46-$C$6,$B$37:$B$51,"*Indirect*")) -> 0 | N46: =IF(K46-$C$6>'General Information'!$D$33,0,IF(K46=$C$6,$E$36,0)+SUMIF($C$37:$C$51,K46-$C$6,$E$37:$E$51)) -> 0
B47: Maintenance 5 | C47: ='Maintenance Policies'!E26 -> 24 | D47: =BD19 -> 230995.13 | E47: =IF(C47>'General Information'!$D$33,0,D47/(1+('General Information'!$D$34/100))^C47) -> 113634.3 | K47: =K46+1 -> 2038 | L47: =IF(K47-$C$6>'General Information'!$D$33,0,IF(K47=$C$6,$D$36,0)+SUMIFS($D$37:$D$51,$C$37:$C$51,K47-$C$6,$B$37:$B$51,"<>*Indirect*")) -> 0 | M47: =IF(K47-$C$6>'General Information'!$D$33,0,SUMIFS($D$37:$D$51,$C$37:$C$51,K47-$C$6,$B$37:$B$51,"*Indirect*")) -> 0 | N47: =IF(K47-$C$6>'General Information'!$D$33,0,IF(K47=$C$6,$E$36,0)+SUMIF($C$37:$C$51,K47-$C$6,$E$37:$E$51)) -> 0
B48: Maintenance 5 Indirect Cost | C48: ='Maintenance Policies'!E26 -> 24 | D48: =F2*F9 -> 32647.02 | E48: =IF(C48>'General Information'!$D$33,0,D48/(1+('General Information'!$D$34/100))^C48) -> 16060.171 | K48: =K47+1 -> 2039 | L48: =IF(K48-$C$6>'General Information'!$D$33,0,IF(K48=$C$6,$D$36,0)+SUMIFS($D$37:$D$51,$C$37:$C$51,K48-$C$6,$B$37:$B$51,"<>*Indirect*")) -> 0 | M48: =IF(K48-$C$6>'General Information'!$D$33,0,SUMIFS($D$37:$D$51,$C$37:$C$51,K48-$C$6,$B$37:$B$51,"*Indirect*")) -> 0 | N48: =IF(K48-$C$6>'General Information'!$D$33,0,IF(K48=$C$6,$E$36,0)+SUMIF($C$37:$C$51,K48-$C$6,$E$37:$E$51)) -> 0
B49: Maintenance 6 | C49: ='Maintenance Policies'!E28 -> 28 | D49: =BL21 -> 357434.34 | E49: =IF(C49>'General Information'!$D$33,0,D49/(1+('General Information'!$D$34/100))^C49) -> 156226.24 | K49: =K48+1 -> 2040 | L49: =IF(K49-$C$6>'General Information'!$D$33,0,IF(K49=$C$6,$D$36,0)+SUMIFS($D$37:$D$51,$C$37:$C$51,K49-$C$6,$B$37:$B$51,"<>*Indirect*")) -> 323004.89 | M49: =IF(K49-$C$6>'General Information'!$D$33,0,SUMIFS($D$37:$D$51,$C$37:$C$51,K49-$C$6,$B$37:$B$51,"*Indirect*")) -> 43529.36 | N49: =IF(K49-$C$6>'General Information'!$D$33,0,IF(K49=$C$6,$E$36,0)+SUMIF($C$37:$C$51,K49-$C$6,$E$37:$E$51)) -> 257079.75
B50: Maintenance 6 Indirect Cost | C50: ='Maintenance Policies'!E28 -> 28 | D50: =F2*F10 -> 43529.36 | E50: =IF(C50>'General Information'!$D$33,0,D50/(1+('General Information'!$D$34/100))^C50) -> 19025.671 | K50: =K49+1 -> 2041 | L50: =IF(K50-$C$6>'General Information'!$D$33,0,IF(K50=$C$6,$D$36,0)+SUMIFS($D$37:$D$51,$C$37:$C$51,K50-$C$6,$B$37:$B$51,"<>*Indirect*")) -> 0 | M50: =IF(K50-$C$6>'General Information'!$D$33,0,SUMIFS($D$37:$D$51,$C$37:$C$51,K50-$C$6,$B$37:$B$51,"*Indirect*")) -> 0 | N50: =IF(K50-$C$6>'General Information'!$D$33,0,IF(K50=$C$6,$E$36,0)+SUMIF($C$37:$C$51,K50-$C$6,$E$37:$E$51)) -> 0
B51: Salvage | C51: ='General Information'!D33 -> 30 | D51: =-'Maintenance Policies'!D32*AV22 -> -438220.82 | E51: =IF(C51>'General Information'!$D$33,0,D51/(1+('General Information'!$D$34/100))^C51) -> -180541.18 | K51: =K50+1 -> 2042 | L51: =IF(K51-$C$6>'General Information'!$D$33,0,IF(K51=$C$6,$D$36,0)+SUMIFS($D$37:$D$51,$C$37:$C$51,K51-$C$6,$B$37:$B$51,"<>*Indirect*")) -> 0 | M51: =IF(K51-$C$6>'General Information'!$D$33,0,SUMIFS($D$37:$D$51,$C$37:$C$51,K51-$C$6,$B$37:$B$51,"*Indirect*")) -> 0 | N51: =IF(K51-$C$6>'General Information'!$D$33,0,IF(K51=$C$6,$E$36,0)+SUMIF($C$37:$C$51,K51-$C$6,$E$37:$E$51)) -> 0
B52: Net Present Worth | E52: =SUM(E36:E51) -> 1750705.5 | K52: =K51+1 -> 2043 | L52: =IF(K52-$C$6>'General Information'!$D$33,0,IF(K52=$C$6,$D$36,0)+SUMIFS($D$37:$D$51,$C$37:$C$51,K52-$C$6,$B$37:$B$51,"<>*Indirect*")) -> 0 | M52: =IF(K52-$C$6>'General Information'!$D$33,0,SUMIFS($D$37:$D$51,$C$37:$C$51,K52-$C$6,$B$37:$B$51,"*Indirect*")) -> 0 | N52: =IF(K52-$C$6>'General Information'!$D$33,0,IF(K52=$C$6,$E$36,0)+SUMIF($C$37:$C$51,K52-$C$6,$E$37:$E$51)) -> 0
K53: =K52+1 -> 2044 | L53: =IF(K53-$C$6>'General Information'!$D$33,0,IF(K53=$C$6,$D$36,0)+SUMIFS($D$37:$D$51,$C$37:$C$51,K53-$C$6,$B$37:$B$51,"<>*Indirect*")) -> 337845.17 | M53: =IF(K53-$C$6>'General Information'!$D$33,0,SUMIFS($D$37:$D$51,$C$37:$C$51,K53-$C$6,$B$37:$B$51,"*Indirect*")) -> 43529.36 | N53: =IF(K53-$C$6>'General Information'!$D$33,0,IF(K53=$C$6,$E$36,0)+SUMIF($C$37:$C$51,K53-$C$6,$E$37:$E$51)) -> 237660
K54: =K53+1 -> 2045 | L54: =IF(K54-$C$6>'General Information'!$D$33,0,IF(K54=$C$6,$D$36,0)+SUMIFS($D$37:$D$51,$C$37:$C$51,K54-$C$6,$B$37:$B$51,"<>*Indirect*")) -> 0 | M54: =IF(K54-$C$6>'General Information'!$D$33,0,SUMIFS($D$37:$D$51,$C$37:$C$51,K54-$C$6,$B$37:$B$51,"*Indirect*")) -> 0 | N54: =IF(K54-$C$6>'General Information'!$D$33,0,IF(K54=$C$6,$E$36,0)+SUMIF($C$37:$C$51,K54-$C$6,$E$37:$E$51)) -> 0
K55: =K54+1 -> 2046 | L55: =IF(K55-$C$6>'General Information'!$D$33,0,IF(K55=$C$6,$D$36,0)+SUMIFS($D$37:$D$51,$C$37:$C$51,K55-$C$6,$B$37:$B$51,"<>*Indirect*")) -> 0 | M55: =IF(K55-$C$6>'General Information'!$D$33,0,SUMIFS($D$37:$D$51,$C$37:$C$51,K55-$C$6,$B$37:$B$51,"*Indirect*")) -> 0 | N55: =IF(K55-$C$6>'General Information'!$D$33,0,IF(K55=$C$6,$E$36,0)+SUMIF($C$37:$C$51,K55-$C$6,$E$37:$E$51)) -> 0
K56: =K55+1 -> 2047 | L56: =IF(K56-$C$6>'General Information'!$D$33,0,IF(K56=$C$6,$D$36,0)+SUMIFS($D$37:$D$51,$C$37:$C$51,K56-$C$6,$B$37:$B$51,"<>*Indirect*")) -> 0 | M56: =IF(K56-$C$6>'General Information'!$D$33,0,SUMIFS($D$37:$D$51,$C$37:$C$51,K56-$C$6,$B$37:$B$51,"*Indirect*")) -> 0 | N56: =IF(K56-$C$6>'General Information'!$D$33,0,IF(K56=$C$6,$E$36,0)+SUMIF($C$37:$C$51,K56-$C$6,$E$37:$E$51)) -> 0
K57: =K56+1 -> 2048 | L57: =IF(K57-$C$6>'General Information'!$D$33,0,IF(K57=$C$6,$D$36,0)+SUMIFS($D$37:$D$51,$C$37:$C$51,K57-$C$6,$B$37:$B$51,"<>*Indirect*")) -> 1168588.9 | M57: =IF(K57-$C$6>'General Information'!$D$33,0,SUMIFS($D$37:$D$51,$C$37:$C$51,K57-$C$6,$B$37:$B$51,"*Indirect*")) -> 76176.38 | N57: =IF(K57-$C$6>'General Information'!$D$33,0,IF(K57=$C$6,$E$36,0)+SUMIF($C$37:$C$51,K57-$C$6,$E$37:$E$51)) -> 689196.33
K58: =K57+1 -> 2049 | L58: =IF(K58-$C$6>'General Information'!$D$33,0,IF(K58=$C$6,$D$36,0)+SUMIFS($D$37:$D$51,$C$37:$C$51,K58-$C$6,$B$37:$B$51,"<>*Indirect*")) -> 0 | M58: =IF(K58-$C$6>'General Information'!$D$33,0,SUMIFS($D$37:$D$51,$C$37:$C$51,K58-$C$6,$B$37:$B$51,"*Indirect*")) -> 0 | N58: =IF(K58-$C$6>'General Information'!$D$33,0,IF(K58=$C$6,$E$36,0)+SUMIF($C$37:$C$51,K58-$C$6,$E$37:$E$51)) -> 0
K59: =K58+1 -> 2050 | L59: =IF(K59-$C$6>'General Information'!$D$33,0,IF(K59=$C$6,$D$36,0)+SUMIFS($D$37:$D$51,$C$37:$C$51,K59-$C$6,$B$37:$B$51,"<>*Indirect*")) -> 0 | M59: =IF(K59-$C$6>'General Information'!$D$33,0,SUMIFS($D$37:$D$51,$C$37:$C$51,K59-$C$6,$B$37:$B$51,"*Indirect*")) -> 0 | N59: =IF(K59-$C$6>'General Information'!$D$33,0,IF(K59=$C$6,$E$36,0)+SUMIF($C$37:$C$51,K59-$C$6,$E$37:$E$51)) -> 0
K60: =K59+1 -> 2051 | L60: =IF(K60-$C$6>'General Information'!$D$33,0,IF(K60=$C$6,$D$36,0)+SUMIFS($D$37:$D$51,$C$37:$C$51,K60-$C$6,$B$37:$B$51,"<>*Indirect*")) -> 0 | M60: =IF(K60-$C$6>'General Information'!$D$33,0,SUMIFS($D$37:$D$51,$C$37:$C$51,K60-$C$6,$B$37:$B$51,"*Indirect*")) -> 0 | N60: =IF(K60-$C$6>'General Information'!$D$33,0,IF(K60=$C$6,$E$36,0)+SUMIF($C$37:$C$51,K60-$C$6,$E$37:$E$51)) -> 0
K61: =K60+1 -> 2052 | L61: =IF(K61-$C$6>'General Information'!$D$33,0,IF(K61=$C$6,$D$36,0)+SUMIFS($D$37:$D$51,$C$37:$C$51,K61-$C$6,$B$37:$B$51,"<>*Indirect*")) -> 230995.13 | M61: =IF(K61-$C$6>'General Information'!$D$33,0,SUMIFS($D$37:$D$51,$C$37:$C$51,K61-$C$6,$B$37:$B$51,"*Indirect*")) -> 32647.02 | N61: =IF(K61-$C$6>'General Information'!$D$33,0,IF(K61=$C$6,$E$36,0)+SUMIF($C$37:$C$51,K61-$C$6,$E$37:$E$51)) -> 129694.47
K62: =K61+1 -> 2053 | L62: =IF(K62-$C$6>'General Information'!$D$33,0,IF(K62=$C$6,$D$36,0)+SUMIFS($D$37:$D$51,$C$37:$C$51,K62-$C$6,$B$37:$B$51,"<>*Indirect*")) -> 0 | M62: =IF(K62-$C$6>'General Information'!$D$33,0,SUMIFS($D$37:$D$51,$C$37:$C$51,K62-$C$6,$B$37:$B$51,"*Indirect*")) -> 0 | N62: =IF(K62-$C$6>'General Information'!$D$33,0,IF(K62=$C$6,$E$36,0)+SUMIF($C$37:$C$51,K62-$C$6,$E$37:$E$51)) -> 0
K63: =K62+1 -> 2054 | L63: =IF(K63-$C$6>'General Information'!$D$33,0,IF(K63=$C$6,$D$36,0)+SUMIFS($D$37:$D$51,$C$37:$C$51,K63-$C$6,$B$37:$B$51,"<>*Indirect*")) -> 0 | M63: =IF(K63-$C$6>'General Information'!$D$33,0,SUMIFS($D$37:$D$51,$C$37:$C$51,K63-$C$6,$B$37:$B$51,"*Indirect*")) -> 0 | N63: =IF(K63-$C$6>'General Information'!$D$33,0,IF(K63=$C$6,$E$36,0)+SUMIF($C$37:$C$51,K63-$C$6,$E$37:$E$51)) -> 0
K64: =K63+1 -> 2055 | L64: =IF(K64-$C$6>'General Information'!$D$33,0,IF(K64=$C$6,$D$36,0)+SUMIFS($D$37:$D$51,$C$37:$C$51,K64-$C$6,$B$37:$B$51,"<>*Indirect*")) -> 0 | M64: =IF(K64-$C$6>'General Information'!$D$33,0,SUMIFS($D$37:$D$51,$C$37:$C$51,K64-$C$6,$B$37:$B$51,"*Indirect*")) -> 0 | N64: =IF(K64-$C$6>'General Information'!$D$33,0,IF(K64=$C$6,$E$36,0)+SUMIF($C$37:$C$51,K64-$C$6,$E$37:$E$51)) -> 0
... K67: =K66+1 -> 2058 | L67: =IF(K67-$C$6>'General Information'!$D$33,0,IF(K67=$C$6,$D$36,0)+SUMIFS($D$37:$D$51,$C$37:$C$51,K67-$C$6,$B$37:$B$51,"<>*Indirect*")) -> -438220.82 | M67: =IF(K67-$C$6>'General Information'!$D$33,0,SUMIFS($D$37:$D$51,$C$37:$C$51,K67-$C$6,$B$37:$B$51,"*Indirect*")) -> 0 | N67: =IF(K67-$C$6>'General Information'!$D$33,0,IF(K67=$C$6,$E$36,0)+SUMIF($C$37:$C$51,K67-$C$6,$E$37:$E$51)) -> -180541.18

Sheet RevenueData
A1: FAA ID | B1: 100LL Fuel Sales | C1: Jet-A Fuel Sales | D1: Transient Tie-downs | E1: Itinerant Hangar Storage | F1: Tenant Fuel Flowage Fee | G1: Business Tenant Revenue | H1: Other Revenue Sources
A2: MKL | B2: 946.42 | C2: 7293.08 | D2: 60.53 | E2: 3 | F2: 94.64 | G2: 108.27 | H2: Office Rent, Enterprise Concessionaire, Interest
A3: SRB | B3: 794.52 | C3: 2153.43 | D3: 13.7 | E3: 1101.37 | F3: 26.3 | G3: 254.8 | H3: $-
A4: MBT | B4: 4939.57 | C4: 1517.81 | D4: 30 | E4: 10 | F4: $- | G4: 2344 | H4: $-
A5: NQA | B5: 592 | C5: 1410 | D5: 1 | E5: 7 | F5: $- | G5: 2250 | H5: 2031
A6: DKX | B6: 2630 | C6: 1044 | D6: 42 | E6: 15 | F6: $- | G6: 110 | H6: 2862
A7: SYI | B7: 1924.14 | C7: 923.66 | D7: $- | E7: $- | F7: $- | G7: 27397.26 | H7: 571.58
A8: GCY | B8: 1000 | C8: 725 | D8: 10 | E8: 5 | F8: 40 | G8: NA | H8: 20
A9: THA | B9: 635.26 | C9: 279 | D9: $- | E9: $- | F9: $- | G9: $- | H9: 25
A10: GKT | B10: 1660.27 | C10: 3427.4 | D10: 3.5 | E10: 350 | F10: $- | G10: $- | H10: $-
A11: JWN | B11: 8400 | C11: 70000 | D11: 1000 | E11: $- | F11: 625 | G11: $- | H11: 9215
A12: MOR | B12: 4604 | C12: 4057 | D12: $- | E12: $- | F12: 140.4 | G12: $- | H12: $-
A13: MQY | B13: 4939.57 | C13: 1517.81 | D13: 30 | E13: 10 | F13: $- | G13: 2344 | H13: $-
A14: RZR | B14: 794 | C14: 2431 | D14: 300 | E14: 150 | F14: 100 | G14: 300 | H14: 25
A15: XNX | B15: 5.26 | C15: 76.71 | D15: 600 airport and 16,389 FBO | E15: $175k for airport and FBO $260,000 | F15: $0.08 flowage per gallon | G15: $6 million FBO revenues. $50,000 revenue share with FBO | H15: $5,000 utlities reimbursements
A16: M91 | B16: 727 | C16: 388 | D16: 6 | E16: $- | F16: $- | G16: 368 | H16: 569
A17: CKV | B17: 1184.59 | C17: 1267.07 | D17: 120 | E17: 667.73 | F17: $- | G17: $- | H17: $-
A18: M54 | B18: 3rd party has fuel contract…revenue captured in tenant flowage fee. | D18: $- | E18: $- | F18: 71.88 | G18: 915.33 | H18: 40.6

Sheet TMP(NewHMA)
A1: =HYPERLINK("#'General Information'!D9","◄ General Information") -> ◄ General Information | C1: =HYPERLINK("#Summary!G1","Summary") -> Summary | D1: =$A$33 -> HMA Reconstruction - Alternative 1 | I1: Hidden
A2: Initial Construction Costs: | J2: Maintenance 1 | R2: Maintenance 2 | Z2: Maintenance 3 | AH2: Maintenance 4 | AP2: Rehabilitation 1 | AX2: Maintenance 5 | BF2: Maintenance 6
A3: STEP 4 of 5 · The quantities for this alternative. Grey cells are yours: C4 to C8 project data (filled from General Information), F4 to F10 closure days, C13 to C22 pay items and E13 to E22 quantities. Everything else calculates. Unit costs come from Pay_Items, and C11 picks which division they are priced from.
A4: Pavement Type: | C4: New HMA
A5: Mainline Pavement Area: | C5: ='General Information'!D26 -> 45883 | D5: S.Y.
A6: Initial Construction Year: | C6: ='General Information'!D25 -> 2028 | AP6: Mill and overlay: | AQ6: 2 | AR6: inches
A7: Asphalt Surface Treatment Type: | C7: Emulsified Asphalt Surface Treatment | D7: Select alternative treatment, if planned. | AP7: Asphalt: | AQ7: 120 | AR7: lbs/SY-in
A8: Markings Area: | C8: ='General Information'!D28 -> 12000 | D8: S.F.
AP9: Tack Coat Application | AQ9: 0.1 | AR9: gal/S.Y.
I10: Price column: 1 Regular, 2 Middle, 3 West, 4 East
B11: Price from: | C11: Regular | D11: =IF(OR($C$11="Regular",$C$11=""),"Regular is the statewide Unit Cost column on Pay_Items.","Prices from the "&$C$11&" column on Pay_Items: "&SUM($I$13:$I$22)&" of "&COUNT($I$13:$I$22)&" pay items used here have a "&$C$11&" cost, the rest fall back to Unit Cost.") -> Regular is the statewide Unit Cost column on Pay_Items. | I11: =IFERROR(MATCH($C$11,PriceSources,0),1) -> 1
A12: Item No. | B12: Pay Item | C12: Description | D12: Unit | E12: Qty | F12: Unit Cost | G12: Item Cost | J12: Item No. | K12: Pay Item | L12: Description | M12: Unit | N12: Qty | O12: Unit Cost | P12: Item Cost | R12: Item No. | S12: Pay Item | T12: Description | U12: Unit | V12: Qty | W12: Unit Cost | X12: Item Cost | Z12: Item No. | AA12: Pay Item | AB12: Description | AC12: Unit | AD12: Qty | AE12: Unit Cost | AF12: Item Cost | AH12: Item No. | AI12: Pay Item | AJ12: Description | AK12: Unit | AL12: Qty | AM12: Unit Cost | AN12: Item Cost | AP12: Item No. | AQ12: Pay Item | AR12: Description | AS12: Unit | AT12: Qty | AU12: Unit Cost | AV12: Item Cost | AX12: Item No. | AY12: Pay Item | AZ12: Description | BA12: Unit | BB12: Qty | BC12: Unit Cost | BD12: Item Cost | BF12: Item No. | BG12: Pay Item | BH12: Description | BI12: Unit | BJ12: Qty | BK12: Unit Cost | BL12: Item Cost
A13: 1 | B13: =IF(C13="","",VLOOKUP(C13,CHOOSE({1,2},Table2[Pay Item Description],Table2[Pay Item No.]),2,0)) | D13: =IF(C13="","N/A",VLOOKUP(C13,CHOOSE({1,2},Table2[Pay Item Description],Table2[Units]),2,0)) -> N/A | F13: =IF(C13="","N/A",IF(INDEX(UnitCostGrid,MATCH(C13,PayItemKeys,0),$I$11)="",INDEX(UnitCostGrid,MATCH(C13,PayItemKeys,0),1),INDEX(UnitCostGrid,MATCH(C13,PayItemKeys,0),$I$11))) -> N/A | G13: =IF(C13="",0,F13*E13) -> 0 | I13: =IF(C13="","",IF(INDEX(UnitCostGrid,MATCH(C13,PayItemKeys,0),$I$11)="",0,1)) | J13: 1 | K13: =IF(L13="",0,VLOOKUP(L13,CHOOSE({1,2},Table2[Pay Item Description],Table2[Pay Item No.]),2,0)) -> P-608-8.1 | L13: =C7 -> Emulsified Asphalt Surface Treatment | M13: =VLOOKUP(L13,CHOOSE({1,2},Table2[Pay Item Description],Table2[Units]),2,0) -> S.Y. | N13: ='Maintenance Policies'!D10*$C$5 -> 45883 | O13: =IF(L13="","N/A",IF(INDEX(UnitCostGrid,MATCH(L13,PayItemKeys,0),$I$11)="",INDEX(UnitCostGrid,MATCH(L13,PayItemKeys,0),1),INDEX(UnitCostGrid,MATCH(L13,PayItemKeys,0),$I$11))) -> 4 | P13: =O13*N13 -> 183532 | R13: 1 | S13: =IF(T13="",0,VLOOKUP(T13,CHOOSE({1,2},Table2[Pay Item Description],Table2[Pay Item No.]),2,0)) -> P-608-8.1 | T13: =C7 -> Emulsified Asphalt Surface Treatment | U13: =VLOOKUP(T13,CHOOSE({1,2},Table2[Pay Item Description],Table2[Units]),2,0) -> S.Y. | V13: ='Maintenance Policies'!D12*$C$5 -> 45883 | W13: =IF(T13="","N/A",IF(INDEX(UnitCostGrid,MATCH(T13,PayItemKeys,0),$I$11)="",INDEX(UnitCostGrid,MATCH(T13,PayItemKeys,0),1),INDEX(UnitCostGrid,MATCH(T13,PayItemKeys,0),$I$11))) -> 4 | X13: =W13*V13 -> 183532 | Z13: 1 | AA13: =IF(AB13="",0,VLOOKUP(AB13,CHOOSE({1,2},Table2[Pay Item Description],Table2[Pay Item No.]),2,0)) -> P-101-5.4a | AB13: =Pay_Items!D11 -> Spall Repair, Asphalt | AC13: =IF(AB13="","N/A",VLOOKUP(AB13,CHOOSE({1,2},Table2[Pay Item Description],Table2[Units]),2,0)) -> S.F. | AD13: ='Maintenance Policies'!D14*($C$5*9) -> 3097.1025 | AE13: =IF(AB13="","N/A",IF(INDEX(UnitCostGrid,MATCH(AB13,PayItemKeys,0),$I$11)="",INDEX(UnitCostGrid,MATCH(AB13,PayItemKeys,0),1),INDEX(UnitCostGrid,MATCH(AB13,PayItemKeys,0),$I$11))) -> 8.5 | AF13: =AE13*AD13 -> 26325.371 | AH13: 1 | AI13: =IF(AJ13="",0,VLOOKUP(AJ13,CHOOSE({1,2},Table2[Pay Item Description],Table2[Pay Item No.]),2,0)) -> P-101-5.4a | AJ13: =Pay_Items!D11 -> Spall Repair, Asphalt | AK13: =IF(AJ13="","N/A",VLOOKUP(AJ13,CHOOSE({1,2},Table2[Pay Item Description],Table2[Units]),2,0)) -> S.F. | AL13: ='Maintenance Policies'!D18*($C$5*9) -> 4129.47 | AM13: =IF(AJ13="","N/A",IF(INDEX(UnitCostGrid,MATCH(AJ13,PayItemKeys,0),$I$11)="",INDEX(UnitCostGrid,MATCH(AJ13,PayItemKeys,0),1),INDEX(UnitCostGrid,MATCH(AJ13,PayItemKeys,0),$I$11))) -> 8.5 | AN13: =AM13*AL13 -> 35100.495 | AP13: 1 | AQ13: =IF(AR13="",0,VLOOKUP(AR13,CHOOSE({1,2},Table2[Pay Item Description],Table2[Pay Item No.]),2,0)) -> P-101-5.6 | AR13: =Pay_Items!D16 -> Cold Milling | AS13: =IF(AR13="","N/A",VLOOKUP(AR13,CHOOSE({1,2},Table2[Pay Item Description],Table2[Units]),2,0)) -> S.Y. | AT13: ='Maintenance Policies'!D22*$C$5 -> 45883 | AU13: =IF(AR13="","N/A",IF(INDEX(UnitCostGrid,MATCH(AR13,PayItemKeys,0),$I$11)="",INDEX(UnitCostGrid,MATCH(AR13,PayItemKeys,0),1),INDEX(UnitCostGrid,MATCH(AR13,PayItemKeys,0),$I$11))) -> 5 | AV13: =AU13*AT13 -> 229415 | AX13: 1 | AY13: =IF(AZ13="",0,VLOOKUP(AZ13,CHOOSE({1,2},Table2[Pay Item Description],Table2[Pay Item No.]),2,0)) -> P-608-8.1 | AZ13: =C7 -> Emulsified Asphalt Surface Treatment | BA13: =IF(AZ13="","N/A",VLOOKUP(AZ13,CHOOSE({1,2},Table2[Pay Item Description],Table2[Units]),2,0)) -> S.Y. | BB13: ='Maintenance Policies'!D26*$C$5 -> 45883 | BC13: =IF(AZ13="","N/A",IF(INDEX(UnitCostGrid,MATCH(AZ13,PayItemKeys,0),$I$11)="",INDEX(UnitCostGrid,MATCH(AZ13,PayItemKeys,0),1),INDEX(UnitCostGrid,MATCH(AZ13,PayItemKeys,0),$I$11))) -> 4 | BD13: =BC13*BB13 -> 183532 | BF13: 1 | BG13: =IF(BH13="",0,VLOOKUP(BH13,CHOOSE({1,2},Table2[Pay Item Description],Table2[Pay Item No.]),2,0)) -> P-101-5.4a | BH13: =Pay_Items!D11 -> Spall Repair, Asphalt | BI13: =IF(BH13="","N/A",VLOOKUP(BH13,CHOOSE({1,2},Table2[Pay Item Description],Table2[Units]),2,0)) -> S.F. | BJ13: ='Maintenance Policies'!D28*($C$5*9) -> 5161.8375 | BK13: =IF(BH13="","N/A",IF(INDEX(UnitCostGrid,MATCH(BH13,PayItemKeys,0),$I$11)="",INDEX(UnitCostGrid,MATCH(BH13,PayItemKeys,0),1),INDEX(UnitCostGrid,MATCH(BH13,PayItemKeys,0),$I$11))) -> 8.5 | BL13: =BK13*BJ13 -> 43875.619
A14: 2 | B14: =IF(C14="","",VLOOKUP(C14,CHOOSE({1,2},Table2[Pay Item Description],Table2[Pay Item No.]),2,0)) | D14: =IF(C14="","N/A",VLOOKUP(C14,CHOOSE({1,2},Table2[Pay Item Description],Table2[Units]),2,0)) -> N/A | F14: =IF(C14="","N/A",IF(INDEX(UnitCostGrid,MATCH(C14,PayItemKeys,0),$I$11)="",INDEX(UnitCostGrid,MATCH(C14,PayItemKeys,0),1),INDEX(UnitCostGrid,MATCH(C14,PayItemKeys,0),$I$11))) -> N/A | G14: =IF(C14="",0,F14*E14) -> 0 | I14: =IF(C14="","",IF(INDEX(UnitCostGrid,MATCH(C14,PayItemKeys,0),$I$11)="",0,1)) | J14: 2 | K14: =IF(L14="",0,VLOOKUP(L14,CHOOSE({1,2},Table2[Pay Item Description],Table2[Pay Item No.]),2,0)) -> P-101-5.3 | L14: =Pay_Items!D10 -> Markings Removal | M14: =IF(L14="","N/A",VLOOKUP(L14,CHOOSE({1,2},Table2[Pay Item Description],Table2[Units]),2,0)) -> S.F. | N14: ='Maintenance Policies'!D10*$C$8 -> 12000 | O14: =IF(L14="","N/A",IF(INDEX(UnitCostGrid,MATCH(L14,PayItemKeys,0),$I$11)="",INDEX(UnitCostGrid,MATCH(L14,PayItemKeys,0),1),INDEX(UnitCostGrid,MATCH(L14,PayItemKeys,0),$I$11))) -> 0.77777778 | P14: =O14*N14 -> 9333.3333 | R14: 2 | S14: =IF(T14="",0,VLOOKUP(T14,CHOOSE({1,2},Table2[Pay Item Description],Table2[Pay Item No.]),2,0)) -> P-101-5.3 | T14: =Pay_Items!D10 -> Markings Removal | U14: =IF(T14="","N/A",VLOOKUP(T14,CHOOSE({1,2},Table2[Pay Item Description],Table2[Units]),2,0)) -> S.F. | V14: ='Maintenance Policies'!D12*$C$8 -> 12000 | W14: =IF(T14="","N/A",IF(INDEX(UnitCostGrid,MATCH(T14,PayItemKeys,0),$I$11)="",INDEX(UnitCostGrid,MATCH(T14,PayItemKeys,0),1),INDEX(UnitCostGrid,MATCH(T14,PayItemKeys,0),$I$11))) -> 0.77777778 | X14: =W14*V14 -> 9333.3333 | Z14: 2 | AA14: =IF(AB14="",0,VLOOKUP(AB14,CHOOSE({1,2},Table2[Pay Item Description],Table2[Pay Item No.]),2,0)) -> P-101-5.2a | AB14: =Pay_Items!D6 -> Crack Repair (Type I), Asphalt | AC14: =IF(AB14="","N/A",VLOOKUP(AB14,CHOOSE({1,2},Table2[Pay Item Description],Table2[Units]),2,0)) -> L.F. | AD14: ='Maintenance Policies'!D15*($C$5*9) -> 13420.778 | AE14: =IF(AB14="","N/A",IF(INDEX(UnitCostGrid,MATCH(AB14,PayItemKeys,0),$I$11)="",INDEX(UnitCostGrid,MATCH(AB14,PayItemKeys,0),1),INDEX(UnitCostGrid,MATCH(AB14,PayItemKeys,0),$I$11))) -> 4 | AF14: =AE14*AD14 -> 53683.11 | AH14: 2 | AI14: =IF(AJ14="",0,VLOOKUP(AJ14,CHOOSE({1,2},Table2[Pay Item Description],Table2[Pay Item No.]),2,0)) -> P-101-5.2a | AJ14: =Pay_Items!D6 -> Crack Repair (Type I), Asphalt | AK14: =IF(AJ14="","N/A",VLOOKUP(AJ14,CHOOSE({1,2},Table2[Pay Item Description],Table2[Units]),2,0)) -> L.F. | AL14: ='Maintenance Policies'!D19*($C$5*9) -> 14453.145 | AM14: =IF(AJ14="","N/A",IF(INDEX(UnitCostGrid,MATCH(AJ14,PayItemKeys,0),$I$11)="",INDEX(UnitCostGrid,MATCH(AJ14,PayItemKeys,0),1),INDEX(UnitCostGrid,MATCH(AJ14,PayItemKeys,0),$I$11))) -> 4 | AN14: =AM14*AL14 -> 57812.58 | AP14: 2 | AQ14: =IF(AR14="",0,VLOOKUP(AR14,CHOOSE({1,2},Table2[Pay Item Description],Table2[Pay Item No.]),2,0)) -> P-603-5.1 | AR14: =Pay_Items!D54 -> Emulsified Asphalt Tack Coat | AS14: =IF(AR14="","N/A",VLOOKUP(AR14,CHOOSE({1,2},Table2[Pay Item Description],Table2[Units]),2,0)) -> GAL | AT14: ='Maintenance Policies'!D22*$C$5*AQ9 -> 4588.3 | AU14: =IF(AR14="","N/A",IF(INDEX(UnitCostGrid,MATCH(AR14,PayItemKeys,0),$I$11)="",INDEX(UnitCostGrid,MATCH(AR14,PayItemKeys,0),1),INDEX(UnitCostGrid,MATCH(AR14,PayItemKeys,0),$I$11))) -> 4.5 | AV14: =AU14*AT14 -> 20647.35 | AX14: 2 | AY14: =IF(AZ14="",0,VLOOKUP(AZ14,CHOOSE({1,2},Table2[Pay Item Description],Table2[Pay Item No.]),2,0)) -> P-101-5.3 | AZ14: =Pay_Items!D10 -> Markings Removal | BA14: =IF(AZ14="","N/A",VLOOKUP(AZ14,CHOOSE({1,2},Table2[Pay Item Description],Table2[Units]),2,0)) -> S.F. | BB14: ='Maintenance Policies'!D26*$C$8 -> 12000 | BC14: =IF(AZ14="","N/A",IF(INDEX(UnitCostGrid,MATCH(AZ14,PayItemKeys,0),$I$11)="",INDEX(UnitCostGrid,MATCH(AZ14,PayItemKeys,0),1),INDEX(UnitCostGrid,MATCH(AZ14,PayItemKeys,0),$I$11))) -> 0.77777778 | BD14: =BC14*BB14 -> 9333.3333 | BF14: 2 | BG14: =IF(BH14="",0,VLOOKUP(BH14,CHOOSE({1,2},Table2[Pay Item Description],Table2[Pay Item No.]),2,0)) -> P-101-5.2a | BH14: =Pay_Items!D6 -> Crack Repair (Type I), Asphalt | BI14: =IF(BH14="","N/A",VLOOKUP(BH14,CHOOSE({1,2},Table2[Pay Item Description],Table2[Units]),2,0)) -> L.F. | BJ14: ='Maintenance Policies'!D29*($C$5*9) -> 16517.88 | BK14: =IF(BH14="","N/A",IF(INDEX(UnitCostGrid,MATCH(BH14,PayItemKeys,0),$I$11)="",INDEX(UnitCostGrid,MATCH(BH14,PayItemKeys,0),1),INDEX(UnitCostGrid,MATCH(BH14,PayItemKeys,0),$I$11))) -> 4 | BL14: =BK14*BJ14 -> 66071.52
A15: 3 | B15: =IF(C15="","",VLOOKUP(C15,CHOOSE({1,2},Table2[Pay Item Description],Table2[Pay Item No.]),2,0)) | D15: =IF(C15="","N/A",VLOOKUP(C15,CHOOSE({1,2},Table2[Pay Item Description],Table2[Units]),2,0)) -> N/A | F15: =IF(C15="","N/A",IF(INDEX(UnitCostGrid,MATCH(C15,PayItemKeys,0),$I$11)="",INDEX(UnitCostGrid,MATCH(C15,PayItemKeys,0),1),INDEX(UnitCostGrid,MATCH(C15,PayItemKeys,0),$I$11))) -> N/A | G15: =IF(C15="",0,F15*E15) -> 0 | I15: =IF(C15="","",IF(INDEX(UnitCostGrid,MATCH(C15,PayItemKeys,0),$I$11)="",0,1)) | J15: 3 | K15: =IF(L15="",0,VLOOKUP(L15,CHOOSE({1,2},Table2[Pay Item Description],Table2[Pay Item No.]),2,0)) -> P-620-5.1a | L15: =Pay_Items!D56 -> Markings (prep, markings, reflective media) | M15: =IF(L15="","N/A",VLOOKUP(L15,CHOOSE({1,2},Table2[Pay Item Description],Table2[Units]),2,0)) -> S.F. | N15: ='Maintenance Policies'!D11*$C$8 -> 12000 | O15: =IF(L15="","N/A",IF(INDEX(UnitCostGrid,MATCH(L15,PayItemKeys,0),$I$11)="",INDEX(UnitCostGrid,MATCH(L15,PayItemKeys,0),1),INDEX(UnitCostGrid,MATCH(L15,PayItemKeys,0),$I$11))) -> 0.66666667 | P15: =O15*N15 -> 8000 | R15: 3 | S15: =IF(T15="",0,VLOOKUP(T15,CHOOSE({1,2},Table2[Pay Item Description],Table2[Pay Item No.]),2,0)) -> P-620-5.1a | T15: =Pay_Items!D56 -> Markings (prep, markings, reflective media) | U15: =Pay_Items!E56 -> S.F. | V15: ='Maintenance Policies'!D13*$C$8 -> 12000 | W15: =IF(T15="","N/A",IF(INDEX(UnitCostGrid,MATCH(T15,PayItemKeys,0),$I$11)="",INDEX(UnitCostGrid,MATCH(T15,PayItemKeys,0),1),INDEX(UnitCostGrid,MATCH(T15,PayItemKeys,0),$I$11))) -> 0.66666667 | X15: =W15*V15 -> 8000 | Z15: 3 | AA15: =IF(AB15="",0,VLOOKUP(AB15,CHOOSE({1,2},Table2[Pay Item Description],Table2[Pay Item No.]),2,0)) -> P-608-8.1 | AB15: =C7 -> Emulsified Asphalt Surface Treatment | AC15: =IF(AB15="","N/A",VLOOKUP(AB15,CHOOSE({1,2},Table2[Pay Item Description],Table2[Units]),2,0)) -> S.Y. | AD15: ='Maintenance Policies'!D16*$C$5 -> 45883 | AE15: =IF(AB15="","N/A",IF(INDEX(UnitCostGrid,MATCH(AB15,PayItemKeys,0),$I$11)="",INDEX(UnitCostGrid,MATCH(AB15,PayItemKeys,0),1),INDEX(UnitCostGrid,MATCH(AB15,PayItemKeys,0),$I$11))) -> 4 | AF15: =AE15*AD15 -> 183532 | AH15: 3 | AI15: =IF(AJ15="",0,VLOOKUP(AJ15,CHOOSE({1,2},Table2[Pay Item Description],Table2[Pay Item No.]),2,0)) -> P-608-8.1 | AJ15: =C7 -> Emulsified Asphalt Surface Treatment | AK15: =IF(AJ15="","N/A",VLOOKUP(AJ15,CHOOSE({1,2},Table2[Pay Item Description],Table2[Units]),2,0)) -> S.Y. | AL15: ='Maintenance Policies'!D20*$C$5 -> 45883 | AM15: =IF(AJ15="","N/A",IF(INDEX(UnitCostGrid,MATCH(AJ15,PayItemKeys,0),$I$11)="",INDEX(UnitCostGrid,MATCH(AJ15,PayItemKeys,0),1),INDEX(UnitCostGrid,MATCH(AJ15,PayItemKeys,0),$I$11))) -> 4 | AN15: =AM15*AL15 -> 183532 | AP15: 3 | AQ15: =IF(AR15="",0,VLOOKUP(AR15,CHOOSE({1,2},Table2[Pay Item Description],Table2[Pay Item No.]),2,0)) -> P-401-8.1a | AR15: =Pay_Items!D37 -> Asphalt Surface Course | AS15: =IF(AR15="","N/A",VLOOKUP(AR15,CHOOSE({1,2},Table2[Pay Item Description],Table2[Units]),2,0)) -> TON | AT15: ='Maintenance Policies'!D22*$C$5*AQ6*AQ7/2000 -> 5505.96 | AU15: =IF(AR15="","N/A",IF(INDEX(UnitCostGrid,MATCH(AR15,PayItemKeys,0),$I$11)="",INDEX(UnitCostGrid,MATCH(AR15,PayItemKeys,0),1),INDEX(UnitCostGrid,MATCH(AR15,PayItemKeys,0),$I$11))) -> 130 | AV15: =AU15*AT15 -> 715774.8 | AX15: 3 | AY15: =IF(AZ15="",0,VLOOKUP(AZ15,CHOOSE({1,2},Table2[Pay Item Description],Table2[Pay Item No.]),2,0)) -> P-620-5.1a | AZ15: =Pay_Items!D56 -> Markings (prep, markings, reflective media) | BA15: =IF(AZ15="","N/A",VLOOKUP(AZ15,CHOOSE({1,2},Table2[Pay Item Description],Table2[Units]),2,0)) -> S.F. | BB15: ='Maintenance Policies'!D27*$C$8 -> 12000 | BC15: =IF(AZ15="","N/A",IF(INDEX(UnitCostGrid,MATCH(AZ15,PayItemKeys,0),$I$11)="",INDEX(UnitCostGrid,MATCH(AZ15,PayItemKeys,0),1),INDEX(UnitCostGrid,MATCH(AZ15,PayItemKeys,0),$I$11))) -> 0.66666667 | BD15: =BC15*BB15 -> 8000 | BF15: 3 | BG15: =IF(BH15="",0,VLOOKUP(BH15,CHOOSE({1,2},Table2[Pay Item Description],Table2[Pay Item No.]),2,0)) -> P-608-8.1 | BH15: =C7 -> Emulsified Asphalt Surface Treatment | BI15: =IF(BH15="","N/A",VLOOKUP(BH15,CHOOSE({1,2},Table2[Pay Item Description],Table2[Units]),2,0)) -> S.Y. | BJ15: ='Maintenance Policies'!D30*$C$5 -> 45883 | BK15: =IF(BH15="","N/A",IF(INDEX(UnitCostGrid,MATCH(BH15,PayItemKeys,0),$I$11)="",INDEX(UnitCostGrid,MATCH(BH15,PayItemKeys,0),1),INDEX(UnitCostGrid,MATCH(BH15,PayItemKeys,0),$I$11))) -> 4 | BL15: =BK15*BJ15 -> 183532
A16: 4 | B16: =IF(C16="","",VLOOKUP(C16,CHOOSE({1,2},Table2[Pay Item Description],Table2[Pay Item No.]),2,0)) | D16: =IF(C16="","N/A",VLOOKUP(C16,CHOOSE({1,2},Table2[Pay Item Description],Table2[Units]),2,0)) -> N/A | F16: =IF(C16="","N/A",IF(INDEX(UnitCostGrid,MATCH(C16,PayItemKeys,0),$I$11)="",INDEX(UnitCostGrid,MATCH(C16,PayItemKeys,0),1),INDEX(UnitCostGrid,MATCH(C16,PayItemKeys,0),$I$11))) -> N/A | G16: =IF(C16="",0,F16*E16) -> 0 | I16: =IF(C16="","",IF(INDEX(UnitCostGrid,MATCH(C16,PayItemKeys,0),$I$11)="",0,1)) | O16: Subtotal | P16: =SUM(P13:P15) -> 200865.33 | W16: Subtotal | X16: =SUM(X13:X15) -> 200865.33 | Z16: 4 | AA16: =IF(AB16="",0,VLOOKUP(AB16,CHOOSE({1,2},Table2[Pay Item Description],Table2[Pay Item No.]),2,0)) -> P-101-5.3 | AB16: =Pay_Items!D10 -> Markings Removal | AC16: =IF(AB16="","N/A",VLOOKUP(AB16,CHOOSE({1,2},Table2[Pay Item Description],Table2[Units]),2,0)) -> S.F. | AD16: ='Maintenance Policies'!D16*$C$8 -> 12000 | AE16: =IF(AB16="","N/A",IF(INDEX(UnitCostGrid,MATCH(AB16,PayItemKeys,0),$I$11)="",INDEX(UnitCostGrid,MATCH(AB16,PayItemKeys,0),1),INDEX(UnitCostGrid,MATCH(AB16,PayItemKeys,0),$I$11))) -> 0.77777778 | AF16: =AE16*AD16 -> 9333.3333 | AH16: 4 | AI16: =IF(AJ16="",0,VLOOKUP(AJ16,CHOOSE({1,2},Table2[Pay Item Description],Table2[Pay Item No.]),2,0)) -> P-101-5.3 | AJ16: =Pay_Items!D10 -> Markings Removal | AK16: =IF(AJ16="","N/A",VLOOKUP(AJ16,CHOOSE({1,2},Table2[Pay Item Description],Table2[Units]),2,0)) -> S.F. | AL16: ='Maintenance Policies'!D20*$C$8 -> 12000 | AM16: =IF(AJ16="","N/A",IF(INDEX(UnitCostGrid,MATCH(AJ16,PayItemKeys,0),$I$11)="",INDEX(UnitCostGrid,MATCH(AJ16,PayItemKeys,0),1),INDEX(UnitCostGrid,MATCH(AJ16,PayItemKeys,0),$I$11))) -> 0.77777778 | AN16: =AM16*AL16 -> 9333.3333 | AP16: 4 | AQ16: =IF(AR16="",0,VLOOKUP(AR16,CHOOSE({1,2},Table2[Pay Item Description],Table2[Pay Item No.]),2,0)) -> P-101-5.2a | AR16: =Pay_Items!D6 -> Crack Repair (Type I), Asphalt | AS16: =IF(AR16="","N/A",VLOOKUP(AR16,CHOOSE({1,2},Table2[Pay Item Description],Table2[Units]),2,0)) -> L.F. | AT16: ='Maintenance Policies'!D23*($C$5*9) -> 6194.205 | AU16: =IF(AR16="","N/A",IF(INDEX(UnitCostGrid,MATCH(AR16,PayItemKeys,0),$I$11)="",INDEX(UnitCostGrid,MATCH(AR16,PayItemKeys,0),1),INDEX(UnitCostGrid,MATCH(AR16,PayItemKeys,0),$I$11))) -> 4 | AV16: =AU16*AT16 -> 24776.82 | BC16: Subtotal | BD16: =SUM(BD13:BD15) -> 200865.33 | BF16: 4 | BG16: =IF(BH16="",0,VLOOKUP(BH16,CHOOSE({1,2},Table2[Pay Item Description],Table2[Pay Item No.]),2,0)) -> P-101-5.3 | BH16: =Pay_Items!D10 -> Markings Removal | BI16: =IF(BH16="","N/A",VLOOKUP(BH16,CHOOSE({1,2},Table2[Pay Item Description],Table2[Units]),2,0)) -> S.F. | BJ16: =C8 -> 12000 | BK16: =IF(BH16="","N/A",IF(INDEX(UnitCostGrid,MATCH(BH16,PayItemKeys,0),$I$11)="",INDEX(UnitCostGrid,MATCH(BH16,PayItemKeys,0),1),INDEX(UnitCostGrid,MATCH(BH16,PayItemKeys,0),$I$11))) -> 0.77777778 | BL16: =BK16*BJ16 -> 9333.3333
A17: 5 | B17: =IF(C17="","",VLOOKUP(C17,CHOOSE({1,2},Table2[Pay Item Description],Table2[Pay Item No.]),2,0)) | D17: =IF(C17="","N/A",VLOOKUP(C17,CHOOSE({1,2},Table2[Pay Item Description],Table2[Units]),2,0)) -> N/A | F17: =IF(C17="","N/A",IF(INDEX(UnitCostGrid,MATCH(C17,PayItemKeys,0),$I$11)="",INDEX(UnitCostGrid,MATCH(C17,PayItemKeys,0),1),INDEX(UnitCostGrid,MATCH(C17,PayItemKeys,0),$I$11))) -> N/A | G17: =IF(C17="",0,F17*E17) -> 0 | I17: =IF(C17="","",IF(INDEX(UnitCostGrid,MATCH(C17,PayItemKeys,0),$I$11)="",0,1)) | L17: Mobilization | P17: =('General Information'!$D$36/100)*P16 -> 20086.533 | T17: Mobilization | X17: =('General Information'!$D$36/100)*X16 -> 20086.533 | Z17: 5 | AA17: =IF(AB17="",0,VLOOKUP(AB17,CHOOSE({1,2},Table2[Pay Item Description],Table2[Pay Item No.]),2,0)) -> P-620-5.1a | AB17: =Pay_Items!D56 -> Markings (prep, markings, reflective media) | AC17: =IF(AB17="","N/A",VLOOKUP(AB17,CHOOSE({1,2},Table2[Pay Item Description],Table2[Units]),2,0)) -> S.F. | AD17: ='Maintenance Policies'!D17*$C$8 -> 12000 | AE17: =IF(AB17="","N/A",IF(INDEX(UnitCostGrid,MATCH(AB17,PayItemKeys,0),$I$11)="",INDEX(UnitCostGrid,MATCH(AB17,PayItemKeys,0),1),INDEX(UnitCostGrid,MATCH(AB17,PayItemKeys,0),$I$11))) -> 0.66666667 | AF17: =AE17*AD17 -> 8000 | AH17: 5 | AI17: =IF(AJ17="",0,VLOOKUP(AJ17,CHOOSE({1,2},Table2[Pay Item Description],Table2[Pay Item No.]),2,0)) -> P-620-5.1a | AJ17: =Pay_Items!D56 -> Markings (prep, markings, reflective media) | AK17: =IF(AJ17="","N/A",VLOOKUP(AJ17,CHOOSE({1,2},Table2[Pay Item Description],Table2[Units]),2,0)) -> S.F. | AL17: ='Maintenance Policies'!D21*$C$8 -> 12000 | AM17: =IF(AJ17="","N/A",IF(INDEX(UnitCostGrid,MATCH(AJ17,PayItemKeys,0),$I$11)="",INDEX(UnitCostGrid,MATCH(AJ17,PayItemKeys,0),1),INDEX(UnitCostGrid,MATCH(AJ17,PayItemKeys,0),$I$11))) -> 0.66666667 | AN17: =AM17*AL17 -> 8000 | AP17: 5 | AQ17: =IF(AR17="",0,VLOOKUP(AR17,CHOOSE({1,2},Table2[Pay Item Description],Table2[Pay Item No.]),2,0)) -> P-101-5.4a | AR17: =Pay_Items!D11 -> Spall Repair, Asphalt | AS17: =IF(AR17="","N/A",VLOOKUP(AR17,CHOOSE({1,2},Table2[Pay Item Description],Table2[Units]),2,0)) -> S.F. | AT17: ='Maintenance Policies'!D24*($C$5*9) -> 2064.735 | AU17: =IF(AR17="","N/A",IF(INDEX(UnitCostGrid,MATCH(AR17,PayItemKeys,0),$I$11)="",INDEX(UnitCostGrid,MATCH(AR17,PayItemKeys,0),1),INDEX(UnitCostGrid,MATCH(AR17,PayItemKeys,0),$I$11))) -> 8.5 | AV17: =AU17*AT17 -> 17550.248 | AZ17: Mobilization | BD17: =('General Information'!$D$36/100)*BD16 -> 20086.533 | BF17: 5 | BG17: =IF(BH17="",0,VLOOKUP(BH17,CHOOSE({1,2},Table2[Pay Item Description],Table2[Pay Item No.]),2,0)) -> P-620-5.1a | BH17: =Pay_Items!D56 -> Markings (prep, markings, reflective media) | BI17: =IF(BH17="","N/A",VLOOKUP(BH17,CHOOSE({1,2},Table2[Pay Item Description],Table2[Units]),2,0)) -> S.F. | BJ17: ='Maintenance Policies'!D31*$C$8 -> 12000 | BK17: =IF(BH17="","N/A",IF(INDEX(UnitCostGrid,MATCH(BH17,PayItemKeys,0),$I$11)="",INDEX(UnitCostGrid,MATCH(BH17,PayItemKeys,0),1),INDEX(UnitCostGrid,MATCH(BH17,PayItemKeys,0),$I$11))) -> 0.66666667 | BL17: =BK17*BJ17 -> 8000
A18: 6 | B18: =IF(C18="","",VLOOKUP(C18,CHOOSE({1,2},Table2[Pay Item Description],Table2[Pay Item No.]),2,0)) | D18: =IF(C18="","N/A",VLOOKUP(C18,CHOOSE({1,2},Table2[Pay Item Description],Table2[Units]),2,0)) -> N/A | F18: =IF(C18="","N/A",IF(INDEX(UnitCostGrid,MATCH(C18,PayItemKeys,0),$I$11)="",INDEX(UnitCostGrid,MATCH(C18,PayItemKeys,0),1),INDEX(UnitCostGrid,MATCH(C18,PayItemKeys,0),$I$11))) -> N/A | G18: =IF(C18="",0,F18*E18) -> 0 | I18: =IF(C18="","",IF(INDEX(UnitCostGrid,MATCH(C18,PayItemKeys,0),$I$11)="",0,1)) | L18: Engineering | P18: =('General Information'!$D$37/100)*P16 -> 10043.267 | T18: Engineering | X18: =('General Information'!$D$37/100)*X16 -> 10043.267 | AE18: Subtotal | AF18: =SUM(AF13:AF17) -> 280873.81 | AM18: Subtotal | AN18: =SUM(AN13:AN17) -> 293778.41 | AP18: 6 | AQ18: =IF(AR18="",0,VLOOKUP(AR18,CHOOSE({1,2},Table2[Pay Item Description],Table2[Pay Item No.]),2,0)) -> P-620-5.1a | AR18: =Pay_Items!D56 -> Markings (prep, markings, reflective media) | AS18: =IF(AR18="","N/A",VLOOKUP(AR18,CHOOSE({1,2},Table2[Pay Item Description],Table2[Units]),2,0)) -> S.F. | AT18: ='Maintenance Policies'!D25*$C$8 -> 12000 | AU18: =IF(AR18="","N/A",IF(INDEX(UnitCostGrid,MATCH(AR18,PayItemKeys,0),$I$11)="",INDEX(UnitCostGrid,MATCH(AR18,PayItemKeys,0),1),INDEX(UnitCostGrid,MATCH(AR18,PayItemKeys,0),$I$11))) -> 0.66666667 | AV18: =AU18*AT18 -> 8000 | AZ18: Engineering | BD18: =('General Information'!$D$37/100)*BD16 -> 10043.267 | BK18: Subtotal | BL18: =SUM(BL13:BL17) -> 310812.47
A19: 7 | B19: =IF(C19="","",VLOOKUP(C19,CHOOSE({1,2},Table2[Pay Item Description],Table2[Pay Item No.]),2,0)) | D19: =IF(C19="","N/A",VLOOKUP(C19,CHOOSE({1,2},Table2[Pay Item Description],Table2[Units]),2,0)) -> N/A | F19: =IF(C19="","N/A",IF(INDEX(UnitCostGrid,MATCH(C19,PayItemKeys,0),$I$11)="",INDEX(UnitCostGrid,MATCH(C19,PayItemKeys,0),1),INDEX(UnitCostGrid,MATCH(C19,PayItemKeys,0),$I$11))) -> N/A | G19: =IF(C19="",0,F19*E19) -> 0 | I19: =IF(C19="","",IF(INDEX(UnitCostGrid,MATCH(C19,PayItemKeys,0),$I$11)="",0,1)) | O19: Total | P19: =SUM(P16:P18) -> 230995.13 | W19: Total | X19: =SUM(X16:X18) -> 230995.13 | AB19: Mobilization | AF19: =('General Information'!$D$36/100)*AF18 -> 28087.381 | AJ19: Mobilization | AN19: =('General Information'!$D$36/100)*AN18 -> 29377.841 | AU19: Subtotal | AV19: =SUM(AV13:AV18) -> 1016164.2 | BC19: Total | BD19: =SUM(BD16:BD18) -> 230995.13 | BH19: Mobilization | BL19: =('General Information'!$D$36/100)*BL18 -> 31081.247
A20: 8 | B20: =IF(C20="","",VLOOKUP(C20,CHOOSE({1,2},Table2[Pay Item Description],Table2[Pay Item No.]),2,0)) | D20: =IF(C20="","N/A",VLOOKUP(C20,CHOOSE({1,2},Table2[Pay Item Description],Table2[Units]),2,0)) -> N/A | F20: =IF(C20="","N/A",IF(INDEX(UnitCostGrid,MATCH(C20,PayItemKeys,0),$I$11)="",INDEX(UnitCostGrid,MATCH(C20,PayItemKeys,0),1),INDEX(UnitCostGrid,MATCH(C20,PayItemKeys,0),$I$11))) -> N/A | G20: =IF(C20="",0,F20*E20) -> 0 | I20: =IF(C20="","",IF(INDEX(UnitCostGrid,MATCH(C20,PayItemKeys,0),$I$11)="",0,1)) | AB20: Engineering | AF20: =('General Information'!$D$37/100)*AF18 -> 14043.691 | AJ20: Engineering | AN20: =('General Information'!$D$37/100)*AN18 -> 14688.92 | AR20: Mobilization | AV20: =('General Information'!$D$36/100)*AV19 -> 101616.42 | BH20: Engineering | BL20: =('General Information'!$D$37/100)*BL18 -> 15540.624
A21: 9 | B21: =IF(C21="","",VLOOKUP(C21,CHOOSE({1,2},Table2[Pay Item Description],Table2[Pay Item No.]),2,0)) | D21: =IF(C21="","N/A",VLOOKUP(C21,CHOOSE({1,2},Table2[Pay Item Description],Table2[Units]),2,0)) -> N/A | F21: =IF(C21="","N/A",IF(INDEX(UnitCostGrid,MATCH(C21,PayItemKeys,0),$I$11)="",INDEX(UnitCostGrid,MATCH(C21,PayItemKeys,0),1),INDEX(UnitCostGrid,MATCH(C21,PayItemKeys,0),$I$11))) -> N/A | G21: =IF(C21="",0,F21*E21) -> 0 | I21: =IF(C21="","",IF(INDEX(UnitCostGrid,MATCH(C21,PayItemKeys,0),$I$11)="",0,1)) | AE21: Total | AF21: =SUM(AF18:AF20) -> 323004.89 | AM21: Total | AN21: =SUM(AN18:AN20) -> 337845.17 | AR21: Engineering | AV21: =('General Information'!$D$37/100)*AV19 -> 50808.211 | BK21: Total | BL21: =SUM(BL18:BL20) -> 357434.34
A22: 10 | B22: =IF(C22="","",VLOOKUP(C22,CHOOSE({1,2},Table2[Pay Item Description],Table2[Pay Item No.]),2,0)) | D22: =IF(C22="","N/A",VLOOKUP(C22,CHOOSE({1,2},Table2[Pay Item Description],Table2[Units]),2,0)) -> N/A | F22: =IF(C22="","N/A",IF(INDEX(UnitCostGrid,MATCH(C22,PayItemKeys,0),$I$11)="",INDEX(UnitCostGrid,MATCH(C22,PayItemKeys,0),1),INDEX(UnitCostGrid,MATCH(C22,PayItemKeys,0),$I$11))) -> N/A | G22: =IF(C22="",0,F22*E22) -> 0 | I22: =IF(C22="","",IF(INDEX(UnitCostGrid,MATCH(C22,PayItemKeys,0),$I$11)="",0,1)) | AU22: Total | AV22: =SUM(AV19:AV21) -> 1168588.9
A24: Subtotal | G24: =SUM(G13:G22) -> 0
B25: Mobilization | G25: =('General Information'!$D$36/100)*G24 -> 0
B26: Engineering | G26: =('General Information'!$D$37/100)*G24 -> 0
A27: Total | G27: =SUM(G24:G26) -> 0
A32: Net Present Worth
A33: HMA Reconstruction - Alternative 1 | I33: Hidden
B35: Item | C35: Year Applied | D35: Actual Cost | E35: Discounted Cost
B36: Initial Construction | C36: =C6 -> 2028 | D36: =G27 -> 0 | E36: =D36 -> 0 | K36: Year | L36: Actual | M36: Discounted
B37: Maintenance 1 | C37: ='Maintenance Policies'!E10 -> 4 | D37: =P19 -> 230995.13 | E37: =IF(C37>'General Information'!$D$33,0,D37/(1+('General Information'!$D$34/100))^C37) -> 205236.18 | K37: =C6 -> 2028 | L37: =IF(K37-$C$6>'General Information'!$D$33,0,IF(K37=$C$6,$D$36,0)+SUMIF($C$37:$C$44,K37-$C$6,$D$37:$D$44)) -> 0 | M37: =IF(K37-$C$6>'General Information'!$D$33,0,IF(K37=$C$6,$E$36,0)+SUMIF($C$37:$C$44,K37-$C$6,$E$37:$E$44)) -> 0
B38: Maintenance 2 | C38: ='Maintenance Policies'!E12 -> 8 | D38: =X19 -> 230995.13 | E38: =IF(C38>'General Information'!$D$33,0,D38/(1+('General Information'!$D$34/100))^C38) -> 182349.69 | K38: =K37+1 -> 2029 | L38: =IF(K38-$C$6>'General Information'!$D$33,0,IF(K38=$C$6,$D$36,0)+SUMIF($C$37:$C$44,K38-$C$6,$D$37:$D$44)) -> 0 | M38: =IF(K38-$C$6>'General Information'!$D$33,0,IF(K38=$C$6,$E$36,0)+SUMIF($C$37:$C$44,K38-$C$6,$E$37:$E$44)) -> 0
B39: Maintenance 3 | C39: ='Maintenance Policies'!E14 -> 12 | D39: =AF21 -> 323004.89 | E39: =IF(C39>'General Information'!$D$33,0,D39/(1+('General Information'!$D$34/100))^C39) -> 226549.13 | K39: =K38+1 -> 2030 | L39: =IF(K39-$C$6>'General Information'!$D$33,0,IF(K39=$C$6,$D$36,0)+SUMIF($C$37:$C$44,K39-$C$6,$D$37:$D$44)) -> 0 | M39: =IF(K39-$C$6>'General Information'!$D$33,0,IF(K39=$C$6,$E$36,0)+SUMIF($C$37:$C$44,K39-$C$6,$E$37:$E$44)) -> 0
B40: Maintenance 4 | C40: ='Maintenance Policies'!E18 -> 16 | D40: =AN21 -> 337845.17 | E40: =IF(C40>'General Information'!$D$33,0,D40/(1+('General Information'!$D$34/100))^C40) -> 210533.94 | K40: =K39+1 -> 2031 | L40: =IF(K40-$C$6>'General Information'!$D$33,0,IF(K40=$C$6,$D$36,0)+SUMIF($C$37:$C$44,K40-$C$6,$D$37:$D$44)) -> 0 | M40: =IF(K40-$C$6>'General Information'!$D$33,0,IF(K40=$C$6,$E$36,0)+SUMIF($C$37:$C$44,K40-$C$6,$E$37:$E$44)) -> 0
B41: Rehabilitation 1 | C41: ='Maintenance Policies'!E22 -> 20 | D41: =AV22 -> 1168588.9 | E41: =IF(C41>'General Information'!$D$33,0,D41/(1+('General Information'!$D$34/100))^C41) -> 647019.31 | K41: =K40+1 -> 2032 | L41: =IF(K41-$C$6>'General Information'!$D$33,0,IF(K41=$C$6,$D$36,0)+SUMIF($C$37:$C$44,K41-$C$6,$D$37:$D$44)) -> 230995.13 | M41: =IF(K41-$C$6>'General Information'!$D$33,0,IF(K41=$C$6,$E$36,0)+SUMIF($C$37:$C$44,K41-$C$6,$E$37:$E$44)) -> 205236.18
B42: Maintenance 5 | C42: ='Maintenance Policies'!E26 -> 24 | D42: =BD19 -> 230995.13 | E42: =IF(C42>'General Information'!$D$33,0,D42/(1+('General Information'!$D$34/100))^C42) -> 113634.3 | K42: =K41+1 -> 2033 | L42: =IF(K42-$C$6>'General Information'!$D$33,0,IF(K42=$C$6,$D$36,0)+SUMIF($C$37:$C$44,K42-$C$6,$D$37:$D$44)) -> 0 | M42: =IF(K42-$C$6>'General Information'!$D$33,0,IF(K42=$C$6,$E$36,0)+SUMIF($C$37:$C$44,K42-$C$6,$E$37:$E$44)) -> 0
B43: Maintenance 6 | C43: ='Maintenance Policies'!E28 -> 28 | D43: =BL21 -> 357434.34 | E43: =IF(C43>'General Information'!$D$33,0,D43/(1+('General Information'!$D$34/100))^C43) -> 156226.24 | K43: =K42+1 -> 2034 | L43: =IF(K43-$C$6>'General Information'!$D$33,0,IF(K43=$C$6,$D$36,0)+SUMIF($C$37:$C$44,K43-$C$6,$D$37:$D$44)) -> 0 | M43: =IF(K43-$C$6>'General Information'!$D$33,0,IF(K43=$C$6,$E$36,0)+SUMIF($C$37:$C$44,K43-$C$6,$E$37:$E$44)) -> 0
B44: Salvage | C44: ='General Information'!D33 -> 30 | D44: =-'Maintenance Policies'!D32*AV22 -> -438220.82 | E44: =IF(C44>'General Information'!$D$33,0,D44/(1+('General Information'!$D$34/100))^C44) -> -180541.18 | K44: =K43+1 -> 2035 | L44: =IF(K44-$C$6>'General Information'!$D$33,0,IF(K44=$C$6,$D$36,0)+SUMIF($C$37:$C$44,K44-$C$6,$D$37:$D$44)) -> 0 | M44: =IF(K44-$C$6>'General Information'!$D$33,0,IF(K44=$C$6,$E$36,0)+SUMIF($C$37:$C$44,K44-$C$6,$E$37:$E$44)) -> 0
B45: Net Present Worth | E45: =SUM(E36:E44) -> 1561007.6 | K45: =K44+1 -> 2036 | L45: =IF(K45-$C$6>'General Information'!$D$33,0,IF(K45=$C$6,$D$36,0)+SUMIF($C$37:$C$44,K45-$C$6,$D$37:$D$44)) -> 230995.13 | M45: =IF(K45-$C$6>'General Information'!$D$33,0,IF(K45=$C$6,$E$36,0)+SUMIF($C$37:$C$44,K45-$C$6,$E$37:$E$44)) -> 182349.69
K46: =K45+1 -> 2037 | L46: =IF(K46-$C$6>'General Information'!$D$33,0,IF(K46=$C$6,$D$36,0)+SUMIF($C$37:$C$44,K46-$C$6,$D$37:$D$44)) -> 0 | M46: =IF(K46-$C$6>'General Information'!$D$33,0,IF(K46=$C$6,$E$36,0)+SUMIF($C$37:$C$44,K46-$C$6,$E$37:$E$44)) -> 0
K47: =K46+1 -> 2038 | L47: =IF(K47-$C$6>'General Information'!$D$33,0,IF(K47=$C$6,$D$36,0)+SUMIF($C$37:$C$44,K47-$C$6,$D$37:$D$44)) -> 0 | M47: =IF(K47-$C$6>'General Information'!$D$33,0,IF(K47=$C$6,$E$36,0)+SUMIF($C$37:$C$44,K47-$C$6,$E$37:$E$44)) -> 0
K48: =K47+1 -> 2039 | L48: =IF(K48-$C$6>'General Information'!$D$33,0,IF(K48=$C$6,$D$36,0)+SUMIF($C$37:$C$44,K48-$C$6,$D$37:$D$44)) -> 0 | M48: =IF(K48-$C$6>'General Information'!$D$33,0,IF(K48=$C$6,$E$36,0)+SUMIF($C$37:$C$44,K48-$C$6,$E$37:$E$44)) -> 0
K49: =K48+1 -> 2040 | L49: =IF(K49-$C$6>'General Information'!$D$33,0,IF(K49=$C$6,$D$36,0)+SUMIF($C$37:$C$44,K49-$C$6,$D$37:$D$44)) -> 323004.89 | M49: =IF(K49-$C$6>'General Information'!$D$33,0,IF(K49=$C$6,$E$36,0)+SUMIF($C$37:$C$44,K49-$C$6,$E$37:$E$44)) -> 226549.13
K50: =K49+1 -> 2041 | L50: =IF(K50-$C$6>'General Information'!$D$33,0,IF(K50=$C$6,$D$36,0)+SUMIF($C$37:$C$44,K50-$C$6,$D$37:$D$44)) -> 0 | M50: =IF(K50-$C$6>'General Information'!$D$33,0,IF(K50=$C$6,$E$36,0)+SUMIF($C$37:$C$44,K50-$C$6,$E$37:$E$44)) -> 0
K51: =K50+1 -> 2042 | L51: =IF(K51-$C$6>'General Information'!$D$33,0,IF(K51=$C$6,$D$36,0)+SUMIF($C$37:$C$44,K51-$C$6,$D$37:$D$44)) -> 0 | M51: =IF(K51-$C$6>'General Information'!$D$33,0,IF(K51=$C$6,$E$36,0)+SUMIF($C$37:$C$44,K51-$C$6,$E$37:$E$44)) -> 0
K52: =K51+1 -> 2043 | L52: =IF(K52-$C$6>'General Information'!$D$33,0,IF(K52=$C$6,$D$36,0)+SUMIF($C$37:$C$44,K52-$C$6,$D$37:$D$44)) -> 0 | M52: =IF(K52-$C$6>'General Information'!$D$33,0,IF(K52=$C$6,$E$36,0)+SUMIF($C$37:$C$44,K52-$C$6,$E$37:$E$44)) -> 0
K53: =K52+1 -> 2044 | L53: =IF(K53-$C$6>'General Information'!$D$33,0,IF(K53=$C$6,$D$36,0)+SUMIF($C$37:$C$44,K53-$C$6,$D$37:$D$44)) -> 337845.17 | M53: =IF(K53-$C$6>'General Information'!$D$33,0,IF(K53=$C$6,$E$36,0)+SUMIF($C$37:$C$44,K53-$C$6,$E$37:$E$44)) -> 210533.94
K54: =K53+1 -> 2045 | L54: =IF(K54-$C$6>'General Information'!$D$33,0,IF(K54=$C$6,$D$36,0)+SUMIF($C$37:$C$44,K54-$C$6,$D$37:$D$44)) -> 0 | M54: =IF(K54-$C$6>'General Information'!$D$33,0,IF(K54=$C$6,$E$36,0)+SUMIF($C$37:$C$44,K54-$C$6,$E$37:$E$44)) -> 0
K55: =K54+1 -> 2046 | L55: =IF(K55-$C$6>'General Information'!$D$33,0,IF(K55=$C$6,$D$36,0)+SUMIF($C$37:$C$44,K55-$C$6,$D$37:$D$44)) -> 0 | M55: =IF(K55-$C$6>'General Information'!$D$33,0,IF(K55=$C$6,$E$36,0)+SUMIF($C$37:$C$44,K55-$C$6,$E$37:$E$44)) -> 0
K56: =K55+1 -> 2047 | L56: =IF(K56-$C$6>'General Information'!$D$33,0,IF(K56=$C$6,$D$36,0)+SUMIF($C$37:$C$44,K56-$C$6,$D$37:$D$44)) -> 0 | M56: =IF(K56-$C$6>'General Information'!$D$33,0,IF(K56=$C$6,$E$36,0)+SUMIF($C$37:$C$44,K56-$C$6,$E$37:$E$44)) -> 0
K57: =K56+1 -> 2048 | L57: =IF(K57-$C$6>'General Information'!$D$33,0,IF(K57=$C$6,$D$36,0)+SUMIF($C$37:$C$44,K57-$C$6,$D$37:$D$44)) -> 1168588.9 | M57: =IF(K57-$C$6>'General Information'!$D$33,0,IF(K57=$C$6,$E$36,0)+SUMIF($C$37:$C$44,K57-$C$6,$E$37:$E$44)) -> 647019.31
... K67: =K66+1 -> 2058 | L67: =IF(K67-$C$6>'General Information'!$D$33,0,IF(K67=$C$6,$D$36,0)+SUMIF($C$37:$C$44,K67-$C$6,$D$37:$D$44)) -> -438220.82 | M67: =IF(K67-$C$6>'General Information'!$D$33,0,IF(K67=$C$6,$E$36,0)+SUMIF($C$37:$C$44,K67-$C$6,$E$37:$E$44)) -> -180541.18

Sheet TMP(NewPCC)
A1: =HYPERLINK("#'General Information'!D9","◄ General Information") -> ◄ General Information | C1: =HYPERLINK("#Summary!G1","Summary") -> Summary | D1: =$A$34 -> PCC Reconstruction - Alternative 2 | I1: Hidden
A2: Initial Construction Costs: | J2: Maintenance 1 | R2: Rehabilitation 1
A3: STEP 4 of 5 · The quantities for this alternative. Grey cells are yours: C4 to C7 project data (filled from General Information), F4 and F5 closure days, C13 to C22 pay items and E13 to E22 quantities. Everything else calculates. Unit costs come from Pay_Items, and C11 picks which division they are priced from.
A4: Pavement Type: | C4: New PCC
A5: Mainline Pavement Area: | C5: ='General Information'!D26 -> 45883 | D5: S.Y.
A6: Initial Construction Year: | C6: ='General Information'!D25 -> 2028
A7: Markings Area: | C7: ='General Information'!D28 -> 12000 | D7: S.F. | J7: No. of Slabs: | K7: =C5/((12.5*12.5)/9) -> 2642.8608
J8: Joint length: | K8: =K7*25+((K7/8)*12.5) -> 70200.99
I10: Price column: 1 Regular, 2 Middle, 3 West, 4 East
B11: Price from: | C11: Regular | D11: =IF(OR($C$11="Regular",$C$11=""),"Regular is the statewide Unit Cost column on Pay_Items.","Prices from the "&$C$11&" column on Pay_Items: "&SUM($I$13:$I$22)&" of "&COUNT($I$13:$I$22)&" pay items used here have a "&$C$11&" cost, the rest fall back to Unit Cost.") -> Regular is the statewide Unit Cost column on Pay_Items. | I11: =IFERROR(MATCH($C$11,PriceSources,0),1) -> 1
A12: Item No. | B12: Pay Item | C12: Description | D12: Unit | E12: Qty | F12: Unit Cost | G12: Item Cost | J12: Item No. | K12: Pay Item | L12: Description | M12: Unit | N12: Qty | O12: Unit Cost | P12: Item Cost | R12: Item No. | S12: Pay Item | T12: Description | U12: Unit | V12: Qty | W12: Unit Cost | X12: Item Cost
A13: 1 | B13: =IF(C13="","",VLOOKUP(C13,CHOOSE({1,2},Table2[Pay Item Description],Table2[Pay Item No.]),2,0)) | D13: =IF(C13="","N/A",VLOOKUP(C13,CHOOSE({1,2},Table2[Pay Item Description],Table2[Units]),2,0)) -> N/A | F13: =IF(C13="","N/A",IF(INDEX(UnitCostGrid,MATCH(C13,PayItemKeys,0),$I$11)="",INDEX(UnitCostGrid,MATCH(C13,PayItemKeys,0),1),INDEX(UnitCostGrid,MATCH(C13,PayItemKeys,0),$I$11))) -> N/A | G13: =IF(C13="",0,F13*E13) -> 0 | I13: =IF(C13="","",IF(INDEX(UnitCostGrid,MATCH(C13,PayItemKeys,0),$I$11)="",0,1)) | J13: 1 | K13: =IF(L13="",0,VLOOKUP(L13,CHOOSE({1,2},Table2[Pay Item Description],Table2[Pay Item No.]),2,0)) -> P-605-5.1a | L13: =Pay_Items!D55 -> Joint Clean and Reseal, Concrete | M13: =IF(L13="","N/A",VLOOKUP(L13,CHOOSE({1,2},Table2[Pay Item Description],Table2[Units]),2,0)) -> L.F. | N13: =K8*'Maintenance Policies'!D37 -> 70200.99 | O13: =IF(L13="","N/A",IF(INDEX(UnitCostGrid,MATCH(L13,PayItemKeys,0),$I$11)="",INDEX(UnitCostGrid,MATCH(L13,PayItemKeys,0),1),INDEX(UnitCostGrid,MATCH(L13,PayItemKeys,0),$I$11))) -> 7 | P13: =O13*N13 -> 491406.93 | R13: 1 | S13: =IF(T13="",0,VLOOKUP(T13,CHOOSE({1,2},Table2[Pay Item Description],Table2[Pay Item No.]),2,0)) -> P-101-5.5c | T13: =Pay_Items!D15 -> Slab Replacement, Concrete | U13: =IF(T13="","N/A",VLOOKUP(T13,CHOOSE({1,2},Table2[Pay Item Description],Table2[Units]),2,0)) -> S.Y. | V13: ='Maintenance Policies'!D41*C5 -> 917.66 | W13: =IF(T13="","N/A",IF(INDEX(UnitCostGrid,MATCH(T13,PayItemKeys,0),$I$11)="",INDEX(UnitCostGrid,MATCH(T13,PayItemKeys,0),1),INDEX(UnitCostGrid,MATCH(T13,PayItemKeys,0),$I$11))) -> 100 | X13: =W13*V13 -> 91766
A14: 2 | B14: =IF(C14="","",VLOOKUP(C14,CHOOSE({1,2},Table2[Pay Item Description],Table2[Pay Item No.]),2,0)) | D14: =IF(C14="","N/A",VLOOKUP(C14,CHOOSE({1,2},Table2[Pay Item Description],Table2[Units]),2,0)) -> N/A | F14: =IF(C14="","N/A",IF(INDEX(UnitCostGrid,MATCH(C14,PayItemKeys,0),$I$11)="",INDEX(UnitCostGrid,MATCH(C14,PayItemKeys,0),1),INDEX(UnitCostGrid,MATCH(C14,PayItemKeys,0),$I$11))) -> N/A | G14: =IF(C14="",0,F14*E14) -> 0 | I14: =IF(C14="","",IF(INDEX(UnitCostGrid,MATCH(C14,PayItemKeys,0),$I$11)="",0,1)) | J14: 2 | K14: =VLOOKUP(L14,CHOOSE({1,2},Table2[Pay Item Description],Table2[Pay Item No.]),2,0) -> P-101-5.2c | L14: =Pay_Items!D8 -> Crack Seal, Concrete | M14: =IF(L14="","N/A",VLOOKUP(L14,CHOOSE({1,2},Table2[Pay Item Description],Table2[Units]),2,0)) -> L.F. | N14: ='Maintenance Policies'!D38*(C5*9) -> 1032.3675 | O14: =IF(L14="","N/A",IF(INDEX(UnitCostGrid,MATCH(L14,PayItemKeys,0),$I$11)="",INDEX(UnitCostGrid,MATCH(L14,PayItemKeys,0),1),INDEX(UnitCostGrid,MATCH(L14,PayItemKeys,0),$I$11))) -> 8 | P14: =O14*N14 -> 8258.94 | R14: 2 | S14: =VLOOKUP(T14,CHOOSE({1,2},Table2[Pay Item Description],Table2[Pay Item No.]),2,0) -> P-101-5.5b | T14: =Pay_Items!D14 -> Full-Depth Repair, Concrete | U14: =IF(T14="","N/A",VLOOKUP(T14,CHOOSE({1,2},Table2[Pay Item Description],Table2[Units]),2,0)) -> S.Y. | V14: ='Maintenance Policies'!D42*C5 -> 137.649 | W14: =IF(T14="","N/A",IF(INDEX(UnitCostGrid,MATCH(T14,PayItemKeys,0),$I$11)="",INDEX(UnitCostGrid,MATCH(T14,PayItemKeys,0),1),INDEX(UnitCostGrid,MATCH(T14,PayItemKeys,0),$I$11))) -> 120 | X14: =W14*V14 -> 16517.88
A15: 3 | B15: =IF(C15="","",VLOOKUP(C15,CHOOSE({1,2},Table2[Pay Item Description],Table2[Pay Item No.]),2,0)) | D15: =IF(C15="","N/A",VLOOKUP(C15,CHOOSE({1,2},Table2[Pay Item Description],Table2[Units]),2,0)) -> N/A | F15: =IF(C15="","N/A",IF(INDEX(UnitCostGrid,MATCH(C15,PayItemKeys,0),$I$11)="",INDEX(UnitCostGrid,MATCH(C15,PayItemKeys,0),1),INDEX(UnitCostGrid,MATCH(C15,PayItemKeys,0),$I$11))) -> N/A | G15: =IF(C15="",0,F15*E15) -> 0 | I15: =IF(C15="","",IF(INDEX(UnitCostGrid,MATCH(C15,PayItemKeys,0),$I$11)="",0,1)) | J15: 3 | K15: =VLOOKUP(L15,CHOOSE({1,2},Table2[Pay Item Description],Table2[Pay Item No.]),2,0) -> P-101-5.5a | L15: =Pay_Items!D13 -> Spall Repair, Concrete | M15: =IF(L15="","N/A",VLOOKUP(L15,CHOOSE({1,2},Table2[Pay Item Description],Table2[Units]),2,0)) -> S.F. | N15: ='Maintenance Policies'!D39*(C5*9) -> 536.8311 | O15: =IF(L15="","N/A",IF(INDEX(UnitCostGrid,MATCH(L15,PayItemKeys,0),$I$11)="",INDEX(UnitCostGrid,MATCH(L15,PayItemKeys,0),1),INDEX(UnitCostGrid,MATCH(L15,PayItemKeys,0),$I$11))) -> 60 | P15: =O15*N15 -> 32209.866 | R15: 3 | S15: =VLOOKUP(T15,CHOOSE({1,2},Table2[Pay Item Description],Table2[Pay Item No.]),2,0) -> P-101-5.5a | T15: =Pay_Items!D13 -> Spall Repair, Concrete | U15: =IF(T15="","N/A",VLOOKUP(T15,CHOOSE({1,2},Table2[Pay Item Description],Table2[Units]),2,0)) -> S.F. | V15: ='Maintenance Policies'!D43*(C5*9) -> 536.8311 | W15: =IF(T15="","N/A",IF(INDEX(UnitCostGrid,MATCH(T15,PayItemKeys,0),$I$11)="",INDEX(UnitCostGrid,MATCH(T15,PayItemKeys,0),1),INDEX(UnitCostGrid,MATCH(T15,PayItemKeys,0),$I$11))) -> 60 | X15: =W15*V15 -> 32209.866
A16: 4 | B16: =IF(C16="","",VLOOKUP(C16,CHOOSE({1,2},Table2[Pay Item Description],Table2[Pay Item No.]),2,0)) | D16: =IF(C16="","N/A",VLOOKUP(C16,CHOOSE({1,2},Table2[Pay Item Description],Table2[Units]),2,0)) -> N/A | F16: =IF(C16="","N/A",IF(INDEX(UnitCostGrid,MATCH(C16,PayItemKeys,0),$I$11)="",INDEX(UnitCostGrid,MATCH(C16,PayItemKeys,0),1),INDEX(UnitCostGrid,MATCH(C16,PayItemKeys,0),$I$11))) -> N/A | G16: =IF(C16="",0,F16*E16) -> 0 | I16: =IF(C16="","",IF(INDEX(UnitCostGrid,MATCH(C16,PayItemKeys,0),$I$11)="",0,1)) | J16: 4 | K16: =VLOOKUP(L16,CHOOSE({1,2},Table2[Pay Item Description],Table2[Pay Item No.]),2,0) -> P-101-5.5b | L16: =Pay_Items!D14 -> Full-Depth Repair, Concrete | M16: =IF(L16="","N/A",VLOOKUP(L16,CHOOSE({1,2},Table2[Pay Item Description],Table2[Units]),2,0)) -> S.Y. | N16: ='Maintenance Policies'!D40*C5 -> 137.649 | O16: =IF(L16="","N/A",IF(INDEX(UnitCostGrid,MATCH(L16,PayItemKeys,0),$I$11)="",INDEX(UnitCostGrid,MATCH(L16,PayItemKeys,0),1),INDEX(UnitCostGrid,MATCH(L16,PayItemKeys,0),$I$11))) -> 120 | P16: =O16*N16 -> 16517.88 | R16: 4 | S16: =VLOOKUP(T16,CHOOSE({1,2},Table2[Pay Item Description],Table2[Pay Item No.]),2,0) -> P-101-5.2c | T16: =Pay_Items!D8 -> Crack Seal, Concrete | U16: =IF(T16="","N/A",VLOOKUP(T16,CHOOSE({1,2},Table2[Pay Item Description],Table2[Units]),2,0)) -> L.F. | V16: ='Maintenance Policies'!D44*(C5*9) -> 1238.841 | W16: =IF(T16="","N/A",IF(INDEX(UnitCostGrid,MATCH(T16,PayItemKeys,0),$I$11)="",INDEX(UnitCostGrid,MATCH(T16,PayItemKeys,0),1),INDEX(UnitCostGrid,MATCH(T16,PayItemKeys,0),$I$11))) -> 8 | X16: =W16*V16 -> 9910.728
A17: 5 | B17: =IF(C17="","",VLOOKUP(C17,CHOOSE({1,2},Table2[Pay Item Description],Table2[Pay Item No.]),2,0)) | D17: =IF(C17="","N/A",VLOOKUP(C17,CHOOSE({1,2},Table2[Pay Item Description],Table2[Units]),2,0)) -> N/A | F17: =IF(C17="","N/A",IF(INDEX(UnitCostGrid,MATCH(C17,PayItemKeys,0),$I$11)="",INDEX(UnitCostGrid,MATCH(C17,PayItemKeys,0),1),INDEX(UnitCostGrid,MATCH(C17,PayItemKeys,0),$I$11))) -> N/A | G17: =IF(C17="",0,F17*E17) -> 0 | I17: =IF(C17="","",IF(INDEX(UnitCostGrid,MATCH(C17,PayItemKeys,0),$I$11)="",0,1)) | O17: Subtotal | P17: =SUM(P13:P16) -> 548393.62 | R17: 5 | S17: =VLOOKUP(T17,CHOOSE({1,2},Table2[Pay Item Description],Table2[Pay Item No.]),2,0) -> P-605-5.1a | T17: =Pay_Items!D55 -> Joint Clean and Reseal, Concrete | U17: =IF(T17="","N/A",VLOOKUP(T17,CHOOSE({1,2},Table2[Pay Item Description],Table2[Units]),2,0)) -> L.F. | V17: ='Maintenance Policies'!D45*K8 -> 70200.99 | W17: =IF(T17="","N/A",IF(INDEX(UnitCostGrid,MATCH(T17,PayItemKeys,0),$I$11)="",INDEX(UnitCostGrid,MATCH(T17,PayItemKeys,0),1),INDEX(UnitCostGrid,MATCH(T17,PayItemKeys,0),$I$11))) -> 7 | X17: =W17*V17 -> 491406.93
A18: 6 | B18: =IF(C18="","",VLOOKUP(C18,CHOOSE({1,2},Table2[Pay Item Description],Table2[Pay Item No.]),2,0)) | D18: =IF(C18="","N/A",VLOOKUP(C18,CHOOSE({1,2},Table2[Pay Item Description],Table2[Units]),2,0)) -> N/A | F18: =IF(C18="","N/A",IF(INDEX(UnitCostGrid,MATCH(C18,PayItemKeys,0),$I$11)="",INDEX(UnitCostGrid,MATCH(C18,PayItemKeys,0),1),INDEX(UnitCostGrid,MATCH(C18,PayItemKeys,0),$I$11))) -> N/A | G18: =IF(C18="",0,F18*E18) -> 0 | I18: =IF(C18="","",IF(INDEX(UnitCostGrid,MATCH(C18,PayItemKeys,0),$I$11)="",0,1)) | L18: Mobilization | P18: =('General Information'!$D$36/100)*P17 -> 54839.362 | W18: Subtotal | X18: =SUM(X13:X17) -> 641811.4
A19: 7 | B19: =IF(C19="","",VLOOKUP(C19,CHOOSE({1,2},Table2[Pay Item Description],Table2[Pay Item No.]),2,0)) | D19: =IF(C19="","N/A",VLOOKUP(C19,CHOOSE({1,2},Table2[Pay Item Description],Table2[Units]),2,0)) -> N/A | F19: =IF(C19="","N/A",IF(INDEX(UnitCostGrid,MATCH(C19,PayItemKeys,0),$I$11)="",INDEX(UnitCostGrid,MATCH(C19,PayItemKeys,0),1),INDEX(UnitCostGrid,MATCH(C19,PayItemKeys,0),$I$11))) -> N/A | G19: =IF(C19="",0,F19*E19) -> 0 | I19: =IF(C19="","",IF(INDEX(UnitCostGrid,MATCH(C19,PayItemKeys,0),$I$11)="",0,1)) | L19: Engineering | P19: =('General Information'!$D$37/100)*P17 -> 27419.681 | T19: Mobilization | X19: =('General Information'!$D$36/100)*X18 -> 64181.14
A20: 8 | B20: =IF(C20="","",VLOOKUP(C20,CHOOSE({1,2},Table2[Pay Item Description],Table2[Pay Item No.]),2,0)) | D20: =IF(C20="","N/A",VLOOKUP(C20,CHOOSE({1,2},Table2[Pay Item Description],Table2[Units]),2,0)) -> N/A | F20: =IF(C20="","N/A",IF(INDEX(UnitCostGrid,MATCH(C20,PayItemKeys,0),$I$11)="",INDEX(UnitCostGrid,MATCH(C20,PayItemKeys,0),1),INDEX(UnitCostGrid,MATCH(C20,PayItemKeys,0),$I$11))) -> N/A | G20: =IF(C20="",0,F20*E20) -> 0 | I20: =IF(C20="","",IF(INDEX(UnitCostGrid,MATCH(C20,PayItemKeys,0),$I$11)="",0,1)) | O20: Total | P20: =SUM(P17:P19) -> 630652.66 | T20: Engineering | X20: =('General Information'!$D$37/100)*X18 -> 32090.57
A21: 9 | B21: =IF(C21="","",VLOOKUP(C21,CHOOSE({1,2},Table2[Pay Item Description],Table2[Pay Item No.]),2,0)) | D21: =IF(C21="","N/A",VLOOKUP(C21,CHOOSE({1,2},Table2[Pay Item Description],Table2[Units]),2,0)) -> N/A | F21: =IF(C21="","N/A",IF(INDEX(UnitCostGrid,MATCH(C21,PayItemKeys,0),$I$11)="",INDEX(UnitCostGrid,MATCH(C21,PayItemKeys,0),1),INDEX(UnitCostGrid,MATCH(C21,PayItemKeys,0),$I$11))) -> N/A | G21: =IF(C21="",0,F21*E21) -> 0 | I21: =IF(C21="","",IF(INDEX(UnitCostGrid,MATCH(C21,PayItemKeys,0),$I$11)="",0,1)) | W21: Total | X21: =SUM(X18:X20) -> 738083.11
A22: 10 | B22: =IF(C22="","",VLOOKUP(C22,CHOOSE({1,2},Table2[Pay Item Description],Table2[Pay Item No.]),2,0)) | D22: =IF(C22="","N/A",VLOOKUP(C22,CHOOSE({1,2},Table2[Pay Item Description],Table2[Units]),2,0)) -> N/A | F22: =IF(C22="","N/A",IF(INDEX(UnitCostGrid,MATCH(C22,PayItemKeys,0),$I$11)="",INDEX(UnitCostGrid,MATCH(C22,PayItemKeys,0),1),INDEX(UnitCostGrid,MATCH(C22,PayItemKeys,0),$I$11))) -> N/A | G22: =IF(C22="",0,F22*E22) -> 0 | I22: =IF(C22="","",IF(INDEX(UnitCostGrid,MATCH(C22,PayItemKeys,0),$I$11)="",0,1))
A24: Subtotal | G24: =SUM(G13:G22) -> 0
B25: Mobilization | G25: =('General Information'!$D$36/100)*G24 -> 0
B26: Engineering | G26: =('General Information'!$D$37/100)*G24 -> 0
A27: Total | G27: =SUM(G24:G26) -> 0
A33: Net Present Worth
A34: PCC Reconstruction - Alternative 2 | I34: Hidden
B36: Item | C36: Year Applied | D36: Actual Cost | E36: Discounted Cost
B37: Initial Construction | C37: =C6 -> 2028 | D37: =G27 -> 0 | E37: =D37 -> 0 | K37: Year | L37: Actual | M37: Discounted
B38: Maintenance 1 | C38: ='Maintenance Policies'!E37 -> 19 | D38: =P20 -> 630652.66 | E38: =IF(C38>'General Information'!$D$33,0,D38/(1+('General Information'!$D$34/100))^C38) -> 359652.4 | K38: =C6 -> 2028 | L38: =IF(K38-$C$6>'General Information'!$D$33,0,IF(K38=$C$6,$D$37,0)+SUMIF($C$38:$C$40,K38-$C$6,$D$38:$D$40)) -> 0 | M38: =IF(K38-$C$6>'General Information'!$D$33,0,IF(K38=$C$6,$E$37,0)+SUMIF($C$38:$C$40,K38-$C$6,$E$38:$E$40)) -> 0
B39: Rehabilitation 1 | C39: ='Maintenance Policies'!E41 -> 27 | D39: =X21 -> 738083.11 | E39: =IF(C39>'General Information'!$D$33,0,D39/(1+('General Information'!$D$34/100))^C39) -> 332276.94 | K39: =K38+1 -> 2029 | L39: =IF(K39-$C$6>'General Information'!$D$33,0,IF(K39=$C$6,$D$37,0)+SUMIF($C$38:$C$40,K39-$C$6,$D$38:$D$40)) -> 0 | M39: =IF(K39-$C$6>'General Information'!$D$33,0,IF(K39=$C$6,$E$37,0)+SUMIF($C$38:$C$40,K39-$C$6,$E$38:$E$40)) -> 0
B40: Salvage | C40: ='General Information'!D33 -> 30 | D40: =-'Maintenance Policies'!D46*G27 -> 0 | E40: =IF(C40>'General Information'!$D$33,0,D40/(1+('General Information'!$D$34/100))^C40) -> 0 | K40: =K39+1 -> 2030 | L40: =IF(K40-$C$6>'General Information'!$D$33,0,IF(K40=$C$6,$D$37,0)+SUMIF($C$38:$C$40,K40-$C$6,$D$38:$D$40)) -> 0 | M40: =IF(K40-$C$6>'General Information'!$D$33,0,IF(K40=$C$6,$E$37,0)+SUMIF($C$38:$C$40,K40-$C$6,$E$38:$E$40)) -> 0
B41: Net Present Worth | E41: =SUM(E37:E40) -> 691929.34 | K41: =K40+1 -> 2031 | L41: =IF(K41-$C$6>'General Information'!$D$33,0,IF(K41=$C$6,$D$37,0)+SUMIF($C$38:$C$40,K41-$C$6,$D$38:$D$40)) -> 0 | M41: =IF(K41-$C$6>'General Information'!$D$33,0,IF(K41=$C$6,$E$37,0)+SUMIF($C$38:$C$40,K41-$C$6,$E$38:$E$40)) -> 0
K42: =K41+1 -> 2032 | L42: =IF(K42-$C$6>'General Information'!$D$33,0,IF(K42=$C$6,$D$37,0)+SUMIF($C$38:$C$40,K42-$C$6,$D$38:$D$40)) -> 0 | M42: =IF(K42-$C$6>'General Information'!$D$33,0,IF(K42=$C$6,$E$37,0)+SUMIF($C$38:$C$40,K42-$C$6,$E$38:$E$40)) -> 0
K43: =K42+1 -> 2033 | L43: =IF(K43-$C$6>'General Information'!$D$33,0,IF(K43=$C$6,$D$37,0)+SUMIF($C$38:$C$40,K43-$C$6,$D$38:$D$40)) -> 0 | M43: =IF(K43-$C$6>'General Information'!$D$33,0,IF(K43=$C$6,$E$37,0)+SUMIF($C$38:$C$40,K43-$C$6,$E$38:$E$40)) -> 0
K44: =K43+1 -> 2034 | L44: =IF(K44-$C$6>'General Information'!$D$33,0,IF(K44=$C$6,$D$37,0)+SUMIF($C$38:$C$40,K44-$C$6,$D$38:$D$40)) -> 0 | M44: =IF(K44-$C$6>'General Information'!$D$33,0,IF(K44=$C$6,$E$37,0)+SUMIF($C$38:$C$40,K44-$C$6,$E$38:$E$40)) -> 0
K45: =K44+1 -> 2035 | L45: =IF(K45-$C$6>'General Information'!$D$33,0,IF(K45=$C$6,$D$37,0)+SUMIF($C$38:$C$40,K45-$C$6,$D$38:$D$40)) -> 0 | M45: =IF(K45-$C$6>'General Information'!$D$33,0,IF(K45=$C$6,$E$37,0)+SUMIF($C$38:$C$40,K45-$C$6,$E$38:$E$40)) -> 0
K46: =K45+1 -> 2036 | L46: =IF(K46-$C$6>'General Information'!$D$33,0,IF(K46=$C$6,$D$37,0)+SUMIF($C$38:$C$40,K46-$C$6,$D$38:$D$40)) -> 0 | M46: =IF(K46-$C$6>'General Information'!$D$33,0,IF(K46=$C$6,$E$37,0)+SUMIF($C$38:$C$40,K46-$C$6,$E$38:$E$40)) -> 0
K47: =K46+1 -> 2037 | L47: =IF(K47-$C$6>'General Information'!$D$33,0,IF(K47=$C$6,$D$37,0)+SUMIF($C$38:$C$40,K47-$C$6,$D$38:$D$40)) -> 0 | M47: =IF(K47-$C$6>'General Information'!$D$33,0,IF(K47=$C$6,$E$37,0)+SUMIF($C$38:$C$40,K47-$C$6,$E$38:$E$40)) -> 0
K48: =K47+1 -> 2038 | L48: =IF(K48-$C$6>'General Information'!$D$33,0,IF(K48=$C$6,$D$37,0)+SUMIF($C$38:$C$40,K48-$C$6,$D$38:$D$40)) -> 0 | M48: =IF(K48-$C$6>'General Information'!$D$33,0,IF(K48=$C$6,$E$37,0)+SUMIF($C$38:$C$40,K48-$C$6,$E$38:$E$40)) -> 0
K49: =K48+1 -> 2039 | L49: =IF(K49-$C$6>'General Information'!$D$33,0,IF(K49=$C$6,$D$37,0)+SUMIF($C$38:$C$40,K49-$C$6,$D$38:$D$40)) -> 0 | M49: =IF(K49-$C$6>'General Information'!$D$33,0,IF(K49=$C$6,$E$37,0)+SUMIF($C$38:$C$40,K49-$C$6,$E$38:$E$40)) -> 0
K50: =K49+1 -> 2040 | L50: =IF(K50-$C$6>'General Information'!$D$33,0,IF(K50=$C$6,$D$37,0)+SUMIF($C$38:$C$40,K50-$C$6,$D$38:$D$40)) -> 0 | M50: =IF(K50-$C$6>'General Information'!$D$33,0,IF(K50=$C$6,$E$37,0)+SUMIF($C$38:$C$40,K50-$C$6,$E$38:$E$40)) -> 0
K51: =K50+1 -> 2041 | L51: =IF(K51-$C$6>'General Information'!$D$33,0,IF(K51=$C$6,$D$37,0)+SUMIF($C$38:$C$40,K51-$C$6,$D$38:$D$40)) -> 0 | M51: =IF(K51-$C$6>'General Information'!$D$33,0,IF(K51=$C$6,$E$37,0)+SUMIF($C$38:$C$40,K51-$C$6,$E$38:$E$40)) -> 0
K52: =K51+1 -> 2042 | L52: =IF(K52-$C$6>'General Information'!$D$33,0,IF(K52=$C$6,$D$37,0)+SUMIF($C$38:$C$40,K52-$C$6,$D$38:$D$40)) -> 0 | M52: =IF(K52-$C$6>'General Information'!$D$33,0,IF(K52=$C$6,$E$37,0)+SUMIF($C$38:$C$40,K52-$C$6,$E$38:$E$40)) -> 0
K53: =K52+1 -> 2043 | L53: =IF(K53-$C$6>'General Information'!$D$33,0,IF(K53=$C$6,$D$37,0)+SUMIF($C$38:$C$40,K53-$C$6,$D$38:$D$40)) -> 0 | M53: =IF(K53-$C$6>'General Information'!$D$33,0,IF(K53=$C$6,$E$37,0)+SUMIF($C$38:$C$40,K53-$C$6,$E$38:$E$40)) -> 0
... K68: =K67+1 -> 2058 | L68: =IF(K68-$C$6>'General Information'!$D$33,0,IF(K68=$C$6,$D$37,0)+SUMIF($C$38:$C$40,K68-$C$6,$D$38:$D$40)) -> 0 | M68: =IF(K68-$C$6>'General Information'!$D$33,0,IF(K68=$C$6,$E$37,0)+SUMIF($C$38:$C$40,K68-$C$6,$E$38:$E$40)) -> 0

Sheet TMP(HMARehab)
A1: =HYPERLINK("#'General Information'!D9","◄ General Information") -> ◄ General Information | C1: =HYPERLINK("#Summary!G1","Summary") -> Summary | D1: =$A$33 -> HMA Mill and Overlay - Alternative 3 | I1: Hidden
A2: Initial Construction Costs: | J2: Maintenance 1 | R2: Maintenance 2 | Z2: Maintenance 3 | AH2: Rehabilitation 1 | AP2: Maintenance 4 | AX2: Maintenance 5 | BF2: Maintenance 6
A3: STEP 4 of 5 · The quantities for this alternative. Grey cells are yours: C4 to C8 project data (filled from General Information), F4 to F10 closure days, C13 to C22 pay items and E13 to E22 quantities. Everything else calculates. Unit costs come from Pay_Items, and C11 picks which division they are priced from.
A4: Pavement Type: | C4: HMA mill and overlay
A5: Mainline Pavement Area: | C5: ='General Information'!D26 -> 45883 | D5: S.Y.
A6: Initial Construction Year: | C6: ='General Information'!D25 -> 2028 | AH6: Mill and overlay: | AI6: 2 | AJ6: inches
A7: Asphalt Surface Treatment Type: | C7: Emulsified Asphalt Surface Treatment | D7: Select alternative treatment, if planned. | AH7: Asphalt: | AI7: 120 | AJ7: lbs/SY-in
A8: Markings Area: | C8: ='General Information'!D28 -> 12000 | D8: S.F.
AH9: Tack Coat Application | AI9: 0.07 | AJ9: gal/S.Y.
I10: Price column: 1 Regular, 2 Middle, 3 West, 4 East
B11: Price from: | C11: Regular | D11: =IF(OR($C$11="Regular",$C$11=""),"Regular is the statewide Unit Cost column on Pay_Items.","Prices from the "&$C$11&" column on Pay_Items: "&SUM($I$13:$I$22)&" of "&COUNT($I$13:$I$22)&" pay items used here have a "&$C$11&" cost, the rest fall back to Unit Cost.") -> Regular is the statewide Unit Cost column on Pay_Items. | I11: =IFERROR(MATCH($C$11,PriceSources,0),1) -> 1
A12: Item No. | B12: Pay Item | C12: Description | D12: Unit | E12: Qty | F12: Unit Cost | G12: Item Cost | J12: Item No. | K12: Pay Item | L12: Description | M12: Unit | N12: Qty | O12: Unit Cost | P12: Item Cost | R12: Item No. | S12: Pay Item | T12: Description | U12: Unit | V12: Qty | W12: Unit Cost | X12: Item Cost | Z12: Item No. | AA12: Pay Item | AB12: Description | AC12: Unit | AD12: Qty | AE12: Unit Cost | AF12: Item Cost | AH12: Item No. | AI12: Pay Item | AJ12: Description | AK12: Unit | AL12: Qty | AM12: Unit Cost | AN12: Item Cost | AP12: Item No. | AQ12: Pay Item | AR12: Description | AS12: Unit | AT12: Qty | AU12: Unit Cost | AV12: Item Cost | AX12: Item No. | AY12: Pay Item | AZ12: Description | BA12: Unit | BB12: Qty | BC12: Unit Cost | BD12: Item Cost | BF12: Item No. | BG12: Pay Item | BH12: Description | BI12: Unit | BJ12: Qty | BK12: Unit Cost | BL12: Item Cost
A13: 1 | B13: =IF(C13="","",VLOOKUP(C13,CHOOSE({1,2},Table2[Pay Item Description],Table2[Pay Item No.]),2,0)) | D13: =IF(C13="","N/A",VLOOKUP(C13,CHOOSE({1,2},Table2[Pay Item Description],Table2[Units]),2,0)) -> N/A | E13: 0 | F13: =IF(C13="","N/A",IF(INDEX(UnitCostGrid,MATCH(C13,PayItemKeys,0),$I$11)="",INDEX(UnitCostGrid,MATCH(C13,PayItemKeys,0),1),INDEX(UnitCostGrid,MATCH(C13,PayItemKeys,0),$I$11))) -> N/A | G13: =IF(C13="",0,F13*E13) -> 0 | I13: =IF(C13="","",IF(INDEX(UnitCostGrid,MATCH(C13,PayItemKeys,0),$I$11)="",0,1)) | J13: 1 | K13: =IF(L13="",0,VLOOKUP(L13,CHOOSE({1,2},Table2[Pay Item Description],Table2[Pay Item No.]),2,0)) -> P-608-8.1 | L13: =C7 -> Emulsified Asphalt Surface Treatment | M13: =IF(L13="","N/A",VLOOKUP(L13,CHOOSE({1,2},Table2[Pay Item Description],Table2[Units]),2,0)) -> S.Y. | N13: ='Maintenance Policies'!D51*$C$5 -> 45883 | O13: =IF(L13="","N/A",IF(INDEX(UnitCostGrid,MATCH(L13,PayItemKeys,0),$I$11)="",INDEX(UnitCostGrid,MATCH(L13,PayItemKeys,0),1),INDEX(UnitCostGrid,MATCH(L13,PayItemKeys,0),$I$11))) -> 4 | P13: =O13*N13 -> 183532 | R13: 1 | S13: =IF(T13="",0,VLOOKUP(T13,CHOOSE({1,2},Table2[Pay Item Description],Table2[Pay Item No.]),2,0)) -> P-101-5.4a | T13: =Pay_Items!D11 -> Spall Repair, Asphalt | U13: =IF(T13="","N/A",VLOOKUP(T13,CHOOSE({1,2},Table2[Pay Item Description],Table2[Units]),2,0)) -> S.F. | V13: ='Maintenance Policies'!D53*($C$5*9) -> 5161.8375 | W13: =IF(T13="","N/A",IF(INDEX(UnitCostGrid,MATCH(T13,PayItemKeys,0),$I$11)="",INDEX(UnitCostGrid,MATCH(T13,PayItemKeys,0),1),INDEX(UnitCostGrid,MATCH(T13,PayItemKeys,0),$I$11))) -> 8.5 | X13: =W13*V13 -> 43875.619 | Z13: 1 | AA13: =IF(AB13="",0,VLOOKUP(AB13,CHOOSE({1,2},Table2[Pay Item Description],Table2[Pay Item No.]),2,0)) -> P-608-8.1 | AB13: =C7 -> Emulsified Asphalt Surface Treatment | AC13: =IF(AB13="","N/A",VLOOKUP(AB13,CHOOSE({1,2},Table2[Pay Item Description],Table2[Units]),2,0)) -> S.Y. | AD13: ='Maintenance Policies'!D57*$C$5 -> 45883 | AE13: =IF(AB13="","N/A",IF(INDEX(UnitCostGrid,MATCH(AB13,PayItemKeys,0),$I$11)="",INDEX(UnitCostGrid,MATCH(AB13,PayItemKeys,0),1),INDEX(UnitCostGrid,MATCH(AB13,PayItemKeys,0),$I$11))) -> 4 | AF13: =AE13*AD13 -> 183532 | AH13: 1 | AI13: =IF(AJ13="",0,VLOOKUP(AJ13,CHOOSE({1,2},Table2[Pay Item Description],Table2[Pay Item No.]),2,0)) -> P-101-5.6 | AJ13: Cold Milling | AK13: =IF(AJ13="","N/A",VLOOKUP(AJ13,CHOOSE({1,2},Table2[Pay Item Description],Table2[Units]),2,0)) -> S.Y. | AL13: ='Maintenance Policies'!D59*$C$5 -> 45883 | AM13: =IF(AJ13="","N/A",IF(INDEX(UnitCostGrid,MATCH(AJ13,PayItemKeys,0),$I$11)="",INDEX(UnitCostGrid,MATCH(AJ13,PayItemKeys,0),1),INDEX(UnitCostGrid,MATCH(AJ13,PayItemKeys,0),$I$11))) -> 5 | AN13: =AM13*AL13 -> 229415 | AP13: 1 | AQ13: =IF(AR13="",0,VLOOKUP(AR13,CHOOSE({1,2},Table2[Pay Item Description],Table2[Pay Item No.]),2,0)) -> P-608-8.1 | AR13: =C7 -> Emulsified Asphalt Surface Treatment | AS13: =IF(AR13="","N/A",VLOOKUP(AR13,CHOOSE({1,2},Table2[Pay Item Description],Table2[Units]),2,0)) -> S.Y. | AT13: ='Maintenance Policies'!D63*$C$5 -> 45883 | AU13: =IF(AR13="","N/A",IF(INDEX(UnitCostGrid,MATCH(AR13,PayItemKeys,0),$I$11)="",INDEX(UnitCostGrid,MATCH(AR13,PayItemKeys,0),1),INDEX(UnitCostGrid,MATCH(AR13,PayItemKeys,0),$I$11))) -> 4 | AV13: =AU13*AT13 -> 183532 | AX13: 1 | AY13: =IF(AZ13="",0,VLOOKUP(AZ13,CHOOSE({1,2},Table2[Pay Item Description],Table2[Pay Item No.]),2,0)) -> P-101-5.4a | AZ13: Spall Repair, Asphalt | BA13: =IF(AZ13="","N/A",VLOOKUP(AZ13,CHOOSE({1,2},Table2[Pay Item Description],Table2[Units]),2,0)) -> S.F. | BB13: ='Maintenance Policies'!D65*($C$5*9) -> 5161.8375 | BC13: =IF(AZ13="","N/A",IF(INDEX(UnitCostGrid,MATCH(AZ13,PayItemKeys,0),$I$11)="",INDEX(UnitCostGrid,MATCH(AZ13,PayItemKeys,0),1),INDEX(UnitCostGrid,MATCH(AZ13,PayItemKeys,0),$I$11))) -> 8.5 | BD13: =BC13*BB13 -> 43875.619 | BF13: 1 | BG13: =IF(BH13="",0,VLOOKUP(BH13,CHOOSE({1,2},Table2[Pay Item Description],Table2[Pay Item No.]),2,0)) -> P-608-8.1 | BH13: =C7 -> Emulsified Asphalt Surface Treatment | BI13: =IF(BH13="","N/A",VLOOKUP(BH13,CHOOSE({1,2},Table2[Pay Item Description],Table2[Units]),2,0)) -> S.Y. | BJ13: ='Maintenance Policies'!D69*$C$5 -> 45883 | BK13: =IF(BH13="","N/A",IF(INDEX(UnitCostGrid,MATCH(BH13,PayItemKeys,0),$I$11)="",INDEX(UnitCostGrid,MATCH(BH13,PayItemKeys,0),1),INDEX(UnitCostGrid,MATCH(BH13,PayItemKeys,0),$I$11))) -> 4 | BL13: =BK13*BJ13 -> 183532
A14: 2 | B14: =IF(C14="","",VLOOKUP(C14,CHOOSE({1,2},Table2[Pay Item Description],Table2[Pay Item No.]),2,0)) | D14: =IF(C14="","N/A",VLOOKUP(C14,CHOOSE({1,2},Table2[Pay Item Description],Table2[Units]),2,0)) -> N/A | E14: 0 | F14: =IF(C14="","N/A",IF(INDEX(UnitCostGrid,MATCH(C14,PayItemKeys,0),$I$11)="",INDEX(UnitCostGrid,MATCH(C14,PayItemKeys,0),1),INDEX(UnitCostGrid,MATCH(C14,PayItemKeys,0),$I$11))) -> N/A | G14: =IF(C14="",0,F14*E14) -> 0 | I14: =IF(C14="","",IF(INDEX(UnitCostGrid,MATCH(C14,PayItemKeys,0),$I$11)="",0,1)) | J14: 2 | K14: =IF(L14="",0,VLOOKUP(L14,CHOOSE({1,2},Table2[Pay Item Description],Table2[Pay Item No.]),2,0)) -> P-101-5.3 | L14: Markings Removal | M14: =IF(L14="","N/A",VLOOKUP(L14,CHOOSE({1,2},Table2[Pay Item Description],Table2[Units]),2,0)) -> S.F. | N14: ='Maintenance Policies'!D52*$C$8 -> 12000 | O14: =IF(L14="","N/A",IF(INDEX(UnitCostGrid,MATCH(L14,PayItemKeys,0),$I$11)="",INDEX(UnitCostGrid,MATCH(L14,PayItemKeys,0),1),INDEX(UnitCostGrid,MATCH(L14,PayItemKeys,0),$I$11))) -> 0.77777778 | P14: =O14*N14 -> 9333.3333 | R14: 2 | S14: =IF(T14="",0,VLOOKUP(T14,CHOOSE({1,2},Table2[Pay Item Description],Table2[Pay Item No.]),2,0)) -> P-101-5.2a | T14: =Pay_Items!D6 -> Crack Repair (Type I), Asphalt | U14: =IF(T14="","N/A",VLOOKUP(T14,CHOOSE({1,2},Table2[Pay Item Description],Table2[Units]),2,0)) -> L.F. | V14: ='Maintenance Policies'!D54*($C$5*9) -> 16517.88 | W14: =IF(T14="","N/A",IF(INDEX(UnitCostGrid,MATCH(T14,PayItemKeys,0),$I$11)="",INDEX(UnitCostGrid,MATCH(T14,PayItemKeys,0),1),INDEX(UnitCostGrid,MATCH(T14,PayItemKeys,0),$I$11))) -> 4 | X14: =W14*V14 -> 66071.52 | Z14: 2 | AA14: =IF(AB14="",0,VLOOKUP(AB14,CHOOSE({1,2},Table2[Pay Item Description],Table2[Pay Item No.]),2,0)) -> P-101-5.3 | AB14: Markings Removal | AC14: =IF(AB14="","N/A",VLOOKUP(AB14,CHOOSE({1,2},Table2[Pay Item Description],Table2[Units]),2,0)) -> S.F. | AD14: ='Maintenance Policies'!D58*$C$8 -> 12000 | AE14: =IF(AB14="","N/A",IF(INDEX(UnitCostGrid,MATCH(AB14,PayItemKeys,0),$I$11)="",INDEX(UnitCostGrid,MATCH(AB14,PayItemKeys,0),1),INDEX(UnitCostGrid,MATCH(AB14,PayItemKeys,0),$I$11))) -> 0.77777778 | AF14: =AE14*AD14 -> 9333.3333 | AH14: 2 | AI14: =IF(AJ14="",0,VLOOKUP(AJ14,CHOOSE({1,2},Table2[Pay Item Description],Table2[Pay Item No.]),2,0)) -> P-603-5.1 | AJ14: Emulsified Asphalt Tack Coat | AK14: =IF(AJ14="","N/A",VLOOKUP(AJ14,CHOOSE({1,2},Table2[Pay Item Description],Table2[Units]),2,0)) -> GAL | AL14: ='Maintenance Policies'!D59*$C$5*AI9 -> 3211.81 | AM14: =IF(AJ14="","N/A",IF(INDEX(UnitCostGrid,MATCH(AJ14,PayItemKeys,0),$I$11)="",INDEX(UnitCostGrid,MATCH(AJ14,PayItemKeys,0),1),INDEX(UnitCostGrid,MATCH(AJ14,PayItemKeys,0),$I$11))) -> 4.5 | AN14: =AM14*AL14 -> 14453.145 | AP14: 2 | AQ14: =IF(AR14="",0,VLOOKUP(AR14,CHOOSE({1,2},Table2[Pay Item Description],Table2[Pay Item No.]),2,0)) -> P-101-5.3 | AR14: Markings Removal | AS14: =IF(AR14="","N/A",VLOOKUP(AR14,CHOOSE({1,2},Table2[Pay Item Description],Table2[Units]),2,0)) -> S.F. | AT14: ='Maintenance Policies'!D64*$C$8 -> 12000 | AU14: =IF(AR14="","N/A",IF(INDEX(UnitCostGrid,MATCH(AR14,PayItemKeys,0),$I$11)="",INDEX(UnitCostGrid,MATCH(AR14,PayItemKeys,0),1),INDEX(UnitCostGrid,MATCH(AR14,PayItemKeys,0),$I$11))) -> 0.77777778 | AV14: =AU14*AT14 -> 9333.3333 | AX14: 2 | AY14: =IF(AZ14="",0,VLOOKUP(AZ14,CHOOSE({1,2},Table2[Pay Item Description],Table2[Pay Item No.]),2,0)) -> P-101-5.2a | AZ14: Crack Repair (Type I), Asphalt | BA14: =IF(AZ14="","N/A",VLOOKUP(AZ14,CHOOSE({1,2},Table2[Pay Item Description],Table2[Units]),2,0)) -> L.F. | BB14: ='Maintenance Policies'!D66*($C$5*9) -> 16517.88 | BC14: =IF(AZ14="","N/A",IF(INDEX(UnitCostGrid,MATCH(AZ14,PayItemKeys,0),$I$11)="",INDEX(UnitCostGrid,MATCH(AZ14,PayItemKeys,0),1),INDEX(UnitCostGrid,MATCH(AZ14,PayItemKeys,0),$I$11))) -> 4 | BD14: =BC14*BB14 -> 66071.52 | BF14: 2 | BG14: =IF(BH14="",0,VLOOKUP(BH14,CHOOSE({1,2},Table2[Pay Item Description],Table2[Pay Item No.]),2,0)) -> P-101-5.3 | BH14: Markings Removal | BI14: =IF(BH14="","N/A",VLOOKUP(BH14,CHOOSE({1,2},Table2[Pay Item Description],Table2[Units]),2,0)) -> S.F. | BJ14: ='Maintenance Policies'!D70*$C$8 -> 12000 | BK14: =IF(BH14="","N/A",IF(INDEX(UnitCostGrid,MATCH(BH14,PayItemKeys,0),$I$11)="",INDEX(UnitCostGrid,MATCH(BH14,PayItemKeys,0),1),INDEX(UnitCostGrid,MATCH(BH14,PayItemKeys,0),$I$11))) -> 0.77777778 | BL14: =BK14*BJ14 -> 9333.3333
A15: 3 | B15: =IF(C15="","",VLOOKUP(C15,CHOOSE({1,2},Table2[Pay Item Description],Table2[Pay Item No.]),2,0)) | D15: =IF(C15="","N/A",VLOOKUP(C15,CHOOSE({1,2},Table2[Pay Item Description],Table2[Units]),2,0)) -> N/A | E15: 0 | F15: =IF(C15="","N/A",IF(INDEX(UnitCostGrid,MATCH(C15,PayItemKeys,0),$I$11)="",INDEX(UnitCostGrid,MATCH(C15,PayItemKeys,0),1),INDEX(UnitCostGrid,MATCH(C15,PayItemKeys,0),$I$11))) -> N/A | G15: =IF(C15="",0,F15*E15) -> 0 | I15: =IF(C15="","",IF(INDEX(UnitCostGrid,MATCH(C15,PayItemKeys,0),$I$11)="",0,1)) | J15: 3 | K15: =IF(L15="",0,VLOOKUP(L15,CHOOSE({1,2},Table2[Pay Item Description],Table2[Pay Item No.]),2,0)) -> P-620-5.1a | L15: Markings (prep, markings, reflective media) | M15: =IF(L15="","N/A",VLOOKUP(L15,CHOOSE({1,2},Table2[Pay Item Description],Table2[Units]),2,0)) -> S.F. | N15: ='Maintenance Policies'!D52*$C$8 -> 12000 | O15: =IF(L15="","N/A",IF(INDEX(UnitCostGrid,MATCH(L15,PayItemKeys,0),$I$11)="",INDEX(UnitCostGrid,MATCH(L15,PayItemKeys,0),1),INDEX(UnitCostGrid,MATCH(L15,PayItemKeys,0),$I$11))) -> 0.66666667 | P15: =O15*N15 -> 8000 | R15: 3 | S15: =IF(T15="",0,VLOOKUP(T15,CHOOSE({1,2},Table2[Pay Item Description],Table2[Pay Item No.]),2,0)) -> P-608-8.1 | T15: =C7 -> Emulsified Asphalt Surface Treatment | U15: =IF(T15="","N/A",VLOOKUP(T15,CHOOSE({1,2},Table2[Pay Item Description],Table2[Units]),2,0)) -> S.Y. | V15: ='Maintenance Policies'!D55*$C$5 -> 45883 | W15: =IF(T15="","N/A",IF(INDEX(UnitCostGrid,MATCH(T15,PayItemKeys,0),$I$11)="",INDEX(UnitCostGrid,MATCH(T15,PayItemKeys,0),1),INDEX(UnitCostGrid,MATCH(T15,PayItemKeys,0),$I$11))) -> 4 | X15: =W15*V15 -> 183532 | Z15: 3 | AA15: =IF(AB15="",0,VLOOKUP(AB15,CHOOSE({1,2},Table2[Pay Item Description],Table2[Pay Item No.]),2,0)) -> P-620-5.1a | AB15: Markings (prep, markings, reflective media) | AC15: =IF(AB15="","N/A",VLOOKUP(AB15,CHOOSE({1,2},Table2[Pay Item Description],Table2[Units]),2,0)) -> S.F. | AD15: ='Maintenance Policies'!D58*$C$8 -> 12000 | AE15: =IF(AB15="","N/A",IF(INDEX(UnitCostGrid,MATCH(AB15,PayItemKeys,0),$I$11)="",INDEX(UnitCostGrid,MATCH(AB15,PayItemKeys,0),1),INDEX(UnitCostGrid,MATCH(AB15,PayItemKeys,0),$I$11))) -> 0.66666667 | AF15: =AE15*AD15 -> 8000 | AH15: 3 | AI15: =IF(AJ15="",0,VLOOKUP(AJ15,CHOOSE({1,2},Table2[Pay Item Description],Table2[Pay Item No.]),2,0)) -> P-401-8.1a | AJ15: Asphalt Surface Course | AK15: =IF(AJ15="","N/A",VLOOKUP(AJ15,CHOOSE({1,2},Table2[Pay Item Description],Table2[Units]),2,0)) -> TON | AL15: ='Maintenance Policies'!D59*$C$5*AI6*AI7/2000 -> 5505.96 | AM15: =IF(AJ15="","N/A",IF(INDEX(UnitCostGrid,MATCH(AJ15,PayItemKeys,0),$I$11)="",INDEX(UnitCostGrid,MATCH(AJ15,PayItemKeys,0),1),INDEX(UnitCostGrid,MATCH(AJ15,PayItemKeys,0),$I$11))) -> 130 | AN15: =AM15*AL15 -> 715774.8 | AP15: 3 | AQ15: =IF(AR15="",0,VLOOKUP(AR15,CHOOSE({1,2},Table2[Pay Item Description],Table2[Pay Item No.]),2,0)) -> P-620-5.1a | AR15: Markings (prep, markings, reflective media) | AS15: =IF(AR15="","N/A",VLOOKUP(AR15,CHOOSE({1,2},Table2[Pay Item Description],Table2[Units]),2,0)) -> S.F. | AT15: ='Maintenance Policies'!D64*$C$8 -> 12000 | AU15: =IF(AR15="","N/A",IF(INDEX(UnitCostGrid,MATCH(AR15,PayItemKeys,0),$I$11)="",INDEX(UnitCostGrid,MATCH(AR15,PayItemKeys,0),1),INDEX(UnitCostGrid,MATCH(AR15,PayItemKeys,0),$I$11))) -> 0.66666667 | AV15: =AU15*AT15 -> 8000 | AX15: 3 | AY15: =IF(AZ15="",0,VLOOKUP(AZ15,CHOOSE({1,2},Table2[Pay Item Description],Table2[Pay Item No.]),2,0)) -> P-608-8.1 | AZ15: =C7 -> Emulsified Asphalt Surface Treatment | BA15: =IF(AZ15="","N/A",VLOOKUP(AZ15,CHOOSE({1,2},Table2[Pay Item Description],Table2[Units]),2,0)) -> S.Y. | BB15: ='Maintenance Policies'!D67*$C$5 -> 45883 | BC15: =IF(AZ15="","N/A",IF(INDEX(UnitCostGrid,MATCH(AZ15,PayItemKeys,0),$I$11)="",INDEX(UnitCostGrid,MATCH(AZ15,PayItemKeys,0),1),INDEX(UnitCostGrid,MATCH(AZ15,PayItemKeys,0),$I$11))) -> 4 | BD15: =BC15*BB15 -> 183532 | BF15: 3 | BG15: =IF(BH15="",0,VLOOKUP(BH15,CHOOSE({1,2},Table2[Pay Item Description],Table2[Pay Item No.]),2,0)) -> P-620-5.1a | BH15: Markings (prep, markings, reflective media) | BI15: =IF(BH15="","N/A",VLOOKUP(BH15,CHOOSE({1,2},Table2[Pay Item Description],Table2[Units]),2,0)) -> S.F. | BJ15: ='Maintenance Policies'!D70*$C$8 -> 12000 | BK15: =IF(BH15="","N/A",IF(INDEX(UnitCostGrid,MATCH(BH15,PayItemKeys,0),$I$11)="",INDEX(UnitCostGrid,MATCH(BH15,PayItemKeys,0),1),INDEX(UnitCostGrid,MATCH(BH15,PayItemKeys,0),$I$11))) -> 0.66666667 | BL15: =BK15*BJ15 -> 8000
A16: 4 | B16: =IF(C16="","",VLOOKUP(C16,CHOOSE({1,2},Table2[Pay Item Description],Table2[Pay Item No.]),2,0)) | D16: =IF(C16="","N/A",VLOOKUP(C16,CHOOSE({1,2},Table2[Pay Item Description],Table2[Units]),2,0)) -> N/A | E16: 0 | F16: =IF(C16="","N/A",IF(INDEX(UnitCostGrid,MATCH(C16,PayItemKeys,0),$I$11)="",INDEX(UnitCostGrid,MATCH(C16,PayItemKeys,0),1),INDEX(UnitCostGrid,MATCH(C16,PayItemKeys,0),$I$11))) -> N/A | G16: =IF(C16="",0,F16*E16) -> 0 | I16: =IF(C16="","",IF(INDEX(UnitCostGrid,MATCH(C16,PayItemKeys,0),$I$11)="",0,1)) | O16: Subtotal | P16: =SUM(P13:P15) -> 200865.33 | R16: 4 | S16: =IF(T16="",0,VLOOKUP(T16,CHOOSE({1,2},Table2[Pay Item Description],Table2[Pay Item No.]),2,0)) -> P-101-5.3 | T16: =Pay_Items!D10 -> Markings Removal | U16: =IF(T16="","N/A",VLOOKUP(T16,CHOOSE({1,2},Table2[Pay Item Description],Table2[Units]),2,0)) -> S.F. | V16: ='Maintenance Policies'!D56*$C$8 -> 12000 | W16: =IF(T16="","N/A",IF(INDEX(UnitCostGrid,MATCH(T16,PayItemKeys,0),$I$11)="",INDEX(UnitCostGrid,MATCH(T16,PayItemKeys,0),1),INDEX(UnitCostGrid,MATCH(T16,PayItemKeys,0),$I$11))) -> 0.77777778 | X16: =W16*V16 -> 9333.3333 | AE16: Subtotal | AF16: =SUM(AF13:AF15) -> 200865.33 | AH16: 4 | AI16: =IF(AJ16="",0,VLOOKUP(AJ16,CHOOSE({1,2},Table2[Pay Item Description],Table2[Pay Item No.]),2,0)) -> P-101-5.2a | AJ16: Crack Repair (Type I), Asphalt | AK16: =IF(AJ16="","N/A",VLOOKUP(AJ16,CHOOSE({1,2},Table2[Pay Item Description],Table2[Units]),2,0)) -> L.F. | AL16: ='Maintenance Policies'!D60*($C$5*9) -> 6194.205 | AM16: =IF(AJ16="","N/A",IF(INDEX(UnitCostGrid,MATCH(AJ16,PayItemKeys,0),$I$11)="",INDEX(UnitCostGrid,MATCH(AJ16,PayItemKeys,0),1),INDEX(UnitCostGrid,MATCH(AJ16,PayItemKeys,0),$I$11))) -> 4 | AN16: =AM16*AL16 -> 24776.82 | AU16: Subtotal | AV16: =SUM(AV13:AV15) -> 200865.33 | AX16: 4 | AY16: =IF(AZ16="",0,VLOOKUP(AZ16,CHOOSE({1,2},Table2[Pay Item Description],Table2[Pay Item No.]),2,0)) -> P-101-5.3 | AZ16: Markings Removal | BA16: =IF(AZ16="","N/A",VLOOKUP(AZ16,CHOOSE({1,2},Table2[Pay Item Description],Table2[Units]),2,0)) -> S.F. | BB16: ='Maintenance Policies'!D68*$C$8 -> 12000 | BC16: =IF(AZ16="","N/A",IF(INDEX(UnitCostGrid,MATCH(AZ16,PayItemKeys,0),$I$11)="",INDEX(UnitCostGrid,MATCH(AZ16,PayItemKeys,0),1),INDEX(UnitCostGrid,MATCH(AZ16,PayItemKeys,0),$I$11))) -> 0.77777778 | BD16: =BC16*BB16 -> 9333.3333 | BK16: Subtotal | BL16: =SUM(BL13:BL15) -> 200865.33
A17: 5 | B17: =IF(C17="","",VLOOKUP(C17,CHOOSE({1,2},Table2[Pay Item Description],Table2[Pay Item No.]),2,0)) | D17: =IF(C17="","N/A",VLOOKUP(C17,CHOOSE({1,2},Table2[Pay Item Description],Table2[Units]),2,0)) -> N/A | E17: 0 | F17: =IF(C17="","N/A",IF(INDEX(UnitCostGrid,MATCH(C17,PayItemKeys,0),$I$11)="",INDEX(UnitCostGrid,MATCH(C17,PayItemKeys,0),1),INDEX(UnitCostGrid,MATCH(C17,PayItemKeys,0),$I$11))) -> N/A | G17: =IF(C17="",0,F17*E17) -> 0 | I17: =IF(C17="","",IF(INDEX(UnitCostGrid,MATCH(C17,PayItemKeys,0),$I$11)="",0,1)) | L17: Mobilization | P17: =('General Information'!$D$36/100)*P16 -> 20086.533 | R17: 5 | S17: =IF(T17="",0,VLOOKUP(T17,CHOOSE({1,2},Table2[Pay Item Description],Table2[Pay Item No.]),2,0)) -> P-620-5.1a | T17: =Pay_Items!D56 -> Markings (prep, markings, reflective media) | U17: =IF(T17="","N/A",VLOOKUP(T17,CHOOSE({1,2},Table2[Pay Item Description],Table2[Units]),2,0)) -> S.F. | V17: ='Maintenance Policies'!D56*$C$8 -> 12000 | W17: =IF(T17="","N/A",IF(INDEX(UnitCostGrid,MATCH(T17,PayItemKeys,0),$I$11)="",INDEX(UnitCostGrid,MATCH(T17,PayItemKeys,0),1),INDEX(UnitCostGrid,MATCH(T17,PayItemKeys,0),$I$11))) -> 0.66666667 | X17: =W17*V17 -> 8000 | AB17: Mobilization | AF17: =('General Information'!$D$36/100)*AF16 -> 20086.533 | AH17: 5 | AI17: =IF(AJ17="",0,VLOOKUP(AJ17,CHOOSE({1,2},Table2[Pay Item Description],Table2[Pay Item No.]),2,0)) -> P-101-5.4a | AJ17: Spall Repair, Asphalt | AK17: =IF(AJ17="","N/A",VLOOKUP(AJ17,CHOOSE({1,2},Table2[Pay Item Description],Table2[Units]),2,0)) -> S.F. | AL17: ='Maintenance Policies'!D61*($C$5*9) -> 2064.735 | AM17: =IF(AJ17="","N/A",IF(INDEX(UnitCostGrid,MATCH(AJ17,PayItemKeys,0),$I$11)="",INDEX(UnitCostGrid,MATCH(AJ17,PayItemKeys,0),1),INDEX(UnitCostGrid,MATCH(AJ17,PayItemKeys,0),$I$11))) -> 8.5 | AN17: =AM17*AL17 -> 17550.248 | AR17: Mobilization | AV17: =('General Information'!$D$36/100)*AV16 -> 20086.533 | AX17: 5 | AY17: =IF(AZ17="",0,VLOOKUP(AZ17,CHOOSE({1,2},Table2[Pay Item Description],Table2[Pay Item No.]),2,0)) -> P-620-5.1a | AZ17: Markings (prep, markings, reflective media) | BA17: =IF(AZ17="","N/A",VLOOKUP(AZ17,CHOOSE({1,2},Table2[Pay Item Description],Table2[Units]),2,0)) -> S.F. | BB17: ='Maintenance Policies'!D68*$C$8 -> 12000 | BC17: =IF(AZ17="","N/A",IF(INDEX(UnitCostGrid,MATCH(AZ17,PayItemKeys,0),$I$11)="",INDEX(UnitCostGrid,MATCH(AZ17,PayItemKeys,0),1),INDEX(UnitCostGrid,MATCH(AZ17,PayItemKeys,0),$I$11))) -> 0.66666667 | BD17: =BC17*BB17 -> 8000 | BH17: Mobilization | BL17: =('General Information'!$D$36/100)*BL16 -> 20086.533
A18: 6 | B18: =IF(C18="","",VLOOKUP(C18,CHOOSE({1,2},Table2[Pay Item Description],Table2[Pay Item No.]),2,0)) | D18: =IF(C18="","N/A",VLOOKUP(C18,CHOOSE({1,2},Table2[Pay Item Description],Table2[Units]),2,0)) -> N/A | E18: 0 | F18: =IF(C18="","N/A",IF(INDEX(UnitCostGrid,MATCH(C18,PayItemKeys,0),$I$11)="",INDEX(UnitCostGrid,MATCH(C18,PayItemKeys,0),1),INDEX(UnitCostGrid,MATCH(C18,PayItemKeys,0),$I$11))) -> N/A | G18: =IF(C18="",0,F18*E18) -> 0 | I18: =IF(C18="","",IF(INDEX(UnitCostGrid,MATCH(C18,PayItemKeys,0),$I$11)="",0,1)) | L18: Engineering | P18: =('General Information'!$D$37/100)*P16 -> 10043.267 | W18: Subtotal | X18: =SUM(X13:X17) -> 310812.47 | AB18: Engineering | AF18: =('General Information'!$D$37/100)*AF16 -> 10043.267 | AH18: 6 | AI18: =IF(AJ18="",0,VLOOKUP(AJ18,CHOOSE({1,2},Table2[Pay Item Description],Table2[Pay Item No.]),2,0)) -> P-620-5.1a | AJ18: Markings (prep, markings, reflective media) | AK18: =IF(AJ18="","N/A",VLOOKUP(AJ18,CHOOSE({1,2},Table2[Pay Item Description],Table2[Units]),2,0)) -> S.F. | AL18: ='Maintenance Policies'!D62*$C$8 -> 12000 | AM18: =IF(AJ18="","N/A",IF(INDEX(UnitCostGrid,MATCH(AJ18,PayItemKeys,0),$I$11)="",INDEX(UnitCostGrid,MATCH(AJ18,PayItemKeys,0),1),INDEX(UnitCostGrid,MATCH(AJ18,PayItemKeys,0),$I$11))) -> 0.66666667 | AN18: =AM18*AL18 -> 8000 | AR18: Engineering | AV18: =('General Information'!$D$37/100)*AV16 -> 10043.267 | BC18: Subtotal | BD18: =SUM(BD13:BD17) -> 310812.47 | BH18: Engineering | BL18: =('General Information'!$D$37/100)*BL16 -> 10043.267
A19: 7 | B19: =IF(C19="","",VLOOKUP(C19,CHOOSE({1,2},Table2[Pay Item Description],Table2[Pay Item No.]),2,0)) | D19: =IF(C19="","N/A",VLOOKUP(C19,CHOOSE({1,2},Table2[Pay Item Description],Table2[Units]),2,0)) -> N/A | E19: 0 | F19: =IF(C19="","N/A",IF(INDEX(UnitCostGrid,MATCH(C19,PayItemKeys,0),$I$11)="",INDEX(UnitCostGrid,MATCH(C19,PayItemKeys,0),1),INDEX(UnitCostGrid,MATCH(C19,PayItemKeys,0),$I$11))) -> N/A | G19: =IF(C19="",0,F19*E19) -> 0 | I19: =IF(C19="","",IF(INDEX(UnitCostGrid,MATCH(C19,PayItemKeys,0),$I$11)="",0,1)) | O19: Total | P19: =SUM(P16:P18) -> 230995.13 | T19: Mobilization | X19: =('General Information'!$D$36/100)*X18 -> 31081.247 | AE19: Total | AF19: =SUM(AF16:AF18) -> 230995.13 | AM19: Subtotal | AN19: =SUM(AN13:AN18) -> 1009970 | AU19: Total | AV19: =SUM(AV16:AV18) -> 230995.13 | AZ19: Mobilization | BD19: =('General Information'!$D$36/100)*BD18 -> 31081.247 | BK19: Total | BL19: =SUM(BL16:BL18) -> 230995.13
A20: 8 | B20: =IF(C20="","",VLOOKUP(C20,CHOOSE({1,2},Table2[Pay Item Description],Table2[Pay Item No.]),2,0)) | D20: =IF(C20="","N/A",VLOOKUP(C20,CHOOSE({1,2},Table2[Pay Item Description],Table2[Units]),2,0)) -> N/A | E20: 0 | F20: =IF(C20="","N/A",IF(INDEX(UnitCostGrid,MATCH(C20,PayItemKeys,0),$I$11)="",INDEX(UnitCostGrid,MATCH(C20,PayItemKeys,0),1),INDEX(UnitCostGrid,MATCH(C20,PayItemKeys,0),$I$11))) -> N/A | G20: =IF(C20="",0,F20*E20) -> 0 | I20: =IF(C20="","",IF(INDEX(UnitCostGrid,MATCH(C20,PayItemKeys,0),$I$11)="",0,1)) | T20: Engineering | X20: =('General Information'!$D$37/100)*X18 -> 15540.624 | AJ20: Mobilization | AN20: =('General Information'!$D$36/100)*AN19 -> 100997 | AZ20: Engineering | BD20: =('General Information'!$D$37/100)*BD18 -> 15540.624
A21: 9 | B21: =IF(C21="","",VLOOKUP(C21,CHOOSE({1,2},Table2[Pay Item Description],Table2[Pay Item No.]),2,0)) | D21: =IF(C21="","N/A",VLOOKUP(C21,CHOOSE({1,2},Table2[Pay Item Description],Table2[Units]),2,0)) -> N/A | E21: 0 | F21: =IF(C21="","N/A",IF(INDEX(UnitCostGrid,MATCH(C21,PayItemKeys,0),$I$11)="",INDEX(UnitCostGrid,MATCH(C21,PayItemKeys,0),1),INDEX(UnitCostGrid,MATCH(C21,PayItemKeys,0),$I$11))) -> N/A | G21: =IF(C21="",0,F21*E21) -> 0 | I21: =IF(C21="","",IF(INDEX(UnitCostGrid,MATCH(C21,PayItemKeys,0),$I$11)="",0,1)) | W21: Total | X21: =SUM(X18:X20) -> 357434.34 | AJ21: Engineering | AN21: =('General Information'!$D$37/100)*AN19 -> 50498.501 | BC21: Total | BD21: =SUM(BD18:BD20) -> 357434.34
A22: 10 | B22: =IF(C22="","",VLOOKUP(C22,CHOOSE({1,2},Table2[Pay Item Description],Table2[Pay Item No.]),2,0)) | D22: =IF(C22="","N/A",VLOOKUP(C22,CHOOSE({1,2},Table2[Pay Item Description],Table2[Units]),2,0)) -> N/A | E22: 0 | F22: =IF(C22="","N/A",IF(INDEX(UnitCostGrid,MATCH(C22,PayItemKeys,0),$I$11)="",INDEX(UnitCostGrid,MATCH(C22,PayItemKeys,0),1),INDEX(UnitCostGrid,MATCH(C22,PayItemKeys,0),$I$11))) -> N/A | G22: =IF(C22="",0,F22*E22) -> 0 | I22: =IF(C22="","",IF(INDEX(UnitCostGrid,MATCH(C22,PayItemKeys,0),$I$11)="",0,1)) | AM22: Total | AN22: =SUM(AN19:AN21) -> 1161465.5
A24: Subtotal | G24: =SUM(G13:G22) -> 0
B25: Mobilization | G25: =('General Information'!$D$36/100)*G24 -> 0
B26: Engineering | G26: =('General Information'!$D$37/100)*G24 -> 0
A27: Total | G27: =SUM(G24:G26) -> 0
A32: Net Present Worth
A33: HMA Mill and Overlay - Alternative 3 | I33: Hidden
B35: Item | C35: Year Applied | D35: Actual Cost | E35: Discounted Cost
B36: Initial Construction | C36: =C6 -> 2028 | D36: =G27 -> 0 | E36: =D36 -> 0 | K36: Year | L36: Actual | M36: Discounted
B37: Maintenance 1 | C37: ='Maintenance Policies'!E51 -> 4 | D37: =P19 -> 230995.13 | E37: =IF(C37>'General Information'!$D$33,0,D37/(1+('General Information'!$D$34/100))^C37) -> 205236.18 | K37: =C6 -> 2028 | L37: =IF(K37-$C$6>'General Information'!$D$33,0,IF(K37=$C$6,$D$36,0)+SUMIF($C$37:$C$44,K37-$C$6,$D$37:$D$44)) -> 0 | M37: =IF(K37-$C$6>'General Information'!$D$33,0,IF(K37=$C$6,$E$36,0)+SUMIF($C$37:$C$44,K37-$C$6,$E$37:$E$44)) -> 0
B38: Maintenance 2 | C38: ='Maintenance Policies'!E53 -> 8 | D38: =X21 -> 357434.34 | E38: =IF(C38>'General Information'!$D$33,0,D38/(1+('General Information'!$D$34/100))^C38) -> 282161.97 | K38: =K37+1 -> 2029 | L38: =IF(K38-$C$6>'General Information'!$D$33,0,IF(K38=$C$6,$D$36,0)+SUMIF($C$37:$C$44,K38-$C$6,$D$37:$D$44)) -> 0 | M38: =IF(K38-$C$6>'General Information'!$D$33,0,IF(K38=$C$6,$E$36,0)+SUMIF($C$37:$C$44,K38-$C$6,$E$37:$E$44)) -> 0
B39: Maintenance 3 | C39: ='Maintenance Policies'!E57 -> 12 | D39: =AF19 -> 230995.13 | E39: =IF(C39>'General Information'!$D$33,0,D39/(1+('General Information'!$D$34/100))^C39) -> 162015.34 | K39: =K38+1 -> 2030 | L39: =IF(K39-$C$6>'General Information'!$D$33,0,IF(K39=$C$6,$D$36,0)+SUMIF($C$37:$C$44,K39-$C$6,$D$37:$D$44)) -> 0 | M39: =IF(K39-$C$6>'General Information'!$D$33,0,IF(K39=$C$6,$E$36,0)+SUMIF($C$37:$C$44,K39-$C$6,$E$37:$E$44)) -> 0
B40: Rehabilitation 1 | C40: ='Maintenance Policies'!E59 -> 16 | D40: =AN22 -> 1161465.5 | E40: =IF(C40>'General Information'!$D$33,0,D40/(1+('General Information'!$D$34/100))^C40) -> 723786.91 | K40: =K39+1 -> 2031 | L40: =IF(K40-$C$6>'General Information'!$D$33,0,IF(K40=$C$6,$D$36,0)+SUMIF($C$37:$C$44,K40-$C$6,$D$37:$D$44)) -> 0 | M40: =IF(K40-$C$6>'General Information'!$D$33,0,IF(K40=$C$6,$E$36,0)+SUMIF($C$37:$C$44,K40-$C$6,$E$37:$E$44)) -> 0
B41: Maintenance 4 | C41: ='Maintenance Policies'!E63 -> 20 | D41: =AV19 -> 230995.13 | E41: =IF(C41>'General Information'!$D$33,0,D41/(1+('General Information'!$D$34/100))^C41) -> 127896.4 | K41: =K40+1 -> 2032 | L41: =IF(K41-$C$6>'General Information'!$D$33,0,IF(K41=$C$6,$D$36,0)+SUMIF($C$37:$C$44,K41-$C$6,$D$37:$D$44)) -> 230995.13 | M41: =IF(K41-$C$6>'General Information'!$D$33,0,IF(K41=$C$6,$E$36,0)+SUMIF($C$37:$C$44,K41-$C$6,$E$37:$E$44)) -> 205236.18
B42: Maintenance 5 | C42: ='Maintenance Policies'!E65 -> 24 | D42: =BD21 -> 357434.34 | E42: =IF(C42>'General Information'!$D$33,0,D42/(1+('General Information'!$D$34/100))^C42) -> 175834.01 | K42: =K41+1 -> 2033 | L42: =IF(K42-$C$6>'General Information'!$D$33,0,IF(K42=$C$6,$D$36,0)+SUMIF($C$37:$C$44,K42-$C$6,$D$37:$D$44)) -> 0 | M42: =IF(K42-$C$6>'General Information'!$D$33,0,IF(K42=$C$6,$E$36,0)+SUMIF($C$37:$C$44,K42-$C$6,$E$37:$E$44)) -> 0
B43: Maintenance 6 | C43: ='Maintenance Policies'!E69 -> 28 | D43: =BL19 -> 230995.13 | E43: =IF(C43>'General Information'!$D$33,0,D43/(1+('General Information'!$D$34/100))^C43) -> 100962.6 | K43: =K42+1 -> 2034 | L43: =IF(K43-$C$6>'General Information'!$D$33,0,IF(K43=$C$6,$D$36,0)+SUMIF($C$37:$C$44,K43-$C$6,$D$37:$D$44)) -> 0 | M43: =IF(K43-$C$6>'General Information'!$D$33,0,IF(K43=$C$6,$E$36,0)+SUMIF($C$37:$C$44,K43-$C$6,$E$37:$E$44)) -> 0
B44: Salvage | C44: ='General Information'!D33 -> 30 | D44: =-'Maintenance Policies'!D71*AN22 -> 0 | E44: =IF(C44>'General Information'!$D$33,0,D44/(1+('General Information'!$D$34/100))^C44) -> 0 | K44: =K43+1 -> 2035 | L44: =IF(K44-$C$6>'General Information'!$D$33,0,IF(K44=$C$6,$D$36,0)+SUMIF($C$37:$C$44,K44-$C$6,$D$37:$D$44)) -> 0 | M44: =IF(K44-$C$6>'General Information'!$D$33,0,IF(K44=$C$6,$E$36,0)+SUMIF($C$37:$C$44,K44-$C$6,$E$37:$E$44)) -> 0
B45: Net Present Worth | E45: =SUM(E36:E44) -> 1777893.4 | K45: =K44+1 -> 2036 | L45: =IF(K45-$C$6>'General Information'!$D$33,0,IF(K45=$C$6,$D$36,0)+SUMIF($C$37:$C$44,K45-$C$6,$D$37:$D$44)) -> 357434.34 | M45: =IF(K45-$C$6>'General Information'!$D$33,0,IF(K45=$C$6,$E$36,0)+SUMIF($C$37:$C$44,K45-$C$6,$E$37:$E$44)) -> 282161.97
K46: =K45+1 -> 2037 | L46: =IF(K46-$C$6>'General Information'!$D$33,0,IF(K46=$C$6,$D$36,0)+SUMIF($C$37:$C$44,K46-$C$6,$D$37:$D$44)) -> 0 | M46: =IF(K46-$C$6>'General Information'!$D$33,0,IF(K46=$C$6,$E$36,0)+SUMIF($C$37:$C$44,K46-$C$6,$E$37:$E$44)) -> 0
K47: =K46+1 -> 2038 | L47: =IF(K47-$C$6>'General Information'!$D$33,0,IF(K47=$C$6,$D$36,0)+SUMIF($C$37:$C$44,K47-$C$6,$D$37:$D$44)) -> 0 | M47: =IF(K47-$C$6>'General Information'!$D$33,0,IF(K47=$C$6,$E$36,0)+SUMIF($C$37:$C$44,K47-$C$6,$E$37:$E$44)) -> 0
K48: =K47+1 -> 2039 | L48: =IF(K48-$C$6>'General Information'!$D$33,0,IF(K48=$C$6,$D$36,0)+SUMIF($C$37:$C$44,K48-$C$6,$D$37:$D$44)) -> 0 | M48: =IF(K48-$C$6>'General Information'!$D$33,0,IF(K48=$C$6,$E$36,0)+SUMIF($C$37:$C$44,K48-$C$6,$E$37:$E$44)) -> 0
K49: =K48+1 -> 2040 | L49: =IF(K49-$C$6>'General Information'!$D$33,0,IF(K49=$C$6,$D$36,0)+SUMIF($C$37:$C$44,K49-$C$6,$D$37:$D$44)) -> 230995.13 | M49: =IF(K49-$C$6>'General Information'!$D$33,0,IF(K49=$C$6,$E$36,0)+SUMIF($C$37:$C$44,K49-$C$6,$E$37:$E$44)) -> 162015.34
K50: =K49+1 -> 2041 | L50: =IF(K50-$C$6>'General Information'!$D$33,0,IF(K50=$C$6,$D$36,0)+SUMIF($C$37:$C$44,K50-$C$6,$D$37:$D$44)) -> 0 | M50: =IF(K50-$C$6>'General Information'!$D$33,0,IF(K50=$C$6,$E$36,0)+SUMIF($C$37:$C$44,K50-$C$6,$E$37:$E$44)) -> 0
K51: =K50+1 -> 2042 | L51: =IF(K51-$C$6>'General Information'!$D$33,0,IF(K51=$C$6,$D$36,0)+SUMIF($C$37:$C$44,K51-$C$6,$D$37:$D$44)) -> 0 | M51: =IF(K51-$C$6>'General Information'!$D$33,0,IF(K51=$C$6,$E$36,0)+SUMIF($C$37:$C$44,K51-$C$6,$E$37:$E$44)) -> 0
K52: =K51+1 -> 2043 | L52: =IF(K52-$C$6>'General Information'!$D$33,0,IF(K52=$C$6,$D$36,0)+SUMIF($C$37:$C$44,K52-$C$6,$D$37:$D$44)) -> 0 | M52: =IF(K52-$C$6>'General Information'!$D$33,0,IF(K52=$C$6,$E$36,0)+SUMIF($C$37:$C$44,K52-$C$6,$E$37:$E$44)) -> 0
K53: =K52+1 -> 2044 | L53: =IF(K53-$C$6>'General Information'!$D$33,0,IF(K53=$C$6,$D$36,0)+SUMIF($C$37:$C$44,K53-$C$6,$D$37:$D$44)) -> 1161465.5 | M53: =IF(K53-$C$6>'General Information'!$D$33,0,IF(K53=$C$6,$E$36,0)+SUMIF($C$37:$C$44,K53-$C$6,$E$37:$E$44)) -> 723786.91
K54: =K53+1 -> 2045 | L54: =IF(K54-$C$6>'General Information'!$D$33,0,IF(K54=$C$6,$D$36,0)+SUMIF($C$37:$C$44,K54-$C$6,$D$37:$D$44)) -> 0 | M54: =IF(K54-$C$6>'General Information'!$D$33,0,IF(K54=$C$6,$E$36,0)+SUMIF($C$37:$C$44,K54-$C$6,$E$37:$E$44)) -> 0
K55: =K54+1 -> 2046 | L55: =IF(K55-$C$6>'General Information'!$D$33,0,IF(K55=$C$6,$D$36,0)+SUMIF($C$37:$C$44,K55-$C$6,$D$37:$D$44)) -> 0 | M55: =IF(K55-$C$6>'General Information'!$D$33,0,IF(K55=$C$6,$E$36,0)+SUMIF($C$37:$C$44,K55-$C$6,$E$37:$E$44)) -> 0
K56: =K55+1 -> 2047 | L56: =IF(K56-$C$6>'General Information'!$D$33,0,IF(K56=$C$6,$D$36,0)+SUMIF($C$37:$C$44,K56-$C$6,$D$37:$D$44)) -> 0 | M56: =IF(K56-$C$6>'General Information'!$D$33,0,IF(K56=$C$6,$E$36,0)+SUMIF($C$37:$C$44,K56-$C$6,$E$37:$E$44)) -> 0
K57: =K56+1 -> 2048 | L57: =IF(K57-$C$6>'General Information'!$D$33,0,IF(K57=$C$6,$D$36,0)+SUMIF($C$37:$C$44,K57-$C$6,$D$37:$D$44)) -> 230995.13 | M57: =IF(K57-$C$6>'General Information'!$D$33,0,IF(K57=$C$6,$E$36,0)+SUMIF($C$37:$C$44,K57-$C$6,$E$37:$E$44)) -> 127896.4
... K67: =K66+1 -> 2058 | L67: =IF(K67-$C$6>'General Information'!$D$33,0,IF(K67=$C$6,$D$36,0)+SUMIF($C$37:$C$44,K67-$C$6,$D$37:$D$44)) -> 0 | M67: =IF(K67-$C$6>'General Information'!$D$33,0,IF(K67=$C$6,$E$36,0)+SUMIF($C$37:$C$44,K67-$C$6,$E$37:$E$44)) -> 0

Sheet TMP(PCCRehab)
A1: Coming soon.
E45: I

Sheet Summary
G1: =HYPERLINK("#'General Information'!D9","◄ General Information") -> ◄ General Information | H1: =HYPERLINK("#Instructions!B9","Instructions") -> Instructions | I1: LCCA SUMMARY | K1: STEP 5 of 5 | W1: CHART DATA (calculated automatically from the table on the left; do not edit)
G2: =IF('General Information'!$D$9="","No airport selected yet: pick one on General Information.",'General Information'!$D$9&" ("&'General Information'!$D$10&") | "&'General Information'!$D$11&", "&'General Information'!$D$13&" region"&IF('General Information'!$D$22="",""," | "&'General Information'!$D$22)&IF('General Information'!$D$23="",""," ("&'General Information'!$D$23&")")&" | construction "&TEXT('General Information'!$D$25,"0")&" | "&TEXT('General Information'!$D$33,"0")&" years at "&TEXT('General Information'!$D$34,"0.##")&"%") -> Gatlinburg-Pigeon Forge Airport (GKT) | Sevierville, East region | Runway 10-28 (Reconstruction) | construction 2028 | 30 years at 3%
A3: Alternative | B3: Name | C3: Initial Construction | D3: Present Worth | E3: Alternative Description | G3: LOWEST PRESENT WORTH | K3: MARGIN TO NEXT | O3: EQUIVALENT ANNUAL COST | W3: Present worth by category
A4: Alt 1 | B4: Alternative 1 | C4: ='Alt 1 (New HMA)'!G27 -> 4285511.8 | D4: ='Alt 1 (New HMA)'!E52 -> 6036217.3 | E4: 4" P-401 surface + 4" P-401 base on 6" P-209 on 6" P-154 | G4: =IF(COUNT($O$12:$O$15)=0,"-",TEXT(MIN($O$12:$O$15),"$#,##0")) -> $5,852,247 | K4: =IF(COUNT($O$12:$O$15)<2,"-",TEXT(IF(COUNT($O$12:$O$15)<2,0,SMALL($O$12:$O$15,2)-MIN($O$12:$O$15)),"$#,##0")) -> $183,970 | O4: =IF(COUNT($O$12:$O$15)=0,"-",TEXT(MIN($O$12:$O$15)*(('General Information'!$D$34/100)*(1+'General Information'!$D$34/100)^'General Information'!$D$33/((1+'General Information'!$D$34/100)^'General Information'!$D$33-1)),"$#,##0")) -> $298,577 | W4: Category | X4: =IF($H$12="","",$H$12) -> Alternative 1 | Y4: =IF($H$13="","",$H$13) -> Alternative 2 | Z4: =IF($H$14="","",$H$14) -> Alternative 3 | AA4: =IF($H$15="","",$H$15)
A5: Alt 2 | B5: Alternative 2 | C5: ='Alt 2 (New PCC)'!G27 -> 5918906.2 | D5: ='Alt 2 (New PCC)'!E43 -> 6065224.9 | E5: 9" P-501 on 6" P-209 on 6" P-154 | G5: =IF(COUNT($O$12:$O$15)=0,"No alternatives yet",INDEX($H$12:$H$15,MATCH(MIN($O$12:$O$15),$O$12:$O$15,0))&IF(INDEX($P$93:$P$96,MATCH(MIN($O$12:$O$15),$O$12:$O$15,0))="",""," - "&INDEX($P$93:$P$96,MATCH(MIN($O$12:$O$15),$O$12:$O$15,0)))) -> Alternative 3 - 11" P501 on 6" P209 | K5: =IF(COUNT($O$12:$O$15)<2,"only one alternative so far",TEXT(IF(COUNT($O$12:$O$15)<2,0,SMALL($O$12:$O$15,2)-MIN($O$12:$O$15))/MIN($O$12:$O$15),"0.0%")&IF(IF(COUNT($O$12:$O$15)<2,0,SMALL($O$12:$O$15,2)-MIN($O$12:$O$15))/MIN($O$12:$O$15)<0.05," - under 5%, treat the two as tied"," of the lowest present worth")) -> 3.1% - under 5%, treat the two as tied | O5: ="per year, "&'General Information'!$D$33&" years at "&'General Information'!$D$34&"%" -> per year, 30 years at 3% | W5: Initial construction | X5: =IF(J12="",0,J12) -> 4285511.8 | Y5: =IF(J13="",0,J13) -> 5918906.2 | Z5: =IF(J14="",0,J14) -> 5681473.8 | AA5: =IF(J15="",0,J15) -> 0
A6: Alt 3 | B6: Alternative 3 | C6: ='Alt 3 (New PCC)'!G27 -> 5681473.8 | D6: ='Alt 3 (New PCC)'!E43 -> 5852247.2 | E6: 11" P-501 on 6" P-209 (no subbase) | W6: Maintenance | X6: =IF(K12="",0,K12) -> 1094529.5 | Y6: =IF(K13="",0,K13) -> 359652.4 | Z6: =IF(K14="",0,K14) -> 359652.4 | AA6: =IF(K15="",0,K15) -> 0
G7: INITIAL CONSTRUCTION | K7: UNIT COST | O7: RATE SENSITIVITY | W7: Rehabilitation | X7: =IF(L12="",0,L12) -> 647019.31 | Y7: =IF(L13="",0,L13) -> 332276.94 | Z7: =IF(L14="",0,L14) -> 332276.94 | AA7: =IF(L15="",0,L15) -> 0
G8: =IF(COUNT($O$12:$O$15)=0,"-",TEXT(INDEX($J$12:$J$15,MATCH(MIN($O$12:$O$15),$O$12:$O$15,0)),"$#,##0")) -> $5,681,474 | K8: =IF(OR(COUNT($O$12:$O$15)=0,'General Information'!$D$26=0,'General Information'!$D$26=""),"-",TEXT(INDEX($J$12:$J$15,MATCH(MIN($O$12:$O$15),$O$12:$O$15,0))/'General Information'!$D$26,"$#,##0")&" / S.Y.") -> $124 / S.Y. | O8: =IF(COUNT($O$12:$O$15)<2,"-",IF(COUNTIF($AB$12:$AB$36,INDEX($H$12:$H$15,MATCH(MIN($O$12:$O$15),$O$12:$O$15,0)))=25,"holds 2-8%","the winner changes")) -> the winner changes | W8: Lost revenue | X8: =IF(M12="",0,M12) -> 189697.85 | Y8: =IF(M13="",0,M13) -> 64017.069 | Z8: =IF(M14="",0,M14) -> 64017.069 | AA8: =IF(M15="",0,M15) -> 0
G9: lowest initial construction cost | K9: per S.Y. of mainline area | O9: =IF(COUNT($O$12:$O$15)<2,"needs two alternatives",IF(COUNTIF($AB$12:$AB$36,INDEX($H$12:$H$15,MATCH(MIN($O$12:$O$15),$O$12:$O$15,0)))=25,"the same alternative is lowest at all 25 rates tested, 2% to 8%","the lowest-cost alternative is not the same at every rate: see chart 2")) -> the lowest-cost alternative is not the same at every rate: see chart 2 | W9: Salvage | X9: =IF(N12="",0,N12) -> -180541.18 | Y9: =IF(N13="",0,N13) -> -609627.75 | Z9: =IF(N14="",0,N14) -> -585173 | AA9: =IF(N15="",0,N15) -> 0
G10: =IF(COUNT($O$12:$O$15)=0,"No alternatives yet. Add them from General Information and this line names the winner.","Lowest present worth: "&INDEX($H$12:$H$15,MATCH(MIN($O$12:$O$15),$O$12:$O$15,0))&" "&TEXT(MIN($O$12:$O$15),"$#,##0")&" "&IF(COUNT($O$12:$O$15)<2,"only one alternative so far",TEXT(SMALL($O$12:$O$15,2)-MIN($O$12:$O$15),"$#,##0")&" ahead of the next")) -> Lowest present worth: Alternative 3 $5,852,247 $183,970 ahead of the next | W10: Net present worth vs. discount rate
G11: Worksheet | H11: Alternative | I11: Type | J11: Initial construction | K11: Maintenance PW | L11: Rehabilitation PW | M11: Lost revenue PW | N11: Salvage PW | O11: Net present worth | P11: vs. lowest NPW | Q11: Closure days in period | R11: Runway availability | W11: Rate (%) | X11: =IF(X$4="","",X$4) -> Alternative 1 | Y11: =IF(Y$4="","",Y$4) -> Alternative 2 | Z11: =IF(Z$4="","",Z$4) -> Alternative 3 | AA11: =IF(AA$4="","",AA$4) | AB11: Lowest at this rate
G12: =IF(INDEX(Database!$D:$D,4)="","",INDEX(Database!$D:$D,4)) -> Alt 1 (New HMA) | H12: =IF($G12="","",INDEX(Database!$A:$A,4)) -> Alternative 1 | I12: =IF($G12="","",INDEX(Database!$B:$B,4)) -> HMA-New | J12: =IF($G12="","",IFERROR(INDEX(INDIRECT("'"&$G12&"'!$G$1:$G$70"),MATCH("Total",INDIRECT("'"&$G12&"'!$A$1:$A$70"),0)),0)) -> 4285511.8 | K12: =IF($G12="","",IFERROR(SUMIFS(INDIRECT("'"&$G12&"'!$E$37:$E$52"),INDIRECT("'"&$G12&"'!$B$37:$B$52"),"Maintenance*",INDIRECT("'"&$G12&"'!$B$37:$B$52"),"<>*Indirect*"),0)) -> 1094529.5 | L12: =IF($G12="","",IFERROR(SUMIFS(INDIRECT("'"&$G12&"'!$E$37:$E$52"),INDIRECT("'"&$G12&"'!$B$37:$B$52"),"Rehabilitation*",INDIRECT("'"&$G12&"'!$B$37:$B$52"),"<>*Indirect*"),0)) -> 647019.31 | M12: =IF($G12="","",IFERROR(SUMIFS(INDIRECT("'"&$G12&"'!$E$37:$E$52"),INDIRECT("'"&$G12&"'!$B$37:$B$52"),"*Indirect*"),0)) -> 189697.85 | N12: =IF($G12="","",IFERROR(SUMIFS(INDIRECT("'"&$G12&"'!$E$37:$E$52"),INDIRECT("'"&$G12&"'!$B$37:$B$52"),"Salvage*"),0)) -> -180541.18 | O12: =IF($G12="","",IFERROR(INDEX(INDIRECT("'"&$G12&"'!$E$1:$E$70"),MATCH("Net Present Worth",INDIRECT("'"&$G12&"'!$B$1:$B$70"),0)),0)) -> 6036217.3 | P12: =IF($G12="","",O12-MIN($O$12:$O$15)) -> 183970.06 | Q12: =IF($G12="","",IF(IFERROR(INDIRECT("'"&$G12&"'!$F$2"),0)>0,SUM($AG$41:$AG$71),IFERROR(SUM(INDIRECT("'"&$G12&"'!$F$4:$F$10")),0))) -> 56 | R12: =IF($G12="","",1-Q12/('General Information'!$D$33*365)) -> 0.99488584 | W12: 2 | X12: =IF($G$12="",0,IFERROR($J$12+SUMPRODUCT((INDIRECT("'"&$G$12&"'!$C$37:$C$52")<='General Information'!$D$33)*INDIRECT("'"&$G$12&"'!$D$37:$D$52")/(1+$W12/100)^INDIRECT("'"&$G$12&"'!$C$37:$C$52")),0)) -> 6310890.6 | Y12: =IF($G$13="",0,IFERROR($J$13+SUMPRODUCT((INDIRECT("'"&$G$13&"'!$C$37:$C$52")<='General Information'!$D$33)*INDIRECT("'"&$G$13&"'!$D$37:$D$52")/(1+$W12/100)^INDIRECT("'"&$G$13&"'!$C$37:$C$52")),0)) -> 6048190.8 | Z12: =IF($G$14="",0,IFERROR($J$14+SUMPRODUCT((INDIRECT("'"&$G$14&"'!$C$37:$C$52")<='General Information'!$D$33)*INDIRECT("'"&$G$14&"'!$D$37:$D$52")/(1+$W12/100)^INDIRECT("'"&$G$14&"'!$C$37:$C$52")),0)) -> 5843528.3 | AA12: =IF($G$15="",0,IFERROR($J$15+SUMPRODUCT((INDIRECT("'"&$G$15&"'!$C$37:$C$52")<='General Information'!$D$33)*INDIRECT("'"&$G$15&"'!$D$37:$D$52")/(1+$W12/100)^INDIRECT("'"&$G$15&"'!$C$37:$C$52")),0)) -> 0 | AB12: =IF(COUNTIF($X12:$AA12,"<>0")=0,"",INDEX($H$12:$H$15,MATCH(SMALL($X12:$AA12,COUNTIF($X12:$AA12,0)+1),$X12:$AA12,0))) -> Alternative 3
G13: =IF(INDEX(Database!$D:$D,5)="","",INDEX(Database!$D:$D,5)) -> Alt 2 (New PCC) | H13: =IF($G13="","",INDEX(Database!$A:$A,5)) -> Alternative 2 | I13: =IF($G13="","",INDEX(Database!$B:$B,5)) -> PCC-New | J13: =IF($G13="","",IFERROR(INDEX(INDIRECT("'"&$G13&"'!$G$1:$G$70"),MATCH("Total",INDIRECT("'"&$G13&"'!$A$1:$A$70"),0)),0)) -> 5918906.2 | K13: =IF($G13="","",IFERROR(SUMIFS(INDIRECT("'"&$G13&"'!$E$37:$E$52"),INDIRECT("'"&$G13&"'!$B$37:$B$52"),"Maintenance*",INDIRECT("'"&$G13&"'!$B$37:$B$52"),"<>*Indirect*"),0)) -> 359652.4 | L13: =IF($G13="","",IFERROR(SUMIFS(INDIRECT("'"&$G13&"'!$E$37:$E$52"),INDIRECT("'"&$G13&"'!$B$37:$B$52"),"Rehabilitation*",INDIRECT("'"&$G13&"'!$B$37:$B$52"),"<>*Indirect*"),0)) -> 332276.94 | M13: =IF($G13="","",IFERROR(SUMIFS(INDIRECT("'"&$G13&"'!$E$37:$E$52"),INDIRECT("'"&$G13&"'!$B$37:$B$52"),"*Indirect*"),0)) -> 64017.069 | N13: =IF($G13="","",IFERROR(SUMIFS(INDIRECT("'"&$G13&"'!$E$37:$E$52"),INDIRECT("'"&$G13&"'!$B$37:$B$52"),"Salvage*"),0)) -> -609627.75 | O13: =IF($G13="","",IFERROR(INDEX(INDIRECT("'"&$G13&"'!$E$1:$E$70"),MATCH("Net Present Worth",INDIRECT("'"&$G13&"'!$B$1:$B$70"),0)),0)) -> 6065224.9 | P13: =IF($G13="","",O13-MIN($O$12:$O$15)) -> 212977.69 | Q13: =IF($G13="","",IF(IFERROR(INDIRECT("'"&$G13&"'!$F$2"),0)>0,SUM($AH$41:$AH$71),IFERROR(SUM(INDIRECT("'"&$G13&"'!$F$4:$F$10")),0))) -> 24 | R13: =IF($G13="","",1-Q13/('General Information'!$D$33*365)) -> 0.99780822 | W13: 2.25 | X13: =IF($G$12="",0,IFERROR($J$12+SUMPRODUCT((INDIRECT("'"&$G$12&"'!$C$37:$C$52")<='General Information'!$D$33)*INDIRECT("'"&$G$12&"'!$D$37:$D$52")/(1+$W13/100)^INDIRECT("'"&$G$12&"'!$C$37:$C$52")),0)) -> 6237611.7 | Y13: =IF($G$13="",0,IFERROR($J$13+SUMPRODUCT((INDIRECT("'"&$G$13&"'!$C$37:$C$52")<='General Information'!$D$33)*INDIRECT("'"&$G$13&"'!$D$37:$D$52")/(1+$W13/100)^INDIRECT("'"&$G$13&"'!$C$37:$C$52")),0)) -> 6054084 | Z13: =IF($G$14="",0,IFERROR($J$14+SUMPRODUCT((INDIRECT("'"&$G$14&"'!$C$37:$C$52")<='General Information'!$D$33)*INDIRECT("'"&$G$14&"'!$D$37:$D$52")/(1+$W13/100)^INDIRECT("'"&$G$14&"'!$C$37:$C$52")),0)) -> 5847101.1 | AA13: =IF($G$15="",0,IFERROR($J$15+SUMPRODUCT((INDIRECT("'"&$G$15&"'!$C$37:$C$52")<='General Information'!$D$33)*INDIRECT("'"&$G$15&"'!$D$37:$D$52")/(1+$W13/100)^INDIRECT("'"&$G$15&"'!$C$37:$C$52")),0)) -> 0 | AB13: =IF(COUNTIF($X13:$AA13,"<>0")=0,"",INDEX($H$12:$H$15,MATCH(SMALL($X13:$AA13,COUNTIF($X13:$AA13,0)+1),$X13:$AA13,0))) -> Alternative 3
G14: =IF(INDEX(Database!$D:$D,6)="","",INDEX(Database!$D:$D,6)) -> Alt 3 (New PCC) | H14: =IF($G14="","",INDEX(Database!$A:$A,6)) -> Alternative 3 | I14: =IF($G14="","",INDEX(Database!$B:$B,6)) -> PCC-New | J14: =IF($G14="","",IFERROR(INDEX(INDIRECT("'"&$G14&"'!$G$1:$G$70"),MATCH("Total",INDIRECT("'"&$G14&"'!$A$1:$A$70"),0)),0)) -> 5681473.8 | K14: =IF($G14="","",IFERROR(SUMIFS(INDIRECT("'"&$G14&"'!$E$37:$E$52"),INDIRECT("'"&$G14&"'!$B$37:$B$52"),"Maintenance*",INDIRECT("'"&$G14&"'!$B$37:$B$52"),"<>*Indirect*"),0)) -> 359652.4 | L14: =IF($G14="","",IFERROR(SUMIFS(INDIRECT("'"&$G14&"'!$E$37:$E$52"),INDIRECT("'"&$G14&"'!$B$37:$B$52"),"Rehabilitation*",INDIRECT("'"&$G14&"'!$B$37:$B$52"),"<>*Indirect*"),0)) -> 332276.94 | M14: =IF($G14="","",IFERROR(SUMIFS(INDIRECT("'"&$G14&"'!$E$37:$E$52"),INDIRECT("'"&$G14&"'!$B$37:$B$52"),"*Indirect*"),0)) -> 64017.069 | N14: =IF($G14="","",IFERROR(SUMIFS(INDIRECT("'"&$G14&"'!$E$37:$E$52"),INDIRECT("'"&$G14&"'!$B$37:$B$52"),"Salvage*"),0)) -> -585173 | O14: =IF($G14="","",IFERROR(INDEX(INDIRECT("'"&$G14&"'!$E$1:$E$70"),MATCH("Net Present Worth",INDIRECT("'"&$G14&"'!$B$1:$B$70"),0)),0)) -> 5852247.2 | P14: =IF($G14="","",O14-MIN($O$12:$O$15)) -> 0 | Q14: =IF($G14="","",IF(IFERROR(INDIRECT("'"&$G14&"'!$F$2"),0)>0,SUM($AI$41:$AI$71),IFERROR(SUM(INDIRECT("'"&$G14&"'!$F$4:$F$10")),0))) -> 24 | R14: =IF($G14="","",1-Q14/('General Information'!$D$33*365)) -> 0.99780822 | W14: 2.5 | X14: =IF($G$12="",0,IFERROR($J$12+SUMPRODUCT((INDIRECT("'"&$G$12&"'!$C$37:$C$52")<='General Information'!$D$33)*INDIRECT("'"&$G$12&"'!$D$37:$D$52")/(1+$W14/100)^INDIRECT("'"&$G$12&"'!$C$37:$C$52")),0)) -> 6167504.6 | Y14: =IF($G$13="",0,IFERROR($J$13+SUMPRODUCT((INDIRECT("'"&$G$13&"'!$C$37:$C$52")<='General Information'!$D$33)*INDIRECT("'"&$G$13&"'!$D$37:$D$52")/(1+$W14/100)^INDIRECT("'"&$G$13&"'!$C$37:$C$52")),0)) -> 6058804.6 | Z14: =IF($G$14="",0,IFERROR($J$14+SUMPRODUCT((INDIRECT("'"&$G$14&"'!$C$37:$C$52")<='General Information'!$D$33)*INDIRECT("'"&$G$14&"'!$D$37:$D$52")/(1+$W14/100)^INDIRECT("'"&$G$14&"'!$C$37:$C$52")),0)) -> 5849670.7 | AA14: =IF($G$15="",0,IFERROR($J$15+SUMPRODUCT((INDIRECT("'"&$G$15&"'!$C$37:$C$52")<='General Information'!$D$33)*INDIRECT("'"&$G$15&"'!$D$37:$D$52")/(1+$W14/100)^INDIRECT("'"&$G$15&"'!$C$37:$C$52")),0)) -> 0 | AB14: =IF(COUNTIF($X14:$AA14,"<>0")=0,"",INDEX($H$12:$H$15,MATCH(SMALL($X14:$AA14,COUNTIF($X14:$AA14,0)+1),$X14:$AA14,0))) -> Alternative 3
G15: =IF(INDEX(Database!$D:$D,7)="","",INDEX(Database!$D:$D,7)) | H15: =IF($G15="","",INDEX(Database!$A:$A,7)) | I15: =IF($G15="","",INDEX(Database!$B:$B,7)) | J15: =IF($G15="","",IFERROR(INDEX(INDIRECT("'"&$G15&"'!$G$1:$G$70"),MATCH("Total",INDIRECT("'"&$G15&"'!$A$1:$A$70"),0)),0)) | K15: =IF($G15="","",IFERROR(SUMIFS(INDIRECT("'"&$G15&"'!$E$37:$E$52"),INDIRECT("'"&$G15&"'!$B$37:$B$52"),"Maintenance*",INDIRECT("'"&$G15&"'!$B$37:$B$52"),"<>*Indirect*"),0)) | L15: =IF($G15="","",IFERROR(SUMIFS(INDIRECT("'"&$G15&"'!$E$37:$E$52"),INDIRECT("'"&$G15&"'!$B$37:$B$52"),"Rehabilitation*",INDIRECT("'"&$G15&"'!$B$37:$B$52"),"<>*Indirect*"),0)) | M15: =IF($G15="","",IFERROR(SUMIFS(INDIRECT("'"&$G15&"'!$E$37:$E$52"),INDIRECT("'"&$G15&"'!$B$37:$B$52"),"*Indirect*"),0)) | N15: =IF($G15="","",IFERROR(SUMIFS(INDIRECT("'"&$G15&"'!$E$37:$E$52"),INDIRECT("'"&$G15&"'!$B$37:$B$52"),"Salvage*"),0)) | O15: =IF($G15="","",IFERROR(INDEX(INDIRECT("'"&$G15&"'!$E$1:$E$70"),MATCH("Net Present Worth",INDIRECT("'"&$G15&"'!$B$1:$B$70"),0)),0)) | P15: =IF($G15="","",O15-MIN($O$12:$O$15)) | Q15: =IF($G15="","",IF(IFERROR(INDIRECT("'"&$G15&"'!$F$2"),0)>0,SUM($AJ$41:$AJ$71),IFERROR(SUM(INDIRECT("'"&$G15&"'!$F$4:$F$10")),0))) | R15: =IF($G15="","",1-Q15/('General Information'!$D$33*365)) | W15: 2.75 | X15: =IF($G$12="",0,IFERROR($J$12+SUMPRODUCT((INDIRECT("'"&$G$12&"'!$C$37:$C$52")<='General Information'!$D$33)*INDIRECT("'"&$G$12&"'!$D$37:$D$52")/(1+$W15/100)^INDIRECT("'"&$G$12&"'!$C$37:$C$52")),0)) -> 6100420.3 | Y15: =IF($G$13="",0,IFERROR($J$13+SUMPRODUCT((INDIRECT("'"&$G$13&"'!$C$37:$C$52")<='General Information'!$D$33)*INDIRECT("'"&$G$13&"'!$D$37:$D$52")/(1+$W15/100)^INDIRECT("'"&$G$13&"'!$C$37:$C$52")),0)) -> 6062479.8 | Z15: =IF($G$14="",0,IFERROR($J$14+SUMPRODUCT((INDIRECT("'"&$G$14&"'!$C$37:$C$52")<='General Information'!$D$33)*INDIRECT("'"&$G$14&"'!$D$37:$D$52")/(1+$W15/100)^INDIRECT("'"&$G$14&"'!$C$37:$C$52")),0)) -> 5851351.5 | AA15: =IF($G$15="",0,IFERROR($J$15+SUMPRODUCT((INDIRECT("'"&$G$15&"'!$C$37:$C$52")<='General Information'!$D$33)*INDIRECT("'"&$G$15&"'!$D$37:$D$52")/(1+$W15/100)^INDIRECT("'"&$G$15&"'!$C$37:$C$52")),0)) -> 0 | AB15: =IF(COUNTIF($X15:$AA15,"<>0")=0,"",INDEX($H$12:$H$15,MATCH(SMALL($X15:$AA15,COUNTIF($X15:$AA15,0)+1),$X15:$AA15,0))) -> Alternative 3
W16: 3 | X16: =IF($G$12="",0,IFERROR($J$12+SUMPRODUCT((INDIRECT("'"&$G$12&"'!$C$37:$C$52")<='General Information'!$D$33)*INDIRECT("'"&$G$12&"'!$D$37:$D$52")/(1+$W16/100)^INDIRECT("'"&$G$12&"'!$C$37:$C$52")),0)) -> 6036217.3 | Y16: =IF($G$13="",0,IFERROR($J$13+SUMPRODUCT((INDIRECT("'"&$G$13&"'!$C$37:$C$52")<='General Information'!$D$33)*INDIRECT("'"&$G$13&"'!$D$37:$D$52")/(1+$W16/100)^INDIRECT("'"&$G$13&"'!$C$37:$C$52")),0)) -> 6065224.9 | Z16: =IF($G$14="",0,IFERROR($J$14+SUMPRODUCT((INDIRECT("'"&$G$14&"'!$C$37:$C$52")<='General Information'!$D$33)*INDIRECT("'"&$G$14&"'!$D$37:$D$52")/(1+$W16/100)^INDIRECT("'"&$G$14&"'!$C$37:$C$52")),0)) -> 5852247.2 | AA16: =IF($G$15="",0,IFERROR($J$15+SUMPRODUCT((INDIRECT("'"&$G$15&"'!$C$37:$C$52")<='General Information'!$D$33)*INDIRECT("'"&$G$15&"'!$D$37:$D$52")/(1+$W16/100)^INDIRECT("'"&$G$15&"'!$C$37:$C$52")),0)) -> 0 | AB16: =IF(COUNTIF($X16:$AA16,"<>0")=0,"",INDEX($H$12:$H$15,MATCH(SMALL($X16:$AA16,COUNTIF($X16:$AA16,0)+1),$X16:$AA16,0))) -> Alternative 3
